Workbook

Sheet Projections
A1: INR Mn | B1: Unit | C1: Source / Driver | D1: 1Q22 | E1: 2Q22 | F1: 3Q22 | G1: 4Q22 | H1: 1Q23 | I1: 2Q23 | J1: 3Q23 | K1: 4Q23 | L1: 1Q24 | M1: 2Q24 | N1: 3Q24 | O1: 4Q24 | P1: 1Q25 | Q1: 2Q25 | R1: 3Q25 | S1: 4Q25 | T1: 1Q26 | U1: 2Q26 | V1: 3Q26 | W1: 4Q26 | X1: 1Q27 | Y1: 2Q27 | Z1: 3Q27 | AA1: 4Q27 | AC1: FY19 | AD1: FY20 | AE1: FY21 | AF1: FY22 | AG1: FY23 | AH1: FY24 | AI1: FY25 | AJ1: FY26 | AK1: FY27E | AL1: FY28E | AM1: FY29E | AN1: FY30E
A2: Fiscal Year End | D2: =DATE(2021,6,30) -> 44377 | E2: =EOMONTH(D2,-3) -> 44286 | F2: =EOMONTH(E2,-3) -> 44196 | G2: =EOMONTH(F2,-3) -> 44104 | H2: =EOMONTH(G2,-3) -> 44012 | I2: =EOMONTH(H2,-3) -> 43921 | J2: =EOMONTH(I2,-3) -> 43830 | K2: =EOMONTH(J2,-3) -> 43738 | L2: =EOMONTH(K2,-3) -> 43646 | ... AA2: =EOMONTH(Z2,-3) -> 42277 | AC2: =DATE(2019,3,31) -> 43555 | AD2: =DATE(2020,3,31) -> 43921 | AE2: =DATE(2021,3,31) -> 44286 | AF2: =DATE(2022,3,31) -> 44651 | AG2: =DATE(2023,3,31) -> 45016 | AH2: =DATE(2024,3,31) -> 45382 | AI2: =DATE(2025,3,31) -> 45747 | AJ2: =DATE(2026,3,31) -> 46112 | AK2: =DATE(2027,3,31) -> 46477 | AL2: =DATE(2028,3,31) -> 46843 | AM2: =DATE(2029,3,31) -> 47208 | AN2: =DATE(2030,3,31) -> 47573
A3: All figures in INR Mn unless stated otherwise. Historical quarters (1Q22-4Q26) and historical annual columns (FY19-FY26) link to the Raw Data tabs. 1Q27-4Q27 are left blank for a later quarterly-projection pass. FY27E-FY30E are annual projections, each chained off the preceding column in this sheet: red (#A20000) cells are hardcoded assumptions -- edit these to change the forecast; black cells are formulas.
A4: SUMMARY
A5: Total GMV | B5: Rs Mn | C5: Formula | D5: =IFERROR(D32+D61+D84,"") | E5: =IFERROR(E32+E61+E84,"") | F5: =IFERROR(F32+F61+F84,"") | G5: =IFERROR(G32+G61+G84,"") | H5: =IFERROR(H32+H61+H84,"") | I5: =IFERROR(I32+I61+I84,"") | J5: =IFERROR(J32+J61+J84,"") | K5: =IFERROR(K32+K61+K84,"") | ... W5: =IFERROR(W32+W61+W84,"") -> 52410 | AC5: =IFERROR(AC32+AC61+AC84,"") -> 0 | AD5: =IFERROR(AD32+AD61+AD84,"") -> 0 | AE5: =IFERROR(AE32+AE61+AE84,"") -> 0 | AF5: =IFERROR(AF32+AF61+AF84,"") | AG5: =IFERROR(AG32+AG61+AG84,"") | AH5: =IFERROR(AH32+AH61+AH84,"") -> 124471 | AI5: =IFERROR(AI32+AI61+AI84,"") -> 156033 | AJ5: =IFERROR(AJ32+AJ61+AJ84,"") -> 199620 | ... AN5: =IFERROR(AN32+AN61+AN84,"") -> 601648.58
A6: YoY growth | B6: % | C6: Formula | H6: =IFERROR(H5/D5-1,"") | I6: =IFERROR(I5/E5-1,"") | J6: =IFERROR(J5/F5-1,"") | K6: =IFERROR(K5/G5-1,"") | L6: =IFERROR(L5/H5-1,"") | M6: =IFERROR(M5/I5-1,"") | N6: =IFERROR(N5/J5-1,"") | O6: =IFERROR(O5/K5-1,"") | ... W6: =IFERROR(W5/S5-1,"") -> 0.27766943 | AD6: =IFERROR(AD5/AC5-1,"") | AE6: =IFERROR(AE5/AD5-1,"") | AF6: =IFERROR(AF5/AE5-1,"") | AG6: =IFERROR(AG5/AF5-1,"") | AH6: =IFERROR(AH5/AG5-1,"") | AI6: =IFERROR(AI5/AH5-1,"") -> 0.2535691 | AJ6: =IFERROR(AJ5/AI5-1,"") -> 0.27934475 | AK6: =IFERROR(AK5/AJ5-1,"") -> 0.31759087 | ... AN6: =IFERROR(AN5/AM5-1,"") -> 0.31768251
A7: Total NSV | B7: Rs Mn | C7: Formula | D7: =IFERROR(D34+D63+D86,"") | E7: =IFERROR(E34+E63+E86,"") | F7: =IFERROR(F34+F63+F86,"") | G7: =IFERROR(G34+G63+G86,"") | H7: =IFERROR(H34+H63+H86,"") | I7: =IFERROR(I34+I63+I86,"") | J7: =IFERROR(J34+J63+J86,"") | K7: =IFERROR(K34+K63+K86,"") | ... W7: =IFERROR(W34+W63+W86,"") -> 26780 | AC7: =IFERROR(AC34+AC63+AC86,"") -> 0 | AD7: =IFERROR(AD34+AD63+AD86,"") -> 0 | AE7: =IFERROR(AE34+AE63+AE86,"") -> 0 | AF7: =IFERROR(AF34+AF63+AF86,"") | AG7: =IFERROR(AG34+AG63+AG86,"") | AH7: =IFERROR(AH34+AH63+AH86,"") -> 63542 | AI7: =IFERROR(AI34+AI63+AI86,"") -> 78235 | AJ7: =IFERROR(AJ34+AJ63+AJ86,"") -> 99990 | ... AN7: =IFERROR(AN34+AN63+AN86,"") -> 299223.77
A8: NSV / GMV | B8: % | C8: Formula | D8: =IFERROR(D7/D5,"") | E8: =IFERROR(E7/E5,"") | F8: =IFERROR(F7/F5,"") | G8: =IFERROR(G7/G5,"") | H8: =IFERROR(H7/H5,"") | I8: =IFERROR(I7/I5,"") | J8: =IFERROR(J7/J5,"") | K8: =IFERROR(K7/K5,"") | ... W8: =IFERROR(W7/W5,"") -> 0.51097119 | AC8: =IFERROR(AC7/AC5,"") | AD8: =IFERROR(AD7/AD5,"") | AE8: =IFERROR(AE7/AE5,"") | AF8: =IFERROR(AF7/AF5,"") | AG8: =IFERROR(AG7/AG5,"") | AH8: =IFERROR(AH7/AH5,"") -> 0.51049642 | AI8: =IFERROR(AI7/AI5,"") -> 0.50140034 | AJ8: =IFERROR(AJ7/AJ5,"") -> 0.50090171
A9: Total Revenue | B9: Rs Mn | C9: Formula | D9: =IFERROR(D36+D65+D88,"") | E9: =IFERROR(E36+E65+E88,"") | F9: =IFERROR(F36+F65+F88,"") | G9: =IFERROR(G36+G65+G88,"") | H9: =IFERROR(H36+H65+H88,"") | I9: =IFERROR(I36+I65+I88,"") | J9: =IFERROR(J36+J65+J88,"") | K9: =IFERROR(K36+K65+K88,"") | ... W9: =IFERROR(W36+W65+W88,"") -> 26480 | AC9: =IFERROR(AC36+AC65+AC88,"") -> 0 | AD9: =IFERROR(AD36+AD65+AD88,"") -> 0 | AE9: =IFERROR(AE36+AE65+AE88,"") -> 0 | AF9: =IFERROR(AF36+AF65+AF88,"") | AG9: =IFERROR(AG36+AG65+AG88,"") | AH9: =IFERROR(AH36+AH65+AH88,"") -> 63856.26 | AI9: =IFERROR(AI36+AI65+AI88,"") -> 79498.2 | AJ9: =IFERROR(AJ36+AJ65+AJ88,"") -> 100221.8 | ... AN9: =IFERROR(AN36+AN65+AN88,"") -> 298728.44
A10: YoY growth | B10: % | C10: Formula | H10: =IFERROR(H9/D9-1,"") | I10: =IFERROR(I9/E9-1,"") | J10: =IFERROR(J9/F9-1,"") | K10: =IFERROR(K9/G9-1,"") | L10: =IFERROR(L9/H9-1,"") | M10: =IFERROR(M9/I9-1,"") | N10: =IFERROR(N9/J9-1,"") | O10: =IFERROR(O9/K9-1,"") | ... W10: =IFERROR(W9/S9-1,"") -> 0.28433959 | AD10: =IFERROR(AD9/AC9-1,"") | AE10: =IFERROR(AE9/AD9-1,"") | AF10: =IFERROR(AF9/AE9-1,"") | AG10: =IFERROR(AG9/AF9-1,"") | AH10: =IFERROR(AH9/AG9-1,"") | AI10: =IFERROR(AI9/AH9-1,"") -> 0.24495547 | AJ10: =IFERROR(AJ9/AI9-1,"") -> 0.26068012 | AK10: =IFERROR(AK9/AJ9-1,"") -> 0.31459731 | ... AN10: =IFERROR(AN9/AM9-1,"") -> 0.31376471
A11: Gross Profit | B11: Rs Mn | C11: Formula | D11: =IFERROR(D38+D67+D90,"") | E11: =IFERROR(E38+E67+E90,"") | F11: =IFERROR(F38+F67+F90,"") | G11: =IFERROR(G38+G67+G90,"") | H11: =IFERROR(H38+H67+H90,"") | I11: =IFERROR(I38+I67+I90,"") | J11: =IFERROR(J38+J67+J90,"") | K11: =IFERROR(K38+K67+K90,"") | ... W11: =IFERROR(W38+W67+W90,"") -> 11980 | AC11: =IFERROR(AC38+AC67+AC90,"") -> 0 | AD11: =IFERROR(AD38+AD67+AD90,"") -> 0 | AE11: =IFERROR(AE38+AE67+AE90,"") -> 0 | AF11: =IFERROR(AF38+AF67+AF90,"") | AG11: =IFERROR(AG38+AG67+AG90,"") | AH11: =IFERROR(AH38+AH67+AH90,"") -> 24033.4 | AI11: =IFERROR(AI38+AI67+AI90,"") -> 34366.6 | AJ11: =IFERROR(AJ38+AJ67+AJ90,"") -> 45005.3 | ... AN11: =IFERROR(AN38+AN67+AN90,"") -> 134793.16
A12: Gross margin (% of NSV) | B12: % | C12: Formula | D12: =IFERROR(D11/D7,"") | E12: =IFERROR(E11/E7,"") | F12: =IFERROR(F11/F7,"") | G12: =IFERROR(G11/G7,"") | H12: =IFERROR(H11/H7,"") | I12: =IFERROR(I11/I7,"") | J12: =IFERROR(J11/J7,"") | K12: =IFERROR(K11/K7,"") | ... W12: =IFERROR(W11/W7,"") -> 0.44734877 | AC12: =IFERROR(AC11/AC7,"") | AD12: =IFERROR(AD11/AD7,"") | AE12: =IFERROR(AE11/AE7,"") | AF12: =IFERROR(AF11/AF7,"") | AG12: =IFERROR(AG11/AG7,"") | AH12: =IFERROR(AH11/AH7,"") -> 0.37822857 | AI12: =IFERROR(AI11/AI7,"") -> 0.43927398 | AJ12: =IFERROR(AJ11/AJ7,"") -> 0.45009801
A13: EBITDA | B13: Rs Mn | C13: Formula | D13: =D99 | E13: =E99 | F13: =F99 | G13: =G99 | H13: =H99 | I13: =I99 | J13: =J99 | K13: =K99 | ... W13: =W99 -> 2220 | AC13: =AC99 | AD13: =AD99 | AE13: =AE99 | AF13: =AF99 | AG13: =AG99 | AH13: =AH99 -> 3461.51 | AI13: =AI99 -> 4739.1 | AJ13: =AJ99 -> 7953.9 | ... AN13: =AN99 -> 23548.976
A14: EBITDA margin (% of NSV) | B14: % | C14: Formula | D14: =IFERROR(D13/D7,"") | E14: =IFERROR(E13/E7,"") | F14: =IFERROR(F13/F7,"") | G14: =IFERROR(G13/G7,"") | H14: =IFERROR(H13/H7,"") | I14: =IFERROR(I13/I7,"") | J14: =IFERROR(J13/J7,"") | K14: =IFERROR(K13/K7,"") | ... W14: =IFERROR(W13/W7,"") -> 0.082897685 | AC14: =IFERROR(AC13/AC7,"") | AD14: =IFERROR(AD13/AD7,"") | AE14: =IFERROR(AE13/AE7,"") | AF14: =IFERROR(AF13/AF7,"") | AG14: =IFERROR(AG13/AG7,"") | AH14: =IFERROR(AH13/AH7,"") -> 0.054475937 | AI14: =IFERROR(AI13/AI7,"") -> 0.06057519 | AJ14: =IFERROR(AJ13/AJ7,"") -> 0.079546955
A15: PAT | B15: Rs Mn | C15: Formula | D15: =D111 | E15: =E111 | F15: =F111 | G15: =G111 | H15: =H111 | I15: =I111 | J15: =J111 | K15: =K111 | ... W15: =W111 -> 778.3 | AC15: =AC111 | AD15: =AD111 | AE15: =AE111 | AF15: =AF111 | AG15: =AG111 | AH15: =AH111 -> 437.17 | AI15: =AI111 -> 737 | AJ15: =AJ111 -> 2644.2 | ... AN15: =AN111 -> 7090.2624
A16: PAT margin (% of Revenue) | B16: % | C16: Formula | D16: =IFERROR(D15/D9,"") | E16: =IFERROR(E15/E9,"") | F16: =IFERROR(F15/F9,"") | G16: =IFERROR(G15/G9,"") | H16: =IFERROR(H15/H9,"") | I16: =IFERROR(I15/I9,"") | J16: =IFERROR(J15/J9,"") | K16: =IFERROR(K15/K9,"") | ... W16: =IFERROR(W15/W9,"") -> 0.029391994 | AC16: =IFERROR(AC15/AC9,"") | AD16: =IFERROR(AD15/AD9,"") | AE16: =IFERROR(AE15/AE9,"") | AF16: =IFERROR(AF15/AF9,"") | AG16: =IFERROR(AG15/AG9,"") | AH16: =IFERROR(AH15/AH9,"") -> 0.0068461573 | AI16: =IFERROR(AI15/AI9,"") -> 0.0092706502 | AJ16: =IFERROR(AJ15/AJ9,"") -> 0.026383481
A17: EPS (diluted) | B17: Rs | C17: Formula | D17: =D113 -> 0.07 | E17: =E113 -> 0.03 | F17: =F113 -> 0.6 | G17: =G113 -> 0.18 | H17: =H113 -> 0 | I17: =I113 -> 0.01 | J17: =J113 -> 0.03 | K17: =K113 -> 0.01 | ... W17: =W113 -> 0.27 | AC17: =AC113 -> -17.7 | AD17: =AD113 -> -11.63 | AE17: =AE113 -> 40.07 | AF17: =AF113 -> 0.87 | AG17: =AG113 -> 0.07 | AH17: =AH113 -> 0.11 | AI17: =AI113 -> 0.23 | AJ17: =AJ113 -> 0.7 | ... AN17: =AN113 -> 2.4886846
A19: Segment mix (% of Total GMV)
A20: Beauty | B20: % | C20: Formula | D20: =IFERROR(D32/D5,"") | E20: =IFERROR(E32/E5,"") | F20: =IFERROR(F32/F5,"") | G20: =IFERROR(G32/G5,"") | H20: =IFERROR(H32/H5,"") | I20: =IFERROR(I32/I5,"") | J20: =IFERROR(J32/J5,"") | K20: =IFERROR(K32/K5,"") | ... W20: =IFERROR(W32/W5,"") -> 0.74260637 | AC20: =IFERROR(AC32/AC5,"") | AD20: =IFERROR(AD32/AD5,"") | AE20: =IFERROR(AE32/AE5,"") | AF20: =IFERROR(AF32/AF5,"") | AG20: =IFERROR(AG32/AG5,"") | AH20: =IFERROR(AH32/AH5,"") -> 0.72750279 | AI20: =IFERROR(AI32/AI5,"") -> 0.75459038 | AJ20: =IFERROR(AJ32/AJ5,"") -> 0.74907324 | ... AN20: =IFERROR(AN32/AN5,"") -> 0.73603931
A21: Fashion | B21: % | C21: Formula | D21: =IFERROR(D61/D5,"") | E21: =IFERROR(E61/E5,"") | F21: =IFERROR(F61/F5,"") | G21: =IFERROR(G61/G5,"") | H21: =IFERROR(H61/H5,"") | I21: =IFERROR(I61/I5,"") | J21: =IFERROR(J61/J5,"") | K21: =IFERROR(K61/K5,"") | ... W21: =IFERROR(W61/W5,"") -> 0.25453158 | AC21: =IFERROR(AC61/AC5,"") | AD21: =IFERROR(AD61/AD5,"") | AE21: =IFERROR(AE61/AE5,"") | AF21: =IFERROR(AF61/AF5,"") | AG21: =IFERROR(AG61/AG5,"") | AH21: =IFERROR(AH61/AH5,"") -> 0.27199107 | AI21: =IFERROR(AI61/AI5,"") -> 0.24381381 | AJ21: =IFERROR(AJ61/AJ5,"") -> 0.24817153 | ... AN21: =IFERROR(AN61/AN5,"") -> 0.26134977
A22: New Business | B22: % | C22: Formula | D22: =IFERROR(D84/D5,"") | E22: =IFERROR(E84/E5,"") | F22: =IFERROR(F84/F5,"") | G22: =IFERROR(G84/G5,"") | H22: =IFERROR(H84/H5,"") | I22: =IFERROR(I84/I5,"") | J22: =IFERROR(J84/J5,"") | K22: =IFERROR(K84/K5,"") | ... W22: =IFERROR(W84/W5,"") -> 0.0028620492 | AC22: =IFERROR(AC84/AC5,"") | AD22: =IFERROR(AD84/AD5,"") | AE22: =IFERROR(AE84/AE5,"") | AF22: =IFERROR(AF84/AF5,"") | AG22: =IFERROR(AG84/AG5,"") | AH22: =IFERROR(AH84/AH5,"") -> 0.00050614199 | AI22: =IFERROR(AI84/AI5,"") -> 0.0015958163 | AJ22: =IFERROR(AJ84/AJ5,"") -> 0.0027552349 | ... AN22: =IFERROR(AN84/AN5,"") -> 0.0026109178
A24: BEAUTY (incl. SuperStore)
A25: Definition: BPC (online + offline) + Superstore by Nykaa + Nykaa Man Grooming + House of Nykaa owned brands. NOTE: AUTC/Orders/AOV here are sourced from the deck's 'BPC Vertical' KPI table, which is a narrower scope than the GMV/NSV/Revenue lines below (GMV includes SuperStore, BPC Vertical orders don't) -- see the equivalent caveat on the Raw Data - Ops KPIs tab. AOV = GMV/Orders here is therefore a blended incl-SuperStore figure, not Nykaa's own reported BPC AOV.
A26: Annual transacting customers (AUTC) | B26: mn | C26: Link: Raw Data - Ops KPIs | D26: ='Raw Data - Ops KPIs'!D35 -> 6.5 | E26: ='Raw Data - Ops KPIs'!E35 -> 7 | F26: ='Raw Data - Ops KPIs'!F35 -> 7.5 | G26: ='Raw Data - Ops KPIs'!G35 -> 8 | H26: ='Raw Data - Ops KPIs'!H35 -> 8.6 | I26: ='Raw Data - Ops KPIs'!I35 -> 9.1 | J26: ='Raw Data - Ops KPIs'!J35 -> 9.6 | K26: ='Raw Data - Ops KPIs'!K35 -> 10 | ... W26: ='Raw Data - Ops KPIs'!W35 -> 19.7 | AF26: ='Raw Data - Ops KPIs'!AF35 -> 8 | AG26: ='Raw Data - Ops KPIs'!AG35 -> 10 | AH26: ='Raw Data - Ops KPIs'!AH35 -> 12.4 | AI26: ='Raw Data - Ops KPIs'!AI35 -> 15.8 | AJ26: ='Raw Data - Ops KPIs'!AJ35 -> 19.7 | AK26: =AJ26*(1+AK27) -> 24.5659 | AL26: =AK26*(1+AL27) -> 30.633677 | AM26: =AL26*(1+AM27) -> 38.200196 | AN26: =AM26*(1+AN27) -> 47.635644
A27: YoY growth | B27: % | C27: Assumption (edit me) | H27: =IFERROR(H26/D26-1,"") -> 0.32307692 | I27: =IFERROR(I26/E26-1,"") -> 0.3 | J27: =IFERROR(J26/F26-1,"") -> 0.28 | K27: =IFERROR(K26/G26-1,"") -> 0.25 | L27: =IFERROR(L26/H26-1,"") -> 0.26744186 | M27: =IFERROR(M26/I26-1,"") -> 0.17582418 | N27: =IFERROR(N26/J26-1,"") -> 0.21875 | O27: =IFERROR(O26/K26-1,"") -> 0.24 | ... W27: =IFERROR(W26/S26-1,"") -> 0.24683544 | AD27: =IFERROR(AD26/AC26-1,"") | AE27: =IFERROR(AE26/AD26-1,"") | AF27: =IFERROR(AF26/AE26-1,"") | AG27: =IFERROR(AG26/AF26-1,"") -> 0.25 | AH27: =IFERROR(AH26/AG26-1,"") -> 0.24 | AI27: =IFERROR(AI26/AH26-1,"") -> 0.27419355 | AJ27: =IFERROR(AJ26/AI26-1,"") -> 0.24683544 | AK27: 0.247 | AL27: 0.247 | AM27: 0.247 | AN27: 0.247
A28: Number of orders | B28: mn | C28: Link: Raw Data - Ops KPIs | D28: ='Raw Data - Ops KPIs'!D37 -> 5.8 | E28: ='Raw Data - Ops KPIs'!E37 -> 6 | F28: ='Raw Data - Ops KPIs'!F37 -> 7.5 | G28: ='Raw Data - Ops KPIs'!G37 -> 7.2 | H28: ='Raw Data - Ops KPIs'!H37 -> 8.1 | I28: ='Raw Data - Ops KPIs'!I37 -> 8.4 | J28: ='Raw Data - Ops KPIs'!J37 -> 9.5 | K28: ='Raw Data - Ops KPIs'!K37 -> 8.8 | ... W28: ='Raw Data - Ops KPIs'!W37 -> 17.5 | AF28: ='Raw Data - Ops KPIs'!AF37 -> 26.5 | AG28: ='Raw Data - Ops KPIs'!AG37 -> 34.8 | AH28: ='Raw Data - Ops KPIs'!AH37 -> 43.7 | AI28: ='Raw Data - Ops KPIs'!AI37 -> 54.5 | AJ28: ='Raw Data - Ops KPIs'!AJ37 -> 65.8 | AK28: =AK26*AK29 -> 82.050106 | AL28: =AL26*AL29 -> 102.31648 | AM28: =AM26*AM29 -> 127.58865 | AN28: =AN26*AN29 -> 159.10305
A29: Average order frequency | B29: x | C29: Assumption (edit me) | D29: =IFERROR(D28/D26,"") -> 0.89230769 | E29: =IFERROR(E28/E26,"") -> 0.85714286 | F29: =IFERROR(F28/F26,"") -> 1 | G29: =IFERROR(G28/G26,"") -> 0.9 | H29: =IFERROR(H28/H26,"") -> 0.94186047 | I29: =IFERROR(I28/I26,"") -> 0.92307692 | J29: =IFERROR(J28/J26,"") -> 0.98958333 | K29: =IFERROR(K28/K26,"") -> 0.88 | ... W29: =IFERROR(W28/W26,"") -> 0.88832487 | AC29: =IFERROR(AC28/AC26,"") | AD29: =IFERROR(AD28/AD26,"") | AE29: =IFERROR(AE28/AE26,"") | AF29: =IFERROR(AF28/AF26,"") -> 3.3125 | AG29: =IFERROR(AG28/AG26,"") -> 3.48 | AH29: =IFERROR(AH28/AH26,"") -> 3.5241935 | AI29: =IFERROR(AI28/AI26,"") -> 3.4493671 | AJ29: =IFERROR(AJ28/AJ26,"") -> 3.3401015 | AK29: 3.34 | AL29: 3.34 | AM29: 3.34 | AN29: 3.34
A30: Average order value | B30: Rs | C30: Formula | D30: =IFERROR(D32/D28,"") -> 0 | E30: =IFERROR(E32/E28,"") -> 0 | F30: =IFERROR(F32/F28,"") -> 0 | G30: =IFERROR(G32/G28,"") -> 0 | H30: =IFERROR(H32/H28,"") -> 0 | I30: =IFERROR(I32/I28,"") -> 0 | J30: =IFERROR(J32/J28,"") -> 0 | K30: =IFERROR(K32/K28,"") -> 0 | ... W30: =IFERROR(W32/W28,"") -> 2224 | AC30: =IFERROR(AC32/AC28,"") | AD30: =IFERROR(AD32/AD28,"") | AE30: =IFERROR(AE32/AE28,"") | AF30: =IFERROR(AF32/AF28,"") | AG30: =IFERROR(AG32/AG28,"") | AH30: =IFERROR(AH32/AH28,"") -> 2072.151 | AI30: =IFERROR(AI32/AI28,"") -> 2160.3853 | AJ30: =IFERROR(AJ32/AJ28,"") -> 2272.4924 | AK30: =AJ30*(1+AK31) -> 2390.662 | AL30: =AK30*(1+AL31) -> 2514.9764 | AM30: =AL30*(1+AM31) -> 2645.7552 | AN30: =AM30*(1+AN31) -> 2783.3345
A31: YoY growth | B31: % | C31: Assumption (edit me) | AK31: 0.052 | AL31: 0.052 | AM31: 0.052 | AN31: 0.052
A32: GMV | B32: Rs Mn | C32: Link: Raw Data - Ops KPIs | D32: ='Raw Data - Ops KPIs'!D40 -> 0 | E32: ='Raw Data - Ops KPIs'!E40 -> 0 | F32: ='Raw Data - Ops KPIs'!F40 -> 0 | G32: ='Raw Data - Ops KPIs'!G40 -> 0 | H32: ='Raw Data - Ops KPIs'!H40 -> 0 | I32: ='Raw Data - Ops KPIs'!I40 -> 0 | J32: ='Raw Data - Ops KPIs'!J40 -> 0 | K32: ='Raw Data - Ops KPIs'!K40 -> 0 | ... W32: ='Raw Data - Ops KPIs'!W40 -> 38920 | AF32: ='Raw Data - Ops KPIs'!AF40 | AG32: ='Raw Data - Ops KPIs'!AG40 | AH32: ='Raw Data - Ops KPIs'!AH40 -> 90553 | AI32: ='Raw Data - Ops KPIs'!AI40 -> 117741 | AJ32: ='Raw Data - Ops KPIs'!AJ40 -> 149530 | AK32: =AK28*AK30 -> 196154.07 | AL32: =AL28*AL30 -> 257323.54 | AM32: =AM28*AM30 -> 337568.34 | AN32: =AN28*AN30 -> 442837.01
A33: YoY growth | B33: % | C33: Formula | H33: =IFERROR(H32/D32-1,"") | I33: =IFERROR(I32/E32-1,"") | J33: =IFERROR(J32/F32-1,"") | K33: =IFERROR(K32/G32-1,"") | L33: =IFERROR(L32/H32-1,"") | M33: =IFERROR(M32/I32-1,"") | N33: =IFERROR(N32/J32-1,"") | O33: =IFERROR(O32/K32-1,"") | ... W33: =IFERROR(W32/S32-1,"") -> 0.27272727 | AD33: =IFERROR(AD32/AC32-1,"") | AE33: =IFERROR(AE32/AD32-1,"") | AF33: =IFERROR(AF32/AE32-1,"") | AG33: =IFERROR(AG32/AF32-1,"") | AH33: =IFERROR(AH32/AG32-1,"") | AI33: =IFERROR(AI32/AH32-1,"") -> 0.30024406 | AJ33: =IFERROR(AJ32/AI32-1,"") -> 0.26999091 | AK33: =IFERROR(AK32/AJ32-1,"") -> 0.31180413 | ... AN33: =IFERROR(AN32/AM32-1,"") -> 0.311844
A34: NSV | B34: Rs Mn | C34: Link: Raw Data - Ops KPIs | D34: ='Raw Data - Ops KPIs'!D43 -> 0 | E34: ='Raw Data - Ops KPIs'!E43 -> 0 | F34: ='Raw Data - Ops KPIs'!F43 -> 0 | G34: ='Raw Data - Ops KPIs'!G43 -> 0 | H34: ='Raw Data - Ops KPIs'!H43 -> 0 | I34: ='Raw Data - Ops KPIs'!I43 -> 0 | J34: ='Raw Data - Ops KPIs'!J43 -> 0 | K34: ='Raw Data - Ops KPIs'!K43 -> 0 | ... W34: ='Raw Data - Ops KPIs'!W43 -> 22690 | AF34: ='Raw Data - Ops KPIs'!AF43 | AG34: ='Raw Data - Ops KPIs'!AG43 | AH34: ='Raw Data - Ops KPIs'!AH43 -> 53620 | AI34: ='Raw Data - Ops KPIs'!AI43 -> 66743 | AJ34: ='Raw Data - Ops KPIs'!AJ43 -> 85050 | AK34: =AK32*AK35 -> 111611.67 | AL34: =AL32*AL35 -> 146417.09 | AM34: =AM32*AM35 -> 192076.39 | AN34: =AN32*AN35 -> 251974.26
A35: NSV / GMV | B35: % | C35: Assumption (edit me) | D35: =IFERROR(D34/D32,"") | E35: =IFERROR(E34/E32,"") | F35: =IFERROR(F34/F32,"") | G35: =IFERROR(G34/G32,"") | H35: =IFERROR(H34/H32,"") | I35: =IFERROR(I34/I32,"") | J35: =IFERROR(J34/J32,"") | K35: =IFERROR(K34/K32,"") | ... W35: =IFERROR(W34/W32,"") -> 0.58299075 | AC35: =IFERROR(AC34/AC32,"") | AD35: =IFERROR(AD34/AD32,"") | AE35: =IFERROR(AE34/AE32,"") | AF35: =IFERROR(AF34/AF32,"") | AG35: =IFERROR(AG34/AG32,"") | AH35: =IFERROR(AH34/AH32,"") -> 0.59213941 | AI35: =IFERROR(AI34/AI32,"") -> 0.56686286 | AJ35: =IFERROR(AJ34/AJ32,"") -> 0.56878218 | AK35: 0.569 | AL35: 0.569 | AM35: 0.569 | AN35: 0.569
A36: Revenue | B36: Rs Mn | C36: Link: Raw Data - Ops KPIs | D36: ='Raw Data - Ops KPIs'!D45 -> 0 | E36: ='Raw Data - Ops KPIs'!E45 -> 0 | F36: ='Raw Data - Ops KPIs'!F45 -> 0 | G36: ='Raw Data - Ops KPIs'!G45 -> 0 | H36: ='Raw Data - Ops KPIs'!H45 -> 0 | I36: ='Raw Data - Ops KPIs'!I45 -> 0 | J36: ='Raw Data - Ops KPIs'!J45 -> 0 | K36: ='Raw Data - Ops KPIs'!K45 -> 0 | ... W36: ='Raw Data - Ops KPIs'!W45 -> 24100 | AF36: ='Raw Data - Ops KPIs'!AF45 | AG36: ='Raw Data - Ops KPIs'!AG45 | AH36: ='Raw Data - Ops KPIs'!AH45 -> 44401 | AI36: ='Raw Data - Ops KPIs'!AI45 -> 72515 | AJ36: ='Raw Data - Ops KPIs'!AJ45 -> 91390 | AK36: =AK34*AK37 -> 119982.54 | AL36: =AL34*AL37 -> 157398.38 | AM36: =AM34*AM37 -> 206482.12 | AN36: =AN34*AN37 -> 270872.33
A37: Revenue / NSV | B37: % | C37: Assumption (edit me) | D37: =IFERROR(D36/D34,"") | E37: =IFERROR(E36/E34,"") | F37: =IFERROR(F36/F34,"") | G37: =IFERROR(G36/G34,"") | H37: =IFERROR(H36/H34,"") | I37: =IFERROR(I36/I34,"") | J37: =IFERROR(J36/J34,"") | K37: =IFERROR(K36/K34,"") | ... W37: =IFERROR(W36/W34,"") -> 1.0621419 | AC37: =IFERROR(AC36/AC34,"") | AD37: =IFERROR(AD36/AD34,"") | AE37: =IFERROR(AE36/AE34,"") | AF37: =IFERROR(AF36/AF34,"") | AG37: =IFERROR(AG36/AG34,"") | AH37: =IFERROR(AH36/AH34,"") -> 0.82806789 | AI37: =IFERROR(AI36/AI34,"") -> 1.086481 | AJ37: =IFERROR(AJ36/AJ34,"") -> 1.0745444 | AK37: 1.075 | AL37: 1.075 | AM37: 1.075 | AN37: 1.075
A38: Gross profit | B38: Rs Mn | C38: Link: Raw Data - Ops KPIs | D38: ='Raw Data - Ops KPIs'!D47 -> 0 | E38: ='Raw Data - Ops KPIs'!E47 -> 0 | F38: ='Raw Data - Ops KPIs'!F47 -> 0 | G38: ='Raw Data - Ops KPIs'!G47 -> 0 | H38: ='Raw Data - Ops KPIs'!H47 -> 0 | I38: ='Raw Data - Ops KPIs'!I47 -> 0 | J38: ='Raw Data - Ops KPIs'!J47 -> 0 | K38: ='Raw Data - Ops KPIs'!K47 -> 0 | ... W38: ='Raw Data - Ops KPIs'!W47 -> 10130 | AF38: ='Raw Data - Ops KPIs'!AF47 | AG38: ='Raw Data - Ops KPIs'!AG47 | AH38: ='Raw Data - Ops KPIs'!AH47 -> 17490 | AI38: ='Raw Data - Ops KPIs'!AI47 -> 29121 | AJ38: ='Raw Data - Ops KPIs'!AJ47 -> 38010 | AK38: =AK34*AK39 -> 49890.415 | AL38: =AL34*AL39 -> 65448.441 | AM38: =AM34*AM39 -> 85858.145 | AN38: =AN34*AN39 -> 112632.49
A39: Gross margin (% of NSV) | B39: % | C39: Assumption (edit me) | D39: =IFERROR(D38/D34,"") | E39: =IFERROR(E38/E34,"") | F39: =IFERROR(F38/F34,"") | G39: =IFERROR(G38/G34,"") | H39: =IFERROR(H38/H34,"") | I39: =IFERROR(I38/I34,"") | J39: =IFERROR(J38/J34,"") | K39: =IFERROR(K38/K34,"") | ... W39: =IFERROR(W38/W34,"") -> 0.44645218 | AC39: =IFERROR(AC38/AC34,"") | AD39: =IFERROR(AD38/AD34,"") | AE39: =IFERROR(AE38/AE34,"") | AF39: =IFERROR(AF38/AF34,"") | AG39: =IFERROR(AG38/AG34,"") | AH39: =IFERROR(AH38/AH34,"") -> 0.32618426 | AI39: =IFERROR(AI38/AI34,"") -> 0.43631542 | AJ39: =IFERROR(AJ38/AJ34,"") -> 0.44691358 | AK39: 0.447 | AL39: 0.447 | AM39: 0.447 | AN39: 0.447
A40: Fulfilment cost | B40: Rs Mn | C40: Link: Raw Data - Ops KPIs | D40: ='Raw Data - Ops KPIs'!D49 -> 0 | E40: ='Raw Data - Ops KPIs'!E49 -> 0 | F40: ='Raw Data - Ops KPIs'!F49 -> 0 | G40: ='Raw Data - Ops KPIs'!G49 -> 0 | H40: ='Raw Data - Ops KPIs'!H49 -> 0 | I40: ='Raw Data - Ops KPIs'!I49 -> 0 | J40: ='Raw Data - Ops KPIs'!J49 -> 0 | K40: ='Raw Data - Ops KPIs'!K49 -> 0 | ... W40: ='Raw Data - Ops KPIs'!W49 -> 2150 | AF40: ='Raw Data - Ops KPIs'!AF49 | AG40: ='Raw Data - Ops KPIs'!AG49 | AH40: ='Raw Data - Ops KPIs'!AH49 -> 3790 | AI40: ='Raw Data - Ops KPIs'!AI49 -> 6284 | AJ40: ='Raw Data - Ops KPIs'!AJ49 -> 7940 | AK40: =AK34*AK41 -> 10379.885 | AL40: =AL34*AL41 -> 13616.79 | AM40: =AM34*AM41 -> 17863.104 | AN40: =AN34*AN41 -> 23433.606
A41: Fulfilment (% of NSV) | B41: % | C41: Assumption (edit me) | D41: =IFERROR(D40/D34,"") | E41: =IFERROR(E40/E34,"") | F41: =IFERROR(F40/F34,"") | G41: =IFERROR(G40/G34,"") | H41: =IFERROR(H40/H34,"") | I41: =IFERROR(I40/I34,"") | J41: =IFERROR(J40/J34,"") | K41: =IFERROR(K40/K34,"") | ... W41: =IFERROR(W40/W34,"") -> 0.094755399 | AC41: =IFERROR(AC40/AC34,"") | AD41: =IFERROR(AD40/AD34,"") | AE41: =IFERROR(AE40/AE34,"") | AF41: =IFERROR(AF40/AF34,"") | AG41: =IFERROR(AG40/AG34,"") | AH41: =IFERROR(AH40/AH34,"") -> 0.070682581 | AI41: =IFERROR(AI40/AI34,"") -> 0.094152196 | AJ41: =IFERROR(AJ40/AJ34,"") -> 0.093356849 | AK41: 0.093 | AL41: 0.093 | AM41: 0.093 | AN41: 0.093
A42: Marketing & S&D expense (combined) | B42: Rs Mn | C42: Formula | D42: =IF(AND(D44="",D45=""),"",IF(D44="",0,D44)+IF(D45="",0,D45)) -> 0 | E42: =IF(AND(E44="",E45=""),"",IF(E44="",0,E44)+IF(E45="",0,E45)) -> 0 | F42: =IF(AND(F44="",F45=""),"",IF(F44="",0,F44)+IF(F45="",0,F45)) -> 0 | G42: =IF(AND(G44="",G45=""),"",IF(G44="",0,G44)+IF(G45="",0,G45)) -> 0 | H42: =IF(AND(H44="",H45=""),"",IF(H44="",0,H44)+IF(H45="",0,H45)) -> 0 | I42: =IF(AND(I44="",I45=""),"",IF(I44="",0,I44)+IF(I45="",0,I45)) -> 0 | J42: =IF(AND(J44="",J45=""),"",IF(J44="",0,J44)+IF(J45="",0,J45)) -> 0 | K42: =IF(AND(K44="",K45=""),"",IF(K44="",0,K44)+IF(K45="",0,K45)) -> 0 | ... W42: =IF(AND(W44="",W45=""),"",IF(W44="",0,W44)+IF(W45="",0,W45)) -> 2780 | AC42: =IF(AND(AC44="",AC45=""),"",IF(AC44="",0,AC44)+IF(AC45="",0,AC45)) | AD42: =IF(AND(AD44="",AD45=""),"",IF(AD44="",0,AD44)+IF(AD45="",0,AD45)) | AE42: =IF(AND(AE44="",AE45=""),"",IF(AE44="",0,AE44)+IF(AE45="",0,AE45)) | AF42: =IF(AND(AF44="",AF45=""),"",IF(AF44="",0,AF44)+IF(AF45="",0,AF45)) | AG42: =IF(AND(AG44="",AG45=""),"",IF(AG44="",0,AG44)+IF(AG45="",0,AG45)) | AH42: =IF(AND(AH44="",AH45=""),"",IF(AH44="",0,AH44)+IF(AH45="",0,AH45)) -> 4665 | AI42: =IF(AND(AI44="",AI45=""),"",IF(AI44="",0,AI44)+IF(AI45="",0,AI45)) -> 8131 | AJ42: =IF(AND(AJ44="",AJ45=""),"",IF(AJ44="",0,AJ44)+IF(AJ45="",0,AJ45)) -> 10910 | AK42: =AK34*AK43 -> 14286.293 | AL42: =AL34*AL43 -> 18741.388 | AM42: =AM34*AM43 -> 24585.778 | AN42: =AN34*AN43 -> 32252.705
A43: Marketing & S&D (% of NSV, combined) | B43: % | C43: Assumption (edit me) | D43: =IFERROR(D42/D34,"") | E43: =IFERROR(E42/E34,"") | F43: =IFERROR(F42/F34,"") | G43: =IFERROR(G42/G34,"") | H43: =IFERROR(H42/H34,"") | I43: =IFERROR(I42/I34,"") | J43: =IFERROR(J42/J34,"") | K43: =IFERROR(K42/K34,"") | ... W43: =IFERROR(W42/W34,"") -> 0.12252093 | AC43: =IFERROR(AC42/AC34,"") | AD43: =IFERROR(AD42/AD34,"") | AE43: =IFERROR(AE42/AE34,"") | AF43: =IFERROR(AF42/AF34,"") | AG43: =IFERROR(AG42/AG34,"") | AH43: =IFERROR(AH42/AH34,"") -> 0.087001119 | AI43: =IFERROR(AI42/AI34,"") -> 0.12182551 | AJ43: =IFERROR(AJ42/AJ34,"") -> 0.12827748 | AK43: 0.128 | AL43: 0.128 | AM43: 0.128 | AN43: 0.128
A44: o/w Marketing (historical, linked) | B44: Rs Mn | C44: Link: Raw Data - Ops KPIs | D44: ='Raw Data - Ops KPIs'!D50 -> 0 | E44: ='Raw Data - Ops KPIs'!E50 -> 0 | F44: ='Raw Data - Ops KPIs'!F50 -> 0 | G44: ='Raw Data - Ops KPIs'!G50 -> 0 | H44: ='Raw Data - Ops KPIs'!H50 -> 0 | I44: ='Raw Data - Ops KPIs'!I50 -> 0 | J44: ='Raw Data - Ops KPIs'!J50 -> 0 | K44: ='Raw Data - Ops KPIs'!K50 -> 0 | ... W44: ='Raw Data - Ops KPIs'!W50 -> 2780 | AF44: ='Raw Data - Ops KPIs'!AF50 | AG44: ='Raw Data - Ops KPIs'!AG50 | AH44: ='Raw Data - Ops KPIs'!AH50 -> 3595 | AI44: ='Raw Data - Ops KPIs'!AI50 -> 6197 | AJ44: ='Raw Data - Ops KPIs'!AJ50 -> 10910
A45: o/w Selling & distribution (historical, linked) | B45: Rs Mn | C45: Link: Raw Data - Ops KPIs | D45: ='Raw Data - Ops KPIs'!D51 -> 0 | E45: ='Raw Data - Ops KPIs'!E51 -> 0 | F45: ='Raw Data - Ops KPIs'!F51 -> 0 | G45: ='Raw Data - Ops KPIs'!G51 -> 0 | H45: ='Raw Data - Ops KPIs'!H51 -> 0 | I45: ='Raw Data - Ops KPIs'!I51 -> 0 | J45: ='Raw Data - Ops KPIs'!J51 -> 0 | K45: ='Raw Data - Ops KPIs'!K51 -> 0 | ... W45: ='Raw Data - Ops KPIs'!W51 -> 0 | AF45: ='Raw Data - Ops KPIs'!AF51 | AG45: ='Raw Data - Ops KPIs'!AG51 | AH45: ='Raw Data - Ops KPIs'!AH51 -> 1070 | AI45: ='Raw Data - Ops KPIs'!AI51 -> 1934 | AJ45: ='Raw Data - Ops KPIs'!AJ51 -> 0
A46: Contribution profit | B46: Rs Mn | C46: Formula | D46: =IFERROR(D38-D40-D42,"") -> 0 | E46: =IFERROR(E38-E40-E42,"") -> 0 | F46: =IFERROR(F38-F40-F42,"") -> 0 | G46: =IFERROR(G38-G40-G42,"") -> 0 | H46: =IFERROR(H38-H40-H42,"") -> 0 | I46: =IFERROR(I38-I40-I42,"") -> 0 | J46: =IFERROR(J38-J40-J42,"") -> 0 | K46: =IFERROR(K38-K40-K42,"") -> 0 | ... W46: =IFERROR(W38-W40-W42,"") -> 5200 | AC46: =IFERROR(AC38-AC40-AC42,"") | AD46: =IFERROR(AD38-AD40-AD42,"") | AE46: =IFERROR(AE38-AE40-AE42,"") | AF46: =IFERROR(AF38-AF40-AF42,"") | AG46: =IFERROR(AG38-AG40-AG42,"") | AH46: =IFERROR(AH38-AH40-AH42,"") -> 9035 | AI46: =IFERROR(AI38-AI40-AI42,"") -> 14706 | AJ46: =IFERROR(AJ38-AJ40-AJ42,"") -> 19160 | ... AN46: =IFERROR(AN38-AN40-AN42,"") -> 56946.182
A47: Contribution margin (% of NSV) | B47: % | C47: Formula | D47: =IFERROR(D46/D34,"") | E47: =IFERROR(E46/E34,"") | F47: =IFERROR(F46/F34,"") | G47: =IFERROR(G46/G34,"") | H47: =IFERROR(H46/H34,"") | I47: =IFERROR(I46/I34,"") | J47: =IFERROR(J46/J34,"") | K47: =IFERROR(K46/K34,"") | ... W47: =IFERROR(W46/W34,"") -> 0.22917585 | AC47: =IFERROR(AC46/AC34,"") | AD47: =IFERROR(AD46/AD34,"") | AE47: =IFERROR(AE46/AE34,"") | AF47: =IFERROR(AF46/AF34,"") | AG47: =IFERROR(AG46/AG34,"") | AH47: =IFERROR(AH46/AH34,"") -> 0.16850056 | AI47: =IFERROR(AI46/AI34,"") -> 0.22033771 | AJ47: =IFERROR(AJ46/AJ34,"") -> 0.22527925 | ... AN47: =IFERROR(AN46/AN34,"") -> 0.226
A48: Other expenses (G&A + employee) | B48: Rs Mn | C48: Link: Raw Data - Ops KPIs | D48: ='Raw Data - Ops KPIs'!D54 -> 0 | E48: ='Raw Data - Ops KPIs'!E54 -> 0 | F48: ='Raw Data - Ops KPIs'!F54 -> 0 | G48: ='Raw Data - Ops KPIs'!G54 -> 0 | H48: ='Raw Data - Ops KPIs'!H54 -> 0 | I48: ='Raw Data - Ops KPIs'!I54 -> 0 | J48: ='Raw Data - Ops KPIs'!J54 -> 0 | K48: ='Raw Data - Ops KPIs'!K54 -> 0 | ... W48: ='Raw Data - Ops KPIs'!W54 -> 2870 | AF48: ='Raw Data - Ops KPIs'!AF54 | AG48: ='Raw Data - Ops KPIs'!AG54 | AH48: ='Raw Data - Ops KPIs'!AH54 -> 5480 | AI48: ='Raw Data - Ops KPIs'!AI54 -> 8775 | AJ48: ='Raw Data - Ops KPIs'!AJ54 -> 10950 | AK48: =AK34*AK49 -> 14397.905 | AL48: =AL34*AL49 -> 18887.805 | AM48: =AM34*AM49 -> 24777.854 | AN48: =AN34*AN49 -> 32504.679
A49: Other expenses (% of NSV) | B49: % | C49: Assumption (edit me) | D49: =IFERROR(D48/D34,"") | E49: =IFERROR(E48/E34,"") | F49: =IFERROR(F48/F34,"") | G49: =IFERROR(G48/G34,"") | H49: =IFERROR(H48/H34,"") | I49: =IFERROR(I48/I34,"") | J49: =IFERROR(J48/J34,"") | K49: =IFERROR(K48/K34,"") | ... W49: =IFERROR(W48/W34,"") -> 0.12648744 | AC49: =IFERROR(AC48/AC34,"") | AD49: =IFERROR(AD48/AD34,"") | AE49: =IFERROR(AE48/AE34,"") | AF49: =IFERROR(AF48/AF34,"") | AG49: =IFERROR(AG48/AG34,"") | AH49: =IFERROR(AH48/AH34,"") -> 0.10220067 | AI49: =IFERROR(AI48/AI34,"") -> 0.13147446 | AJ49: =IFERROR(AJ48/AJ34,"") -> 0.1287478 | AK49: 0.129 | AL49: 0.129 | AM49: 0.129 | AN49: 0.129
A50: EBITDA | B50: Rs Mn | C50: Formula | D50: =IFERROR(D46-D48,"") -> 0 | E50: =IFERROR(E46-E48,"") -> 0 | F50: =IFERROR(F46-F48,"") -> 0 | G50: =IFERROR(G46-G48,"") -> 0 | H50: =IFERROR(H46-H48,"") -> 0 | I50: =IFERROR(I46-I48,"") -> 0 | J50: =IFERROR(J46-J48,"") -> 0 | K50: =IFERROR(K46-K48,"") -> 0 | ... W50: =IFERROR(W46-W48,"") -> 2330 | AC50: =IFERROR(AC46-AC48,"") | AD50: =IFERROR(AD46-AD48,"") | AE50: =IFERROR(AE46-AE48,"") | AF50: =IFERROR(AF46-AF48,"") | AG50: =IFERROR(AG46-AG48,"") | AH50: =IFERROR(AH46-AH48,"") -> 3555 | AI50: =IFERROR(AI46-AI48,"") -> 5931 | AJ50: =IFERROR(AJ46-AJ48,"") -> 8210 | ... AN50: =IFERROR(AN46-AN48,"") -> 24441.503
A51: EBITDA margin (% of NSV) | B51: % | C51: Formula | D51: =IFERROR(D50/D34,"") | E51: =IFERROR(E50/E34,"") | F51: =IFERROR(F50/F34,"") | G51: =IFERROR(G50/G34,"") | H51: =IFERROR(H50/H34,"") | I51: =IFERROR(I50/I34,"") | J51: =IFERROR(J50/J34,"") | K51: =IFERROR(K50/K34,"") | ... W51: =IFERROR(W50/W34,"") -> 0.10268841 | AC51: =IFERROR(AC50/AC34,"") | AD51: =IFERROR(AD50/AD34,"") | AE51: =IFERROR(AE50/AE34,"") | AF51: =IFERROR(AF50/AF34,"") | AG51: =IFERROR(AG50/AG34,"") | AH51: =IFERROR(AH50/AH34,"") -> 0.066299888 | AI51: =IFERROR(AI50/AI34,"") -> 0.088863252 | AJ51: =IFERROR(AJ50/AJ34,"") -> 0.096531452 | ... AN51: =IFERROR(AN50/AN34,"") -> 0.097
A53: FASHION
A54: Definition: Nykaa Fashion + LBB + Nykaa Man Lifestyle.
A55: Annual transacting customers (AUTC) | B55: mn | C55: Link: Raw Data - Ops KPIs | D55: ='Raw Data - Ops KPIs'!D93 -> 1 | E55: ='Raw Data - Ops KPIs'!E93 -> 1.3 | F55: ='Raw Data - Ops KPIs'!F93 -> 1.6 | G55: ='Raw Data - Ops KPIs'!G93 -> 1.8 | H55: ='Raw Data - Ops KPIs'!H93 -> 2 | I55: ='Raw Data - Ops KPIs'!I93 -> 2.1 | J55: ='Raw Data - Ops KPIs'!J93 -> 2.4 | K55: ='Raw Data - Ops KPIs'!K93 -> 2.5 | ... W55: ='Raw Data - Ops KPIs'!W93 -> 4.3 | AF55: ='Raw Data - Ops KPIs'!AF93 -> 1.8 | AG55: ='Raw Data - Ops KPIs'!AG93 -> 2.5 | AH55: ='Raw Data - Ops KPIs'!AH93 -> 3 | AI55: ='Raw Data - Ops KPIs'!AI93 -> 3.2 | AJ55: ='Raw Data - Ops KPIs'!AJ93 -> 4.3 | AK55: =AJ55*(1+AK56) -> 5.7792 | AL55: =AK55*(1+AL56) -> 7.7672448 | AM55: =AL55*(1+AM56) -> 10.439177 | AN55: =AM55*(1+AN56) -> 14.030254
A56: YoY growth | B56: % | C56: Assumption (edit me) | H56: =IFERROR(H55/D55-1,"") -> 1 | I56: =IFERROR(I55/E55-1,"") -> 0.61538462 | J56: =IFERROR(J55/F55-1,"") -> 0.5 | K56: =IFERROR(K55/G55-1,"") -> 0.38888889 | L56: =IFERROR(L55/H55-1,"") -> 0.3 | M56: =IFERROR(M55/I55-1,"") -> 0.33333333 | N56: =IFERROR(N55/J55-1,"") -> 0.20833333 | O56: =IFERROR(O55/K55-1,"") -> 0.2 | ... W56: =IFERROR(W55/S55-1,"") -> 0.34375 | AD56: =IFERROR(AD55/AC55-1,"") | AE56: =IFERROR(AE55/AD55-1,"") | AF56: =IFERROR(AF55/AE55-1,"") | AG56: =IFERROR(AG55/AF55-1,"") -> 0.38888889 | AH56: =IFERROR(AH55/AG55-1,"") -> 0.2 | AI56: =IFERROR(AI55/AH55-1,"") -> 0.066666667 | AJ56: =IFERROR(AJ55/AI55-1,"") -> 0.34375 | AK56: 0.344 | AL56: 0.344 | AM56: 0.344 | AN56: 0.344
A57: Number of orders | B57: mn | C57: Link: Raw Data - Ops KPIs | D57: ='Raw Data - Ops KPIs'!D95 -> 1.1 | E57: ='Raw Data - Ops KPIs'!E95 -> 1.3 | F57: ='Raw Data - Ops KPIs'!F95 -> 1.3 | G57: ='Raw Data - Ops KPIs'!G95 -> 1.3 | H57: ='Raw Data - Ops KPIs'!H95 -> 1.5 | I57: ='Raw Data - Ops KPIs'!I95 -> 1.4 | J57: ='Raw Data - Ops KPIs'!J95 -> 1.7 | K57: ='Raw Data - Ops KPIs'!K95 -> 1.4 | ... W57: ='Raw Data - Ops KPIs'!W95 -> 2.7 | AF57: ='Raw Data - Ops KPIs'!AF95 -> 5 | AG57: ='Raw Data - Ops KPIs'!AG95 -> 6 | AH57: ='Raw Data - Ops KPIs'!AH95 -> 7 | AI57: ='Raw Data - Ops KPIs'!AI95 -> 7.7 | AJ57: ='Raw Data - Ops KPIs'!AJ95 -> 10.1 | AK57: =AK55*AK58 -> 13.58112 | AL57: =AL55*AL58 -> 18.253025 | AM57: =AM55*AM58 -> 24.532066 | AN57: =AN55*AN58 -> 32.971097
A58: Average order frequency | B58: x | C58: Assumption (edit me) | D58: =IFERROR(D57/D55,"") -> 1.1 | E58: =IFERROR(E57/E55,"") -> 1 | F58: =IFERROR(F57/F55,"") -> 0.8125 | G58: =IFERROR(G57/G55,"") -> 0.72222222 | H58: =IFERROR(H57/H55,"") -> 0.75 | I58: =IFERROR(I57/I55,"") -> 0.66666667 | J58: =IFERROR(J57/J55,"") -> 0.70833333 | K58: =IFERROR(K57/K55,"") -> 0.56 | ... W58: =IFERROR(W57/W55,"") -> 0.62790698 | AC58: =IFERROR(AC57/AC55,"") | AD58: =IFERROR(AD57/AD55,"") | AE58: =IFERROR(AE57/AE55,"") | AF58: =IFERROR(AF57/AF55,"") -> 2.7777778 | AG58: =IFERROR(AG57/AG55,"") -> 2.4 | AH58: =IFERROR(AH57/AH55,"") -> 2.3333333 | AI58: =IFERROR(AI57/AI55,"") -> 2.40625 | AJ58: =IFERROR(AJ57/AJ55,"") -> 2.3488372 | AK58: 2.35 | AL58: 2.35 | AM58: 2.35 | AN58: 2.35
A59: Average order value | B59: Rs | C59: Formula | D59: =IFERROR(D61/D57,"") -> 0 | E59: =IFERROR(E61/E57,"") -> 0 | F59: =IFERROR(F61/F57,"") -> 0 | G59: =IFERROR(G61/G57,"") -> 0 | H59: =IFERROR(H61/H57,"") -> 0 | I59: =IFERROR(I61/I57,"") -> 0 | J59: =IFERROR(J61/J57,"") -> 0 | K59: =IFERROR(K61/K57,"") -> 0 | ... W59: =IFERROR(W61/W57,"") -> 4940.7407 | AC59: =IFERROR(AC61/AC57,"") | AD59: =IFERROR(AD61/AD57,"") | AE59: =IFERROR(AE61/AE57,"") | AF59: =IFERROR(AF61/AF57,"") | AG59: =IFERROR(AG61/AG57,"") | AH59: =IFERROR(AH61/AH57,"") -> 4836.4286 | AI59: =IFERROR(AI61/AI57,"") -> 4940.6494 | AJ59: =IFERROR(AJ61/AJ57,"") -> 4904.9505 | AK59: =AJ59*(1+AK60) -> 4870.6158 | AL59: =AK59*(1+AL60) -> 4836.5215 | AM59: =AL59*(1+AM60) -> 4802.6659 | AN59: =AM59*(1+AN60) -> 4769.0472
A60: YoY growth | B60: % | C60: Assumption (edit me) | AK60: -0.007 | AL60: -0.007 | AM60: -0.007 | AN60: -0.007
A61: GMV | B61: Rs Mn | C61: Link: Raw Data - Ops KPIs | D61: ='Raw Data - Ops KPIs'!D98 -> 0 | E61: ='Raw Data - Ops KPIs'!E98 -> 0 | F61: ='Raw Data - Ops KPIs'!F98 -> 0 | G61: ='Raw Data - Ops KPIs'!G98 -> 0 | H61: ='Raw Data - Ops KPIs'!H98 -> 0 | I61: ='Raw Data - Ops KPIs'!I98 -> 0 | J61: ='Raw Data - Ops KPIs'!J98 -> 0 | K61: ='Raw Data - Ops KPIs'!K98 -> 0 | ... W61: ='Raw Data - Ops KPIs'!W98 -> 13340 | AF61: ='Raw Data - Ops KPIs'!AF98 | AG61: ='Raw Data - Ops KPIs'!AG98 | AH61: ='Raw Data - Ops KPIs'!AH98 -> 33855 | AI61: ='Raw Data - Ops KPIs'!AI98 -> 38043 | AJ61: ='Raw Data - Ops KPIs'!AJ98 -> 49540 | AK61: =AK57*AK59 -> 66148.418 | AL61: =AL57*AL59 -> 88281.15 | AM61: =AM57*AM59 -> 117819.32 | AN61: =AN57*AN59 -> 157240.72
A62: YoY growth | B62: % | C62: Formula | H62: =IFERROR(H61/D61-1,"") | I62: =IFERROR(I61/E61-1,"") | J62: =IFERROR(J61/F61-1,"") | K62: =IFERROR(K61/G61-1,"") | L62: =IFERROR(L61/H61-1,"") | M62: =IFERROR(M61/I61-1,"") | N62: =IFERROR(N61/J61-1,"") | O62: =IFERROR(O61/K61-1,"") | ... W62: =IFERROR(W61/S61-1,"") -> 0.28640309 | AD62: =IFERROR(AD61/AC61-1,"") | AE62: =IFERROR(AE61/AD61-1,"") | AF62: =IFERROR(AF61/AE61-1,"") | AG62: =IFERROR(AG61/AF61-1,"") | AH62: =IFERROR(AH61/AG61-1,"") | AI62: =IFERROR(AI61/AH61-1,"") -> 0.12370403 | AJ62: =IFERROR(AJ61/AI61-1,"") -> 0.30221066 | AK62: =IFERROR(AK61/AJ61-1,"") -> 0.33525269 | ... AN62: =IFERROR(AN61/AM61-1,"") -> 0.334592
A63: NSV | B63: Rs Mn | C63: Link: Raw Data - Ops KPIs | D63: ='Raw Data - Ops KPIs'!D101 -> 0 | E63: ='Raw Data - Ops KPIs'!E101 -> 0 | F63: ='Raw Data - Ops KPIs'!F101 -> 0 | G63: ='Raw Data - Ops KPIs'!G101 -> 0 | H63: ='Raw Data - Ops KPIs'!H101 -> 0 | I63: ='Raw Data - Ops KPIs'!I101 -> 0 | J63: ='Raw Data - Ops KPIs'!J101 -> 0 | K63: ='Raw Data - Ops KPIs'!K101 -> 0 | ... W63: ='Raw Data - Ops KPIs'!W101 -> 3970 | AF63: ='Raw Data - Ops KPIs'!AF101 | AG63: ='Raw Data - Ops KPIs'!AG101 | AH63: ='Raw Data - Ops KPIs'!AH101 -> 9878 | AI63: ='Raw Data - Ops KPIs'!AI101 -> 11257 | AJ63: ='Raw Data - Ops KPIs'!AJ101 -> 14470 | AK63: =AK61*AK64 -> 19315.338 | AL63: =AL61*AL64 -> 25778.096 | AM63: =AM61*AM64 -> 34403.24 | AN63: =AN61*AN64 -> 45914.289
A64: NSV / GMV | B64: % | C64: Assumption (edit me) | D64: =IFERROR(D63/D61,"") | E64: =IFERROR(E63/E61,"") | F64: =IFERROR(F63/F61,"") | G64: =IFERROR(G63/G61,"") | H64: =IFERROR(H63/H61,"") | I64: =IFERROR(I63/I61,"") | J64: =IFERROR(J63/J61,"") | K64: =IFERROR(K63/K61,"") | ... W64: =IFERROR(W63/W61,"") -> 0.2976012 | AC64: =IFERROR(AC63/AC61,"") | AD64: =IFERROR(AD63/AD61,"") | AE64: =IFERROR(AE63/AE61,"") | AF64: =IFERROR(AF63/AF61,"") | AG64: =IFERROR(AG63/AG61,"") | AH64: =IFERROR(AH63/AH61,"") -> 0.29177374 | AI64: =IFERROR(AI63/AI61,"") -> 0.29590201 | AJ64: =IFERROR(AJ63/AJ61,"") -> 0.2920872 | AK64: 0.292 | AL64: 0.292 | AM64: 0.292 | AN64: 0.292
A65: Revenue | B65: Rs Mn | C65: Link: Raw Data - Ops KPIs | D65: ='Raw Data - Ops KPIs'!D103 -> 0 | E65: ='Raw Data - Ops KPIs'!E103 -> 0 | F65: ='Raw Data - Ops KPIs'!F103 -> 900 | G65: ='Raw Data - Ops KPIs'!G103 -> 0 | H65: ='Raw Data - Ops KPIs'!H103 -> 0 | I65: ='Raw Data - Ops KPIs'!I103 -> 0 | J65: ='Raw Data - Ops KPIs'!J103 -> 1339 | K65: ='Raw Data - Ops KPIs'!K103 -> 0 | ... W65: ='Raw Data - Ops KPIs'!W103 -> 2250 | AF65: ='Raw Data - Ops KPIs'!AF103 -> 900 | AG65: ='Raw Data - Ops KPIs'!AG103 -> 1339 | AH65: ='Raw Data - Ops KPIs'!AH103 -> 5684 | AI65: ='Raw Data - Ops KPIs'!AI103 -> 6747 | AJ65: ='Raw Data - Ops KPIs'!AJ103 -> 8320 | AK65: =AK63*AK66 -> 11106.319 | AL65: =AL63*AL66 -> 14822.405 | AM65: =AM63*AM66 -> 19781.863 | AN65: =AN63*AN66 -> 26400.716
A66: Revenue / NSV | B66: % | C66: Assumption (edit me) | D66: =IFERROR(D65/D63,"") | E66: =IFERROR(E65/E63,"") | F66: =IFERROR(F65/F63,"") | G66: =IFERROR(G65/G63,"") | H66: =IFERROR(H65/H63,"") | I66: =IFERROR(I65/I63,"") | J66: =IFERROR(J65/J63,"") | K66: =IFERROR(K65/K63,"") | ... W66: =IFERROR(W65/W63,"") -> 0.56675063 | AC66: =IFERROR(AC65/AC63,"") | AD66: =IFERROR(AD65/AD63,"") | AE66: =IFERROR(AE65/AE63,"") | AF66: =IFERROR(AF65/AF63,"") | AG66: =IFERROR(AG65/AG63,"") | AH66: =IFERROR(AH65/AH63,"") -> 0.57542013 | AI66: =IFERROR(AI65/AI63,"") -> 0.5993604 | AJ66: =IFERROR(AJ65/AJ63,"") -> 0.57498272 | AK66: 0.575 | AL66: 0.575 | AM66: 0.575 | AN66: 0.575
A67: Gross profit | B67: Rs Mn | C67: Link: Raw Data - Ops KPIs | D67: ='Raw Data - Ops KPIs'!D105 -> 0 | E67: ='Raw Data - Ops KPIs'!E105 -> 0 | F67: ='Raw Data - Ops KPIs'!F105 -> 0 | G67: ='Raw Data - Ops KPIs'!G105 -> 0 | H67: ='Raw Data - Ops KPIs'!H105 -> 0 | I67: ='Raw Data - Ops KPIs'!I105 -> 0 | J67: ='Raw Data - Ops KPIs'!J105 -> 0 | K67: ='Raw Data - Ops KPIs'!K105 -> 0 | ... W67: ='Raw Data - Ops KPIs'!W105 -> 1840 | AF67: ='Raw Data - Ops KPIs'!AF105 | AG67: ='Raw Data - Ops KPIs'!AG105 | AH67: ='Raw Data - Ops KPIs'!AH105 -> 4429 | AI67: ='Raw Data - Ops KPIs'!AI105 -> 5519 | AJ67: ='Raw Data - Ops KPIs'!AJ105 -> 6920 | AK67: =AK63*AK68 -> 9232.7316 | AL67: =AL63*AL68 -> 12321.93 | AM67: =AM63*AM68 -> 16444.749 | AN67: =AN63*AN68 -> 21947.03
A68: Gross margin (% of NSV) | B68: % | C68: Assumption (edit me) | D68: =IFERROR(D67/D63,"") | E68: =IFERROR(E67/E63,"") | F68: =IFERROR(F67/F63,"") | G68: =IFERROR(G67/G63,"") | H68: =IFERROR(H67/H63,"") | I68: =IFERROR(I67/I63,"") | J68: =IFERROR(J67/J63,"") | K68: =IFERROR(K67/K63,"") | ... W68: =IFERROR(W67/W63,"") -> 0.46347607 | AC68: =IFERROR(AC67/AC63,"") | AD68: =IFERROR(AD67/AD63,"") | AE68: =IFERROR(AE67/AE63,"") | AF68: =IFERROR(AF67/AF63,"") | AG68: =IFERROR(AG67/AG63,"") | AH68: =IFERROR(AH67/AH63,"") -> 0.44837012 | AI68: =IFERROR(AI67/AI63,"") -> 0.49027272 | AJ68: =IFERROR(AJ67/AJ63,"") -> 0.47823082 | AK68: 0.478 | AL68: 0.478 | AM68: 0.478 | AN68: 0.478
A69: Fulfilment cost | B69: Rs Mn | C69: Link: Raw Data - Ops KPIs | D69: ='Raw Data - Ops KPIs'!D107 -> 0 | E69: ='Raw Data - Ops KPIs'!E107 -> 0 | F69: ='Raw Data - Ops KPIs'!F107 -> 0 | G69: ='Raw Data - Ops KPIs'!G107 -> 0 | H69: ='Raw Data - Ops KPIs'!H107 -> 0 | I69: ='Raw Data - Ops KPIs'!I107 -> 0 | J69: ='Raw Data - Ops KPIs'!J107 -> 0 | K69: ='Raw Data - Ops KPIs'!K107 -> 0 | ... W69: ='Raw Data - Ops KPIs'!W107 -> 450 | AF69: ='Raw Data - Ops KPIs'!AF107 | AG69: ='Raw Data - Ops KPIs'!AG107 | AH69: ='Raw Data - Ops KPIs'!AH107 -> 1097 | AI69: ='Raw Data - Ops KPIs'!AI107 -> 1095 | AJ69: ='Raw Data - Ops KPIs'!AJ107 -> 1630 | AK69: =AK63*AK70 -> 2182.6332 | AL69: =AL63*AL70 -> 2912.9248 | AM69: =AM63*AM70 -> 3887.5662 | AN69: =AN63*AN70 -> 5188.3147
A70: Fulfilment (% of NSV) | B70: % | C70: Assumption (edit me) | D70: =IFERROR(D69/D63,"") | E70: =IFERROR(E69/E63,"") | F70: =IFERROR(F69/F63,"") | G70: =IFERROR(G69/G63,"") | H70: =IFERROR(H69/H63,"") | I70: =IFERROR(I69/I63,"") | J70: =IFERROR(J69/J63,"") | K70: =IFERROR(K69/K63,"") | ... W70: =IFERROR(W69/W63,"") -> 0.11335013 | AC70: =IFERROR(AC69/AC63,"") | AD70: =IFERROR(AD69/AD63,"") | AE70: =IFERROR(AE69/AE63,"") | AF70: =IFERROR(AF69/AF63,"") | AG70: =IFERROR(AG69/AG63,"") | AH70: =IFERROR(AH69/AH63,"") -> 0.11105487 | AI70: =IFERROR(AI69/AI63,"") -> 0.097272808 | AJ70: =IFERROR(AJ69/AJ63,"") -> 0.11264686 | AK70: 0.113 | AL70: 0.113 | AM70: 0.113 | AN70: 0.113
A71: Marketing & S&D expense (combined) | B71: Rs Mn | C71: Formula | D71: =IF(AND(D73="",D74=""),"",IF(D73="",0,D73)+IF(D74="",0,D74)) -> 0 | E71: =IF(AND(E73="",E74=""),"",IF(E73="",0,E73)+IF(E74="",0,E74)) -> 0 | F71: =IF(AND(F73="",F74=""),"",IF(F73="",0,F73)+IF(F74="",0,F74)) -> 0 | G71: =IF(AND(G73="",G74=""),"",IF(G73="",0,G73)+IF(G74="",0,G74)) -> 0 | H71: =IF(AND(H73="",H74=""),"",IF(H73="",0,H73)+IF(H74="",0,H74)) -> 0 | I71: =IF(AND(I73="",I74=""),"",IF(I73="",0,I73)+IF(I74="",0,I74)) -> 0 | J71: =IF(AND(J73="",J74=""),"",IF(J73="",0,J73)+IF(J74="",0,J74)) -> 0 | K71: =IF(AND(K73="",K74=""),"",IF(K73="",0,K73)+IF(K74="",0,K74)) -> 0 | ... W71: =IF(AND(W73="",W74=""),"",IF(W73="",0,W73)+IF(W74="",0,W74)) -> 910 | AC71: =IF(AND(AC73="",AC74=""),"",IF(AC73="",0,AC73)+IF(AC74="",0,AC74)) | AD71: =IF(AND(AD73="",AD74=""),"",IF(AD73="",0,AD73)+IF(AD74="",0,AD74)) | AE71: =IF(AND(AE73="",AE74=""),"",IF(AE73="",0,AE73)+IF(AE74="",0,AE74)) | AF71: =IF(AND(AF73="",AF74=""),"",IF(AF73="",0,AF73)+IF(AF74="",0,AF74)) | AG71: =IF(AND(AG73="",AG74=""),"",IF(AG73="",0,AG73)+IF(AG74="",0,AG74)) | AH71: =IF(AND(AH73="",AH74=""),"",IF(AH73="",0,AH73)+IF(AH74="",0,AH74)) -> 2047 | AI71: =IF(AND(AI73="",AI74=""),"",IF(AI73="",0,AI73)+IF(AI74="",0,AI74)) -> 3540 | AJ71: =IF(AND(AJ73="",AJ74=""),"",IF(AJ73="",0,AJ73)+IF(AJ74="",0,AJ74)) -> 3820 | AK71: =AK63*AK72 -> 5099.2493 | AL71: =AL63*AL72 -> 6805.4173 | AM71: =AM63*AM72 -> 9082.4554 | AN71: =AN63*AN72 -> 12121.372
A72: Marketing & S&D (% of NSV, combined) | B72: % | C72: Assumption (edit me) | D72: =IFERROR(D71/D63,"") | E72: =IFERROR(E71/E63,"") | F72: =IFERROR(F71/F63,"") | G72: =IFERROR(G71/G63,"") | H72: =IFERROR(H71/H63,"") | I72: =IFERROR(I71/I63,"") | J72: =IFERROR(J71/J63,"") | K72: =IFERROR(K71/K63,"") | ... W72: =IFERROR(W71/W63,"") -> 0.22921914 | AC72: =IFERROR(AC71/AC63,"") | AD72: =IFERROR(AD71/AD63,"") | AE72: =IFERROR(AE71/AE63,"") | AF72: =IFERROR(AF71/AF63,"") | AG72: =IFERROR(AG71/AG63,"") | AH72: =IFERROR(AH71/AH63,"") -> 0.20722818 | AI72: =IFERROR(AI71/AI63,"") -> 0.314471 | AJ72: =IFERROR(AJ71/AJ63,"") -> 0.26399447 | AK72: 0.264 | AL72: 0.264 | AM72: 0.264 | AN72: 0.264
A73: o/w Marketing (historical, linked) | B73: Rs Mn | C73: Link: Raw Data - Ops KPIs | D73: ='Raw Data - Ops KPIs'!D108 -> 0 | E73: ='Raw Data - Ops KPIs'!E108 -> 0 | F73: ='Raw Data - Ops KPIs'!F108 -> 0 | G73: ='Raw Data - Ops KPIs'!G108 -> 0 | H73: ='Raw Data - Ops KPIs'!H108 -> 0 | I73: ='Raw Data - Ops KPIs'!I108 -> 0 | J73: ='Raw Data - Ops KPIs'!J108 -> 0 | K73: ='Raw Data - Ops KPIs'!K108 -> 0 | ... W73: ='Raw Data - Ops KPIs'!W108 -> 910 | AF73: ='Raw Data - Ops KPIs'!AF108 | AG73: ='Raw Data - Ops KPIs'!AG108 | AH73: ='Raw Data - Ops KPIs'!AH108 -> 1928 | AI73: ='Raw Data - Ops KPIs'!AI108 -> 3309 | AJ73: ='Raw Data - Ops KPIs'!AJ108 -> 3820
A74: o/w Selling & distribution (historical, linked) | B74: Rs Mn | C74: Link: Raw Data - Ops KPIs | D74: ='Raw Data - Ops KPIs'!D109 -> 0 | E74: ='Raw Data - Ops KPIs'!E109 -> 0 | F74: ='Raw Data - Ops KPIs'!F109 -> 0 | G74: ='Raw Data - Ops KPIs'!G109 -> 0 | H74: ='Raw Data - Ops KPIs'!H109 -> 0 | I74: ='Raw Data - Ops KPIs'!I109 -> 0 | J74: ='Raw Data - Ops KPIs'!J109 -> 0 | K74: ='Raw Data - Ops KPIs'!K109 -> 0 | ... W74: ='Raw Data - Ops KPIs'!W109 -> 0 | AF74: ='Raw Data - Ops KPIs'!AF109 | AG74: ='Raw Data - Ops KPIs'!AG109 | AH74: ='Raw Data - Ops KPIs'!AH109 -> 119 | AI74: ='Raw Data - Ops KPIs'!AI109 -> 231 | AJ74: ='Raw Data - Ops KPIs'!AJ109 -> 0
A75: Contribution profit | B75: Rs Mn | C75: Formula | D75: =IFERROR(D67-D69-D71,"") -> 0 | E75: =IFERROR(E67-E69-E71,"") -> 0 | F75: =IFERROR(F67-F69-F71,"") -> 0 | G75: =IFERROR(G67-G69-G71,"") -> 0 | H75: =IFERROR(H67-H69-H71,"") -> 0 | I75: =IFERROR(I67-I69-I71,"") -> 0 | J75: =IFERROR(J67-J69-J71,"") -> 0 | K75: =IFERROR(K67-K69-K71,"") -> 0 | ... W75: =IFERROR(W67-W69-W71,"") -> 480 | AC75: =IFERROR(AC67-AC69-AC71,"") | AD75: =IFERROR(AD67-AD69-AD71,"") | AE75: =IFERROR(AE67-AE69-AE71,"") | AF75: =IFERROR(AF67-AF69-AF71,"") | AG75: =IFERROR(AG67-AG69-AG71,"") | AH75: =IFERROR(AH67-AH69-AH71,"") -> 1285 | AI75: =IFERROR(AI67-AI69-AI71,"") -> 884 | AJ75: =IFERROR(AJ67-AJ69-AJ71,"") -> 1470 | ... AN75: =IFERROR(AN67-AN69-AN71,"") -> 4637.3432
A76: Contribution margin (% of NSV) | B76: % | C76: Formula | D76: =IFERROR(D75/D63,"") | E76: =IFERROR(E75/E63,"") | F76: =IFERROR(F75/F63,"") | G76: =IFERROR(G75/G63,"") | H76: =IFERROR(H75/H63,"") | I76: =IFERROR(I75/I63,"") | J76: =IFERROR(J75/J63,"") | K76: =IFERROR(K75/K63,"") | ... W76: =IFERROR(W75/W63,"") -> 0.1209068 | AC76: =IFERROR(AC75/AC63,"") | AD76: =IFERROR(AD75/AD63,"") | AE76: =IFERROR(AE75/AE63,"") | AF76: =IFERROR(AF75/AF63,"") | AG76: =IFERROR(AG75/AG63,"") | AH76: =IFERROR(AH75/AH63,"") -> 0.13008706 | AI76: =IFERROR(AI75/AI63,"") -> 0.078528915 | AJ76: =IFERROR(AJ75/AJ63,"") -> 0.1015895 | ... AN76: =IFERROR(AN75/AN63,"") -> 0.101
A77: Other expenses (G&A + employee) | B77: Rs Mn | C77: Link: Raw Data - Ops KPIs | D77: ='Raw Data - Ops KPIs'!D112 -> 0 | E77: ='Raw Data - Ops KPIs'!E112 -> 0 | F77: ='Raw Data - Ops KPIs'!F112 -> 0 | G77: ='Raw Data - Ops KPIs'!G112 -> 0 | H77: ='Raw Data - Ops KPIs'!H112 -> 0 | I77: ='Raw Data - Ops KPIs'!I112 -> 0 | J77: ='Raw Data - Ops KPIs'!J112 -> 0 | K77: ='Raw Data - Ops KPIs'!K112 -> 0 | ... W77: ='Raw Data - Ops KPIs'!W112 -> 470 | AF77: ='Raw Data - Ops KPIs'!AF112 | AG77: ='Raw Data - Ops KPIs'!AG112 | AH77: ='Raw Data - Ops KPIs'!AH112 -> 1226 | AI77: ='Raw Data - Ops KPIs'!AI112 -> 1820 | AJ77: ='Raw Data - Ops KPIs'!AJ112 -> 1850 | AK77: =AK63*AK78 -> 2472.3633 | AL77: =AL63*AL78 -> 3299.5963 | AM77: =AM63*AM78 -> 4403.6148 | AN77: =AN63*AN78 -> 5877.029
A78: Other expenses (% of NSV) | B78: % | C78: Assumption (edit me) | D78: =IFERROR(D77/D63,"") | E78: =IFERROR(E77/E63,"") | F78: =IFERROR(F77/F63,"") | G78: =IFERROR(G77/G63,"") | H78: =IFERROR(H77/H63,"") | I78: =IFERROR(I77/I63,"") | J78: =IFERROR(J77/J63,"") | K78: =IFERROR(K77/K63,"") | ... W78: =IFERROR(W77/W63,"") -> 0.11838791 | AC78: =IFERROR(AC77/AC63,"") | AD78: =IFERROR(AD77/AD63,"") | AE78: =IFERROR(AE77/AE63,"") | AF78: =IFERROR(AF77/AF63,"") | AG78: =IFERROR(AG77/AG63,"") | AH78: =IFERROR(AH77/AH63,"") -> 0.12411419 | AI78: =IFERROR(AI77/AI63,"") -> 0.16167718 | AJ78: =IFERROR(AJ77/AJ63,"") -> 0.12785073 | AK78: 0.128 | AL78: 0.128 | AM78: 0.128 | AN78: 0.128
A79: EBITDA | B79: Rs Mn | C79: Formula | D79: =IFERROR(D75-D77,"") -> 0 | E79: =IFERROR(E75-E77,"") -> 0 | F79: =IFERROR(F75-F77,"") -> 0 | G79: =IFERROR(G75-G77,"") -> 0 | H79: =IFERROR(H75-H77,"") -> 0 | I79: =IFERROR(I75-I77,"") -> 0 | J79: =IFERROR(J75-J77,"") -> 0 | K79: =IFERROR(K75-K77,"") -> 0 | ... W79: =IFERROR(W75-W77,"") -> 10 | AC79: =IFERROR(AC75-AC77,"") | AD79: =IFERROR(AD75-AD77,"") | AE79: =IFERROR(AE75-AE77,"") | AF79: =IFERROR(AF75-AF77,"") | AG79: =IFERROR(AG75-AG77,"") | AH79: =IFERROR(AH75-AH77,"") -> 59 | AI79: =IFERROR(AI75-AI77,"") -> -936 | AJ79: =IFERROR(AJ75-AJ77,"") -> -380 | ... AN79: =IFERROR(AN75-AN77,"") -> -1239.6858
A80: EBITDA margin (% of NSV) | B80: % | C80: Formula | D80: =IFERROR(D79/D63,"") | E80: =IFERROR(E79/E63,"") | F80: =IFERROR(F79/F63,"") | G80: =IFERROR(G79/G63,"") | H80: =IFERROR(H79/H63,"") | I80: =IFERROR(I79/I63,"") | J80: =IFERROR(J79/J63,"") | K80: =IFERROR(K79/K63,"") | ... W80: =IFERROR(W79/W63,"") -> 0.0025188917 | AC80: =IFERROR(AC79/AC63,"") | AD80: =IFERROR(AD79/AD63,"") | AE80: =IFERROR(AE79/AE63,"") | AF80: =IFERROR(AF79/AF63,"") | AG80: =IFERROR(AG79/AG63,"") | AH80: =IFERROR(AH79/AH63,"") -> 0.005972869 | AI80: =IFERROR(AI79/AI63,"") -> -0.083148263 | AJ80: =IFERROR(AJ79/AJ63,"") -> -0.02626123 | ... AN80: =IFERROR(AN79/AN63,"") -> -0.027
A82: NEW BUSINESS (GCC + International)
A83: Beauty retail in the Gulf Cooperation Council (via Apparel Group JV) and international markets. Small, volatile, residual segment (Total - Beauty - Fashion in the Raw Data tab) -- treat these projections as indicative only.
A84: GMV | B84: Rs Mn | C84: Link: Raw Data - Ops KPIs | D84: ='Raw Data - Ops KPIs'!D126 | E84: ='Raw Data - Ops KPIs'!E126 | F84: ='Raw Data - Ops KPIs'!F126 | G84: ='Raw Data - Ops KPIs'!G126 | H84: ='Raw Data - Ops KPIs'!H126 | I84: ='Raw Data - Ops KPIs'!I126 | J84: ='Raw Data - Ops KPIs'!J126 | K84: ='Raw Data - Ops KPIs'!K126 | ... W84: ='Raw Data - Ops KPIs'!W126 -> 150 | AF84: ='Raw Data - Ops KPIs'!AF126 | AG84: ='Raw Data - Ops KPIs'!AG126 | AH84: ='Raw Data - Ops KPIs'!AH126 -> 63 | AI84: ='Raw Data - Ops KPIs'!AI126 -> 249 | AJ84: ='Raw Data - Ops KPIs'!AJ126 -> 550 | AK84: =AJ84*(1+AK85) -> 715 | AL84: =AK84*(1+AL85) -> 929.5 | AM84: =AL84*(1+AM85) -> 1208.35 | AN84: =AM84*(1+AN85) -> 1570.855
A85: YoY growth | B85: % | C85: Assumption (edit me) | H85: =IFERROR(H84/D84-1,"") | I85: =IFERROR(I84/E84-1,"") | J85: =IFERROR(J84/F84-1,"") | K85: =IFERROR(K84/G84-1,"") | L85: =IFERROR(L84/H84-1,"") | M85: =IFERROR(M84/I84-1,"") | N85: =IFERROR(N84/J84-1,"") | O85: =IFERROR(O84/K84-1,"") | ... W85: =IFERROR(W84/S84-1,"") -> 1.1428571 | AD85: =IFERROR(AD84/AC84-1,"") | AE85: =IFERROR(AE84/AD84-1,"") | AF85: =IFERROR(AF84/AE84-1,"") | AG85: =IFERROR(AG84/AF84-1,"") | AH85: =IFERROR(AH84/AG84-1,"") | AI85: =IFERROR(AI84/AH84-1,"") -> 2.952381 | AJ85: =IFERROR(AJ84/AI84-1,"") -> 1.2088353 | AK85: 0.3 | AL85: 0.3 | AM85: 0.3 | AN85: 0.3
A86: NSV | B86: Rs Mn | C86: Link: Raw Data - Ops KPIs | D86: ='Raw Data - Ops KPIs'!D128 | E86: ='Raw Data - Ops KPIs'!E128 | F86: ='Raw Data - Ops KPIs'!F128 | G86: ='Raw Data - Ops KPIs'!G128 | H86: ='Raw Data - Ops KPIs'!H128 | I86: ='Raw Data - Ops KPIs'!I128 | J86: ='Raw Data - Ops KPIs'!J128 | K86: ='Raw Data - Ops KPIs'!K128 | ... W86: ='Raw Data - Ops KPIs'!W128 -> 120 | AF86: ='Raw Data - Ops KPIs'!AF128 | AG86: ='Raw Data - Ops KPIs'!AG128 | AH86: ='Raw Data - Ops KPIs'!AH128 -> 44 | AI86: ='Raw Data - Ops KPIs'!AI128 -> 235 | AJ86: ='Raw Data - Ops KPIs'!AJ128 -> 470 | AK86: =AK84*AK87 -> 607.75 | AL86: =AL84*AL87 -> 790.075 | AM86: =AM84*AM87 -> 1027.0975 | AN86: =AN84*AN87 -> 1335.2268
A87: NSV / GMV | B87: % | C87: Assumption (edit me) | D87: =IFERROR(D86/D84,"") | E87: =IFERROR(E86/E84,"") | F87: =IFERROR(F86/F84,"") | G87: =IFERROR(G86/G84,"") | H87: =IFERROR(H86/H84,"") | I87: =IFERROR(I86/I84,"") | J87: =IFERROR(J86/J84,"") | K87: =IFERROR(K86/K84,"") | ... W87: =IFERROR(W86/W84,"") -> 0.8 | AC87: =IFERROR(AC86/AC84,"") | AD87: =IFERROR(AD86/AD84,"") | AE87: =IFERROR(AE86/AE84,"") | AF87: =IFERROR(AF86/AF84,"") | AG87: =IFERROR(AG86/AG84,"") | AH87: =IFERROR(AH86/AH84,"") -> 0.6984127 | AI87: =IFERROR(AI86/AI84,"") -> 0.9437751 | AJ87: =IFERROR(AJ86/AJ84,"") -> 0.85454545 | AK87: 0.85 | AL87: 0.85 | AM87: 0.85 | AN87: 0.85
A88: Revenue | B88: Rs Mn | C88: Link: Raw Data - Ops KPIs | D88: ='Raw Data - Ops KPIs'!D129 | E88: ='Raw Data - Ops KPIs'!E129 | F88: ='Raw Data - Ops KPIs'!F129 | G88: ='Raw Data - Ops KPIs'!G129 | H88: ='Raw Data - Ops KPIs'!H129 | I88: ='Raw Data - Ops KPIs'!I129 | J88: ='Raw Data - Ops KPIs'!J129 | K88: ='Raw Data - Ops KPIs'!K129 | ... W88: ='Raw Data - Ops KPIs'!W129 -> 130 | AF88: ='Raw Data - Ops KPIs'!AF129 | AG88: ='Raw Data - Ops KPIs'!AG129 | AH88: ='Raw Data - Ops KPIs'!AH129 -> 13771.26 | AI88: ='Raw Data - Ops KPIs'!AI129 -> 236.2 | AJ88: ='Raw Data - Ops KPIs'!AJ129 -> 511.8 | AK88: =AK86*AK89 -> 662.4475 | AL88: =AL86*AL89 -> 861.18175 | AM88: =AM86*AM89 -> 1119.5363 | AN88: =AN86*AN89 -> 1455.3972
A89: Revenue / NSV | B89: % | C89: Assumption (edit me) | D89: =IFERROR(D88/D86,"") | E89: =IFERROR(E88/E86,"") | F89: =IFERROR(F88/F86,"") | G89: =IFERROR(G88/G86,"") | H89: =IFERROR(H88/H86,"") | I89: =IFERROR(I88/I86,"") | J89: =IFERROR(J88/J86,"") | K89: =IFERROR(K88/K86,"") | ... W89: =IFERROR(W88/W86,"") -> 1.0833333 | AC89: =IFERROR(AC88/AC86,"") | AD89: =IFERROR(AD88/AD86,"") | AE89: =IFERROR(AE88/AE86,"") | AF89: =IFERROR(AF88/AF86,"") | AG89: =IFERROR(AG88/AG86,"") | AH89: =IFERROR(AH88/AH86,"") -> 312.98318 | AI89: =IFERROR(AI88/AI86,"") -> 1.0051064 | AJ89: =IFERROR(AJ88/AJ86,"") -> 1.0889362 | AK89: 1.09 | AL89: 1.09 | AM89: 1.09 | AN89: 1.09
A90: Contribution profit | B90: Rs Mn | C90: Link: Raw Data - Ops KPIs | D90: ='Raw Data - Ops KPIs'!D133 | E90: ='Raw Data - Ops KPIs'!E133 | F90: ='Raw Data - Ops KPIs'!F133 | G90: ='Raw Data - Ops KPIs'!G133 | H90: ='Raw Data - Ops KPIs'!H133 | I90: ='Raw Data - Ops KPIs'!I133 | J90: ='Raw Data - Ops KPIs'!J133 | K90: ='Raw Data - Ops KPIs'!K133 | ... W90: ='Raw Data - Ops KPIs'!W133 -> 10 | AF90: ='Raw Data - Ops KPIs'!AF133 | AG90: ='Raw Data - Ops KPIs'!AG133 | AH90: ='Raw Data - Ops KPIs'!AH133 -> 2114.4 | AI90: ='Raw Data - Ops KPIs'!AI133 -> -273.4 | AJ90: ='Raw Data - Ops KPIs'!AJ133 -> 75.3 | AK90: =AK86*AK91 -> 97.24 | AL90: =AL86*AL91 -> 126.412 | AM90: =AM86*AM91 -> 164.3356 | AN90: =AN86*AN91 -> 213.63628
A91: Contribution margin (% of NSV) | B91: % | C91: Assumption (edit me) | D91: =IFERROR(D90/D86,"") | E91: =IFERROR(E90/E86,"") | F91: =IFERROR(F90/F86,"") | G91: =IFERROR(G90/G86,"") | H91: =IFERROR(H90/H86,"") | I91: =IFERROR(I90/I86,"") | J91: =IFERROR(J90/J86,"") | K91: =IFERROR(K90/K86,"") | ... W91: =IFERROR(W90/W86,"") -> 0.083333333 | AC91: =IFERROR(AC90/AC86,"") | AD91: =IFERROR(AD90/AD86,"") | AE91: =IFERROR(AE90/AE86,"") | AF91: =IFERROR(AF90/AF86,"") | AG91: =IFERROR(AG90/AG86,"") | AH91: =IFERROR(AH90/AH86,"") -> 48.054545 | AI91: =IFERROR(AI90/AI86,"") -> -1.1634043 | AJ91: =IFERROR(AJ90/AJ86,"") -> 0.16021277 | AK91: 0.16 | AL91: 0.16 | AM91: 0.16 | AN91: 0.16
A92: Other expenses (G&A + employee) | B92: Rs Mn | C92: Link: Raw Data - Ops KPIs | D92: ='Raw Data - Ops KPIs'!D134 | E92: ='Raw Data - Ops KPIs'!E134 | F92: ='Raw Data - Ops KPIs'!F134 | G92: ='Raw Data - Ops KPIs'!G134 | H92: ='Raw Data - Ops KPIs'!H134 | I92: ='Raw Data - Ops KPIs'!I134 | J92: ='Raw Data - Ops KPIs'!J134 | K92: ='Raw Data - Ops KPIs'!K134 | ... W92: ='Raw Data - Ops KPIs'!W134 -> 130 | AF92: ='Raw Data - Ops KPIs'!AF134 | AG92: ='Raw Data - Ops KPIs'!AG134 | AH92: ='Raw Data - Ops KPIs'!AH134 -> 2266.89 | AI92: ='Raw Data - Ops KPIs'!AI134 -> -17.5 | AJ92: ='Raw Data - Ops KPIs'!AJ134 -> -48.6 | AK92: =AK86*AK93 -> -60.775 | AL92: =AL86*AL93 -> -79.0075 | AM92: =AM86*AM93 -> -102.70975 | AN92: =AN86*AN93 -> -133.52268
A93: Other expenses (% of NSV) | B93: % | C93: Assumption (edit me) | D93: =IFERROR(D92/D86,"") | E93: =IFERROR(E92/E86,"") | F93: =IFERROR(F92/F86,"") | G93: =IFERROR(G92/G86,"") | H93: =IFERROR(H92/H86,"") | I93: =IFERROR(I92/I86,"") | J93: =IFERROR(J92/J86,"") | K93: =IFERROR(K92/K86,"") | ... W93: =IFERROR(W92/W86,"") -> 1.0833333 | AC93: =IFERROR(AC92/AC86,"") | AD93: =IFERROR(AD92/AD86,"") | AE93: =IFERROR(AE92/AE86,"") | AF93: =IFERROR(AF92/AF86,"") | AG93: =IFERROR(AG92/AG86,"") | AH93: =IFERROR(AH92/AH86,"") -> 51.520227 | AI93: =IFERROR(AI92/AI86,"") -> -0.074468085 | AJ93: =IFERROR(AJ92/AJ86,"") -> -0.10340426 | AK93: -0.1 | AL93: -0.1 | AM93: -0.1 | AN93: -0.1
A94: EBITDA | B94: Rs Mn | C94: Formula | D94: =IFERROR(D90-D92,"") | E94: =IFERROR(E90-E92,"") | F94: =IFERROR(F90-F92,"") | G94: =IFERROR(G90-G92,"") | H94: =IFERROR(H90-H92,"") | I94: =IFERROR(I90-I92,"") | J94: =IFERROR(J90-J92,"") | K94: =IFERROR(K90-K92,"") | ... W94: =IFERROR(W90-W92,"") -> -120 | AC94: =IFERROR(AC90-AC92,"") -> 0 | AD94: =IFERROR(AD90-AD92,"") -> 0 | AE94: =IFERROR(AE90-AE92,"") -> 0 | AF94: =IFERROR(AF90-AF92,"") | AG94: =IFERROR(AG90-AG92,"") | AH94: =IFERROR(AH90-AH92,"") -> -152.49 | AI94: =IFERROR(AI90-AI92,"") -> -255.9 | AJ94: =IFERROR(AJ90-AJ92,"") -> 123.9 | ... AN94: =IFERROR(AN90-AN92,"") -> 347.15896
A95: EBITDA margin (% of NSV) | B95: % | C95: Formula | D95: =IFERROR(D94/D86,"") | E95: =IFERROR(E94/E86,"") | F95: =IFERROR(F94/F86,"") | G95: =IFERROR(G94/G86,"") | H95: =IFERROR(H94/H86,"") | I95: =IFERROR(I94/I86,"") | J95: =IFERROR(J94/J86,"") | K95: =IFERROR(K94/K86,"") | ... W95: =IFERROR(W94/W86,"") -> -1 | AC95: =IFERROR(AC94/AC86,"") | AD95: =IFERROR(AD94/AD86,"") | AE95: =IFERROR(AE94/AE86,"") | AF95: =IFERROR(AF94/AF86,"") | AG95: =IFERROR(AG94/AG86,"") | AH95: =IFERROR(AH94/AH86,"") -> -3.4656818 | AI95: =IFERROR(AI94/AI86,"") -> -1.0889362 | AJ95: =IFERROR(AJ94/AJ86,"") -> 0.26361702 | ... AN95: =IFERROR(AN94/AN86,"") -> 0.26
A97: CONSOLIDATED BRIDGE (EBITDA TO EPS)
A98: Segment EBITDAs (Beauty + Fashion + New Business) roll up here, then D&A / finance costs / other income / tax bring it down to PAT and EPS -- these lines aren't split by segment in Nykaa's disclosure, so they only exist at the consolidated level.
A99: Total EBITDA (Beauty + Fashion + New Business) | B99: Rs Mn | C99: Formula | D99: =IFERROR(D50+D79+D94,"") | E99: =IFERROR(E50+E79+E94,"") | F99: =IFERROR(F50+F79+F94,"") | G99: =IFERROR(G50+G79+G94,"") | H99: =IFERROR(H50+H79+H94,"") | I99: =IFERROR(I50+I79+I94,"") | J99: =IFERROR(J50+J79+J94,"") | K99: =IFERROR(K50+K79+K94,"") | ... W99: =IFERROR(W50+W79+W94,"") -> 2220 | AC99: =IFERROR(AC50+AC79+AC94,"") | AD99: =IFERROR(AD50+AD79+AD94,"") | AE99: =IFERROR(AE50+AE79+AE94,"") | AF99: =IFERROR(AF50+AF79+AF94,"") | AG99: =IFERROR(AG50+AG79+AG94,"") | AH99: =IFERROR(AH50+AH79+AH94,"") -> 3461.51 | AI99: =IFERROR(AI50+AI79+AI94,"") -> 4739.1 | AJ99: =IFERROR(AJ50+AJ79+AJ94,"") -> 7953.9 | ... AN99: =IFERROR(AN50+AN79+AN94,"") -> 23548.976
A100: EBITDA margin (% of Revenue) | B100: % | C100: Formula | D100: =IFERROR(D99/D9,"") | E100: =IFERROR(E99/E9,"") | F100: =IFERROR(F99/F9,"") | G100: =IFERROR(G99/G9,"") | H100: =IFERROR(H99/H9,"") | I100: =IFERROR(I99/I9,"") | J100: =IFERROR(J99/J9,"") | K100: =IFERROR(K99/K9,"") | ... W100: =IFERROR(W99/W9,"") -> 0.083836858 | AC100: =IFERROR(AC99/AC9,"") | AD100: =IFERROR(AD99/AD9,"") | AE100: =IFERROR(AE99/AE9,"") | AF100: =IFERROR(AF99/AF9,"") | AG100: =IFERROR(AG99/AG9,"") | AH100: =IFERROR(AH99/AH9,"") -> 0.054207841 | AI100: =IFERROR(AI99/AI9,"") -> 0.05961267 | AJ100: =IFERROR(AJ99/AJ9,"") -> 0.079362973 | ... AN100: =IFERROR(AN99/AN9,"") -> 0.078830714
A101: Depreciation & amortisation | B101: Rs Mn | C101: Link: Raw Data - financials | D101: ='Raw Data - financials'!D15 -> 194.97 | E101: ='Raw Data - financials'!E15 -> 213.08 | F101: ='Raw Data - financials'!F15 -> 251.24 | G101: ='Raw Data - financials'!G15 -> 304.84 | H101: ='Raw Data - financials'!H15 -> 310.12 | I101: ='Raw Data - financials'!I15 -> 385.02 | J101: ='Raw Data - financials'!J15 -> 507 | K101: ='Raw Data - financials'!K15 -> 530.42 | ... W101: ='Raw Data - financials'!W15 -> 842.2 | AC101: ='Raw Data - financials'!AC15 -> 308.76 | AD101: ='Raw Data - financials'!AD15 -> 595.09 | AE101: ='Raw Data - financials'!AE15 -> 671.28 | AF101: ='Raw Data - financials'!AF15 -> 964.13 | AG101: ='Raw Data - financials'!AG15 -> 1732.56 | AH101: ='Raw Data - financials'!AH15 -> 2242.33 | AI101: ='Raw Data - financials'!AI15 -> 2664 | AJ101: ='Raw Data - financials'!AJ15 -> 3203.3 | AK101: =AK9*AK102 -> 4216.0419 | AL101: =AL9*AL102 -> 5538.6228 | AM101: =AM9*AM102 -> 7276.2725 | AN101: =AN9*AN102 -> 9559.3101
A102: D&A (% of Revenue) | B102: % | C102: Assumption (edit me) | D102: =IFERROR(D101/D9,"") | E102: =IFERROR(E101/E9,"") | F102: =IFERROR(F101/F9,"") | G102: =IFERROR(G101/G9,"") | H102: =IFERROR(H101/H9,"") | I102: =IFERROR(I101/I9,"") | J102: =IFERROR(J101/J9,"") | K102: =IFERROR(K101/K9,"") | ... W102: =IFERROR(W101/W9,"") -> 0.031805136 | AC102: =IFERROR(AC101/AC9,"") | AD102: =IFERROR(AD101/AD9,"") | AE102: =IFERROR(AE101/AE9,"") | AF102: =IFERROR(AF101/AF9,"") | AG102: =IFERROR(AG101/AG9,"") | AH102: =IFERROR(AH101/AH9,"") -> 0.035115273 | AI102: =IFERROR(AI101/AI9,"") -> 0.033510193 | AJ102: =IFERROR(AJ101/AJ9,"") -> 0.031962108 | AK102: 0.032 | AL102: 0.032 | AM102: 0.032 | AN102: 0.032
A103: EBIT | B103: Rs Mn | C103: Formula | D103: =IFERROR(D99-D101,"") | E103: =IFERROR(E99-E101,"") | F103: =IFERROR(F99-F101,"") | G103: =IFERROR(G99-G101,"") | H103: =IFERROR(H99-H101,"") | I103: =IFERROR(I99-I101,"") | J103: =IFERROR(J99-J101,"") | K103: =IFERROR(K99-K101,"") | ... W103: =IFERROR(W99-W101,"") -> 1377.8 | AC103: =IFERROR(AC99-AC101,"") | AD103: =IFERROR(AD99-AD101,"") | AE103: =IFERROR(AE99-AE101,"") | AF103: =IFERROR(AF99-AF101,"") | AG103: =IFERROR(AG99-AG101,"") | AH103: =IFERROR(AH99-AH101,"") -> 1219.18 | AI103: =IFERROR(AI99-AI101,"") -> 2075.1 | AJ103: =IFERROR(AJ99-AJ101,"") -> 4750.6 | ... AN103: =IFERROR(AN99-AN101,"") -> 13989.666
A104: Finance costs | B104: Rs Mn | C104: Link: Raw Data - financials | D104: ='Raw Data - financials'!D14 -> 90.14 | E104: ='Raw Data - financials'!E14 -> 113.49 | F104: ='Raw Data - financials'!F14 -> 127.9 | G104: ='Raw Data - financials'!G14 -> 133.58 | H104: ='Raw Data - financials'!H14 -> 150.63 | I104: ='Raw Data - financials'!I14 -> 203.56 | J104: ='Raw Data - financials'!J14 -> 204.25 | K104: ='Raw Data - financials'!K14 -> 187.61 | ... W104: ='Raw Data - financials'!W14 -> 263.3 | AC104: ='Raw Data - financials'!AC14 -> 263.42 | AD104: ='Raw Data - financials'!AD14 -> 442.93 | AE104: ='Raw Data - financials'!AE14 -> 307.01 | AF104: ='Raw Data - financials'!AF14 -> 465.11 | AG104: ='Raw Data - financials'!AG14 -> 746.05 | AH104: ='Raw Data - financials'!AH14 -> 828.32 | AI104: ='Raw Data - financials'!AI14 -> 1073.2 | AJ104: ='Raw Data - financials'!AJ14 -> 1171.2 | AK104: =AK9*AK105 -> 1541.4903 | AL104: =AL9*AL105 -> 2025.059 | AM104: =AM9*AM105 -> 2660.3871 | AN104: =AN9*AN105 -> 3495.1227
A105: Finance costs (% of Revenue) | B105: % | C105: Assumption (edit me) | D105: =IFERROR(D104/D9,"") | E105: =IFERROR(E104/E9,"") | F105: =IFERROR(F104/F9,"") | G105: =IFERROR(G104/G9,"") | H105: =IFERROR(H104/H9,"") | I105: =IFERROR(I104/I9,"") | J105: =IFERROR(J104/J9,"") | K105: =IFERROR(K104/K9,"") | ... W105: =IFERROR(W104/W9,"") -> 0.0099433535 | AC105: =IFERROR(AC104/AC9,"") | AD105: =IFERROR(AD104/AD9,"") | AE105: =IFERROR(AE104/AE9,"") | AF105: =IFERROR(AF104/AF9,"") | AG105: =IFERROR(AG104/AG9,"") | AH105: =IFERROR(AH104/AH9,"") -> 0.012971633 | AI105: =IFERROR(AI104/AI9,"") -> 0.013499677 | AJ105: =IFERROR(AJ104/AJ9,"") -> 0.01168608 | AK105: 0.0117 | AL105: 0.0117 | AM105: 0.0117 | AN105: 0.0117
...

Sheet Raw Data - financials
A1: INR Mn | B1: Unit | C1: Source | D1: 1Q22 | E1: 2Q22 | F1: 3Q22 | G1: 4Q22 | H1: 1Q23 | I1: 2Q23 | J1: 3Q23 | K1: 4Q23 | L1: 1Q24 | M1: 2Q24 | N1: 3Q24 | O1: 4Q24 | P1: 1Q25 | Q1: 2Q25 | R1: 3Q25 | S1: 4Q25 | T1: 1Q26 | U1: 2Q26 | V1: 3Q26 | W1: 4Q26 | X1: 1Q27 | Y1: 2Q27 | Z1: 3Q27 | AA1: 4Q27 | AC1: FY19 | AD1: FY20 | AE1: FY21 | AF1: FY22 | AG1: FY23 | AH1: FY24 | AI1: FY25 | AJ1: FY26
A2: Fiscal Year End | D2: =EOMONTH(E2,-3) -> 44377 | E2: =EOMONTH(F2,-3) -> 44469 | F2: =EOMONTH(G2,-3) -> 44561 | G2: =EOMONTH(H2,-3) -> 44651 | H2: =EOMONTH(I2,-3) -> 44742 | I2: =EOMONTH(J2,-3) -> 44834 | J2: =EOMONTH(K2,-3) -> 44926 | K2: =EOMONTH(L2,-3) -> 45016 | ... V2: =EOMONTH(W2,-3) -> 46022 | W2: 46112 | X2: =EOMONTH(W2,3) -> 46203 | Y2: =EOMONTH(X2,3) -> 46295 | Z2: =EOMONTH(Y2,3) -> 46387 | AA2: =EOMONTH(Z2,3) -> 46477 | AC2: 43555 | AD2: 43921 | AE2: 44286 | AF2: 44651 | AG2: 45016 | AH2: 45382 | AI2: 45747 | AJ2: 46112
A3: All figures in INR Mn unless stated otherwise.
A4: PROFIT & LOSS (CONSOLIDATED)
A5: Revenue from operations | B5: INR Mn | C5: Company filings | D5: 8169.91 | E5: 8852.64 | F5: 10983.6 | G5: 9733.2 | H5: 11484.21 | I5: 12308.29 | J5: 14628.26 | K5: 13017.24 | L5: 14218.24 | M5: 15070.24 | N5: 17887.98 | O5: 16679.8 | P5: 17461.1 | Q5: 18747.4 | R5: 22672.1 | S5: 20617.6 | T5: 21549.4 | U5: 23459.8 | V5: 28732.6 | W5: 26481.7 | AC5: 11113.94 | AD5: 17675.33 | AE5: 24408.96 | AF5: 37739.35 | AG5: 51438 | AH5: 63856.26 | AI5: 79498.2 | AJ5: 100223.5
A6: Other income | B6: INR Mn | C6: Company filings | D6: 47.22 | E6: 51.98 | F6: 59.13 | G6: 111.39 | H6: 83.63 | I6: 64.76 | J6: 56.36 | K6: 97.38 | L6: 67.21 | M6: 85.73 | N6: 75.84 | O6: 70.63 | P6: 73.3 | Q6: 54.5 | R6: 55.3 | S6: 89.5 | T6: 93.3 | U6: 80.3 | V6: 62.6 | W6: 91.5 | AC6: 49.88 | AD6: 103.17 | AE6: 117.41 | AF6: 269.72 | AG6: 302.13 | AH6: 299.42 | AI6: 272.6 | AJ6: 327.7
A7: Total Income | B7: INR Mn | D7: =SUM(D5:D6) -> 8217.13 | E7: =SUM(E5:E6) -> 8904.62 | F7: =SUM(F5:F6) -> 11042.73 | G7: =SUM(G5:G6) -> 9844.59 | H7: =SUM(H5:H6) -> 11567.84 | I7: =SUM(I5:I6) -> 12373.05 | J7: =SUM(J5:J6) -> 14684.62 | K7: =SUM(K5:K6) -> 13114.62 | ... W7: =SUM(W5:W6) -> 26573.2 | AC7: =SUM(AC5:AC6) -> 11163.82 | AD7: =SUM(AD5:AD6) -> 17778.5 | AE7: =SUM(AE5:AE6) -> 24526.37 | AF7: =SUM(AF5:AF6) -> 38009.07 | AG7: =SUM(AG5:AG6) -> 51740.13 | AH7: =SUM(AH5:AH6) -> 64155.68 | AI7: =SUM(AI5:AI6) -> 79770.8 | AJ7: =SUM(AJ5:AJ6) -> 100551.2
A9: Expenses
A10: Cost of material consumed | B10: INR Mn | C10: Company filings | D10: 229.37 | E10: 179.32 | F10: 176.56 | G10: 257.87 | H10: 232.97 | I10: 222.51 | J10: 166.08 | K10: 972.77 | L10: 186 | M10: 155.06 | N10: 235.19 | O10: 74.87 | P10: 25.9 | Q10: 14.5 | R10: 27.8 | S10: 12.8 | T10: 33.3 | U10: 3.4 | V10: 22.1 | W10: 87.3 | AC10: 2.41 | AD10: 173.43 | AE10: 382.41 | AF10: 843.12 | AG10: 1594.33 | AH10: 651.13 | AI10: 81 | AJ10: 146.1
A11: Purchase of traded goods | B11: INR Mn | C11: Company filings | D11: 5509.42 | E11: 4848.33 | F11: 6902.15 | G11: 6643.6 | H11: 7415.45 | I11: 5858.02 | J11: 9188.98 | K11: 6017.46 | L11: 9781.98 | M11: 5530.25 | N11: 12322.52 | O11: 10182.01 | P11: 11718 | Q11: 10860.8 | R11: 12849.6 | S11: 11402.3 | T11: 14444.5 | U11: 11965.3 | V11: 15047.7 | W11: 15728.3 | AC11: 7852.43 | AD11: 11787.46 | AE11: 14956.06 | AF11: 24078.31 | AG11: 28479.91 | AH11: 37816.75 | AI11: 46830.8 | AJ11: 57185.8
A12: Changes in inventories of finished goods and stock-in-trade | B12: INR Mn | C12: Company filings | D12: -885.47 | E12: 42.57 | F12: -1182.69 | G12: -1420.88 | H12: -1263 | I12: 650.38 | J12: -1073.5 | K12: 268.69 | L12: -1935.99 | M12: 2888.69 | N12: -2277.21 | O12: -679.51 | P12: -1842.6 | Q12: -338.1 | R12: -116.7 | S12: 112.3 | T12: -2543.5 | U12: 955.7 | V12: 688 | W12: -1366.8 | AC12: -1252.07 | AD12: -1818.84 | AE12: -460.22 | AF12: -3621.28 | AG12: -1417.43 | AH12: -2004.02 | AI12: -2185.2 | AJ12: -2266.6
A13: Employee benefits expense | B13: INR Mn | C13: Company filings | D13: 726.05 | E13: 694.01 | F13: 933.21 | G13: 908 | H13: 1147.09 | I13: 1217.61 | J13: 1279.16 | K13: 1273.31 | L13: 1385.76 | M13: 1363.2 | N13: 1479.3 | O13: 1420.75 | P13: 1558.6 | Q13: 1614.9 | R13: 1746 | S13: 1741.2 | T13: 1820.2 | U13: 1827.7 | V13: 2029 | W13: 2038.4 | AC13: 1172.96 | AD13: 1956.13 | AE13: 2836.47 | AF13: 3259.39 | AG13: 4917.17 | AH13: 5649.01 | AI13: 6660.7 | AJ13: 7715.3
A14: Finance costs | B14: INR Mn | C14: Company filings | D14: 90.14 | E14: 113.49 | F14: 127.9 | G14: 133.58 | H14: 150.63 | I14: 203.56 | J14: 204.25 | K14: 187.61 | L14: 185.48 | M14: 213.09 | N14: 218.41 | O14: 211.34 | P14: 213.1 | Q14: 242.3 | R14: 319.3 | S14: 298.5 | T14: 301.6 | U14: 314.7 | V14: 291.6 | W14: 263.3 | AC14: 263.42 | AD14: 442.93 | AE14: 307.01 | AF14: 465.11 | AG14: 746.05 | AH14: 828.32 | AI14: 1073.2 | AJ14: 1171.2
A15: Depreciation and amortisation expense | B15: INR Mn | C15: Company filings | D15: 194.97 | E15: 213.08 | F15: 251.24 | G15: 304.84 | H15: 310.12 | I15: 385.02 | J15: 507 | K15: 530.42 | L15: 519.2 | M15: 546.36 | N15: 580.28 | O15: 596.49 | P15: 600.6 | Q15: 636.2 | R15: 698.2 | S15: 729 | T15: 761.4 | U15: 790.9 | V15: 808.8 | W15: 842.2 | AC15: 308.76 | AD15: 595.09 | AE15: 671.28 | AF15: 964.13 | AG15: 1732.56 | AH15: 2242.33 | AI15: 2664 | AJ15: 3203.3
A16: Other expenses | B16: INR Mn | C16: Company filings | D16: 2321.16 | E16: 2800.17 | F16: 3464.6 | G16: 2959.42 | H16: 3491.18 | I16: 3748.4 | J16: 4285.94 | K16: 3778.07 | L16: 4065.83 | M16: 4326.75 | N16: 5140.44 | O16: 4748.86 | P16: 5040 | Q16: 5558.7 | R16: 6757.6 | S16: 6015.5 | T16: 6388.1 | U16: 7118.2 | V16: 8648.2 | W16: 7765.3 | AC16: 3133.11 | AD16: 4766.6 | AE16: 5079.98 | AF16: 11547.23 | AG16: 15303.59 | AH16: 18281.89 | AI16: 23371.8 | AJ16: 29919.8
A17: Total Expenses | B17: INR Mn | D17: =SUM(D10:D16) -> 8185.64 | E17: =SUM(E10:E16) -> 8890.97 | F17: =SUM(F10:F16) -> 10672.97 | G17: =SUM(G10:G16) -> 9786.43 | H17: =SUM(H10:H16) -> 11484.44 | I17: =SUM(I10:I16) -> 12285.5 | J17: =SUM(J10:J16) -> 14557.91 | K17: =SUM(K10:K16) -> 13028.33 | ... W17: =SUM(W10:W16) -> 25358 | AC17: =SUM(AC10:AC16) -> 11481.02 | AD17: =SUM(AD10:AD16) -> 17902.8 | AE17: =SUM(AE10:AE16) -> 23772.99 | AF17: =SUM(AF10:AF16) -> 37536.01 | AG17: =SUM(AG10:AG16) -> 51356.18 | AH17: =SUM(AH10:AH16) -> 63465.41 | AI17: =SUM(AI10:AI16) -> 78496.3 | AJ17: =SUM(AJ10:AJ16) -> 97074.9
A19: Profit Before Exceptional Items and Tax | B19: INR Mn | D19: =D7-D17 -> 31.49 | E19: =E7-E17 -> 13.65 | F19: =F7-F17 -> 369.76 | G19: =G7-G17 -> 58.16 | H19: =H7-H17 -> 83.4 | I19: =I7-I17 -> 87.55 | J19: =J7-J17 -> 126.71 | K19: =K7-K17 -> 86.29 | ... W19: =W7-W17 -> 1215.2 | AC19: =AC7-AC17 -> -317.2 | AD19: =AD7-AD17 -> -124.3 | AE19: =AE7-AE17 -> 753.38 | AF19: =AF7-AF17 -> 473.06 | AG19: =AG7-AG17 -> 383.95 | AH19: =AH7-AH17 -> 690.27 | AI19: =AI7-AI17 -> 1274.5 | AJ19: =AJ7-AJ17 -> 3476.3
A20: Exceptional items, net | B20: INR Mn | C20: Company filings | D20: 0 | E20: 0 | F20: 0 | G20: 0 | H20: 0 | I20: 0 | J20: 0 | K20: 0 | L20: 0 | M20: 0 | N20: 0 | O20: 0 | P20: 0 | Q20: 0 | R20: 0 | S20: 0 | T20: 0 | U20: 10.4 | V20: 163.6 | W20: 0 | AC20: 0 | AD20: 0 | AE20: 0 | AF20: 0 | AG20: 0 | AH20: 0 | AI20: 0 | AJ20: 174
A21: Profit Before Tax | B21: INR Mn | D21: =D19-D20 -> 31.49 | E21: =E19-E20 -> 13.65 | F21: =F19-F20 -> 369.76 | G21: =G19-G20 -> 58.16 | H21: =H19-H20 -> 83.4 | I21: =I19-I20 -> 87.55 | J21: =J19-J20 -> 126.71 | K21: =K19-K20 -> 86.29 | ... W21: =W19-W20 -> 1215.2 | AC21: =AC19-AC20 -> -317.2 | AD21: =AD19-AD20 -> -124.3 | AE21: =AE19-AE20 -> 753.38 | AF21: =AF19-AF20 -> 473.06 | AG21: =AG19-AG20 -> 383.95 | AH21: =AH19-AH20 -> 690.27 | AI21: =AI19-AI20 -> 1274.5 | AJ21: =AJ19-AJ20 -> 3302.3
A23: Tax expense
A24: Current tax | B24: INR Mn | C24: Company filings | D24: 133.64 | E24: 3.66 | F24: 144.35 | G24: 141.28 | H24: 113.25 | I24: 215.91 | J24: 270.99 | K24: 260.96 | L24: 236.23 | M24: 215.86 | N24: 308.98 | O24: 306.28 | P24: 420.3 | Q24: 211.2 | R24: 319.9 | S24: -536.4 | T24: 177.3 | U24: 209.2 | V24: 279.2 | W24: 709.2 | AC24: 0 | AD24: 45.37 | AE24: 400.78 | AF24: 422.93 | AG24: 861.11 | AH24: 1067.35 | AI24: 415 | AJ24: 1374.9
A25: Current tax pertaining to earlier years | B25: INR Mn | C25: Company filings | D25: 0 | E25: 0 | F25: 0 | G25: 23.46 | H25: 0 | I25: 0 | J25: 0 | K25: 0 | L25: 0 | M25: 0 | N25: 0 | O25: 0 | P25: 0 | Q25: 0 | R25: 0 | S25: 0 | T25: 0 | U25: 0 | V25: 0 | W25: 0 | AC25: 0 | AD25: 0 | AE25: 0 | AF25: 23.46 | AG25: 0 | AH25: 0 | AI25: 0 | AJ25: 0
A26: Deferred tax expense/(credit) | B26: INR Mn | C26: Company filings | D26: -137.37 | E26: -1.73 | F26: -64.74 | G26: -124.27 | H26: -86.72 | I26: -184.91 | J26: -236.32 | K26: -217.42 | L26: -203.6 | M26: -176.18 | N26: -226.43 | O26: -208.03 | P26: -341.9 | Q26: -133 | R26: -144 | S26: 741.4 | T26: 15.1 | U26: 14.8 | V26: 139.6 | W26: -281.5 | AC26: -71.81 | AD26: -6.27 | AE26: -266.85 | AF26: -328.11 | AG26: -725.37 | AH26: -814.24 | AI26: 122.5 | AJ26: -112
A27: Deferred tax credit for unrecognised business loss (earlier years) | B27: INR Mn | C27: Company filings | D27: 0 | E27: 0 | F27: 0 | G27: -58.1 | H27: 0 | I27: 0 | J27: 0 | K27: 0 | L27: 0 | M27: 0 | N27: 0 | O27: 0 | P27: 0 | Q27: 0 | R27: 0 | S27: 0 | T27: 0 | U27: 0 | V27: 0 | W27: 0 | AC27: 0 | AD27: 0 | AE27: 0 | AF27: -58.1 | AG27: 0 | AH27: 0 | AI27: 0 | AJ27: 0
A28: Total Tax Expense/(Income) | B28: INR Mn | D28: =SUM(D24:D27) -> -3.73 | E28: =SUM(E24:E27) -> 1.93 | F28: =SUM(F24:F27) -> 79.61 | G28: =SUM(G24:G27) -> -17.63 | H28: =SUM(H24:H27) -> 26.53 | I28: =SUM(I24:I27) -> 31 | J28: =SUM(J24:J27) -> 34.67 | K28: =SUM(K24:K27) -> 43.54 | ... W28: =SUM(W24:W27) -> 427.7 | AC28: =SUM(AC24:AC27) -> -71.81 | AD28: =SUM(AD24:AD27) -> 39.1 | AE28: =SUM(AE24:AE27) -> 133.93 | AF28: =SUM(AF24:AF27) -> 60.18 | AG28: =SUM(AG24:AG27) -> 135.74 | AH28: =SUM(AH24:AH27) -> 253.11 | AI28: =SUM(AI24:AI27) -> 537.5 | AJ28: =SUM(AJ24:AJ27) -> 1262.9
A30: Net Profit After Tax | B30: INR Mn | D30: =D21-D28 -> 35.22 | E30: =E21-E28 -> 11.72 | F30: =F21-F28 -> 290.15 | G30: =G21-G28 -> 75.79 | H30: =H21-H28 -> 56.87 | I30: =I21-I28 -> 56.55 | J30: =J21-J28 -> 92.04 | K30: =K21-K28 -> 42.75 | ... W30: =W21-W28 -> 787.5 | AC30: =AC21-AC28 -> -245.39 | AD30: =AD21-AD28 -> -163.4 | AE30: =AE21-AE28 -> 619.45 | AF30: =AF21-AF28 -> 412.88 | AG30: =AG21-AG28 -> 248.21 | AH30: =AH21-AH28 -> 437.16 | AI30: =AI21-AI28 -> 737 | AJ30: =AJ21-AJ28 -> 2039.4
A31: Share in profit/(loss) of associate | B31: INR Mn | C31: Company filings | D31: 0 | E31: 0 | F31: 0 | G31: 0 | H31: -6.77 | I31: -4.64 | J31: -7.19 | K31: -20 | L31: -10.31 | M31: -14.89 | N31: -7.8 | O31: -6.66 | P31: -6 | Q31: -4.7 | R31: -5.6 | S31: 0 | T31: 0 | U31: 0 | V31: 0 | W31: 0 | AC31: 0 | AD31: 0 | AE31: 0 | AF31: 0 | AG31: -38.6 | AH31: -39.67 | AI31: -16.3 | AJ31: 0
A32: Net Profit/(Loss) for the Period | B32: INR Mn | D32: =D30+D31 -> 35.22 | E32: =E30+E31 -> 11.72 | F32: =F30+F31 -> 290.15 | G32: =G30+G31 -> 75.79 | H32: =H30+H31 -> 50.1 | I32: =I30+I31 -> 51.91 | J32: =J30+J31 -> 84.85 | K32: =K30+K31 -> 22.75 | ... W32: =W30+W31 -> 787.5 | AC32: =AC30+AC31 -> -245.39 | AD32: =AD30+AD31 -> -163.4 | AE32: =AE30+AE31 -> 619.45 | AF32: =AF30+AF31 -> 412.88 | AG32: =AG30+AG31 -> 209.61 | AH32: =AH30+AH31 -> 397.49 | AI32: =AI30+AI31 -> 720.7 | AJ32: =AJ30+AJ31 -> 2039.4
A34: Attributable to:
A35: Equity shareholders of parent | B35: INR Mn | C35: Company filings | D35: 34.15 | E35: 11.7 | F35: 279.3 | G35: 85.6 | H35: 45.5 | I35: 41.08 | J35: 81.93 | K35: 24.11 | L35: 33.03 | M35: 58.46 | N35: 161.86 | O35: 69.31 | P35: 96.4 | Q35: 100.4 | R35: 261.2 | S35: 202.8 | T35: 233.2 | U35: 344.3 | V35: 633.1 | W35: 783.8 | AC35: -245.18 | AD35: -166.09 | AE35: 618.48 | AF35: 410.75 | AG35: 192.62 | AH35: 322.65 | AI35: 660.8 | AJ35: 1994.4
A36: Non-controlling interests | B36: INR Mn | C36: Company filings | D36: 1.07 | E36: 0.02 | F36: 10.85 | G36: -9.81 | H36: 4.6 | I36: 10.83 | J36: 2.92 | K36: -1.36 | L36: 21.22 | M36: 19.54 | N36: 12.68 | O36: 21.4 | P36: 40 | Q36: 29.3 | R36: 2.9 | S36: -12.3 | T36: 11.5 | U36: -14.5 | V36: 44.3 | W36: 3.7 | AC36: -0.21 | AD36: 2.69 | AE36: 0.97 | AF36: 2.13 | AG36: 16.99 | AH36: 74.84 | AI36: 59.9 | AJ36: 45
A38: Total Other Comprehensive Income/(Loss), net of tax | B38: INR Mn | C38: Company filings | P38: 0 | Q38: -20.2 | R38: -1.3 | S38: -21.6 | T38: 1.2 | U38: 22.5 | V38: 4.8 | W38: 23.5 | AC38: 2.51 | AD38: 1.09 | AE38: -21.8 | AF38: 5.56 | AG38: 1.57 | AH38: 4.43 | AI38: -43.1 | AJ38: 52 | AL38: =SUM(D38:G38)-AF38 -> -5.56 | AM38: =SUM(H38:K38)-AG38 -> -1.57 | AN38: =SUM(L38:O38)-AH38 -> -4.43
A39: Total Comprehensive Income/(Loss) | B39: INR Mn | D39: =D32+D38 -> 35.22 | E39: =E32+E38 -> 11.72 | F39: =F32+F38 -> 290.15 | G39: =G32+G38 -> 75.79 | H39: =H32+H38 -> 50.1 | I39: =I32+I38 -> 51.91 | J39: =J32+J38 -> 84.85 | K39: =K32+K38 -> 22.75 | ... W39: =W32+W38 -> 811 | AC39: =AC32+AC38 -> -242.88 | AD39: =AD32+AD38 -> -162.31 | AE39: =AE32+AE38 -> 597.65 | AF39: =AF32+AF38 -> 418.44 | AG39: =AG32+AG38 -> 211.18 | AH39: =AH32+AH38 -> 401.92 | AI39: =AI32+AI38 -> 677.6 | AJ39: =AJ32+AJ38 -> 2091.4 | AL39: =SUM(D39:G39)-AF39 -> -5.56 | AM39: =SUM(H39:K39)-AG39 -> -1.57 | AN39: =SUM(L39:O39)-AH39 -> -4.42
A41: Basic EPS | B41: INR | C41: Company filings | D41: 0.08 | E41: 0.03 | F41: 0.6 | G41: 0.18 | H41: 0 | I41: 0.01 | J41: 0.03 | K41: 0.01 | L41: 0.02 | M41: 0.02 | N41: 0.06 | O41: 0.02 | P41: 0.03 | Q41: 0.04 | R41: 0.09 | S41: 0.07 | T41: 0.08 | U41: 0.12 | V41: 0.22 | W41: 0.27 | AC41: -17.7 | AD41: -11.63 | AE41: 41.66 | AF41: 0.88 | AG41: 0.07 | AH41: 0.11 | AI41: 0.23 | AJ41: 0.7
A42: Diluted EPS | B42: INR | C42: Company filings | D42: 0.07 | E42: 0.03 | F42: 0.6 | G42: 0.18 | H42: 0 | I42: 0.01 | J42: 0.03 | K42: 0.01 | L42: 0.02 | M42: 0.02 | N42: 0.06 | O42: 0.02 | P42: 0.03 | Q42: 0.04 | R42: 0.09 | S42: 0.07 | T42: 0.08 | U42: 0.12 | V42: 0.22 | W42: 0.27 | AC42: -17.7 | AD42: -11.63 | AE42: 40.07 | AF42: 0.87 | AG42: 0.07 | AH42: 0.11 | AI42: 0.23 | AJ42: 0.7
A43: Note: FY19-FY21 EPS computed on face value of Rs 10/share (Restated Ind AS statements, RHP); face value changed to Re 1/share from FY22 following share sub-division. Not directly comparable across the break.
A46: BALANCE SHEET (CONSOLIDATED)
A47: ASSETS
A48: Non-current assets
A49: Property, plant and equipment | B49: INR Mn | C49: Company filings | G49: 1244.42 | I49: 1713.47 | K49: 2313.46 | M49: 2315.23 | O49: 2357.72 | Q49: 2351.5 | S49: 2717.2 | U49: 2712.6 | W49: 2999.7 | AC49: 429.05 | AD49: 701.49 | AE49: 686.52 | AF49: 1244.42 | AG49: 2313.46 | AH49: 2357.72 | AI49: 2717.2 | AJ49: 2999.7
A50: Capital work-in-progress | B50: INR Mn | C50: Company filings | G50: 97.64 | I50: 108.64 | K50: 20.22 | M50: 8.52 | O50: 60.77 | Q50: 20.6 | S50: 31.7 | U50: 46.9 | W50: 92.5 | AC50: 3.2 | AD50: 7.78 | AE50: 19.69 | AF50: 97.64 | AG50: 20.22 | AH50: 60.77 | AI50: 31.7 | AJ50: 92.5
A51: Goodwill | B51: INR Mn | C51: Company filings | G51: 474.78 | I51: 789.04 | K51: 610.65 | M51: 610.65 | O51: 610.65 | Q51: 610.7 | S51: 975 | U51: 975.1 | W51: 975 | AC51: 1.43 | AD51: 1.43 | AE51: 5.43 | AF51: 474.78 | AG51: 610.65 | AH51: 610.65 | AI51: 975 | AJ51: 975
A52: Other intangible assets | B52: INR Mn | C52: Company filings | G52: 640.05 | I52: 664.77 | K52: 944.85 | M52: 1009.09 | O52: 1104.67 | Q52: 1063.9 | S52: 1357.4 | U52: 1244.3 | W52: 1490.1 | AC52: 106.03 | AD52: 127.45 | AE52: 230.34 | AF52: 640.05 | AG52: 944.85 | AH52: 1104.67 | AI52: 1357.4 | AJ52: 1490.1
A53: Right of use assets | B53: INR Mn | C53: Company filings | G53: 2473.26 | I53: 4069.36 | K53: 3119.21 | M53: 2768.35 | O53: 2608.54 | Q53: 2786.2 | S53: 3298.6 | U53: 3865.4 | W53: 4614.7 | AC53: 859.31 | AD53: 1439.94 | AE53: 1389.34 | AF53: 2473.26 | AG53: 3119.21 | AH53: 2608.54 | AI53: 3298.6 | AJ53: 4614.7
A54: Intangible assets under development | B54: INR Mn | C54: Company filings | G54: 147.31 | I54: 246.38 | K54: 288.56 | M54: 254.59 | O54: 236.99 | Q54: 328.7 | S54: 335.7 | U54: 402.2 | W54: 0 | AC54: 0 | AD54: 12.45 | AE54: 3.88 | AF54: 147.31 | AG54: 288.56 | AH54: 236.99 | AI54: 335.7 | AJ54: 0
A55: Investments accounted for using equity method | B55: INR Mn | C55: Company filings | G55: 0 | I55: 0 | K55: 0 | M55: 0 | O55: 338.23 | Q55: 327.6 | S55: 0 | U55: 0 | W55: 0 | AC55: 0 | AD55: 0 | AE55: 0 | AF55: 0 | AG55: 0 | AH55: 338.23 | AI55: 0 | AJ55: 0
A56: Financial assets - Investments | B56: INR Mn | C56: Company filings | G56: 0 | I56: 405.08 | K56: 381.2 | M56: 356 | O56: 4.88 | Q56: 4.9 | S56: 1.6 | U56: 1.6 | W56: 1.6 | AC56: 32.3 | AD56: 38.03 | AE56: 13.19 | AF56: 0 | AG56: 381.2 | AH56: 4.88 | AI56: 1.6 | AJ56: 1.6
A57: Financial assets - Loans | B57: INR Mn | C57: Company filings | G57: 0 | I57: 0 | K57: 0 | M57: 0 | O57: 0 | Q57: 0 | S57: 0 | U57: 0 | W57: 0 | AC57: 56.31 | AD57: 105.84 | AE57: 161.79 | AF57: 0 | AG57: 0 | AH57: 0 | AI57: 0 | AJ57: 0
A58: Financial assets - Other financial assets | B58: INR Mn | C58: Company filings | G58: 718.79 | I58: 889.82 | K58: 434.5 | M58: 417.87 | O58: 492.36 | Q58: 1153.7 | S58: 986.8 | U58: 593.9 | W58: 685.2 | AC58: 0 | AD58: 0 | AE58: 0 | AF58: 718.79 | AG58: 434.5 | AH58: 492.36 | AI58: 986.8 | AJ58: 685.2
A59: Deferred tax assets (net) | B59: INR Mn | C59: Company filings | G59: 1152.18 | I59: 1424.09 | K59: 1877.73 | M59: 2258.39 | O59: 2689.91 | Q59: 3173.5 | S59: 2579.5 | U59: 2550.5 | W59: 2687.8 | AC59: 501.48 | AD59: 506.11 | AE59: 780.41 | AF59: 1152.18 | AG59: 1877.73 | AH59: 2689.91 | AI59: 2579.5 | AJ59: 2687.8
A60: Non-current tax assets (net) | B60: INR Mn | C60: Company filings | G60: 138.7 | I60: 187.28 | K60: 211.82 | M60: 352.36 | O60: 456.72 | Q60: 22.8 | S60: 639.5 | U60: 844.4 | W60: 622.6 | AC60: 110.46 | AD60: 110.45 | AE60: 85.63 | AF60: 138.7 | AG60: 211.82 | AH60: 456.72 | AI60: 639.5 | AJ60: 622.6
A61: Other non-current assets | B61: INR Mn | C61: Company filings | G61: 102.69 | I61: 235.41 | K61: 241.6 | M61: 191.36 | O61: 115.36 | Q61: 82.9 | S61: 101.5 | U61: 51.8 | W61: 55.2 | AC61: 16.73 | AD61: 38.91 | AE61: 13.53 | AF61: 102.69 | AG61: 241.6 | AH61: 115.36 | AI61: 101.5 | AJ61: 55.2
A62: Total Non-Current Assets | B62: INR Mn | G62: =SUM(G49:G61) -> 7189.82 | I62: =SUM(I49:I61) -> 10733.34 | K62: =SUM(K49:K61) -> 10443.8 | M62: =SUM(M49:M61) -> 10542.41 | O62: =SUM(O49:O61) -> 11076.8 | Q62: =SUM(Q49:Q61) -> 11927 | S62: =SUM(S49:S61) -> 13024.5 | U62: =SUM(U49:U61) -> 13288.7 | W62: =SUM(W49:W61) -> 14224.4 | AC62: =SUM(AC49:AC61) -> 2116.3 | AD62: =SUM(AD49:AD61) -> 3089.88 | AE62: =SUM(AE49:AE61) -> 3389.75 | AF62: =SUM(AF49:AF61) -> 7189.82 | AG62: =SUM(AG49:AG61) -> 10443.8 | AH62: =SUM(AH49:AH61) -> 11076.8 | AI62: =SUM(AI49:AI61) -> 13024.5 | AJ62: =SUM(AJ49:AJ61) -> 14224.4
A64: Current assets
A65: Inventories | B65: INR Mn | C65: Company filings | G65: 8756.21 | I65: 9332.37 | K65: 10051.4 | M65: 10937.07 | O65: 11920.46 | Q65: 14111 | S65: 14175.4 | U65: 15729.2 | W65: 16421.6 | AC65: 2445.96 | AD65: 4453.36 | AE65: 4980.92 | AF65: 8756.21 | AG65: 10051.4 | AH65: 11920.46 | AI65: 14175.4 | AJ65: 16421.6
A66: Financial assets - Investments | B66: INR Mn | C66: Company filings | G66: 0 | I66: 0 | K66: 0 | M66: 0 | O66: 0 | Q66: 0 | S66: 0 | U66: 0 | W66: 0 | AC66: 1350.4 | AD66: 0 | AE66: 0 | AF66: 0 | AG66: 0 | AH66: 0 | AI66: 0 | AJ66: 0
A67: Trade receivables | B67: INR Mn | C67: Company filings | G67: 945.33 | I67: 1263.57 | K67: 1635.31 | M67: 1764.15 | O67: 2416 | Q67: 2547 | S67: 2466.1 | U67: 2588 | W67: 2893.8 | AC67: 579.24 | AD67: 984.32 | AE67: 766.35 | AF67: 945.33 | AG67: 1635.31 | AH67: 2416 | AI67: 2466.1 | AJ67: 2893.8
A68: Cash and cash equivalents | B68: INR Mn | C68: Company filings | G68: 658.9 | I68: 259.14 | K68: 413.76 | M68: 259.63 | O68: 757.77 | Q68: 836.7 | S68: 1249.4 | U68: 1125.7 | W68: 1772 | AC68: 114.1 | AD68: 1011.91 | AE68: 835.82 | AF68: 658.9 | AG68: 413.76 | AH68: 757.77 | AI68: 1249.4 | AJ68: 1772
A69: Bank balance other than cash and cash equivalents | B69: INR Mn | C69: Company filings | G69: 2011.53 | I69: 1353.82 | K69: 1073.64 | M69: 1193.95 | O69: 1640.81 | Q69: 1110.9 | S69: 922.1 | U69: 1011 | W69: 1428.3 | AC69: 5.34 | AD69: 744.28 | AE69: 1640.88 | AF69: 2011.53 | AG69: 1073.64 | AH69: 1640.81 | AI69: 922.1 | AJ69: 1428.3
A70: Financial assets - Loans | B70: INR Mn | C70: Company filings | G70: 0 | I70: 0 | K70: 0 | M70: 0 | O70: 0 | Q70: 0 | S70: 0 | U70: 0 | W70: 0 | AC70: 48.19 | AD70: 74.11 | AE70: 54.26 | AF70: 0 | AG70: 0 | AH70: 0 | AI70: 0 | AJ70: 0
A71: Other financial assets (current) | B71: INR Mn | C71: Company filings | G71: 4878.78 | I71: 2552.45 | K71: 2644.86 | M71: 2723.34 | O71: 1833.22 | Q71: 1729.5 | S71: 2693 | U71: 3192.8 | W71: 3122.5 | AC71: 466.83 | AD71: 258.99 | AE71: 520.12 | AF71: 4878.78 | AG71: 2644.86 | AH71: 1833.22 | AI71: 2693 | AJ71: 3122.5
A72: Other current assets | B72: INR Mn | C72: Company filings | G72: 2019.78 | I72: 3369.24 | K72: 3237.01 | M72: 3938.04 | O72: 4361.2 | Q72: 4972.1 | S72: 5264.8 | U72: 6388.6 | W72: 6251.2 | AC72: 630.21 | AD72: 627.97 | AE72: 831.8 | AF72: 2019.78 | AG72: 3237.01 | AH72: 4361.2 | AI72: 5264.8 | AJ72: 6251.2
A73: Total Current Assets | B73: INR Mn | G73: =SUM(G65:G72) -> 19270.53 | I73: =SUM(I65:I72) -> 18130.59 | K73: =SUM(K65:K72) -> 19055.98 | M73: =SUM(M65:M72) -> 20816.18 | O73: =SUM(O65:O72) -> 22929.46 | Q73: =SUM(Q65:Q72) -> 25307.2 | S73: =SUM(S65:S72) -> 26770.8 | U73: =SUM(U65:U72) -> 30035.3 | W73: =SUM(W65:W72) -> 31889.4 | AC73: =SUM(AC65:AC72) -> 5640.27 | AD73: =SUM(AD65:AD72) -> 8154.94 | AE73: =SUM(AE65:AE72) -> 9630.15 | AF73: =SUM(AF65:AF72) -> 19270.53 | AG73: =SUM(AG65:AG72) -> 19055.98 | AH73: =SUM(AH65:AH72) -> 22929.46 | AI73: =SUM(AI65:AI72) -> 26770.8 | AJ73: =SUM(AJ65:AJ72) -> 31889.4
A75: TOTAL ASSETS | B75: INR Mn | G75: =G62+G73 -> 26460.35 | I75: =I62+I73 -> 28863.93 | K75: =K62+K73 -> 29499.78 | M75: =M62+M73 -> 31358.59 | O75: =O62+O73 -> 34006.26 | Q75: =Q62+Q73 -> 37234.2 | S75: =S62+S73 -> 39795.3 | U75: =U62+U73 -> 43324 | W75: =W62+W73 -> 46113.8 | AC75: =AC62+AC73 -> 7756.57 | AD75: =AD62+AD73 -> 11244.82 | AE75: =AE62+AE73 -> 13019.9 | AF75: =AF62+AF73 -> 26460.35 | AG75: =AG62+AG73 -> 29499.78 | AH75: =AH62+AH73 -> 34006.26 | AI75: =AI62+AI73 -> 39795.3 | AJ75: =AJ62+AJ73 -> 46113.8
A77: EQUITY AND LIABILITIES
A78: Equity
A79: Equity share capital | B79: INR Mn | C79: Company filings | G79: 474.11 | I79: 474.55 | K79: 2852.45 | M79: 2853.73 | O79: 2855.99 | Q79: 2857.9 | S79: 2859.3 | U79: 2861.3 | W79: 2863.3 | AC79: 142.43 | AD79: 145.5 | AE79: 150.58 | AF79: 474.11 | AG79: 2852.45 | AH79: 2855.99 | AI79: 2859.3 | AJ79: 2863.3
A80: Other equity | B80: INR Mn | C80: Company filings | G80: 12924.89 | I80: 13138.2 | K80: 10927.65 | M80: 11059.05 | O80: 9766.34 | Q80: 10190 | S80: 10153.5 | U80: 11017.2 | W80: 11516.5 | AC80: 2163.15 | AD80: 3075.99 | AE80: 4748.81 | AF80: 12924.89 | AG80: 10927.65 | AH80: 9766.34 | AI80: 10153.5 | AJ80: 11516.5
A81: Equity attributable to equity holders of the parent | B81: INR Mn | G81: =SUM(G79:G80) -> 13399 | I81: =SUM(I79:I80) -> 13612.75 | K81: =SUM(K79:K80) -> 13780.1 | M81: =SUM(M79:M80) -> 13912.78 | O81: =SUM(O79:O80) -> 12622.33 | Q81: =SUM(Q79:Q80) -> 13047.9 | S81: =SUM(S79:S80) -> 13012.8 | U81: =SUM(U79:U80) -> 13878.5 | W81: =SUM(W79:W80) -> 14379.8 | AC81: =SUM(AC79:AC80) -> 2305.58 | AD81: =SUM(AD79:AD80) -> 3221.49 | AE81: =SUM(AE79:AE80) -> 4899.39 | AF81: =SUM(AF79:AF80) -> 13399 | AG81: =SUM(AG79:AG80) -> 13780.1 | AH81: =SUM(AH79:AH80) -> 12622.33 | AI81: =SUM(AI79:AI80) -> 13012.8 | AJ81: =SUM(AJ79:AJ80) -> 14379.8
A82: Non-controlling interest | B82: INR Mn | C82: Company filings | G82: 56.15 | I82: 95.09 | K82: 141.45 | M82: 182.6 | O82: 188.11 | Q82: 287.8 | S82: 413.8 | U82: 515.8 | W82: 641.2 | AC82: 4.69 | AD82: 7.38 | AE82: 8.36 | AF82: 56.15 | AG82: 141.45 | AH82: 188.11 | AI82: 413.8 | AJ82: 641.2
A83: Total Equity | B83: INR Mn | G83: =G81+G82 -> 13455.15 | I83: =I81+I82 -> 13707.84 | K83: =K81+K82 -> 13921.55 | M83: =M81+M82 -> 14095.38 | O83: =O81+O82 -> 12810.44 | Q83: =Q81+Q82 -> 13335.7 | S83: =S81+S82 -> 13426.6 | U83: =U81+U82 -> 14394.3 | W83: =W81+W82 -> 15021 | AC83: =AC81+AC82 -> 2310.27 | AD83: =AD81+AD82 -> 3228.87 | AE83: =AE81+AE82 -> 4907.75 | AF83: =AF81+AF82 -> 13455.15 | AG83: =AG81+AG82 -> 13921.55 | AH83: =AH81+AH82 -> 12810.44 | AI83: =AI81+AI82 -> 13426.6 | AJ83: =AJ81+AJ82 -> 15021
A85: Non-current liabilities
A86: Borrowings | B86: INR Mn | C86: Company filings | G86: 9.22 | I86: 6.53 | K86: 3.61 | M86: 0.47 | O86: 0 | Q86: 625 | S86: 1102.1 | U86: 327.4 | W86: 183.3 | AC86: 1.28 | AD86: 1.5 | AE86: 16.6 | AF86: 9.22 | AG86: 3.61 | AH86: 0 | AI86: 1102.1 | AJ86: 183.3
A87: Lease liabilities | B87: INR Mn | C87: Company filings | G87: 2043.19 | I87: 3354.12 | K87: 2133.68 | M87: 1766.89 | O87: 1593.03 | Q87: 1665.8 | S87: 2115.5 | U87: 2562 | W87: 2968.5 | AC87: 763.61 | AD87: 1302.58 | AE87: 1073.9 | AF87: 2043.19 | AG87: 2133.68 | AH87: 1593.03 | AI87: 2115.5 | AJ87: 2968.5
A88: Other financial liabilities | B88: INR Mn | C88: Company filings | G88: 1222.26 | I88: 1280.33 | K88: 1373.2 | M88: 0 | O88: 711.85 | Q88: 0 | S88: 1358.8 | U88: 0 | W88: 16.6 | AC88: 0 | AD88: 0 | AE88: 0 | AF88: 1222.26 | AG88: 1373.2 | AH88: 711.85 | AI88: 1358.8 | AJ88: 16.6
A89: Provisions | B89: INR Mn | C89: Company filings | G89: 77.96 | I89: 89.21 | K89: 92.65 | M89: 108.65 | O89: 102.21 | Q89: 145.5 | S89: 186.4 | U89: 187 | W89: 341.9 | AC89: 24.46 | AD89: 52.61 | AE89: 73.45 | AF89: 77.96 | AG89: 92.65 | AH89: 102.21 | AI89: 186.4 | AJ89: 341.9
A90: Total Non-Current Liabilities | B90: INR Mn | G90: =SUM(G86:G89) -> 3352.63 | I90: =SUM(I86:I89) -> 4730.19 | K90: =SUM(K86:K89) -> 3603.14 | M90: =SUM(M86:M89) -> 1876.01 | O90: =SUM(O86:O89) -> 2407.09 | Q90: =SUM(Q86:Q89) -> 2436.3 | S90: =SUM(S86:S89) -> 4762.8 | U90: =SUM(U86:U89) -> 3076.4 | W90: =SUM(W86:W89) -> 3510.3 | AC90: =SUM(AC86:AC89) -> 789.35 | AD90: =SUM(AD86:AD89) -> 1356.69 | AE90: =SUM(AE86:AE89) -> 1163.95 | AF90: =SUM(AF86:AF89) -> 3352.63 | AG90: =SUM(AG86:AG89) -> 3603.14 | AH90: =SUM(AH86:AH89) -> 2407.09 | AI90: =SUM(AI86:AI89) -> 4762.8 | AJ90: =SUM(AJ86:AJ89) -> 3510.3
A92: Current liabilities
A93: Borrowings | B93: INR Mn | C93: Company filings | G93: 3321.12 | I93: 4862.24 | K93: 4600.01 | M93: 6596.02 | O93: 6803.95 | Q93: 9388.7 | S93: 8511.5 | U93: 9571.1 | W93: 7288.8 | AC93: 2254.48 | AD93: 2673.26 | AE93: 1858.05 | AF93: 3321.12 | AG93: 4600.01 | AH93: 6803.95 | AI93: 8511.5 | AJ93: 7288.8
A94: Lease liabilities | B94: INR Mn | C94: Company filings | G94: 552.7 | I94: 844.52 | K94: 1247.63 | M94: 1293.16 | O94: 1297.89 | Q94: 1383.4 | S94: 1476.8 | U94: 1609.7 | W94: 1937.5 | AC94: 84.63 | AD94: 147.44 | AE94: 378.16 | AF94: 552.7 | AG94: 1247.63 | AH94: 1297.89 | AI94: 1476.8 | AJ94: 1937.5
A95: Trade payables - micro & small enterprises | B95: INR Mn | C95: Company filings | G95: 560.7 | I95: 228.37 | K95: 418.93 | M95: 510.01 | O95: 370.16 | Q95: 423.4 | S95: 452.6 | U95: 762.4 | W95: 1163.4 | AC95: 12.77 | AD95: 104.6 | AE95: 90.75 | AF95: 560.7 | AG95: 418.93 | AH95: 370.16 | AI95: 452.6 | AJ95: 1163.4
A96: Trade payables - other creditors | B96: INR Mn | C96: Company filings | G96: 3059.84 | I96: 1559.62 | K96: 2234.96 | M96: 2367.64 | O96: 3496.76 | Q96: 5040.7 | S96: 5895.7 | U96: 6144.8 | W96: 6161.6 | AC96: 1804.89 | AD96: 3028.05 | AE96: 3071.37 | AF96: 3059.84 | AG96: 2234.96 | AH96: 3496.76 | AI96: 5895.7 | AJ96: 6161.6
A97: Other financial liabilities | B97: INR Mn | C97: Company filings | G97: 1666.92 | I97: 2319.95 | K97: 2703.61 | M97: 3962.46 | O97: 6084.58 | Q97: 4540.9 | S97: 4386.1 | U97: 6755.2 | W97: 9473 | AC97: 275.44 | AD97: 470.53 | AE97: 850.14 | AF97: 1666.92 | AG97: 2703.61 | AH97: 6084.58 | AI97: 4386.1 | AJ97: 9473
A98: Provisions | B98: INR Mn | C98: Company filings | G98: 88.66 | I98: 97.1 | K98: 113.86 | M98: 87.54 | O98: 86.9 | Q98: 113.6 | S98: 101.9 | U98: 123.8 | W98: 268.1 | AC98: 0.37 | AD98: 0.67 | AE98: 108.47 | AF98: 88.66 | AG98: 113.86 | AH98: 86.9 | AI98: 101.9 | AJ98: 268.1
A99: Contract liabilities | B99: INR Mn | C99: Company filings | G99: 160.41 | I99: 258.81 | K99: 234.78 | M99: 249.52 | O99: 273.42 | Q99: 271.7 | S99: 376.1 | U99: 561.8 | W99: 600.7 | AC99: 101.91 | AD99: 148.7 | AE99: 169.15 | AF99: 160.41 | AG99: 234.78 | AH99: 273.42 | AI99: 376.1 | AJ99: 600.7
A100: Current tax liabilities (net) | B100: INR Mn | C100: Company filings | G100: 21.73 | I100: 80.4 | K100: 0 | M100: 0 | O100: 0 | Q100: 299.8 | S100: 0 | U100: 0 | W100: 0 | AC100: 0 | AD100: 2.69 | AE100: 246.94 | AF100: 21.73 | AG100: 0 | AH100: 0 | AI100: 0 | AJ100: 0
A101: Other current liabilities | B101: INR Mn | C101: Company filings | G101: 220.49 | I101: 174.89 | K101: 421.31 | M101: 320.85 | O101: 375.07 | S101: 405.2 | U101: 324.5 | W101: 689.4 | AC101: 122.46 | AD101: 83.32 | AE101: 175.17 | AF101: 220.49 | AG101: 421.31 | AH101: 375.07 | AI101: 405.2 | AJ101: 689.4
A102: Total Current Liabilities | B102: INR Mn | G102: =SUM(G93:G101) -> 9652.57 | I102: =SUM(I93:I101) -> 10425.9 | K102: =SUM(K93:K101) -> 11975.09 | M102: =SUM(M93:M101) -> 15387.2 | O102: =SUM(O93:O101) -> 18788.73 | Q102: =SUM(Q93:Q101) -> 21462.2 | S102: =SUM(S93:S101) -> 21605.9 | U102: =SUM(U93:U101) -> 25853.3 | W102: =SUM(W93:W101) -> 27582.5 | AC102: =SUM(AC93:AC101) -> 4656.95 | AD102: =SUM(AD93:AD101) -> 6659.26 | AE102: =SUM(AE93:AE101) -> 6948.2 | AF102: =SUM(AF93:AF101) -> 9652.57 | AG102: =SUM(AG93:AG101) -> 11975.09 | AH102: =SUM(AH93:AH101) -> 18788.73 | AI102: =SUM(AI93:AI101) -> 21605.9 | AJ102: =SUM(AJ93:AJ101) -> 27582.5
A104: Total Liabilities | B104: INR Mn | G104: =G90+G102 -> 13005.2 | I104: =I90+I102 -> 15156.09 | K104: =K90+K102 -> 15578.23 | M104: =M90+M102 -> 17263.21 | O104: =O90+O102 -> 21195.82 | Q104: =Q90+Q102 -> 23898.5 | S104: =S90+S102 -> 26368.7 | U104: =U90+U102 -> 28929.7 | W104: =W90+W102 -> 31092.8 | AC104: =AC90+AC102 -> 5446.3 | AD104: =AD90+AD102 -> 8015.95 | AE104: =AE90+AE102 -> 8112.15 | AF104: =AF90+AF102 -> 13005.2 | AG104: =AG90+AG102 -> 15578.23 | AH104: =AH90+AH102 -> 21195.82 | AI104: =AI90+AI102 -> 26368.7 | AJ104: =AJ90+AJ102 -> 31092.8
A105: TOTAL EQUITY AND LIABILITIES | B105: INR Mn | G105: =G83+G104 -> 26460.35 | I105: =I83+I104 -> 28863.93 | K105: =K83+K104 -> 29499.78 | M105: =M83+M104 -> 31358.59 | O105: =O83+O104 -> 34006.26 | Q105: =Q83+Q104 -> 37234.2 | S105: =S83+S104 -> 39795.3 | U105: =U83+U104 -> 43324 | W105: =W83+W104 -> 46113.8 | AC105: =AC83+AC104 -> 7756.57 | AD105: =AD83+AD104 -> 11244.82 | AE105: =AE83+AE104 -> 13019.9 | AF105: =AF83+AF104 -> 26460.35 | AG105: =AG83+AG104 -> 29499.78 | AH105: =AH83+AH104 -> 34006.26 | AI105: =AI83+AI104 -> 39795.3 | AJ105: =AJ83+AJ104 -> 46113.8
A106: Check (Total Assets - Total Equity and Liabilities) | B106: INR Mn | G106: =G75-G105 -> 0 | I106: =I75-I105 -> 0 | K106: =K75-K105 -> 0 | M106: =M75-M105 -> 0 | O106: =O75-O105 -> 0 | Q106: =Q75-Q105 -> 0 | S106: =S75-S105 -> 0 | U106: =U75-U105 -> 0 | W106: =W75-W105 -> 0 | AC106: =AC75-AC105 -> 0 | AD106: =AD75-AD105 -> 0 | AE106: =AE75-AE105 -> 0 | AF106: =AF75-AF105 -> 0 | AG106: =AG75-AG105 -> 0 | AH106: =AH75-AH105 -> 0 | AI106: =AI75-AI105 -> 0 | AJ106: =AJ75-AJ105 -> 0
A109: CASH FLOW STATEMENT (CONSOLIDATED)
A110: Profit/(loss) before tax (per Statement of Profit and Loss) | B110: INR Mn | C110: Company filings | AC110: -317.2 | AD110: -124.3 | AE110: 753.38 | AF110: 473.06 | AG110: 383.95 | AH110: 690.27 | AI110: 1274.5 | AJ110: 3302.3
A111: Adjustments to reconcile profit before tax to net cash flows
A112: Depreciation of PP&E and right-of-use assets | B112: INR Mn | C112: Company filings | AC112: 308.76 | AD112: 595.09 | AE112: 671.28 | AF112: 835 | AG112: 1559.73 | AH112: 1998.62 | AI112: 2321.2 | AJ112: 2766.1
A113: Amortisation of intangible assets | B113: INR Mn | C113: Company filings | AC113: 0 | AD113: 0 | AE113: 0 | AF113: 129.12 | AG113: 172.81 | AH113: 243.71 | AI113: 342.8 | AJ113: 437.2
A114: Interest expense and other finance costs | B114: INR Mn | C114: Company filings | AC114: 263.42 | AD114: 442.93 | AE114: 307.01 | AF114: 465.11 | AG114: 746.05 | AH114: 828.32 | AI114: 1073.2 | AJ114: 1171.2
A115: Foreign exchange (gain)/loss | B115: INR Mn | C115: Company filings | AC115: 0 | AD115: 0 | AE115: 0 | AF115: 0.65 | AG115: -3.11 | AH115: 6.41 | AI115: 0 | AJ115: -31.9
A116: Realised gain from sale of investments | B116: INR Mn | C116: Company filings | AC116: 0 | AD116: -74.41 | AE116: 0 | AF116: 0 | AG116: 0 | AH116: 0 | AI116: 0 | AJ116: 0
A117: Unrealised gain on fair valuation of investments | B117: INR Mn | C117: Company filings | AC117: -15.28 | AD117: 0 | AE117: 0 | AF117: 0 | AG117: 0 | AH117: 0 | AI117: 0 | AJ117: 0
...

Sheet Raw Data - Ops KPIs
A3: All figures in INR Mn unless stated otherwise.
A5: Metric | B5: Unit | C5: Source - Deck section | D5: Q1FY22 | E5: Q2FY22 | F5: Q3FY22 | G5: Q4FY22 | H5: Q1FY23 | I5: Q2FY23 | J5: Q3FY23 | K5: Q4FY23 | L5: Q1FY24 | M5: Q2FY24 | N5: Q3FY24 | O5: Q4FY24 | P5: Q1FY25 | Q5: Q2FY25 | R5: Q3FY25 | S5: Q4FY25 | T5: Q1FY26 | U5: Q2FY26 | V5: Q3FY26 | W5: Q4FY26 | X5: Q1FY27 | Y5: Q2FY27 | Z5: Q3FY27 | AA5: Q4FY27 | AF5: FY22 | AG5: FY23 | AH5: FY24 | AI5: FY25 | AJ5: FY26
A6: Consolidated Operating KPIs
A7: Number of visits | B7: mn | C7: One Nykaa Highlights | D7: 312.4 | E7: 335 | F7: 347 | G7: 328 | H7: 354 | I7: 372 | J7: 403 | K7: 369 | L7: 395 | M7: 430 | N7: 468 | O7: 447 | AF7: =IF(COUNT(D7:G7)=0,"",SUM(D7:G7)) -> 1322.4 | AG7: =IF(COUNT(H7:K7)=0,"",SUM(H7:K7)) -> 1498 | AH7: =IF(COUNT(L7:O7)=0,"",SUM(L7:O7)) -> 1740 | AI7: =IF(COUNT(P7:S7)=0,"",SUM(P7:S7)) | AJ7: =IF(COUNT(T7:W7)=0,"",SUM(T7:W7))
A8: Annual transacting customers | B8: mn | C8: One Nykaa Highlights | D8: 7.7 | E8: 8.6 | F8: 9.4 | G8: 10.2 | H8: 11 | I8: 11.7 | J8: 12.5 | K8: 13 | L8: 13.5 | M8: 14 | N8: 14.6 | O8: 15.4 | AF8: =IF(G8="","",G8) -> 10.2 | AG8: =IF(K8="","",K8) -> 13 | AH8: =IF(O8="","",O8) -> 15.4 | AI8: =IF(S8="","",S8) | AJ8: =IF(W8="","",W8)
A9: YoY growth | B9: % | H9: =IFERROR(H8/D8-1,"") -> 0.42857143 | I9: =IFERROR(I8/E8-1,"") -> 0.36046512 | J9: =IFERROR(J8/F8-1,"") -> 0.32978723 | K9: =IFERROR(K8/G8-1,"") -> 0.2745098 | L9: =IFERROR(L8/H8-1,"") -> 0.22727273 | M9: =IFERROR(M8/I8-1,"") -> 0.1965812 | N9: =IFERROR(N8/J8-1,"") -> 0.168 | O9: =IFERROR(O8/K8-1,"") -> 0.18461538 | ... AA9: =IFERROR(AA8/W8-1,"") | AF9: =IFERROR(AF8/AE8-1,"") | AG9: =IFERROR(AG8/AF8-1,"") -> 0.2745098 | AH9: =IFERROR(AH8/AG8-1,"") -> 0.18461538 | AI9: =IFERROR(AI8/AH8-1,"") | AJ9: =IFERROR(AJ8/AI8-1,"")
A10: Number of orders | B10: mn | C10: One Nykaa Highlights | D10: 7 | E10: 7.4 | F10: 9 | G10: 8.7 | H10: 9.9 | I10: 10.1 | J10: 11.6 | K10: 10.6 | L10: 11.4 | M10: 12.2 | N10: 13.7 | O10: 13.4 | AF10: =IF(COUNT(D10:G10)=0,"",SUM(D10:G10)) -> 32.1 | AG10: =IF(COUNT(H10:K10)=0,"",SUM(H10:K10)) -> 42.2 | AH10: =IF(COUNT(L10:O10)=0,"",SUM(L10:O10)) -> 50.7 | AI10: =IF(COUNT(P10:S10)=0,"",SUM(P10:S10)) | AJ10: =IF(COUNT(T10:W10)=0,"",SUM(T10:W10))
A11: Total GMV | B11: Rs Mn | C11: One Nykaa Highlights | D11: 14696 | E11: 16229 | F11: 20428 | G11: 17979 | H11: 21588 | I11: 23457 | J11: 27965 | K11: 24454 | L11: 26678 | M11: 29435 | N11: 36195 | O11: 32163 | P11: 33209 | Q11: 36525 | R11: 45279 | S11: 41020 | T11: 41820 | U11: 47440 | V11: 57950 | W11: 52410 | AF11: =IF(COUNT(D11:G11)=0,"",SUM(D11:G11)) -> 69332 | AG11: =IF(COUNT(H11:K11)=0,"",SUM(H11:K11)) -> 97464 | AH11: =IF(COUNT(L11:O11)=0,"",SUM(L11:O11)) -> 124471 | AI11: =IF(COUNT(P11:S11)=0,"",SUM(P11:S11)) -> 156033 | AJ11: =IF(COUNT(T11:W11)=0,"",SUM(T11:W11)) -> 199620
A12: YoY growth | B12: % | H12: =IFERROR(H11/D11-1,"") -> 0.46897115 | I12: =IFERROR(I11/E11-1,"") -> 0.44537556 | J12: =IFERROR(J11/F11-1,"") -> 0.36895438 | K12: =IFERROR(K11/G11-1,"") -> 0.36014239 | L12: =IFERROR(L11/H11-1,"") -> 0.23577914 | M12: =IFERROR(M11/I11-1,"") -> 0.2548493 | N12: =IFERROR(N11/J11-1,"") -> 0.29429644 | O12: =IFERROR(O11/K11-1,"") -> 0.31524495 | ... AA12: =IFERROR(AA11/W11-1,"") -> -1 | AF12: =IFERROR(AF11/AE11-1,"") | AG12: =IFERROR(AG11/AF11-1,"") -> 0.4057578 | AH12: =IFERROR(AH11/AG11-1,"") -> 0.27709718 | AI12: =IFERROR(AI11/AH11-1,"") -> 0.2535691 | AJ12: =IFERROR(AJ11/AI11-1,"") -> 0.27934475
A13: QoQ growth | B13: % | E13: =IFERROR(E11/D11-1,"") -> 0.1043141 | F13: =IFERROR(F11/E11-1,"") -> 0.25873436 | G13: =IFERROR(G11/F11-1,"") -> -0.11988447 | H13: =IFERROR(H11/G11-1,"") -> 0.20073419 | I13: =IFERROR(I11/H11-1,"") -> 0.086575875 | J13: =IFERROR(J11/I11-1,"") -> 0.19218144 | K13: =IFERROR(K11/J11-1,"") -> -0.12554979 | L13: =IFERROR(L11/K11-1,"") -> 0.090946266 | ... AA13: =IFERROR(AA11/Z11-1,"")
A14: Total NSV | B14: Rs Mn | C14: One Nykaa Highlights | D14: 8050 | E14: 8688 | F14: 10729 | G14: 9650 | H14: 11272 | I14: 12049 | J14: 14401 | K14: 12904 | L14: 14205 | M14: 14982 | N14: 17866 | O14: 16489 | P14: 17183 | Q14: 18432 | R14: 22190 | S14: 20430 | T14: 21370 | U14: 23400 | V14: 28440 | W14: 26780 | AF14: =IF(COUNT(D14:G14)=0,"",SUM(D14:G14)) -> 37117 | AG14: =IF(COUNT(H14:K14)=0,"",SUM(H14:K14)) -> 50626 | AH14: =IF(COUNT(L14:O14)=0,"",SUM(L14:O14)) -> 63542 | AI14: =IF(COUNT(P14:S14)=0,"",SUM(P14:S14)) -> 78235 | AJ14: =IF(COUNT(T14:W14)=0,"",SUM(T14:W14)) -> 99990
A15: NSV / GMV | B15: % | D15: =IFERROR(D14/D11,"") -> 0.5477681 | E15: =IFERROR(E14/E11,"") -> 0.53533798 | F15: =IFERROR(F14/F11,"") -> 0.5252105 | G15: =IFERROR(G14/G11,"") -> 0.5367373 | H15: =IFERROR(H14/H11,"") -> 0.52214193 | I15: =IFERROR(I14/I11,"") -> 0.5136633 | J15: =IFERROR(J14/J11,"") -> 0.51496513 | K15: =IFERROR(K14/K11,"") -> 0.52768463 | ... AA15: =IFERROR(AA14/AA11,"") | AF15: =IFERROR(AF14/AF11,"") -> 0.53535164 | AG15: =IFERROR(AG14/AG11,"") -> 0.51943282 | AH15: =IFERROR(AH14/AH11,"") -> 0.51049642 | AI15: =IFERROR(AI14/AI11,"") -> 0.50140034 | AJ15: =IFERROR(AJ14/AJ11,"") -> 0.50090171
A16: Total Revenue | B16: Rs Mn | C16: One Nykaa Highlights / Financial Performance | D16: 8169.91 | E16: 8852.64 | F16: 10983.6 | G16: 9733.2 | H16: 11484.21 | I16: 12308.29 | J16: 14628.26 | K16: 13017.24 | L16: 14218.24 | M16: 15070.24 | N16: 17887.98 | O16: 16679.8 | P16: 17461.1 | Q16: 18747.4 | R16: 22672.1 | S16: 20617.6 | T16: 21549.4 | U16: 23459.8 | V16: 28732.6 | W16: 26480 | AF16: =IF(COUNT(D16:G16)=0,"",SUM(D16:G16)) -> 37739.35 | AG16: =IF(COUNT(H16:K16)=0,"",SUM(H16:K16)) -> 51438 | AH16: =IF(COUNT(L16:O16)=0,"",SUM(L16:O16)) -> 63856.26 | AI16: =IF(COUNT(P16:S16)=0,"",SUM(P16:S16)) -> 79498.2 | AJ16: =IF(COUNT(T16:W16)=0,"",SUM(T16:W16)) -> 100221.8
A17: YoY growth | B17: % | H17: =IFERROR(H16/D16-1,"") -> 0.40567154 | I17: =IFERROR(I16/E16-1,"") -> 0.39035248 | J17: =IFERROR(J16/F16-1,"") -> 0.33182745 | K17: =IFERROR(K16/G16-1,"") -> 0.33740599 | L17: =IFERROR(L16/H16-1,"") -> 0.23806862 | M17: =IFERROR(M16/I16-1,"") -> 0.22439754 | N17: =IFERROR(N16/J16-1,"") -> 0.22283717 | O17: =IFERROR(O16/K16-1,"") -> 0.28136225 | ... AA17: =IFERROR(AA16/W16-1,"") -> -1 | AF17: =IFERROR(AF16/AE16-1,"") | AG17: =IFERROR(AG16/AF16-1,"") -> 0.36298055 | AH17: =IFERROR(AH16/AG16-1,"") -> 0.24142191 | AI17: =IFERROR(AI16/AH16-1,"") -> 0.24495547 | AJ17: =IFERROR(AJ16/AI16-1,"") -> 0.26068012
A18: Revenue / NSV | B18: % | D18: =IFERROR(D16/D14,"") -> 1.0148957 | E18: =IFERROR(E16/E14,"") -> 1.0189503 | F18: =IFERROR(F16/F14,"") -> 1.0237301 | G18: =IFERROR(G16/G14,"") -> 1.0086218 | H18: =IFERROR(H16/H14,"") -> 1.0188263 | I18: =IFERROR(I16/I14,"") -> 1.0215196 | J18: =IFERROR(J16/J14,"") -> 1.0157808 | K18: =IFERROR(K16/K14,"") -> 1.0087756 | ... AA18: =IFERROR(AA16/AA14,"") | AF18: =IFERROR(AF16/AF14,"") -> 1.0167672 | AG18: =IFERROR(AG16/AG14,"") -> 1.0160392 | AH18: =IFERROR(AH16/AH14,"") -> 1.0049457 | AI18: =IFERROR(AI16/AI14,"") -> 1.0161462 | AJ18: =IFERROR(AJ16/AJ14,"") -> 1.0023182
A19: Gross profit | B19: Rs Mn | C19: Financial Performance (Total column) | D19: 3316.59 | E19: 3782.42 | F19: 5087.58 | G19: 4252.61 | H19: 5098.79 | I19: 5577.38 | J19: 6346.7 | K19: 5758.32 | L19: 6186.25 | M19: 6496.24 | N19: 7607.48 | O19: 7102.43 | P19: 7559.8 | Q19: 8210.2 | R19: 9911.4 | S19: 9090.2 | T19: 9615.1 | U19: 10535.4 | V19: 12974.8 | W19: 12030 | AF19: =IF(COUNT(D19:G19)=0,"",SUM(D19:G19)) -> 16439.2 | AG19: =IF(COUNT(H19:K19)=0,"",SUM(H19:K19)) -> 22781.19 | AH19: =IF(COUNT(L19:O19)=0,"",SUM(L19:O19)) -> 27392.4 | AI19: =IF(COUNT(P19:S19)=0,"",SUM(P19:S19)) -> 34771.6 | AJ19: =IF(COUNT(T19:W19)=0,"",SUM(T19:W19)) -> 45155.3
A20: Gross margin (% of NSV) | B20: % | D20: =IFERROR(D19/D14,"") -> 0.41199876 | E20: =IFERROR(E19/E14,"") -> 0.43536142 | F20: =IFERROR(F19/F14,"") -> 0.47418958 | G20: =IFERROR(G19/G14,"") -> 0.44068497 | H20: =IFERROR(H19/H14,"") -> 0.4523412 | I20: =IFERROR(I19/I14,"") -> 0.46289153 | J20: =IFERROR(J19/J14,"") -> 0.44071245 | K20: =IFERROR(K19/K14,"") -> 0.44624303 | ... AA20: =IFERROR(AA19/AA14,"") | AF20: =IFERROR(AF19/AF14,"") -> 0.44290217 | AG20: =IFERROR(AG19/AG14,"") -> 0.44998993 | AH20: =IFERROR(AH19/AH14,"") -> 0.43109125 | AI20: =IFERROR(AI19/AI14,"") -> 0.44445069 | AJ20: =IFERROR(AJ19/AJ14,"") -> 0.45159816
A21: Fulfilment cost | B21: Rs Mn | C21: Financial Performance (Total column) | D21: 934 | E21: 910 | F21: 1162 | G21: 949 | H21: 1294 | I21: 1454 | J21: 1288 | K21: 1286 | L21: 1357 | M21: 1459 | N21: 1718 | O21: 1550 | P21: 1667 | Q21: 1748 | R21: 2090 | S21: 1920 | T21: 2030 | U21: 2270 | V21: 2690 | W21: 2600 | AF21: =IF(COUNT(D21:G21)=0,"",SUM(D21:G21)) -> 3955 | AG21: =IF(COUNT(H21:K21)=0,"",SUM(H21:K21)) -> 5322 | AH21: =IF(COUNT(L21:O21)=0,"",SUM(L21:O21)) -> 6084 | AI21: =IF(COUNT(P21:S21)=0,"",SUM(P21:S21)) -> 7425 | AJ21: =IF(COUNT(T21:W21)=0,"",SUM(T21:W21)) -> 9590
A22: Marketing & S&D expense (combined) | B22: Rs Mn | C22: Financial Performance (Total column) | D22: 1099 | E22: 1521 | F22: 1846 | G22: 1561 | H22: 1524 | I22: 1635 | J22: 1982 | K22: 1670 | L22: 1919 | M22: 2036 | N22: 2558 | O22: 2361 | P22: 2483 | Q22: 2767 | R22: 3620 | S22: 3160 | T22: 3180 | U22: 3560 | V22: 4380 | W22: 3740 | AF22: =IF(COUNT(D22:G22)=0,"",SUM(D22:G22)) -> 6027 | AG22: =IF(COUNT(H22:K22)=0,"",SUM(H22:K22)) -> 6811 | AH22: =IF(COUNT(L22:O22)=0,"",SUM(L22:O22)) -> 8874 | AI22: =IF(COUNT(P22:S22)=0,"",SUM(P22:S22)) -> 12030 | AJ22: =IF(COUNT(T22:W22)=0,"",SUM(T22:W22)) -> 14860
A23: Contribution profit | B23: Rs Mn | D23: =IF(OR(ISBLANK(D19),ISBLANK(D21),ISBLANK(D22)),"",IFERROR(D19-D21-D22,"")) -> 1283.59 | E23: =IF(OR(ISBLANK(E19),ISBLANK(E21),ISBLANK(E22)),"",IFERROR(E19-E21-E22,"")) -> 1351.42 | F23: =IF(OR(ISBLANK(F19),ISBLANK(F21),ISBLANK(F22)),"",IFERROR(F19-F21-F22,"")) -> 2079.58 | G23: =IF(OR(ISBLANK(G19),ISBLANK(G21),ISBLANK(G22)),"",IFERROR(G19-G21-G22,"")) -> 1742.61 | H23: =IF(OR(ISBLANK(H19),ISBLANK(H21),ISBLANK(H22)),"",IFERROR(H19-H21-H22,"")) -> 2280.79 | I23: =IF(OR(ISBLANK(I19),ISBLANK(I21),ISBLANK(I22)),"",IFERROR(I19-I21-I22,"")) -> 2488.38 | J23: =IF(OR(ISBLANK(J19),ISBLANK(J21),ISBLANK(J22)),"",IFERROR(J19-J21-J22,"")) -> 3076.7 | K23: =IF(OR(ISBLANK(K19),ISBLANK(K21),ISBLANK(K22)),"",IFERROR(K19-K21-K22,"")) -> 2802.32 | ... AA23: =IF(OR(ISBLANK(AA19),ISBLANK(AA21),ISBLANK(AA22)),"",IFERROR(AA19-AA21-AA22,"")) | AF23: =IF(OR(ISBLANK(AF19),ISBLANK(AF21),ISBLANK(AF22)),"",IFERROR(AF19-AF21-AF22,"")) -> 6457.2 | AG23: =IF(OR(ISBLANK(AG19),ISBLANK(AG21),ISBLANK(AG22)),"",IFERROR(AG19-AG21-AG22,"")) -> 10648.19 | AH23: =IF(OR(ISBLANK(AH19),ISBLANK(AH21),ISBLANK(AH22)),"",IFERROR(AH19-AH21-AH22,"")) -> 12434.4 | AI23: =IF(OR(ISBLANK(AI19),ISBLANK(AI21),ISBLANK(AI22)),"",IFERROR(AI19-AI21-AI22,"")) -> 15316.6 | AJ23: =IF(OR(ISBLANK(AJ19),ISBLANK(AJ21),ISBLANK(AJ22)),"",IFERROR(AJ19-AJ21-AJ22,"")) -> 20705.3
A24: Contribution margin (% of NSV) | B24: % | D24: =IFERROR(D23/D14,"") -> 0.15945217 | E24: =IFERROR(E23/E14,"") -> 0.15555018 | F24: =IFERROR(F23/F14,"") -> 0.19382794 | G24: =IFERROR(G23/G14,"") -> 0.18058135 | H24: =IFERROR(H23/H14,"") -> 0.2023412 | I24: =IFERROR(I23/I14,"") -> 0.2065217 | J24: =IFERROR(J23/J14,"") -> 0.21364489 | K24: =IFERROR(K23/K14,"") -> 0.21716677 | ... AA24: =IFERROR(AA23/AA14,"") | AF24: =IFERROR(AF23/AF14,"") -> 0.1739688 | AG24: =IFERROR(AG23/AG14,"") -> 0.21033046 | AH24: =IFERROR(AH23/AH14,"") -> 0.19568789 | AI24: =IFERROR(AI23/AI14,"") -> 0.19577683 | AJ24: =IFERROR(AJ23/AJ14,"") -> 0.20707371
A25: Other expenses (G&A + employee) | B25: Rs Mn | C25: Financial Performance (Total column) | D25: 1014.15 | E25: 1063.18 | F25: 1735.81 | G25: 1357 | H25: 1820.27 | I25: 1877.01 | J25: 2295.1 | K25: 2095.38 | L25: 2175.59 | M25: 2194.95 | N25: 2343.74 | O25: 2258.61 | P25: 2448.6 | Q25: 2658.6 | R25: 2793.6 | S25: 2676.7 | T25: 2898.3 | U25: 2995.9 | V25: 3387.2 | W25: 3470 | AF25: =IF(COUNT(D25:G25)=0,"",SUM(D25:G25)) -> 5170.14 | AG25: =IF(COUNT(H25:K25)=0,"",SUM(H25:K25)) -> 8087.76 | AH25: =IF(COUNT(L25:O25)=0,"",SUM(L25:O25)) -> 8972.89 | AI25: =IF(COUNT(P25:S25)=0,"",SUM(P25:S25)) -> 10577.5 | AJ25: =IF(COUNT(T25:W25)=0,"",SUM(T25:W25)) -> 12751.4
A26: EBITDA | B26: Rs Mn | D26: =IF(OR(ISBLANK(D23),ISBLANK(D25)),"",IFERROR(D23-D25,"")) -> 269.44 | E26: =IF(OR(ISBLANK(E23),ISBLANK(E25)),"",IFERROR(E23-E25,"")) -> 288.24 | F26: =IF(OR(ISBLANK(F23),ISBLANK(F25)),"",IFERROR(F23-F25,"")) -> 343.77 | G26: =IF(OR(ISBLANK(G23),ISBLANK(G25)),"",IFERROR(G23-G25,"")) -> 385.61 | H26: =IF(OR(ISBLANK(H23),ISBLANK(H25)),"",IFERROR(H23-H25,"")) -> 460.52 | I26: =IF(OR(ISBLANK(I23),ISBLANK(I25)),"",IFERROR(I23-I25,"")) -> 611.37 | J26: =IF(OR(ISBLANK(J23),ISBLANK(J25)),"",IFERROR(J23-J25,"")) -> 781.6 | K26: =IF(OR(ISBLANK(K23),ISBLANK(K25)),"",IFERROR(K23-K25,"")) -> 706.94 | ... AA26: =IF(OR(ISBLANK(AA23),ISBLANK(AA25)),"",IFERROR(AA23-AA25,"")) | AF26: =IF(OR(ISBLANK(AF23),ISBLANK(AF25)),"",IFERROR(AF23-AF25,"")) -> 1287.06 | AG26: =IF(OR(ISBLANK(AG23),ISBLANK(AG25)),"",IFERROR(AG23-AG25,"")) -> 2560.43 | AH26: =IF(OR(ISBLANK(AH23),ISBLANK(AH25)),"",IFERROR(AH23-AH25,"")) -> 3461.51 | AI26: =IF(OR(ISBLANK(AI23),ISBLANK(AI25)),"",IFERROR(AI23-AI25,"")) -> 4739.1 | AJ26: =IF(OR(ISBLANK(AJ23),ISBLANK(AJ25)),"",IFERROR(AJ23-AJ25,"")) -> 7953.9
A27: EBITDA margin (% of NSV) | B27: % | D27: =IFERROR(D26/D14,"") -> 0.033470807 | E27: =IFERROR(E26/E14,"") -> 0.033176796 | F27: =IFERROR(F26/F14,"") -> 0.032041197 | G27: =IFERROR(G26/G14,"") -> 0.039959585 | H27: =IFERROR(H26/H14,"") -> 0.040855216 | I27: =IFERROR(I26/I14,"") -> 0.05074031 | J27: =IFERROR(J26/J14,"") -> 0.054274009 | K27: =IFERROR(K26/K14,"") -> 0.054784563 | ... AA27: =IFERROR(AA26/AA14,"") | AF27: =IFERROR(AF26/AF14,"") -> 0.034675755 | AG27: =IFERROR(AG26/AG14,"") -> 0.050575396 | AH27: =IFERROR(AH26/AH14,"") -> 0.054475937 | AI27: =IFERROR(AI26/AI14,"") -> 0.06057519 | AJ27: =IFERROR(AJ26/AJ14,"") -> 0.079546955
A29: Beauty (incl. SuperStore) - Omnichannel Retail
A30: Definition: BPC (online + offline) + Superstore by Nykaa + Nykaa Man Grooming + House of Nykaa owned brands
A31: Number of visits | B31: mn | C31: Beauty Omnichannel Retail | D31: 205 | E31: 211 | F31: 221 | G31: 204 | H31: 222 | I31: 234 | J31: 250 | K31: 231 | L31: 269 | M31: 287 | N31: 311 | O31: 303 | P31: 330 | Q31: 357 | R31: 401 | S31: 393 | T31: 411 | U31: 450 | V31: 538 | W31: =AJ31-SUM(T31:V31) -> 495 | AF31: =IF(COUNT(D31:G31)=0,"",SUM(D31:G31)) -> 841 | AG31: =IF(COUNT(H31:K31)=0,"",SUM(H31:K31)) -> 937 | AH31: =IF(COUNT(L31:O31)=0,"",SUM(L31:O31)) -> 1170 | AI31: =IF(COUNT(P31:S31)=0,"",SUM(P31:S31)) -> 1481 | AJ31: 1894
A32: Monthly average unique visitors | B32: mn | C32: Beauty Omnichannel Retail | D32: 17.3 | E32: 19.4 | F32: 19.8 | G32: 18.5 | H32: 21.8 | I32: 22.1 | J32: 24.2 | K32: 22.5 | L32: 27.3 | M32: 26.8 | N32: 29.6 | O32: 31.9 | P32: 32.6 | Q32: 34.2 | R32: 38.1 | S32: 38 | T32: 38.8 | U32: 41.6 | V32: 50.7 | AF32: =IFERROR(AVERAGE(D32:G32),"") -> 18.75 | AG32: =IFERROR(AVERAGE(H32:K32),"") -> 22.65 | AH32: 30.2 | AI32: =IFERROR(AVERAGE(P32:S32),"") -> 35.725 | AJ32: 44.7
A33: Conversion - orders/visits | B33: % | D33: =IFERROR(D37/D31,"") -> 0.028292683 | E33: =IFERROR(E37/E31,"") -> 0.028436019 | F33: =IFERROR(F37/F31,"") -> 0.033936652 | G33: =IFERROR(G37/G31,"") -> 0.035294118 | H33: =IFERROR(H37/H31,"") -> 0.036486486 | I33: =IFERROR(I37/I31,"") -> 0.035897436 | J33: =IFERROR(J37/J31,"") -> 0.038 | K33: =IFERROR(K37/K31,"") -> 0.038095238 | ... AA33: =IFERROR(AA37/AA31,"") | AF33: =IFERROR(AF37/AF31,"") -> 0.031510107 | AG33: =IFERROR(AG37/AG31,"") -> 0.037139808 | AH33: =IFERROR(AH37/AH31,"") -> 0.037350427 | AI33: =IFERROR(AI37/AI31,"") -> 0.03679946 | AJ33: =IFERROR(AJ37/AJ31,"") -> 0.034741288
A34: Conversion - transacting customers/visits | B34: % | D34: =IFERROR(D35/D31,"") -> 0.031707317 | E34: =IFERROR(E35/E31,"") -> 0.033175355 | F34: =IFERROR(F35/F31,"") -> 0.033936652 | G34: =IFERROR(G35/G31,"") -> 0.039215686 | H34: =IFERROR(H35/H31,"") -> 0.038738739 | I34: =IFERROR(I35/I31,"") -> 0.038888889 | J34: =IFERROR(J35/J31,"") -> 0.0384 | K34: =IFERROR(K35/K31,"") -> 0.043290043 | ... AA34: =IFERROR(AA35/AA31,"") | AF34: =IFERROR(AF35/AF31,"") -> 0.0095124851 | AG34: =IFERROR(AG35/AG31,"") -> 0.010672359 | AH34: =IFERROR(AH35/AH31,"") -> 0.010598291 | AI34: =IFERROR(AI35/AI31,"") -> 0.010668467 | AJ34: =IFERROR(AJ35/AJ31,"") -> 0.010401267
A35: Annual transacting customers | B35: mn | C35: Beauty Omnichannel Retail | D35: 6.5 | E35: 7 | F35: 7.5 | G35: 8 | H35: 8.6 | I35: 9.1 | J35: 9.6 | K35: 10 | L35: 10.9 | M35: 10.7 | N35: 11.7 | O35: 12.4 | P35: 13.1 | Q35: 13.7 | R35: 14.8 | S35: 15.8 | T35: 16.5 | U35: 17.5 | V35: 18.7 | W35: 19.7 | AF35: =IF(G35="","",G35) -> 8 | AG35: =IF(K35="","",K35) -> 10 | AH35: =IF(O35="","",O35) -> 12.4 | AI35: =IF(S35="","",S35) -> 15.8 | AJ35: =IF(W35="","",W35) -> 19.7
A36: Average order frequency | B36: x | D36: =IFERROR(D37*4/D35,"") -> 3.5692308 | E36: =IFERROR(E37*4/E35,"") -> 3.4285714 | F36: =IFERROR(F37*4/F35,"") -> 4 | G36: =IFERROR(G37*4/G35,"") -> 3.6 | H36: =IFERROR(H37*4/H35,"") -> 3.7674419 | I36: =IFERROR(I37*4/I35,"") -> 3.6923077 | J36: =IFERROR(J37*4/J35,"") -> 3.9583333 | K36: =IFERROR(K37*4/K35,"") -> 3.52 | ... AA36: =IFERROR(AA37*4/AA35,"") | AF36: =IFERROR(AF37*4/AF35,"") -> 13.25 | AG36: =IFERROR(AG37*4/AG35,"") -> 13.92 | AH36: =IFERROR(AH37*4/AH35,"") -> 14.096774 | AI36: =IFERROR(AI37*4/AI35,"") -> 13.797468 | AJ36: =IFERROR(AJ37*4/AJ35,"") -> 13.360406
A37: Number of orders | B37: mn | C37: Beauty Omnichannel Retail | D37: 5.8 | E37: 6 | F37: 7.5 | G37: 7.2 | H37: 8.1 | I37: 8.4 | J37: 9.5 | K37: 8.8 | L37: 9.9 | M37: 10.5 | N37: 11.6 | O37: 11.7 | P37: 12.4 | Q37: 12.9 | R37: 15 | S37: 14.2 | T37: 14.5 | U37: 15.7 | V37: 18.1 | W37: =AJ37-SUM(T37:V37) -> 17.5 | AF37: =IF(COUNT(D37:G37)=0,"",SUM(D37:G37)) -> 26.5 | AG37: =IF(COUNT(H37:K37)=0,"",SUM(H37:K37)) -> 34.8 | AH37: =IF(COUNT(L37:O37)=0,"",SUM(L37:O37)) -> 43.7 | AI37: =IF(COUNT(P37:S37)=0,"",SUM(P37:S37)) -> 54.5 | AJ37: 65.8
A38: Average order value (computed: GMV / Orders) | B38: Rs | D38: =IFERROR(D40/D37,"") -> 0 | E38: =IFERROR(E40/E37,"") -> 0 | F38: =IFERROR(F40/F37,"") -> 0 | G38: =IFERROR(G40/G37,"") -> 0 | H38: =IFERROR(H40/H37,"") -> 0 | I38: =IFERROR(I40/I37,"") -> 0 | J38: =IFERROR(J40/J37,"") -> 0 | K38: =IFERROR(K40/K37,"") -> 0 | ... AA38: =IFERROR(AA40/AA37,"") | AF38: =IFERROR(AF40/AF37,"") | AG38: =IFERROR(AG40/AG37,"") | AH38: =IFERROR(AH40/AH37,"") -> 2072.151 | AI38: =IFERROR(AI40/AI37,"") -> 2160.3853 | AJ38: =IFERROR(AJ40/AJ37,"") -> 2272.4924
A39: Average order value (as reported) | B39: Rs | C39: Link: row 148 (Beauty AOV reconciliation) | D39: =IF(D148="","",IFERROR(D148,"")) -> 1832 | E39: =IF(E148="","",IFERROR(E148,"")) -> 1910 | F39: =IF(F148="","",IFERROR(F148,"")) -> 1967 | G39: =IF(G148="","",IFERROR(G148,"")) -> 1716 | H39: =IF(H148="","",IFERROR(H148,"")) -> 1780 | I39: =IF(I148="","",IFERROR(I148,"")) -> 1872 | J39: =IF(J148="","",IFERROR(J148,"")) -> 1958 | K39: =IF(K148="","",IFERROR(K148,"")) -> 1803 | ... V39: =IF(V148="","",IFERROR(V148,"")) -> 2173 | AF39: =IF(AF148="","",IFERROR(AF148,"")) -> 1857 | AG39: =IF(AG148="","",IFERROR(AG148,"")) -> 1857 | AH39: =IF(AH148="","",IFERROR(AH148,"")) -> 1985 | AI39: =IF(AI148="","",IFERROR(AI148,"")) -> 2021 | AJ39: =IF(AJ148="","",IFERROR(AJ148,"")) -> 2068
A40: GMV | B40: Rs Mn | C40: Beauty Omnichannel Retail | L40: 19908 | M40: 21559 | N40: 25696 | O40: 23390 | P40: 25429 | Q40: 27833 | R40: 33899 | S40: 30580 | T40: 32080 | U40: 35510 | V40: 43020 | W40: 38920 | AF40: =IF(COUNT(D40:G40)=0,"",SUM(D40:G40)) | AG40: =IF(COUNT(H40:K40)=0,"",SUM(H40:K40)) | AH40: =IF(COUNT(L40:O40)=0,"",SUM(L40:O40)) -> 90553 | AI40: =IF(COUNT(P40:S40)=0,"",SUM(P40:S40)) -> 117741 | AJ40: =IF(COUNT(T40:W40)=0,"",SUM(T40:W40)) -> 149530
A41: YoY growth | B41: % | H41: =IFERROR(H40/D40-1,"") | I41: =IFERROR(I40/E40-1,"") | J41: =IFERROR(J40/F40-1,"") | K41: =IFERROR(K40/G40-1,"") | L41: =IFERROR(L40/H40-1,"") | M41: =IFERROR(M40/I40-1,"") | N41: =IFERROR(N40/J40-1,"") | O41: =IFERROR(O40/K40-1,"") | ... AA41: =IFERROR(AA40/W40-1,"") -> -1 | AF41: =IFERROR(AF40/AE40-1,"") | AG41: =IFERROR(AG40/AF40-1,"") | AH41: =IFERROR(AH40/AG40-1,"") | AI41: =IFERROR(AI40/AH40-1,"") -> 0.30024406 | AJ41: =IFERROR(AJ40/AI40-1,"") -> 0.26999091
A42: QoQ growth | B42: % | E42: =IFERROR(E40/D40-1,"") | F42: =IFERROR(F40/E40-1,"") | G42: =IFERROR(G40/F40-1,"") | H42: =IFERROR(H40/G40-1,"") | I42: =IFERROR(I40/H40-1,"") | J42: =IFERROR(J40/I40-1,"") | K42: =IFERROR(K40/J40-1,"") | L42: =IFERROR(L40/K40-1,"") | ... AA42: =IFERROR(AA40/Z40-1,"")
A43: NSV | B43: Rs Mn | C43: Beauty Omnichannel Retail | L43: 12121 | M43: 12566 | N43: 14954 | O43: 13979 | P43: 14695 | Q43: 15661 | R43: 18817 | S43: 17570 | T43: 18340 | U43: 19810 | V43: 24210 | W43: 22690 | AF43: =IF(COUNT(D43:G43)=0,"",SUM(D43:G43)) | AG43: =IF(COUNT(H43:K43)=0,"",SUM(H43:K43)) | AH43: =IF(COUNT(L43:O43)=0,"",SUM(L43:O43)) -> 53620 | AI43: =IF(COUNT(P43:S43)=0,"",SUM(P43:S43)) -> 66743 | AJ43: =IF(COUNT(T43:W43)=0,"",SUM(T43:W43)) -> 85050
A44: NSV / GMV | B44: % | D44: =IFERROR(D43/D40,"") | E44: =IFERROR(E43/E40,"") | F44: =IFERROR(F43/F40,"") | G44: =IFERROR(G43/G40,"") | H44: =IFERROR(H43/H40,"") | I44: =IFERROR(I43/I40,"") | J44: =IFERROR(J43/J40,"") | K44: =IFERROR(K43/K40,"") | ... AA44: =IFERROR(AA43/AA40,"") | AF44: =IFERROR(AF43/AF40,"") | AG44: =IFERROR(AG43/AG40,"") | AH44: =IFERROR(AH43/AH40,"") -> 0.59213941 | AI44: =IFERROR(AI43/AI40,"") -> 0.56686286 | AJ44: =IFERROR(AJ43/AJ40,"") -> 0.56878218
A45: Revenue | B45: Rs Mn | C45: Beauty Omnichannel Retail / Financial Performance | L45: 12984 | N45: 16227 | O45: 15190 | P45: 15935 | Q45: 17029 | R45: 20601 | S45: 18950 | T45: 19750 | U45: 21320 | V45: 26220 | W45: 24100 | AF45: =IF(COUNT(D45:G45)=0,"",SUM(D45:G45)) | AG45: =IF(COUNT(H45:K45)=0,"",SUM(H45:K45)) | AH45: =IF(COUNT(L45:O45)=0,"",SUM(L45:O45)) -> 44401 | AI45: =IF(COUNT(P45:S45)=0,"",SUM(P45:S45)) -> 72515 | AJ45: =IF(COUNT(T45:W45)=0,"",SUM(T45:W45)) -> 91390
A46: Revenue / NSV | B46: % | D46: =IFERROR(D45/D43,"") | E46: =IFERROR(E45/E43,"") | F46: =IFERROR(F45/F43,"") | G46: =IFERROR(G45/G43,"") | H46: =IFERROR(H45/H43,"") | I46: =IFERROR(I45/I43,"") | J46: =IFERROR(J45/J43,"") | K46: =IFERROR(K45/K43,"") | ... AA46: =IFERROR(AA45/AA43,"") | AF46: =IFERROR(AF45/AF43,"") | AG46: =IFERROR(AG45/AG43,"") | AH46: =IFERROR(AH45/AH43,"") -> 0.82806789 | AI46: =IFERROR(AI45/AI43,"") -> 1.086481 | AJ46: =IFERROR(AJ45/AJ43,"") -> 1.0745444
A47: Gross profit | B47: Rs Mn | C47: Financial Performance | L47: 5223 | N47: 6317 | O47: 5950 | P47: 6328 | Q47: 6828 | R47: 8175 | S47: 7790 | T47: 8190 | U47: 8840 | V47: 10850 | W47: 10130 | AF47: =IF(COUNT(D47:G47)=0,"",SUM(D47:G47)) | AG47: =IF(COUNT(H47:K47)=0,"",SUM(H47:K47)) | AH47: =IF(COUNT(L47:O47)=0,"",SUM(L47:O47)) -> 17490 | AI47: =IF(COUNT(P47:S47)=0,"",SUM(P47:S47)) -> 29121 | AJ47: =IF(COUNT(T47:W47)=0,"",SUM(T47:W47)) -> 38010
A48: Gross margin (% of NSV) | B48: % | D48: =IFERROR(D47/D43,"") | E48: =IFERROR(E47/E43,"") | F48: =IFERROR(F47/F43,"") | G48: =IFERROR(G47/G43,"") | H48: =IFERROR(H47/H43,"") | I48: =IFERROR(I47/I43,"") | J48: =IFERROR(J47/J43,"") | K48: =IFERROR(K47/K43,"") | ... AA48: =IFERROR(AA47/AA43,"") | AF48: =IFERROR(AF47/AF43,"") | AG48: =IFERROR(AG47/AG43,"") | AH48: =IFERROR(AH47/AH43,"") -> 0.32618426 | AI48: =IFERROR(AI47/AI43,"") -> 0.43631542 | AJ48: =IFERROR(AJ47/AJ43,"") -> 0.44691358
A49: Fulfilment cost | B49: Rs Mn | C49: Financial Performance | L49: 1114 | N49: 1396 | O49: 1280 | P49: 1417 | Q49: 1488 | R49: 1749 | S49: 1630 | T49: 1700 | U49: 1870 | V49: 2220 | W49: 2150 | AF49: =IF(COUNT(D49:G49)=0,"",SUM(D49:G49)) | AG49: =IF(COUNT(H49:K49)=0,"",SUM(H49:K49)) | AH49: =IF(COUNT(L49:O49)=0,"",SUM(L49:O49)) -> 3790 | AI49: =IF(COUNT(P49:S49)=0,"",SUM(P49:S49)) -> 6284 | AJ49: =IF(COUNT(T49:W49)=0,"",SUM(T49:W49)) -> 7940
A50: Marketing expenses | B50: Rs Mn | C50: Financial Performance | L50: 971 | N50: 1414 | O50: 1210 | P50: 1268 | Q50: 1462 | R50: 1897 | S50: 1570 | T50: 2340 | U50: 2600 | V50: 3190 | W50: 2780 | AF50: =IF(COUNT(D50:G50)=0,"",SUM(D50:G50)) | AG50: =IF(COUNT(H50:K50)=0,"",SUM(H50:K50)) | AH50: =IF(COUNT(L50:O50)=0,"",SUM(L50:O50)) -> 3595 | AI50: =IF(COUNT(P50:S50)=0,"",SUM(P50:S50)) -> 6197 | AJ50: =IF(COUNT(T50:W50)=0,"",SUM(T50:W50)) -> 10910
A51: Selling & distribution expense | B51: Rs Mn | C51: Financial Performance | L51: 285 | N51: 385 | O51: 400 | P51: 413 | Q51: 439 | R51: 532 | S51: 550 | T51: 0 | U51: 0 | V51: 0 | W51: 0 | AF51: =IF(COUNT(D51:G51)=0,"",SUM(D51:G51)) | AG51: =IF(COUNT(H51:K51)=0,"",SUM(H51:K51)) | AH51: =IF(COUNT(L51:O51)=0,"",SUM(L51:O51)) -> 1070 | AI51: =IF(COUNT(P51:S51)=0,"",SUM(P51:S51)) -> 1934 | AJ51: =IF(COUNT(T51:W51)=0,"",SUM(T51:W51)) -> 0
A52: Contribution profit | B52: Rs Mn | D52: =IF(OR(ISBLANK(D47),ISBLANK(D49),ISBLANK(D50),ISBLANK(D51)),"",IFERROR(D47-D49-D50-D51,"")) | E52: =IF(OR(ISBLANK(E47),ISBLANK(E49),ISBLANK(E50),ISBLANK(E51)),"",IFERROR(E47-E49-E50-E51,"")) | F52: =IF(OR(ISBLANK(F47),ISBLANK(F49),ISBLANK(F50),ISBLANK(F51)),"",IFERROR(F47-F49-F50-F51,"")) | G52: =IF(OR(ISBLANK(G47),ISBLANK(G49),ISBLANK(G50),ISBLANK(G51)),"",IFERROR(G47-G49-G50-G51,"")) | H52: =IF(OR(ISBLANK(H47),ISBLANK(H49),ISBLANK(H50),ISBLANK(H51)),"",IFERROR(H47-H49-H50-H51,"")) | I52: =IF(OR(ISBLANK(I47),ISBLANK(I49),ISBLANK(I50),ISBLANK(I51)),"",IFERROR(I47-I49-I50-I51,"")) | J52: =IF(OR(ISBLANK(J47),ISBLANK(J49),ISBLANK(J50),ISBLANK(J51)),"",IFERROR(J47-J49-J50-J51,"")) | K52: =IF(OR(ISBLANK(K47),ISBLANK(K49),ISBLANK(K50),ISBLANK(K51)),"",IFERROR(K47-K49-K50-K51,"")) | ... AA52: =IF(OR(ISBLANK(AA47),ISBLANK(AA49),ISBLANK(AA50),ISBLANK(AA51)),"",IFERROR(AA47-AA49-AA50-AA51,"")) | AF52: =IF(OR(ISBLANK(AF47),ISBLANK(AF49),ISBLANK(AF50),ISBLANK(AF51)),"",IFERROR(AF47-AF49-AF50-AF51,"")) | AG52: =IF(OR(ISBLANK(AG47),ISBLANK(AG49),ISBLANK(AG50),ISBLANK(AG51)),"",IFERROR(AG47-AG49-AG50-AG51,"")) | AH52: =IF(OR(ISBLANK(AH47),ISBLANK(AH49),ISBLANK(AH50),ISBLANK(AH51)),"",IFERROR(AH47-AH49-AH50-AH51,"")) -> 9035 | AI52: =IF(OR(ISBLANK(AI47),ISBLANK(AI49),ISBLANK(AI50),ISBLANK(AI51)),"",IFERROR(AI47-AI49-AI50-AI51,"")) -> 14706 | AJ52: =IF(OR(ISBLANK(AJ47),ISBLANK(AJ49),ISBLANK(AJ50),ISBLANK(AJ51)),"",IFERROR(AJ47-AJ49-AJ50-AJ51,"")) -> 19160
A53: Contribution margin (% of NSV) | B53: % | D53: =IFERROR(D52/D43,"") | E53: =IFERROR(E52/E43,"") | F53: =IFERROR(F52/F43,"") | G53: =IFERROR(G52/G43,"") | H53: =IFERROR(H52/H43,"") | I53: =IFERROR(I52/I43,"") | J53: =IFERROR(J52/J43,"") | K53: =IFERROR(K52/K43,"") | ... AA53: =IFERROR(AA52/AA43,"") | AF53: =IFERROR(AF52/AF43,"") | AG53: =IFERROR(AG52/AG43,"") | AH53: =IFERROR(AH52/AH43,"") -> 0.16850056 | AI53: =IFERROR(AI52/AI43,"") -> 0.22033771 | AJ53: =IFERROR(AJ52/AJ43,"") -> 0.22527925
A54: Other expenses (G&A + employee) | B54: Rs Mn | C54: Financial Performance | L54: 1800 | N54: 1890 | O54: 1790 | P54: 1975 | Q54: 2095 | R54: 2345 | S54: 2360 | T54: 2500 | U54: 2590 | V54: 2990 | W54: 2870 | AF54: =IF(COUNT(D54:G54)=0,"",SUM(D54:G54)) | AG54: =IF(COUNT(H54:K54)=0,"",SUM(H54:K54)) | AH54: =IF(COUNT(L54:O54)=0,"",SUM(L54:O54)) -> 5480 | AI54: =IF(COUNT(P54:S54)=0,"",SUM(P54:S54)) -> 8775 | AJ54: =IF(COUNT(T54:W54)=0,"",SUM(T54:W54)) -> 10950
A55: EBITDA | B55: Rs Mn | D55: =IF(OR(ISBLANK(D52),ISBLANK(D54)),"",IFERROR(D52-D54,"")) | E55: =IF(OR(ISBLANK(E52),ISBLANK(E54)),"",IFERROR(E52-E54,"")) | F55: =IF(OR(ISBLANK(F52),ISBLANK(F54)),"",IFERROR(F52-F54,"")) | G55: =IF(OR(ISBLANK(G52),ISBLANK(G54)),"",IFERROR(G52-G54,"")) | H55: =IF(OR(ISBLANK(H52),ISBLANK(H54)),"",IFERROR(H52-H54,"")) | I55: =IF(OR(ISBLANK(I52),ISBLANK(I54)),"",IFERROR(I52-I54,"")) | J55: =IF(OR(ISBLANK(J52),ISBLANK(J54)),"",IFERROR(J52-J54,"")) | K55: =IF(OR(ISBLANK(K52),ISBLANK(K54)),"",IFERROR(K52-K54,"")) | ... AA55: =IF(OR(ISBLANK(AA52),ISBLANK(AA54)),"",IFERROR(AA52-AA54,"")) | AF55: =IF(OR(ISBLANK(AF52),ISBLANK(AF54)),"",IFERROR(AF52-AF54,"")) | AG55: =IF(OR(ISBLANK(AG52),ISBLANK(AG54)),"",IFERROR(AG52-AG54,"")) | AH55: =IF(OR(ISBLANK(AH52),ISBLANK(AH54)),"",IFERROR(AH52-AH54,"")) -> 3555 | AI55: =IF(OR(ISBLANK(AI52),ISBLANK(AI54)),"",IFERROR(AI52-AI54,"")) -> 5931 | AJ55: =IF(OR(ISBLANK(AJ52),ISBLANK(AJ54)),"",IFERROR(AJ52-AJ54,"")) -> 8210
A56: EBITDA margin (% of NSV) | B56: % | D56: =IFERROR(D55/D43,"") | E56: =IFERROR(E55/E43,"") | F56: =IFERROR(F55/F43,"") | G56: =IFERROR(G55/G43,"") | H56: =IFERROR(H55/H43,"") | I56: =IFERROR(I55/I43,"") | J56: =IFERROR(J55/J43,"") | K56: =IFERROR(K55/K43,"") | ... AA56: =IFERROR(AA55/AA43,"") | AF56: =IFERROR(AF55/AF43,"") | AG56: =IFERROR(AG55/AG43,"") | AH56: =IFERROR(AH55/AH43,"") -> 0.066299888 | AI56: =IFERROR(AI55/AI43,"") -> 0.088863252 | AJ56: =IFERROR(AJ55/AJ43,"") -> 0.096531452
A58: BPC / Luxe store count | B58: # | C58: Beauty Omnichannel Retail | E58: 84 | G58: 104 | I58: 124 | J58: 141 | K58: 145 | O58: 187 | R58: 221 | AF58: =IF(G58="","",G58) -> 104 | AG58: =IF(K58="","",K58) -> 145 | AH58: =IF(O58="","",O58) -> 187 | AI58: =IF(S58="","",S58) | AJ58: =IF(W58="","",W58)
A59: Number of cities (retail) | B59: # | C59: Beauty Omnichannel Retail | D59: 39 | E59: 41 | F59: 45 | G59: 49 | H59: 52 | I59: 53 | J59: 56 | K59: 60 | M59: 61 | Q59: 72 | R59: 73 | S59: 79 | U59: 90 | AF59: =IF(G59="","",G59) -> 49 | AG59: =IF(K59="","",K59) -> 60 | AH59: =IF(O59="","",O59) | AI59: =IF(S59="","",S59) -> 79 | AJ59: =IF(W59="","",W59)
A60: Total retail space | B60: sq ft | C60: Beauty Omnichannel Retail | E60: 0.07 | G60: 0.1 | I60: 0.12 | J60: 0.14 | O60: 0.17 | R60: 0.21 | AF60: =IF(G60="","",G60) -> 0.1 | AG60: =IF(K60="","",K60) | AH60: =IF(O60="","",O60) -> 0.17 | AI60: =IF(S60="","",S60) | AJ60: =IF(W60="","",W60)
A61: BPC app downloads (cumulative) | B61: mn | C61: Beauty Omnichannel Retail | AF61: =IF(G61="","",G61) | AG61: =IF(K61="","",K61) | AH61: =IF(O61="","",O61) | AI61: =IF(S61="","",S61) | AJ61: =IF(W61="","",W61)
A63: House of Nykaa (owned brands portfolio)
A64: House of Nykaa - Beauty brands GMV | B64: Rs Mn | C64: House of Nykaa | D64: 851 | E64: 1202 | F64: 1746 | G64: 1779 | H64: 1663 | I64: 1966 | J64: 2247 | K64: 2013 | L64: 2310 | M64: 2438 | N64: 3152 | O64: 3054 | P64: 3406 | Q64: 3602 | R64: 4686 | S64: 5260 | T64: 5780 | U64: 6270 | V64: 7750 | AF64: =IF(COUNT(D64:G64)=0,"",SUM(D64:G64)) -> 5578 | AG64: =IF(COUNT(H64:K64)=0,"",SUM(H64:K64)) -> 7889 | AH64: =IF(COUNT(L64:O64)=0,"",SUM(L64:O64)) -> 10954 | AI64: =IF(COUNT(P64:S64)=0,"",SUM(P64:S64)) -> 16954 | AJ64: =IF(COUNT(T64:W64)=0,"",SUM(T64:W64)) -> 19800
A65: of which: Dot & Key GMV | B65: Rs Mn | C65: House of Nykaa | AF65: =IF(COUNT(D65:G65)=0,"",SUM(D65:G65)) | AG65: =IF(COUNT(H65:K65)=0,"",SUM(H65:K65)) | AH65: =IF(COUNT(L65:O65)=0,"",SUM(L65:O65)) | AI65: =IF(COUNT(P65:S65)=0,"",SUM(P65:S65)) | AJ65: =IF(COUNT(T65:W65)=0,"",SUM(T65:W65))
A66: of which: Kay Beauty GMV | B66: Rs Mn | C66: House of Nykaa | AF66: =IF(COUNT(D66:G66)=0,"",SUM(D66:G66)) | AG66: =IF(COUNT(H66:K66)=0,"",SUM(H66:K66)) | AH66: =IF(COUNT(L66:O66)=0,"",SUM(L66:O66)) | AI66: =IF(COUNT(P66:S66)=0,"",SUM(P66:S66)) | AJ66: =IF(COUNT(T66:W66)=0,"",SUM(T66:W66))
A67: House of Nykaa - Fashion brands GMV | B67: Rs Mn | C67: House of Nykaa | D67: 210 | E67: 290 | F67: 406 | H67: 706 | I67: 780 | J67: 902 | L67: 916 | M67: 989 | N67: 1174 | P67: 903 | Q67: 1090 | R67: 1200 | S67: 1120 | T67: 970 | U67: 950 | AF67: =IF(COUNT(D67:G67)=0,"",SUM(D67:G67)) -> 906 | AG67: =IF(COUNT(H67:K67)=0,"",SUM(H67:K67)) -> 2388 | AH67: =IF(COUNT(L67:O67)=0,"",SUM(L67:O67)) -> 3079 | AI67: =IF(COUNT(P67:S67)=0,"",SUM(P67:S67)) -> 4313 | AJ67: =IF(COUNT(T67:W67)=0,"",SUM(T67:W67)) -> 1920
A68: House of Nykaa - Total owned-brand GMV | B68: Rs Mn | D68: =IFERROR(D64+D67,"") -> 1061 | E68: =IFERROR(E64+E67,"") -> 1492 | F68: =IFERROR(F64+F67,"") -> 2152 | G68: =IFERROR(G64+G67,"") -> 1779 | H68: =IFERROR(H64+H67,"") -> 2369 | I68: =IFERROR(I64+I67,"") -> 2746 | J68: =IFERROR(J64+J67,"") -> 3149 | K68: =IFERROR(K64+K67,"") -> 2013 | ... AA68: =IFERROR(AA64+AA67,"") -> 0 | AF68: =IFERROR(AF64+AF67,"") -> 6484 | AG68: =IFERROR(AG64+AG67,"") -> 10277 | AH68: =IFERROR(AH64+AH67,"") -> 14033 | AI68: =IFERROR(AI64+AI67,"") -> 21267 | AJ68: =IFERROR(AJ64+AJ67,"") -> 21720
A69: Share of total company GMV | B69: % | D69: =IFERROR(D68/D11,"") -> 0.072196516 | E69: =IFERROR(E68/E11,"") -> 0.091934192 | F69: =IFERROR(F68/F11,"") -> 0.1053456 | G69: =IFERROR(G68/G11,"") -> 0.098948774 | H69: =IFERROR(H68/H11,"") -> 0.10973689 | I69: =IFERROR(I68/I11,"") -> 0.11706527 | J69: =IFERROR(J68/J11,"") -> 0.11260504 | K69: =IFERROR(K68/K11,"") -> 0.082317821 | ... AA69: =IFERROR(AA68/AA11,"") | AF69: =IFERROR(AF68/AF11,"") -> 0.093521029 | AG69: =IFERROR(AG68/AG11,"") -> 0.10544406 | AH69: =IFERROR(AH68/AH11,"") -> 0.11274112 | AI69: =IFERROR(AI68/AI11,"") -> 0.13629809 | AJ69: =IFERROR(AJ68/AJ11,"") -> 0.10880673
A70: Number of owned brands (House of Nykaa) | B70: # | C70: House of Nykaa | D70: 7 | E70: 8 | F70: 9 | G70: 10 | H70: 10 | I70: 10 | J70: 10 | K70: 12 | L70: 13 | AF70: =IF(G70="","",G70) -> 10 | AG70: =IF(K70="","",K70) -> 12 | AH70: =IF(O70="","",O70) | AI70: =IF(S70="","",S70) | AJ70: =IF(W70="","",W70)
A72: eB2B: Superstore by Nykaa
A73: B2B distribution platform selling to offline beauty retailers. Cost breakdown not separately disclosed as of this build -- Nykaa has so far only given qualitative bps commentary; revisit once/if a full P&L split is disclosed.
A74: GMV | B74: Rs Mn | C74: eB2B: Superstore by Nykaa | G74: 214 | J74: 1012 | N74: 1700 | R74: 2597 | AF74: =IF(COUNT(D74:G74)=0,"",SUM(D74:G74)) -> 214 | AG74: =IF(COUNT(H74:K74)=0,"",SUM(H74:K74)) -> 1012 | AH74: =IF(COUNT(L74:O74)=0,"",SUM(L74:O74)) -> 1700 | AI74: =IF(COUNT(P74:S74)=0,"",SUM(P74:S74)) -> 2597 | AJ74: =IF(COUNT(T74:W74)=0,"",SUM(T74:W74))
A75: YoY growth | B75: % | H75: =IFERROR(H74/D74-1,"") | I75: =IFERROR(I74/E74-1,"") | J75: =IFERROR(J74/F74-1,"") | K75: =IFERROR(K74/G74-1,"") -> -1 | L75: =IFERROR(L74/H74-1,"") | M75: =IFERROR(M74/I74-1,"") | N75: =IFERROR(N74/J74-1,"") -> 0.6798419 | O75: =IFERROR(O74/K74-1,"") | ... AA75: =IFERROR(AA74/W74-1,"") | AF75: =IFERROR(AF74/AE74-1,"") | AG75: =IFERROR(AG74/AF74-1,"") -> 3.728972 | AH75: =IFERROR(AH74/AG74-1,"") -> 0.6798419 | AI75: =IFERROR(AI74/AH74-1,"") -> 0.52764706 | AJ75: =IFERROR(AJ74/AI74-1,"")
A76: NSV | B76: Rs Mn | C76: eB2B: Superstore by Nykaa | AF76: =IF(COUNT(D76:G76)=0,"",SUM(D76:G76)) | AG76: =IF(COUNT(H76:K76)=0,"",SUM(H76:K76)) | AH76: =IF(COUNT(L76:O76)=0,"",SUM(L76:O76)) | AI76: =IF(COUNT(P76:S76)=0,"",SUM(P76:S76)) | AJ76: =IF(COUNT(T76:W76)=0,"",SUM(T76:W76))
A77: Contribution to Beauty GMV | B77: % | D77: =IFERROR(D74/D40,"") | E77: =IFERROR(E74/E40,"") | F77: =IFERROR(F74/F40,"") | G77: =IFERROR(G74/G40,"") | H77: =IFERROR(H74/H40,"") | I77: =IFERROR(I74/I40,"") | J77: =IFERROR(J74/J40,"") | K77: =IFERROR(K74/K40,"") | ... AA77: =IFERROR(AA74/AA40,"") | AF77: =IFERROR(AF74/AF40,"") | AG77: =IFERROR(AG74/AG40,"") | AH77: =IFERROR(AH74/AH40,"") -> 0.018773536 | AI77: =IFERROR(AI74/AI40,"") -> 0.022056888 | AJ77: =IFERROR(AJ74/AJ40,"")
A78: Beauty (ex-SuperStore) -- derived, not directly disclosed since 4Q24
A79: Beauty (ex-SuperStore) GMV | B79: Rs Mn | D79: =IF(OR(ISBLANK(D40),ISBLANK(D74)),"",IFERROR(D40-D74,"")) | E79: =IF(OR(ISBLANK(E40),ISBLANK(E74)),"",IFERROR(E40-E74,"")) | F79: =IF(OR(ISBLANK(F40),ISBLANK(F74)),"",IFERROR(F40-F74,"")) | G79: =IF(OR(ISBLANK(G40),ISBLANK(G74)),"",IFERROR(G40-G74,"")) | H79: =IF(OR(ISBLANK(H40),ISBLANK(H74)),"",IFERROR(H40-H74,"")) | I79: =IF(OR(ISBLANK(I40),ISBLANK(I74)),"",IFERROR(I40-I74,"")) | J79: =IF(OR(ISBLANK(J40),ISBLANK(J74)),"",IFERROR(J40-J74,"")) | K79: =IF(OR(ISBLANK(K40),ISBLANK(K74)),"",IFERROR(K40-K74,"")) | ... AA79: =IF(OR(ISBLANK(AA40),ISBLANK(AA74)),"",IFERROR(AA40-AA74,"")) | AF79: =IF(OR(ISBLANK(AF40),ISBLANK(AF74)),"",IFERROR(AF40-AF74,"")) | AG79: =IF(OR(ISBLANK(AG40),ISBLANK(AG74)),"",IFERROR(AG40-AG74,"")) | AH79: =IF(OR(ISBLANK(AH40),ISBLANK(AH74)),"",IFERROR(AH40-AH74,"")) -> 88853 | AI79: =IF(OR(ISBLANK(AI40),ISBLANK(AI74)),"",IFERROR(AI40-AI74,"")) -> 115144 | AJ79: =IF(OR(ISBLANK(AJ40),ISBLANK(AJ74)),"",IFERROR(AJ40-AJ74,""))
A80: Beauty (ex-SuperStore) NSV | B80: Rs Mn | D80: =IF(OR(ISBLANK(D43),ISBLANK(D76)),"",IFERROR(D43-D76,"")) | E80: =IF(OR(ISBLANK(E43),ISBLANK(E76)),"",IFERROR(E43-E76,"")) | F80: =IF(OR(ISBLANK(F43),ISBLANK(F76)),"",IFERROR(F43-F76,"")) | G80: =IF(OR(ISBLANK(G43),ISBLANK(G76)),"",IFERROR(G43-G76,"")) | H80: =IF(OR(ISBLANK(H43),ISBLANK(H76)),"",IFERROR(H43-H76,"")) | I80: =IF(OR(ISBLANK(I43),ISBLANK(I76)),"",IFERROR(I43-I76,"")) | J80: =IF(OR(ISBLANK(J43),ISBLANK(J76)),"",IFERROR(J43-J76,"")) | K80: =IF(OR(ISBLANK(K43),ISBLANK(K76)),"",IFERROR(K43-K76,"")) | ... AA80: =IF(OR(ISBLANK(AA43),ISBLANK(AA76)),"",IFERROR(AA43-AA76,"")) | AF80: =IF(OR(ISBLANK(AF43),ISBLANK(AF76)),"",IFERROR(AF43-AF76,"")) | AG80: =IF(OR(ISBLANK(AG43),ISBLANK(AG76)),"",IFERROR(AG43-AG76,"")) | AH80: =IF(OR(ISBLANK(AH43),ISBLANK(AH76)),"",IFERROR(AH43-AH76,"")) | AI80: =IF(OR(ISBLANK(AI43),ISBLANK(AI76)),"",IFERROR(AI43-AI76,"")) | AJ80: =IF(OR(ISBLANK(AJ43),ISBLANK(AJ76)),"",IFERROR(AJ43-AJ76,""))
A81: Transacting retailers | B81: # | C81: eB2B: Superstore by Nykaa | F81: 4153 | G81: 18806 | H81: 45030 | I81: 73412 | J81: 92415 | L81: 119564 | M81: 129431 | N81: 146000 | P81: 210000 | Q81: 235000 | R81: 256000 | S81: 276000 | T81: 305000 | U81: 332000 | V81: 359000 | AF81: =IF(G81="","",G81) -> 18806 | AG81: =IF(K81="","",K81) | AH81: =IF(O81="","",O81) | AI81: =IF(S81="","",S81) -> 276000 | AJ81: =IF(W81="","",W81)
A82: Activation rate (% of registered retailers) | B82: % | C82: eB2B: Superstore by Nykaa | F82: 0.36 | G82: 0.46 | J82: 0.69 | K82: 0.71 | AF82: =IF(G82="","",G82) -> 0.46 | AG82: =IF(K82="","",K82) -> 0.71 | AH82: =IF(O82="","",O82) | AI82: =IF(S82="","",S82) | AJ82: =IF(W82="","",W82)
A83: Cities | B83: # | C83: eB2B: Superstore by Nykaa | F83: 88 | G83: 302 | H83: 516 | I83: 659 | J83: 652 | K83: 700 | L83: 699 | M83: 770 | R83: 1100 | S83: 1100 | AF83: =IF(G83="","",G83) -> 302 | AG83: =IF(K83="","",K83) -> 700 | AH83: =IF(O83="","",O83) | AI83: =IF(S83="","",S83) -> 1100 | AJ83: =IF(W83="","",W83)
A84: Brands listed | B84: # | C84: eB2B: Superstore by Nykaa | F84: 31 | G84: 134 | H84: 165 | I84: 182 | J84: 185 | K84: 190 | L84: 188 | AF84: =IF(G84="","",G84) -> 134 | AG84: =IF(K84="","",K84) -> 190 | AH84: =IF(O84="","",O84) | AI84: =IF(S84="","",S84) | AJ84: =IF(W84="","",W84)
A85: Orders | B85: '000 | C85: eB2B: Superstore by Nykaa | F85: 8.8 | G85: 48.6 | H85: 103.7 | I85: 172.7 | J85: 216 | K85: 728.9 | L85: 263.9 | M85: 280 | N85: 337 | Q85: 406 | AF85: =IF(COUNT(D85:G85)=0,"",SUM(D85:G85)) -> 57.4 | AG85: =IF(COUNT(H85:K85)=0,"",SUM(H85:K85)) -> 1221.3 | AH85: =IF(COUNT(L85:O85)=0,"",SUM(L85:O85)) -> 880.9 | AI85: =IF(COUNT(P85:S85)=0,"",SUM(P85:S85)) -> 406 | AJ85: =IF(COUNT(T85:W85)=0,"",SUM(T85:W85))
A87: Fashion
A88: Definition: Nykaa Fashion + LBB + Nykaa Man Lifestyle
A89: Number of visits | B89: mn | C89: Fashion | D89: 98 | E89: 115 | F89: 115 | G89: 113 | H89: 118 | I89: 122 | J89: 137 | K89: 127 | L89: 126 | M89: 145 | N89: 157 | O89: 144 | P89: 127 | Q89: 147 | R89: 169 | S89: 174 | T89: 165 | U89: 191 | V89: 221 | W89: =AJ89-SUM(T89:V89) -> 210 | AF89: =IF(COUNT(D89:G89)=0,"",SUM(D89:G89)) -> 441 | AG89: =IF(COUNT(H89:K89)=0,"",SUM(H89:K89)) -> 504 | AH89: =IF(COUNT(L89:O89)=0,"",SUM(L89:O89)) -> 572 | AI89: =IF(COUNT(P89:S89)=0,"",SUM(P89:S89)) -> 617 | AJ89: 787
A90: Monthly average unique visitors | B90: mn | C90: Fashion | D90: 13.4 | E90: 16.2 | F90: 16.4 | G90: 16 | H90: 16.2 | I90: 16.4 | J90: 19.4 | K90: 17.3 | L90: 16.6 | M90: 17.6 | N90: 18.8 | O90: 17.4 | P90: 15.8 | Q90: 18.1 | R90: 20.5 | S90: 22.2 | T90: 20.4 | U90: 23.5 | V90: 27.7 | AF90: =IFERROR(AVERAGE(D90:G90),"") -> 15.5 | AG90: =IFERROR(AVERAGE(H90:K90),"") -> 17.325 | AH90: 17.6 | AI90: =IFERROR(AVERAGE(P90:S90),"") -> 19.15 | AJ90: 24.2
A91: Conversion - orders/visits | B91: % | D91: =IFERROR(D95/D89,"") -> 0.01122449 | E91: =IFERROR(E95/E89,"") -> 0.011304348 | F91: =IFERROR(F95/F89,"") -> 0.011304348 | G91: =IFERROR(G95/G89,"") -> 0.011504425 | H91: =IFERROR(H95/H89,"") -> 0.012711864 | I91: =IFERROR(I95/I89,"") -> 0.01147541 | J91: =IFERROR(J95/J89,"") -> 0.012408759 | K91: =IFERROR(K95/K89,"") -> 0.011023622 | ... AA91: =IFERROR(AA95/AA89,"") | AF91: =IFERROR(AF95/AF89,"") -> 0.011337868 | AG91: =IFERROR(AG95/AG89,"") -> 0.011904762 | AH91: =IFERROR(AH95/AH89,"") -> 0.012237762 | AI91: =IFERROR(AI95/AI89,"") -> 0.012479741 | AJ91: =IFERROR(AJ95/AJ89,"") -> 0.012833545
A92: Conversion - transacting customers/visits | B92: % | D92: =IFERROR(D93/D89,"") -> 0.010204082 | E92: =IFERROR(E93/E89,"") -> 0.011304348 | F92: =IFERROR(F93/F89,"") -> 0.013913043 | G92: =IFERROR(G93/G89,"") -> 0.015929204 | H92: =IFERROR(H93/H89,"") -> 0.016949153 | I92: =IFERROR(I93/I89,"") -> 0.017213115 | J92: =IFERROR(J93/J89,"") -> 0.017518248 | K92: =IFERROR(K93/K89,"") -> 0.019685039 | ... AA92: =IFERROR(AA93/AA89,"") | AF92: =IFERROR(AF93/AF89,"") -> 0.0040816327 | AG92: =IFERROR(AG93/AG89,"") -> 0.0049603175 | AH92: =IFERROR(AH93/AH89,"") -> 0.0052447552 | AI92: =IFERROR(AI93/AI89,"") -> 0.0051863857 | AJ92: =IFERROR(AJ93/AJ89,"") -> 0.0054637865
A93: Annual transacting customers | B93: mn | C93: Fashion | D93: 1 | E93: 1.3 | F93: 1.6 | G93: 1.8 | H93: 2 | I93: 2.1 | J93: 2.4 | K93: 2.5 | L93: 2.6 | M93: 2.8 | N93: 2.9 | O93: 3 | P93: 3.1 | Q93: 3 | R93: 3.1 | S93: 3.2 | T93: 3.4 | U93: 3.7 | V93: 4.1 | W93: 4.3 | AF93: =IF(G93="","",G93) -> 1.8 | AG93: =IF(K93="","",K93) -> 2.5 | AH93: =IF(O93="","",O93) -> 3 | AI93: =IF(S93="","",S93) -> 3.2 | AJ93: =IF(W93="","",W93) -> 4.3
A94: Average order frequency | B94: x | D94: =IFERROR(D95*4/D93,"") -> 4.4 | E94: =IFERROR(E95*4/E93,"") -> 4 | F94: =IFERROR(F95*4/F93,"") -> 3.25 | G94: =IFERROR(G95*4/G93,"") -> 2.8888889 | H94: =IFERROR(H95*4/H93,"") -> 3 | I94: =IFERROR(I95*4/I93,"") -> 2.6666667 | J94: =IFERROR(J95*4/J93,"") -> 2.8333333 | K94: =IFERROR(K95*4/K93,"") -> 2.24 | ... AA94: =IFERROR(AA95*4/AA93,"") | AF94: =IFERROR(AF95*4/AF93,"") -> 11.111111 | AG94: =IFERROR(AG95*4/AG93,"") -> 9.6 | AH94: =IFERROR(AH95*4/AH93,"") -> 9.3333333 | AI94: =IFERROR(AI95*4/AI93,"") -> 9.625 | AJ94: =IFERROR(AJ95*4/AJ93,"") -> 9.3953488
A95: Number of orders | B95: mn | C95: Fashion | D95: 1.1 | E95: 1.3 | F95: 1.3 | G95: 1.3 | H95: 1.5 | I95: 1.4 | J95: 1.7 | K95: 1.4 | L95: 1.5 | M95: 1.6 | N95: 2.1 | O95: 1.8 | P95: 1.7 | Q95: 1.8 | R95: 2.1 | S95: 2.1 | T95: 2 | U95: 2.4 | V95: 3 | W95: =AJ95-SUM(T95:V95) -> 2.7 | AF95: =IF(COUNT(D95:G95)=0,"",SUM(D95:G95)) -> 5 | AG95: =IF(COUNT(H95:K95)=0,"",SUM(H95:K95)) -> 6 | AH95: =IF(COUNT(L95:O95)=0,"",SUM(L95:O95)) -> 7 | AI95: =IF(COUNT(P95:S95)=0,"",SUM(P95:S95)) -> 7.7 | AJ95: 10.1
A96: Average order value (computed: GMV / Orders) | B96: Rs | D96: =IFERROR(D98/D95,"") -> 0 | E96: =IFERROR(E98/E95,"") -> 0 | F96: =IFERROR(F98/F95,"") -> 0 | G96: =IFERROR(G98/G95,"") -> 0 | H96: =IFERROR(H98/H95,"") -> 0 | I96: =IFERROR(I98/I95,"") -> 0 | J96: =IFERROR(J98/J95,"") -> 0 | K96: =IFERROR(K98/K95,"") -> 0 | ... AA96: =IFERROR(AA98/AA95,"") | AF96: =IFERROR(AF98/AF95,"") | AG96: =IFERROR(AG98/AG95,"") | AH96: =IFERROR(AH98/AH95,"") -> 4836.4286 | AI96: =IFERROR(AI98/AI95,"") -> 4940.6494 | AJ96: =IFERROR(AJ98/AJ95,"") -> 4904.9505
A97: Average order value (as reported) | B97: Rs | C97: Link: row 153 (Fashion AOV reconciliation) | D97: =IF(D153="","",IFERROR(D153,"")) -> 3153 | E97: =IF(E153="","",IFERROR(E153,"")) -> 3242 | F97: =IF(F153="","",IFERROR(F153,"")) -> 3558 | G97: =IF(G153="","",IFERROR(G153,"")) -> 3616 | H97: =IF(H153="","",IFERROR(H153,"")) -> 3732 | I97: =IF(I153="","",IFERROR(I153,"")) -> 3940 | J97: =IF(J153="","",IFERROR(J153,"")) -> 3959 | K97: =IF(K153="","",IFERROR(K153,"")) -> 4266 | ... V97: =IF(V153="","",IFERROR(V153,"")) -> 4794 | AF97: =IF(AF153="","",IFERROR(AF153,"")) -> 3400 | AG97: =IF(AG153="","",IFERROR(AG153,"")) -> 3973 | AH97: =IF(AH153="","",IFERROR(AH153,"")) -> 4361 | AI97: =IF(AI153="","",IFERROR(AI153,"")) -> 4609 | AJ97: =IF(AJ153="","",IFERROR(AJ153,"")) -> 4652
A98: GMV | B98: Rs Mn | C98: Fashion | L98: 6758 | M98: 7872 | N98: 10465 | O98: 8760 | P98: 7741 | Q98: 8633 | R98: 11299 | S98: 10370 | T98: 9640 | U98: 11800 | V98: 14760 | W98: 13340 | AF98: =IF(COUNT(D98:G98)=0,"",SUM(D98:G98)) | AG98: =IF(COUNT(H98:K98)=0,"",SUM(H98:K98)) | AH98: =IF(COUNT(L98:O98)=0,"",SUM(L98:O98)) -> 33855 | AI98: =IF(COUNT(P98:S98)=0,"",SUM(P98:S98)) -> 38043 | AJ98: =IF(COUNT(T98:W98)=0,"",SUM(T98:W98)) -> 49540
A99: YoY growth | B99: % | H99: =IFERROR(H98/D98-1,"") | I99: =IFERROR(I98/E98-1,"") | J99: =IFERROR(J98/F98-1,"") | K99: =IFERROR(K98/G98-1,"") | L99: =IFERROR(L98/H98-1,"") | M99: =IFERROR(M98/I98-1,"") | N99: =IFERROR(N98/J98-1,"") | O99: =IFERROR(O98/K98-1,"") | ... AA99: =IFERROR(AA98/W98-1,"") -> -1 | AF99: =IFERROR(AF98/AE98-1,"") | AG99: =IFERROR(AG98/AF98-1,"") | AH99: =IFERROR(AH98/AG98-1,"") | AI99: =IFERROR(AI98/AH98-1,"") -> 0.12370403 | AJ99: =IFERROR(AJ98/AI98-1,"") -> 0.30221066
A100: QoQ growth | B100: % | E100: =IFERROR(E98/D98-1,"") | F100: =IFERROR(F98/E98-1,"") | G100: =IFERROR(G98/F98-1,"") | H100: =IFERROR(H98/G98-1,"") | I100: =IFERROR(I98/H98-1,"") | J100: =IFERROR(J98/I98-1,"") | K100: =IFERROR(K98/J98-1,"") | L100: =IFERROR(L98/K98-1,"") | ... AA100: =IFERROR(AA98/Z98-1,"")
A101: NSV | B101: Rs Mn | C101: Fashion | L101: 2089 | M101: 2411 | N101: 2899 | O101: 2479 | P101: 2449 | Q101: 2713 | R101: 3295 | S101: 2800 | T101: 2940 | U101: 3460 | V101: 4100 | W101: 3970 | AF101: =IF(COUNT(D101:G101)=0,"",SUM(D101:G101)) | AG101: =IF(COUNT(H101:K101)=0,"",SUM(H101:K101)) | AH101: =IF(COUNT(L101:O101)=0,"",SUM(L101:O101)) -> 9878 | AI101: =IF(COUNT(P101:S101)=0,"",SUM(P101:S101)) -> 11257 | AJ101: =IF(COUNT(T101:W101)=0,"",SUM(T101:W101)) -> 14470
A102: NSV / GMV | B102: % | D102: =IFERROR(D101/D98,"") | E102: =IFERROR(E101/E98,"") | F102: =IFERROR(F101/F98,"") | G102: =IFERROR(G101/G98,"") | H102: =IFERROR(H101/H98,"") | I102: =IFERROR(I101/I98,"") | J102: =IFERROR(J101/J98,"") | K102: =IFERROR(K101/K98,"") | ... AA102: =IFERROR(AA101/AA98,"") | AF102: =IFERROR(AF101/AF98,"") | AG102: =IFERROR(AG101/AG98,"") | AH102: =IFERROR(AH101/AH98,"") -> 0.29177374 | AI102: =IFERROR(AI101/AI98,"") -> 0.29590201 | AJ102: =IFERROR(AJ101/AJ98,"") -> 0.2920872
A103: Revenue | B103: Rs Mn | C103: Fashion / Financial Performance | F103: 900 | J103: 1339 | L103: 1225 | M103: 1365 | N103: 1640 | O103: 1454 | P103: 1486 | Q103: 1661 | R103: 1990 | S103: 1610 | T103: 1710 | U103: 2010 | V103: 2350 | W103: 2250 | AF103: =IF(COUNT(D103:G103)=0,"",SUM(D103:G103)) -> 900 | AG103: =IF(COUNT(H103:K103)=0,"",SUM(H103:K103)) -> 1339 | AH103: =IF(COUNT(L103:O103)=0,"",SUM(L103:O103)) -> 5684 | AI103: =IF(COUNT(P103:S103)=0,"",SUM(P103:S103)) -> 6747 | AJ103: =IF(COUNT(T103:W103)=0,"",SUM(T103:W103)) -> 8320
A104: Revenue / NSV | B104: % | D104: =IFERROR(D103/D101,"") | E104: =IFERROR(E103/E101,"") | F104: =IFERROR(F103/F101,"") | G104: =IFERROR(G103/G101,"") | H104: =IFERROR(H103/H101,"") | I104: =IFERROR(I103/I101,"") | J104: =IFERROR(J103/J101,"") | K104: =IFERROR(K103/K101,"") | ... AA104: =IFERROR(AA103/AA101,"") | AF104: =IFERROR(AF103/AF101,"") | AG104: =IFERROR(AG103/AG101,"") | AH104: =IFERROR(AH103/AH101,"") -> 0.57542013 | AI104: =IFERROR(AI103/AI101,"") -> 0.5993604 | AJ104: =IFERROR(AJ103/AJ101,"") -> 0.57498272
A105: Gross profit | B105: Rs Mn | C105: Financial Performance | L105: 957 | M105: 1061 | N105: 1274 | O105: 1137 | P105: 1210 | Q105: 1348 | R105: 1691 | S105: 1270 | T105: 1390 | U105: 1650 | V105: 2040 | W105: 1840 | AF105: =IF(COUNT(D105:G105)=0,"",SUM(D105:G105)) | AG105: =IF(COUNT(H105:K105)=0,"",SUM(H105:K105)) | AH105: =IF(COUNT(L105:O105)=0,"",SUM(L105:O105)) -> 4429 | AI105: =IF(COUNT(P105:S105)=0,"",SUM(P105:S105)) -> 5519 | AJ105: =IF(COUNT(T105:W105)=0,"",SUM(T105:W105)) -> 6920
A106: Gross margin (% of NSV) | B106: % | D106: =IFERROR(D105/D101,"") | E106: =IFERROR(E105/E101,"") | F106: =IFERROR(F105/F101,"") | G106: =IFERROR(G105/G101,"") | H106: =IFERROR(H105/H101,"") | I106: =IFERROR(I105/I101,"") | J106: =IFERROR(J105/J101,"") | K106: =IFERROR(K105/K101,"") | ... AA106: =IFERROR(AA105/AA101,"") | AF106: =IFERROR(AF105/AF101,"") | AG106: =IFERROR(AG105/AG101,"") | AH106: =IFERROR(AH105/AH101,"") -> 0.44837012 | AI106: =IFERROR(AI105/AI101,"") -> 0.49027272 | AJ106: =IFERROR(AJ105/AJ101,"") -> 0.47823082
A107: Fulfilment cost | B107: Rs Mn | C107: Financial Performance | L107: 237 | M107: 283 | N107: 318 | O107: 259 | P107: 237 | Q107: 248 | R107: 330 | S107: 280 | T107: 330 | U107: 390 | V107: 460 | W107: 450 | AF107: =IF(COUNT(D107:G107)=0,"",SUM(D107:G107)) | AG107: =IF(COUNT(H107:K107)=0,"",SUM(H107:K107)) | AH107: =IF(COUNT(L107:O107)=0,"",SUM(L107:O107)) -> 1097 | AI107: =IF(COUNT(P107:S107)=0,"",SUM(P107:S107)) -> 1095 | AJ107: =IF(COUNT(T107:W107)=0,"",SUM(T107:W107)) -> 1630
A108: Marketing expenses | B108: Rs Mn | C108: Financial Performance | L108: 594 | N108: 714 | O108: 620 | P108: 672 | Q108: 790 | R108: 1007 | S108: 840 | T108: 830 | U108: 930 | V108: 1150 | W108: 910 | AF108: =IF(COUNT(D108:G108)=0,"",SUM(D108:G108)) | AG108: =IF(COUNT(H108:K108)=0,"",SUM(H108:K108)) | AH108: =IF(COUNT(L108:O108)=0,"",SUM(L108:O108)) -> 1928 | AI108: =IF(COUNT(P108:S108)=0,"",SUM(P108:S108)) -> 3309 | AJ108: =IF(COUNT(T108:W108)=0,"",SUM(T108:W108)) -> 3820
...

Sheet Financial Statements
A1: INR Mn | B1: Unit | C1: Source | D1: 1Q22 | E1: 2Q22 | F1: 3Q22 | G1: 4Q22 | H1: 1Q23 | I1: 2Q23 | J1: 3Q23 | K1: 4Q23 | L1: 1Q24 | M1: 2Q24 | N1: 3Q24 | O1: 4Q24 | P1: 1Q25 | Q1: 2Q25 | R1: 3Q25 | S1: 4Q25 | T1: 1Q26 | U1: 2Q26 | V1: 3Q26 | W1: 4Q26 | X1: 1Q27 | Y1: 2Q27 | Z1: 3Q27 | AA1: 4Q27 | AC1: FY19 | AD1: FY20 | AE1: FY21 | AF1: FY22 | AG1: FY23 | AH1: FY24 | AI1: FY25 | AJ1: FY26 | AK1: FY27E | AL1: FY28E | AM1: FY29E | AN1: FY30E
A2: Fiscal Year End | D2: =DATE(2021,6,30) -> 44377 | E2: =EOMONTH(D2,-3) -> 44286 | F2: =EOMONTH(E2,-3) -> 44196 | G2: =EOMONTH(F2,-3) -> 44104 | H2: =EOMONTH(G2,-3) -> 44012 | I2: =EOMONTH(H2,-3) -> 43921 | J2: =EOMONTH(I2,-3) -> 43830 | K2: =EOMONTH(J2,-3) -> 43738 | L2: =EOMONTH(K2,-3) -> 43646 | ... AA2: =EOMONTH(Z2,-3) -> 42277 | AC2: =DATE(2019,3,31) -> 43555 | AD2: =DATE(2020,3,31) -> 43921 | AE2: =DATE(2021,3,31) -> 44286 | AF2: =DATE(2022,3,31) -> 44651 | AG2: =DATE(2023,3,31) -> 45016 | AH2: =DATE(2024,3,31) -> 45382 | AI2: =DATE(2025,3,31) -> 45747 | AJ2: =DATE(2026,3,31) -> 46112 | AK2: =DATE(2027,3,31) -> 46477 | AL2: =DATE(2028,3,31) -> 46843 | AM2: =DATE(2029,3,31) -> 47208 | AN2: =DATE(2030,3,31) -> 47573
A3: All figures in INR Mn unless stated otherwise. This sheet is a reported-format presentation, linked to the Projections sheet (KPI/PnL/BS builds) and to Raw Data - financials (for historical line-item granularity Projections doesn't carry). Where the Projections sheet only models a combined or summarized figure, the projected columns (FY27E-30E) show that combined value on ONE representative line within the group and leave the other reported sub-lines blank -- add your own split assumptions there if/when you want more granularity. Historical quarters/years are actuals, linked either from Projections (for figures already tied there) or directly from Raw Data - financials. Balance Sheet follows Nykaa's own disclosure cadence (Q2/Q4 only); Cash Flow is disclosed annually only, so both sections are annual-only in the projected columns and Q2/Q4-only historically.
A4: PROFIT & LOSS (CONSOLIDATED, REPORTED FORMAT)
A5: Revenue, Other income, COGS (combined), Employee benefits, Finance costs, D&A, Other expenses (plug), Tax (combined) and PAT/EPS are the SAME figures as the Projections sheet's Consolidated P&L block -- linked, not re-derived. The individual reported sub-lines below each combined line (e.g. 'Purchase of traded goods', 'Current tax pertaining to earlier years') are actuals for historical periods but are not separately modeled for FY27E-30E, so they show 0 there -- the full projected value sits on the first sub-line of each group (Cost of material consumed; Current tax).
A6: Revenue from operations | B6: Rs Mn | D6: =IF('Raw Data - financials'!D5="","",'Raw Data - financials'!D5) -> 8169.91 | E6: =IF('Raw Data - financials'!E5="","",'Raw Data - financials'!E5) -> 8852.64 | F6: =IF('Raw Data - financials'!F5="","",'Raw Data - financials'!F5) -> 10983.6 | G6: =IF('Raw Data - financials'!G5="","",'Raw Data - financials'!G5) -> 9733.2 | H6: =IF('Raw Data - financials'!H5="","",'Raw Data - financials'!H5) -> 11484.21 | I6: =IF('Raw Data - financials'!I5="","",'Raw Data - financials'!I5) -> 12308.29 | J6: =IF('Raw Data - financials'!J5="","",'Raw Data - financials'!J5) -> 14628.26 | K6: =IF('Raw Data - financials'!K5="","",'Raw Data - financials'!K5) -> 13017.24 | ... W6: =IF('Raw Data - financials'!W5="","",'Raw Data - financials'!W5) -> 26481.7 | AC6: =IF('Raw Data - financials'!AC5="","",'Raw Data - financials'!AC5) -> 11113.94 | AD6: =IF('Raw Data - financials'!AD5="","",'Raw Data - financials'!AD5) -> 17675.33 | AE6: =IF('Raw Data - financials'!AE5="","",'Raw Data - financials'!AE5) -> 24408.96 | AF6: =IF('Raw Data - financials'!AF5="","",'Raw Data - financials'!AF5) -> 37739.35 | AG6: =IF('Raw Data - financials'!AG5="","",'Raw Data - financials'!AG5) -> 51438 | AH6: =IF('Raw Data - financials'!AH5="","",'Raw Data - financials'!AH5) -> 63856.26 | AI6: =IF('Raw Data - financials'!AI5="","",'Raw Data - financials'!AI5) -> 79498.2 | AJ6: =IF('Raw Data - financials'!AJ5="","",'Raw Data - financials'!AJ5) -> 100223.5 | AK6: =IF(Projections!AK118="","",Projections!AK118) -> 131751.31 | AL6: =IF(Projections!AL118="","",Projections!AL118) -> 173081.96 | AM6: =IF(Projections!AM118="","",Projections!AM118) -> 227383.52 | AN6: =IF(Projections!AN118="","",Projections!AN118) -> 298728.44
A7: Other income | B7: Rs Mn | D7: =IF(Projections!D119="","",Projections!D119) -> 47.22 | E7: =IF(Projections!E119="","",Projections!E119) -> 51.98 | F7: =IF(Projections!F119="","",Projections!F119) -> 59.13 | G7: =IF(Projections!G119="","",Projections!G119) -> 111.39 | H7: =IF(Projections!H119="","",Projections!H119) -> 83.63 | I7: =IF(Projections!I119="","",Projections!I119) -> 64.76 | J7: =IF(Projections!J119="","",Projections!J119) -> 56.36 | K7: =IF(Projections!K119="","",Projections!K119) -> 97.38 | ... W7: =IF(Projections!W119="","",Projections!W119) -> 91.5 | AC7: =IF(Projections!AC119="","",Projections!AC119) -> 49.88 | AD7: =IF(Projections!AD119="","",Projections!AD119) -> 103.17 | AE7: =IF(Projections!AE119="","",Projections!AE119) -> 117.41 | AF7: =IF(Projections!AF119="","",Projections!AF119) -> 269.72 | AG7: =IF(Projections!AG119="","",Projections!AG119) -> 302.13 | AH7: =IF(Projections!AH119="","",Projections!AH119) -> 299.42 | AI7: =IF(Projections!AI119="","",Projections!AI119) -> 272.6 | AJ7: =IF(Projections!AJ119="","",Projections!AJ119) -> 327.7 | ... AN7: =IF(Projections!AN119="","",Projections!AN119) -> 985.80385
A8: Total Income | B8: Rs Mn | D8: =IFERROR(D6+D7,"") -> 8217.13 | E8: =IFERROR(E6+E7,"") -> 8904.62 | F8: =IFERROR(F6+F7,"") -> 11042.73 | G8: =IFERROR(G6+G7,"") -> 9844.59 | H8: =IFERROR(H6+H7,"") -> 11567.84 | I8: =IFERROR(I6+I7,"") -> 12373.05 | J8: =IFERROR(J6+J7,"") -> 14684.62 | K8: =IFERROR(K6+K7,"") -> 13114.62 | ... W8: =IFERROR(W6+W7,"") -> 26573.2 | AC8: =IFERROR(AC6+AC7,"") -> 11163.82 | AD8: =IFERROR(AD6+AD7,"") -> 17778.5 | AE8: =IFERROR(AE6+AE7,"") -> 24526.37 | AF8: =IFERROR(AF6+AF7,"") -> 38009.07 | AG8: =IFERROR(AG6+AG7,"") -> 51740.13 | AH8: =IFERROR(AH6+AH7,"") -> 64155.68 | AI8: =IFERROR(AI6+AI7,"") -> 79770.8 | AJ8: =IFERROR(AJ6+AJ7,"") -> 100551.2 | ... AN8: =IFERROR(AN6+AN7,"") -> 299714.24
A10: Expenses
A11: Cost of material consumed | B11: Rs Mn | D11: =IF('Raw Data - financials'!D10="","",'Raw Data - financials'!D10) -> 229.37 | E11: =IF('Raw Data - financials'!E10="","",'Raw Data - financials'!E10) -> 179.32 | F11: =IF('Raw Data - financials'!F10="","",'Raw Data - financials'!F10) -> 176.56 | G11: =IF('Raw Data - financials'!G10="","",'Raw Data - financials'!G10) -> 257.87 | H11: =IF('Raw Data - financials'!H10="","",'Raw Data - financials'!H10) -> 232.97 | I11: =IF('Raw Data - financials'!I10="","",'Raw Data - financials'!I10) -> 222.51 | J11: =IF('Raw Data - financials'!J10="","",'Raw Data - financials'!J10) -> 166.08 | K11: =IF('Raw Data - financials'!K10="","",'Raw Data - financials'!K10) -> 972.77 | ... W11: =IF('Raw Data - financials'!W10="","",'Raw Data - financials'!W10) -> 87.3 | AC11: =IF('Raw Data - financials'!AC10="","",'Raw Data - financials'!AC10) -> 2.41 | AD11: =IF('Raw Data - financials'!AD10="","",'Raw Data - financials'!AD10) -> 173.43 | AE11: =IF('Raw Data - financials'!AE10="","",'Raw Data - financials'!AE10) -> 382.41 | AF11: =IF('Raw Data - financials'!AF10="","",'Raw Data - financials'!AF10) -> 843.12 | AG11: =IF('Raw Data - financials'!AG10="","",'Raw Data - financials'!AG10) -> 1594.33 | AH11: =IF('Raw Data - financials'!AH10="","",'Raw Data - financials'!AH10) -> 651.13 | AI11: =IF('Raw Data - financials'!AI10="","",'Raw Data - financials'!AI10) -> 81 | AJ11: =IF('Raw Data - financials'!AJ10="","",'Raw Data - financials'!AJ10) -> 146.1 | AK11: =IF(Projections!AK122="","",Projections!AK122) -> 83003.324 | AL11: =IF(Projections!AL122="","",Projections!AL122) -> 109041.64 | AM11: =IF(Projections!AM122="","",Projections!AM122) -> 143251.62 | AN11: =IF(Projections!AN122="","",Projections!AN122) -> 188198.92
A12: Purchase of traded goods | B12: Rs Mn | D12: =IF('Raw Data - financials'!D11="","",'Raw Data - financials'!D11) -> 5509.42 | E12: =IF('Raw Data - financials'!E11="","",'Raw Data - financials'!E11) -> 4848.33 | F12: =IF('Raw Data - financials'!F11="","",'Raw Data - financials'!F11) -> 6902.15 | G12: =IF('Raw Data - financials'!G11="","",'Raw Data - financials'!G11) -> 6643.6 | H12: =IF('Raw Data - financials'!H11="","",'Raw Data - financials'!H11) -> 7415.45 | I12: =IF('Raw Data - financials'!I11="","",'Raw Data - financials'!I11) -> 5858.02 | J12: =IF('Raw Data - financials'!J11="","",'Raw Data - financials'!J11) -> 9188.98 | K12: =IF('Raw Data - financials'!K11="","",'Raw Data - financials'!K11) -> 6017.46 | ... W12: =IF('Raw Data - financials'!W11="","",'Raw Data - financials'!W11) -> 15728.3 | AC12: =IF('Raw Data - financials'!AC11="","",'Raw Data - financials'!AC11) -> 7852.43 | AD12: =IF('Raw Data - financials'!AD11="","",'Raw Data - financials'!AD11) -> 11787.46 | AE12: =IF('Raw Data - financials'!AE11="","",'Raw Data - financials'!AE11) -> 14956.06 | AF12: =IF('Raw Data - financials'!AF11="","",'Raw Data - financials'!AF11) -> 24078.31 | AG12: =IF('Raw Data - financials'!AG11="","",'Raw Data - financials'!AG11) -> 28479.91 | AH12: =IF('Raw Data - financials'!AH11="","",'Raw Data - financials'!AH11) -> 37816.75 | AI12: =IF('Raw Data - financials'!AI11="","",'Raw Data - financials'!AI11) -> 46830.8 | AJ12: =IF('Raw Data - financials'!AJ11="","",'Raw Data - financials'!AJ11) -> 57185.8 | AK12: 0 | AL12: 0 | AM12: 0 | AN12: 0
A13: Changes in inventories of finished goods and stock-in-trade | B13: Rs Mn | D13: =IF('Raw Data - financials'!D12="","",'Raw Data - financials'!D12) -> -885.47 | E13: =IF('Raw Data - financials'!E12="","",'Raw Data - financials'!E12) -> 42.57 | F13: =IF('Raw Data - financials'!F12="","",'Raw Data - financials'!F12) -> -1182.69 | G13: =IF('Raw Data - financials'!G12="","",'Raw Data - financials'!G12) -> -1420.88 | H13: =IF('Raw Data - financials'!H12="","",'Raw Data - financials'!H12) -> -1263 | I13: =IF('Raw Data - financials'!I12="","",'Raw Data - financials'!I12) -> 650.38 | J13: =IF('Raw Data - financials'!J12="","",'Raw Data - financials'!J12) -> -1073.5 | K13: =IF('Raw Data - financials'!K12="","",'Raw Data - financials'!K12) -> 268.69 | ... W13: =IF('Raw Data - financials'!W12="","",'Raw Data - financials'!W12) -> -1366.8 | AC13: =IF('Raw Data - financials'!AC12="","",'Raw Data - financials'!AC12) -> -1252.07 | AD13: =IF('Raw Data - financials'!AD12="","",'Raw Data - financials'!AD12) -> -1818.84 | AE13: =IF('Raw Data - financials'!AE12="","",'Raw Data - financials'!AE12) -> -460.22 | AF13: =IF('Raw Data - financials'!AF12="","",'Raw Data - financials'!AF12) -> -3621.28 | AG13: =IF('Raw Data - financials'!AG12="","",'Raw Data - financials'!AG12) -> -1417.43 | AH13: =IF('Raw Data - financials'!AH12="","",'Raw Data - financials'!AH12) -> -2004.02 | AI13: =IF('Raw Data - financials'!AI12="","",'Raw Data - financials'!AI12) -> -2185.2 | AJ13: =IF('Raw Data - financials'!AJ12="","",'Raw Data - financials'!AJ12) -> -2266.6 | AK13: 0 | AL13: 0 | AM13: 0 | AN13: 0
A14: Employee benefits expense | B14: Rs Mn | D14: =IF(Projections!D124="","",Projections!D124) -> 726.05 | E14: =IF(Projections!E124="","",Projections!E124) -> 694.01 | F14: =IF(Projections!F124="","",Projections!F124) -> 933.21 | G14: =IF(Projections!G124="","",Projections!G124) -> 908 | H14: =IF(Projections!H124="","",Projections!H124) -> 1147.09 | I14: =IF(Projections!I124="","",Projections!I124) -> 1217.61 | J14: =IF(Projections!J124="","",Projections!J124) -> 1279.16 | K14: =IF(Projections!K124="","",Projections!K124) -> 1273.31 | ... W14: =IF(Projections!W124="","",Projections!W124) -> 2038.4 | AC14: =IF(Projections!AC124="","",Projections!AC124) -> 1172.96 | AD14: =IF(Projections!AD124="","",Projections!AD124) -> 1956.13 | AE14: =IF(Projections!AE124="","",Projections!AE124) -> 2836.47 | AF14: =IF(Projections!AF124="","",Projections!AF124) -> 3259.39 | AG14: =IF(Projections!AG124="","",Projections!AG124) -> 4917.17 | AH14: =IF(Projections!AH124="","",Projections!AH124) -> 5649.01 | AI14: =IF(Projections!AI124="","",Projections!AI124) -> 6660.7 | AJ14: =IF(Projections!AJ124="","",Projections!AJ124) -> 7715.3 | ... AN14: =IF(Projections!AN124="","",Projections!AN124) -> 35847.413
A15: Finance costs | B15: Rs Mn | D15: =IF(Projections!D126="","",Projections!D126) -> 90.14 | E15: =IF(Projections!E126="","",Projections!E126) -> 113.49 | F15: =IF(Projections!F126="","",Projections!F126) -> 127.9 | G15: =IF(Projections!G126="","",Projections!G126) -> 133.58 | H15: =IF(Projections!H126="","",Projections!H126) -> 150.63 | I15: =IF(Projections!I126="","",Projections!I126) -> 203.56 | J15: =IF(Projections!J126="","",Projections!J126) -> 204.25 | K15: =IF(Projections!K126="","",Projections!K126) -> 187.61 | ... W15: =IF(Projections!W126="","",Projections!W126) -> 263.3 | AC15: =IF(Projections!AC126="","",Projections!AC126) -> 263.42 | AD15: =IF(Projections!AD126="","",Projections!AD126) -> 442.93 | AE15: =IF(Projections!AE126="","",Projections!AE126) -> 307.01 | AF15: =IF(Projections!AF126="","",Projections!AF126) -> 465.11 | AG15: =IF(Projections!AG126="","",Projections!AG126) -> 746.05 | AH15: =IF(Projections!AH126="","",Projections!AH126) -> 828.32 | AI15: =IF(Projections!AI126="","",Projections!AI126) -> 1073.2 | AJ15: =IF(Projections!AJ126="","",Projections!AJ126) -> 1171.2 | ... AN15: =IF(Projections!AN126="","",Projections!AN126) -> 3495.1227
A16: Depreciation and amortisation expense | B16: Rs Mn | D16: =IF(Projections!D127="","",Projections!D127) -> 194.97 | E16: =IF(Projections!E127="","",Projections!E127) -> 213.08 | F16: =IF(Projections!F127="","",Projections!F127) -> 251.24 | G16: =IF(Projections!G127="","",Projections!G127) -> 304.84 | H16: =IF(Projections!H127="","",Projections!H127) -> 310.12 | I16: =IF(Projections!I127="","",Projections!I127) -> 385.02 | J16: =IF(Projections!J127="","",Projections!J127) -> 507 | K16: =IF(Projections!K127="","",Projections!K127) -> 530.42 | ... W16: =IF(Projections!W127="","",Projections!W127) -> 842.2 | AC16: =IF(Projections!AC127="","",Projections!AC127) -> 308.76 | AD16: =IF(Projections!AD127="","",Projections!AD127) -> 595.09 | AE16: =IF(Projections!AE127="","",Projections!AE127) -> 671.28 | AF16: =IF(Projections!AF127="","",Projections!AF127) -> 964.13 | AG16: =IF(Projections!AG127="","",Projections!AG127) -> 1732.56 | AH16: =IF(Projections!AH127="","",Projections!AH127) -> 2242.33 | AI16: =IF(Projections!AI127="","",Projections!AI127) -> 2664 | AJ16: =IF(Projections!AJ127="","",Projections!AJ127) -> 3203.3 | ... AN16: =IF(Projections!AN127="","",Projections!AN127) -> 9559.3101
A17: Other expenses | B17: Rs Mn | D17: =IF(Projections!D128="","",Projections!D128) -> 2321.16 | E17: =IF(Projections!E128="","",Projections!E128) -> 2800.17 | F17: =IF(Projections!F128="","",Projections!F128) -> 3464.6 | G17: =IF(Projections!G128="","",Projections!G128) -> 2959.42 | H17: =IF(Projections!H128="","",Projections!H128) -> 3491.18 | I17: =IF(Projections!I128="","",Projections!I128) -> 3748.4 | J17: =IF(Projections!J128="","",Projections!J128) -> 4285.94 | K17: =IF(Projections!K128="","",Projections!K128) -> 3778.07 | ... W17: =IF(Projections!W128="","",Projections!W128) -> 7765.3 | AC17: =IF(Projections!AC128="","",Projections!AC128) -> 3133.11 | AD17: =IF(Projections!AD128="","",Projections!AD128) -> 4766.6 | AE17: =IF(Projections!AE128="","",Projections!AE128) -> 5079.98 | AF17: =IF(Projections!AF128="","",Projections!AF128) -> 11547.23 | AG17: =IF(Projections!AG128="","",Projections!AG128) -> 15303.59 | AH17: =IF(Projections!AH128="","",Projections!AH128) -> 18281.89 | AI17: =IF(Projections!AI128="","",Projections!AI128) -> 23371.8 | AJ17: =IF(Projections!AJ128="","",Projections!AJ128) -> 29919.8 | ... AN17: =IF(Projections!AN128="","",Projections!AN128) -> 51133.134
A18: Total Expenses | B18: Rs Mn | D18: =IFERROR(D11+D12+D13+D14+D15+D16+D17,"") -> 8185.64 | E18: =IFERROR(E11+E12+E13+E14+E15+E16+E17,"") -> 8890.97 | F18: =IFERROR(F11+F12+F13+F14+F15+F16+F17,"") -> 10672.97 | G18: =IFERROR(G11+G12+G13+G14+G15+G16+G17,"") -> 9786.43 | H18: =IFERROR(H11+H12+H13+H14+H15+H16+H17,"") -> 11484.44 | I18: =IFERROR(I11+I12+I13+I14+I15+I16+I17,"") -> 12285.5 | J18: =IFERROR(J11+J12+J13+J14+J15+J16+J17,"") -> 14557.91 | K18: =IFERROR(K11+K12+K13+K14+K15+K16+K17,"") -> 13028.33 | ... W18: =IFERROR(W11+W12+W13+W14+W15+W16+W17,"") -> 25358 | AC18: =IFERROR(AC11+AC12+AC13+AC14+AC15+AC16+AC17,"") -> 11481.02 | AD18: =IFERROR(AD11+AD12+AD13+AD14+AD15+AD16+AD17,"") -> 17902.8 | AE18: =IFERROR(AE11+AE12+AE13+AE14+AE15+AE16+AE17,"") -> 23772.99 | AF18: =IFERROR(AF11+AF12+AF13+AF14+AF15+AF16+AF17,"") -> 37536.01 | AG18: =IFERROR(AG11+AG12+AG13+AG14+AG15+AG16+AG17,"") -> 51356.18 | AH18: =IFERROR(AH11+AH12+AH13+AH14+AH15+AH16+AH17,"") -> 63465.41 | AI18: =IFERROR(AI11+AI12+AI13+AI14+AI15+AI16+AI17,"") -> 78496.3 | AJ18: =IFERROR(AJ11+AJ12+AJ13+AJ14+AJ15+AJ16+AJ17,"") -> 97074.9 | ... AN18: =IFERROR(AN11+AN12+AN13+AN14+AN15+AN16+AN17,"") -> 288233.9
A20: Profit Before Exceptional Items and Tax | B20: Rs Mn | D20: =IFERROR(D8-D18,"") -> 31.49 | E20: =IFERROR(E8-E18,"") -> 13.65 | F20: =IFERROR(F8-F18,"") -> 369.76 | G20: =IFERROR(G8-G18,"") -> 58.16 | H20: =IFERROR(H8-H18,"") -> 83.4 | I20: =IFERROR(I8-I18,"") -> 87.55 | J20: =IFERROR(J8-J18,"") -> 126.71 | K20: =IFERROR(K8-K18,"") -> 86.29 | ... W20: =IFERROR(W8-W18,"") -> 1215.2 | AC20: =IFERROR(AC8-AC18,"") -> -317.2 | AD20: =IFERROR(AD8-AD18,"") -> -124.3 | AE20: =IFERROR(AE8-AE18,"") -> 753.38 | AF20: =IFERROR(AF8-AF18,"") -> 473.06 | AG20: =IFERROR(AG8-AG18,"") -> 383.95 | AH20: =IFERROR(AH8-AH18,"") -> 690.27 | AI20: =IFERROR(AI8-AI18,"") -> 1274.5 | AJ20: =IFERROR(AJ8-AJ18,"") -> 3476.3 | ... AN20: =IFERROR(AN8-AN18,"") -> 11480.347
A21: Exceptional items, net | B21: Rs Mn | D21: =IF('Raw Data - financials'!D20="","",'Raw Data - financials'!D20) -> 0 | E21: =IF('Raw Data - financials'!E20="","",'Raw Data - financials'!E20) -> 0 | F21: =IF('Raw Data - financials'!F20="","",'Raw Data - financials'!F20) -> 0 | G21: =IF('Raw Data - financials'!G20="","",'Raw Data - financials'!G20) -> 0 | H21: =IF('Raw Data - financials'!H20="","",'Raw Data - financials'!H20) -> 0 | I21: =IF('Raw Data - financials'!I20="","",'Raw Data - financials'!I20) -> 0 | J21: =IF('Raw Data - financials'!J20="","",'Raw Data - financials'!J20) -> 0 | K21: =IF('Raw Data - financials'!K20="","",'Raw Data - financials'!K20) -> 0 | ... W21: =IF('Raw Data - financials'!W20="","",'Raw Data - financials'!W20) -> 0 | AC21: =IF('Raw Data - financials'!AC20="","",'Raw Data - financials'!AC20) -> 0 | AD21: =IF('Raw Data - financials'!AD20="","",'Raw Data - financials'!AD20) -> 0 | AE21: =IF('Raw Data - financials'!AE20="","",'Raw Data - financials'!AE20) -> 0 | AF21: =IF('Raw Data - financials'!AF20="","",'Raw Data - financials'!AF20) -> 0 | AG21: =IF('Raw Data - financials'!AG20="","",'Raw Data - financials'!AG20) -> 0 | AH21: =IF('Raw Data - financials'!AH20="","",'Raw Data - financials'!AH20) -> 0 | AI21: =IF('Raw Data - financials'!AI20="","",'Raw Data - financials'!AI20) -> 0 | AJ21: =IF('Raw Data - financials'!AJ20="","",'Raw Data - financials'!AJ20) -> 174 | AK21: 0 | AL21: 0 | AM21: 0 | AN21: 0
A22: Profit Before Tax | B22: Rs Mn | D22: =IFERROR(D20-D21,"") -> 31.49 | E22: =IFERROR(E20-E21,"") -> 13.65 | F22: =IFERROR(F20-F21,"") -> 369.76 | G22: =IFERROR(G20-G21,"") -> 58.16 | H22: =IFERROR(H20-H21,"") -> 83.4 | I22: =IFERROR(I20-I21,"") -> 87.55 | J22: =IFERROR(J20-J21,"") -> 126.71 | K22: =IFERROR(K20-K21,"") -> 86.29 | ... W22: =IFERROR(W20-W21,"") -> 1215.2 | AC22: =IFERROR(AC20-AC21,"") -> -317.2 | AD22: =IFERROR(AD20-AD21,"") -> -124.3 | AE22: =IFERROR(AE20-AE21,"") -> 753.38 | AF22: =IFERROR(AF20-AF21,"") -> 473.06 | AG22: =IFERROR(AG20-AG21,"") -> 383.95 | AH22: =IFERROR(AH20-AH21,"") -> 690.27 | AI22: =IFERROR(AI20-AI21,"") -> 1274.5 | AJ22: =IFERROR(AJ20-AJ21,"") -> 3302.3 | ... AN22: =IFERROR(AN20-AN21,"") -> 11480.347
A24: Tax expense
A25: Current tax | B25: Rs Mn | D25: =IF('Raw Data - financials'!D24="","",'Raw Data - financials'!D24) -> 133.64 | E25: =IF('Raw Data - financials'!E24="","",'Raw Data - financials'!E24) -> 3.66 | F25: =IF('Raw Data - financials'!F24="","",'Raw Data - financials'!F24) -> 144.35 | G25: =IF('Raw Data - financials'!G24="","",'Raw Data - financials'!G24) -> 141.28 | H25: =IF('Raw Data - financials'!H24="","",'Raw Data - financials'!H24) -> 113.25 | I25: =IF('Raw Data - financials'!I24="","",'Raw Data - financials'!I24) -> 215.91 | J25: =IF('Raw Data - financials'!J24="","",'Raw Data - financials'!J24) -> 270.99 | K25: =IF('Raw Data - financials'!K24="","",'Raw Data - financials'!K24) -> 260.96 | ... W25: =IF('Raw Data - financials'!W24="","",'Raw Data - financials'!W24) -> 709.2 | AC25: =IF('Raw Data - financials'!AC24="","",'Raw Data - financials'!AC24) -> 0 | AD25: =IF('Raw Data - financials'!AD24="","",'Raw Data - financials'!AD24) -> 45.37 | AE25: =IF('Raw Data - financials'!AE24="","",'Raw Data - financials'!AE24) -> 400.78 | AF25: =IF('Raw Data - financials'!AF24="","",'Raw Data - financials'!AF24) -> 422.93 | AG25: =IF('Raw Data - financials'!AG24="","",'Raw Data - financials'!AG24) -> 861.11 | AH25: =IF('Raw Data - financials'!AH24="","",'Raw Data - financials'!AH24) -> 1067.35 | AI25: =IF('Raw Data - financials'!AI24="","",'Raw Data - financials'!AI24) -> 415 | AJ25: =IF('Raw Data - financials'!AJ24="","",'Raw Data - financials'!AJ24) -> 1374.9 | AK25: =IF(Projections!AK131="","",Projections!AK131) -> 1965.5665 | AL25: =IF(Projections!AL131="","",Projections!AL131) -> 2569.4824 | AM25: =IF(Projections!AM131="","",Projections!AM131) -> 3358.7237 | AN25: =IF(Projections!AN131="","",Projections!AN131) -> 4390.0847
A26: Current tax pertaining to earlier years | B26: Rs Mn | D26: =IF('Raw Data - financials'!D25="","",'Raw Data - financials'!D25) -> 0 | E26: =IF('Raw Data - financials'!E25="","",'Raw Data - financials'!E25) -> 0 | F26: =IF('Raw Data - financials'!F25="","",'Raw Data - financials'!F25) -> 0 | G26: =IF('Raw Data - financials'!G25="","",'Raw Data - financials'!G25) -> 23.46 | H26: =IF('Raw Data - financials'!H25="","",'Raw Data - financials'!H25) -> 0 | I26: =IF('Raw Data - financials'!I25="","",'Raw Data - financials'!I25) -> 0 | J26: =IF('Raw Data - financials'!J25="","",'Raw Data - financials'!J25) -> 0 | K26: =IF('Raw Data - financials'!K25="","",'Raw Data - financials'!K25) -> 0 | ... W26: =IF('Raw Data - financials'!W25="","",'Raw Data - financials'!W25) -> 0 | AC26: =IF('Raw Data - financials'!AC25="","",'Raw Data - financials'!AC25) -> 0 | AD26: =IF('Raw Data - financials'!AD25="","",'Raw Data - financials'!AD25) -> 0 | AE26: =IF('Raw Data - financials'!AE25="","",'Raw Data - financials'!AE25) -> 0 | AF26: =IF('Raw Data - financials'!AF25="","",'Raw Data - financials'!AF25) -> 23.46 | AG26: =IF('Raw Data - financials'!AG25="","",'Raw Data - financials'!AG25) -> 0 | AH26: =IF('Raw Data - financials'!AH25="","",'Raw Data - financials'!AH25) -> 0 | AI26: =IF('Raw Data - financials'!AI25="","",'Raw Data - financials'!AI25) -> 0 | AJ26: =IF('Raw Data - financials'!AJ25="","",'Raw Data - financials'!AJ25) -> 0 | AK26: 0 | AL26: 0 | AM26: 0 | AN26: 0
A27: Deferred tax expense/(credit) | B27: Rs Mn | D27: =IF('Raw Data - financials'!D26="","",'Raw Data - financials'!D26) -> -137.37 | E27: =IF('Raw Data - financials'!E26="","",'Raw Data - financials'!E26) -> -1.73 | F27: =IF('Raw Data - financials'!F26="","",'Raw Data - financials'!F26) -> -64.74 | G27: =IF('Raw Data - financials'!G26="","",'Raw Data - financials'!G26) -> -124.27 | H27: =IF('Raw Data - financials'!H26="","",'Raw Data - financials'!H26) -> -86.72 | I27: =IF('Raw Data - financials'!I26="","",'Raw Data - financials'!I26) -> -184.91 | J27: =IF('Raw Data - financials'!J26="","",'Raw Data - financials'!J26) -> -236.32 | K27: =IF('Raw Data - financials'!K26="","",'Raw Data - financials'!K26) -> -217.42 | ... W27: =IF('Raw Data - financials'!W26="","",'Raw Data - financials'!W26) -> -281.5 | AC27: =IF('Raw Data - financials'!AC26="","",'Raw Data - financials'!AC26) -> -71.81 | AD27: =IF('Raw Data - financials'!AD26="","",'Raw Data - financials'!AD26) -> -6.27 | AE27: =IF('Raw Data - financials'!AE26="","",'Raw Data - financials'!AE26) -> -266.85 | AF27: =IF('Raw Data - financials'!AF26="","",'Raw Data - financials'!AF26) -> -328.11 | AG27: =IF('Raw Data - financials'!AG26="","",'Raw Data - financials'!AG26) -> -725.37 | AH27: =IF('Raw Data - financials'!AH26="","",'Raw Data - financials'!AH26) -> -814.24 | AI27: =IF('Raw Data - financials'!AI26="","",'Raw Data - financials'!AI26) -> 122.5 | AJ27: =IF('Raw Data - financials'!AJ26="","",'Raw Data - financials'!AJ26) -> -112 | AK27: 0 | AL27: 0 | AM27: 0 | AN27: 0
A28: Deferred tax credit for unrecognised business loss (earlier years) | B28: Rs Mn | D28: =IF('Raw Data - financials'!D27="","",'Raw Data - financials'!D27) -> 0 | E28: =IF('Raw Data - financials'!E27="","",'Raw Data - financials'!E27) -> 0 | F28: =IF('Raw Data - financials'!F27="","",'Raw Data - financials'!F27) -> 0 | G28: =IF('Raw Data - financials'!G27="","",'Raw Data - financials'!G27) -> -58.1 | H28: =IF('Raw Data - financials'!H27="","",'Raw Data - financials'!H27) -> 0 | I28: =IF('Raw Data - financials'!I27="","",'Raw Data - financials'!I27) -> 0 | J28: =IF('Raw Data - financials'!J27="","",'Raw Data - financials'!J27) -> 0 | K28: =IF('Raw Data - financials'!K27="","",'Raw Data - financials'!K27) -> 0 | ... W28: =IF('Raw Data - financials'!W27="","",'Raw Data - financials'!W27) -> 0 | AC28: =IF('Raw Data - financials'!AC27="","",'Raw Data - financials'!AC27) -> 0 | AD28: =IF('Raw Data - financials'!AD27="","",'Raw Data - financials'!AD27) -> 0 | AE28: =IF('Raw Data - financials'!AE27="","",'Raw Data - financials'!AE27) -> 0 | AF28: =IF('Raw Data - financials'!AF27="","",'Raw Data - financials'!AF27) -> -58.1 | AG28: =IF('Raw Data - financials'!AG27="","",'Raw Data - financials'!AG27) -> 0 | AH28: =IF('Raw Data - financials'!AH27="","",'Raw Data - financials'!AH27) -> 0 | AI28: =IF('Raw Data - financials'!AI27="","",'Raw Data - financials'!AI27) -> 0 | AJ28: =IF('Raw Data - financials'!AJ27="","",'Raw Data - financials'!AJ27) -> 0 | AK28: 0 | AL28: 0 | AM28: 0 | AN28: 0
A29: Total Tax Expense/(Income) | B29: Rs Mn | D29: =IFERROR(D25+D26+D27+D28,"") -> -3.73 | E29: =IFERROR(E25+E26+E27+E28,"") -> 1.93 | F29: =IFERROR(F25+F26+F27+F28,"") -> 79.61 | G29: =IFERROR(G25+G26+G27+G28,"") -> -17.63 | H29: =IFERROR(H25+H26+H27+H28,"") -> 26.53 | I29: =IFERROR(I25+I26+I27+I28,"") -> 31 | J29: =IFERROR(J25+J26+J27+J28,"") -> 34.67 | K29: =IFERROR(K25+K26+K27+K28,"") -> 43.54 | ... W29: =IFERROR(W25+W26+W27+W28,"") -> 427.7 | AC29: =IFERROR(AC25+AC26+AC27+AC28,"") -> -71.81 | AD29: =IFERROR(AD25+AD26+AD27+AD28,"") -> 39.1 | AE29: =IFERROR(AE25+AE26+AE27+AE28,"") -> 133.93 | AF29: =IFERROR(AF25+AF26+AF27+AF28,"") -> 60.18 | AG29: =IFERROR(AG25+AG26+AG27+AG28,"") -> 135.74 | AH29: =IFERROR(AH25+AH26+AH27+AH28,"") -> 253.11 | AI29: =IFERROR(AI25+AI26+AI27+AI28,"") -> 537.5 | AJ29: =IFERROR(AJ25+AJ26+AJ27+AJ28,"") -> 1262.9 | ... AN29: =IFERROR(AN25+AN26+AN27+AN28,"") -> 4390.0847
A31: Profit After Tax (PAT) | B31: Rs Mn | D31: =IFERROR(D22-D29,"") -> 35.22 | E31: =IFERROR(E22-E29,"") -> 11.72 | F31: =IFERROR(F22-F29,"") -> 290.15 | G31: =IFERROR(G22-G29,"") -> 75.79 | H31: =IFERROR(H22-H29,"") -> 56.87 | I31: =IFERROR(I22-I29,"") -> 56.55 | J31: =IFERROR(J22-J29,"") -> 92.04 | K31: =IFERROR(K22-K29,"") -> 42.75 | ... W31: =IFERROR(W22-W29,"") -> 787.5 | AC31: =IFERROR(AC22-AC29,"") -> -245.39 | AD31: =IFERROR(AD22-AD29,"") -> -163.4 | AE31: =IFERROR(AE22-AE29,"") -> 619.45 | AF31: =IFERROR(AF22-AF29,"") -> 412.88 | AG31: =IFERROR(AG22-AG29,"") -> 248.21 | AH31: =IFERROR(AH22-AH29,"") -> 437.16 | AI31: =IFERROR(AI22-AI29,"") -> 737 | AJ31: =IFERROR(AJ22-AJ29,"") -> 2039.4 | ... AN31: =IFERROR(AN22-AN29,"") -> 7090.2624
A32: EPS (diluted) | B32: Rs | D32: =IF(Projections!D133="","",Projections!D133) -> 0.07 | E32: =IF(Projections!E133="","",Projections!E133) -> 0.03 | F32: =IF(Projections!F133="","",Projections!F133) -> 0.6 | G32: =IF(Projections!G133="","",Projections!G133) -> 0.18 | H32: =IF(Projections!H133="","",Projections!H133) -> 0 | I32: =IF(Projections!I133="","",Projections!I133) -> 0.01 | J32: =IF(Projections!J133="","",Projections!J133) -> 0.03 | K32: =IF(Projections!K133="","",Projections!K133) -> 0.01 | ... W32: =IF(Projections!W133="","",Projections!W133) -> 0.27 | AC32: =IF(Projections!AC133="","",Projections!AC133) -> -17.7 | AD32: =IF(Projections!AD133="","",Projections!AD133) -> -11.63 | AE32: =IF(Projections!AE133="","",Projections!AE133) -> 40.07 | AF32: =IF(Projections!AF133="","",Projections!AF133) -> 0.87 | AG32: =IF(Projections!AG133="","",Projections!AG133) -> 0.07 | AH32: =IF(Projections!AH133="","",Projections!AH133) -> 0.11 | AI32: =IF(Projections!AI133="","",Projections!AI133) -> 0.23 | AJ32: =IF(Projections!AJ133="","",Projections!AJ133) -> 0.7 | ... AN32: =IF(Projections!AN133="","",Projections!AN133) -> 2.4886846
A34: BALANCE SHEET (CONSOLIDATED, REPORTED FORMAT)
A35: Historical quarters/years link straight to Raw Data - financials actuals (full granularity). For FY27E-30E, every reported sub-line links 1:1 to the Projections sheet's now-fully-detailed Balance Sheet (Property, plant / Right-of-use / Other intangibles link to the gross-block detail section; lease liabilities are grown at the same rate as right-of-use assets; borrowings are split non-current/current and held flat; trade payables stay one modeled total on 'other creditors', with 'micro & small' shown as 0 for projected years; smaller items use either a flat hold or a %-of-Revenue assumption -- see the Projections sheet's Balance Sheet section for each line's driver). Subtotals (Total Non-Current/Current Assets etc.) are formulas here, not links, so they work for both historical and projected columns and serve as a consistency check against Projections' own subtotals.
A36: ASSETS
A37: Non-current assets
A38: Property, plant and equipment | B38: Rs Mn | E38: =IF('Raw Data - financials'!E49="","",'Raw Data - financials'!E49) | G38: =IF('Raw Data - financials'!G49="","",'Raw Data - financials'!G49) -> 1244.42 | I38: =IF('Raw Data - financials'!I49="","",'Raw Data - financials'!I49) -> 1713.47 | K38: =IF('Raw Data - financials'!K49="","",'Raw Data - financials'!K49) -> 2313.46 | M38: =IF('Raw Data - financials'!M49="","",'Raw Data - financials'!M49) -> 2315.23 | O38: =IF('Raw Data - financials'!O49="","",'Raw Data - financials'!O49) -> 2357.72 | Q38: =IF('Raw Data - financials'!Q49="","",'Raw Data - financials'!Q49) -> 2351.5 | S38: =IF('Raw Data - financials'!S49="","",'Raw Data - financials'!S49) -> 2717.2 | U38: =IF('Raw Data - financials'!U49="","",'Raw Data - financials'!U49) -> 2712.6 | W38: =IF('Raw Data - financials'!W49="","",'Raw Data - financials'!W49) -> 2999.7 | AC38: =IF('Raw Data - financials'!AC49="","",'Raw Data - financials'!AC49) -> 429.05 | AD38: =IF('Raw Data - financials'!AD49="","",'Raw Data - financials'!AD49) -> 701.49 | AE38: =IF('Raw Data - financials'!AE49="","",'Raw Data - financials'!AE49) -> 686.52 | AF38: =IF('Raw Data - financials'!AF49="","",'Raw Data - financials'!AF49) -> 1244.42 | AG38: =IF('Raw Data - financials'!AG49="","",'Raw Data - financials'!AG49) -> 2313.46 | AH38: =IF('Raw Data - financials'!AH49="","",'Raw Data - financials'!AH49) -> 2357.72 | AI38: =IF('Raw Data - financials'!AI49="","",'Raw Data - financials'!AI49) -> 2717.2 | AJ38: =IF('Raw Data - financials'!AJ49="","",'Raw Data - financials'!AJ49) -> 2999.7 | AK38: =IF(Projections!AK139="","",Projections!AK139) -> 2999.7 | AL38: =IF(Projections!AL139="","",Projections!AL139) -> 2999.7 | AM38: =IF(Projections!AM139="","",Projections!AM139) -> 2999.7 | AN38: =IF(Projections!AN139="","",Projections!AN139) -> 2999.7
A39: Capital work-in-progress | B39: Rs Mn | E39: =IF('Raw Data - financials'!E50="","",'Raw Data - financials'!E50) | G39: =IF('Raw Data - financials'!G50="","",'Raw Data - financials'!G50) -> 97.64 | I39: =IF('Raw Data - financials'!I50="","",'Raw Data - financials'!I50) -> 108.64 | K39: =IF('Raw Data - financials'!K50="","",'Raw Data - financials'!K50) -> 20.22 | M39: =IF('Raw Data - financials'!M50="","",'Raw Data - financials'!M50) -> 8.52 | O39: =IF('Raw Data - financials'!O50="","",'Raw Data - financials'!O50) -> 60.77 | Q39: =IF('Raw Data - financials'!Q50="","",'Raw Data - financials'!Q50) -> 20.6 | S39: =IF('Raw Data - financials'!S50="","",'Raw Data - financials'!S50) -> 31.7 | U39: =IF('Raw Data - financials'!U50="","",'Raw Data - financials'!U50) -> 46.9 | W39: =IF('Raw Data - financials'!W50="","",'Raw Data - financials'!W50) -> 92.5 | AC39: =IF('Raw Data - financials'!AC50="","",'Raw Data - financials'!AC50) -> 3.2 | AD39: =IF('Raw Data - financials'!AD50="","",'Raw Data - financials'!AD50) -> 7.78 | AE39: =IF('Raw Data - financials'!AE50="","",'Raw Data - financials'!AE50) -> 19.69 | AF39: =IF('Raw Data - financials'!AF50="","",'Raw Data - financials'!AF50) -> 97.64 | AG39: =IF('Raw Data - financials'!AG50="","",'Raw Data - financials'!AG50) -> 20.22 | AH39: =IF('Raw Data - financials'!AH50="","",'Raw Data - financials'!AH50) -> 60.77 | AI39: =IF('Raw Data - financials'!AI50="","",'Raw Data - financials'!AI50) -> 31.7 | AJ39: =IF('Raw Data - financials'!AJ50="","",'Raw Data - financials'!AJ50) -> 92.5 | AK39: =IF(Projections!AK140="","",Projections!AK140) -> 92.5 | AL39: =IF(Projections!AL140="","",Projections!AL140) -> 92.5 | AM39: =IF(Projections!AM140="","",Projections!AM140) -> 92.5 | AN39: =IF(Projections!AN140="","",Projections!AN140) -> 92.5
A40: Goodwill | B40: Rs Mn | E40: =IF('Raw Data - financials'!E51="","",'Raw Data - financials'!E51) | G40: =IF('Raw Data - financials'!G51="","",'Raw Data - financials'!G51) -> 474.78 | I40: =IF('Raw Data - financials'!I51="","",'Raw Data - financials'!I51) -> 789.04 | K40: =IF('Raw Data - financials'!K51="","",'Raw Data - financials'!K51) -> 610.65 | M40: =IF('Raw Data - financials'!M51="","",'Raw Data - financials'!M51) -> 610.65 | O40: =IF('Raw Data - financials'!O51="","",'Raw Data - financials'!O51) -> 610.65 | Q40: =IF('Raw Data - financials'!Q51="","",'Raw Data - financials'!Q51) -> 610.7 | S40: =IF('Raw Data - financials'!S51="","",'Raw Data - financials'!S51) -> 975 | U40: =IF('Raw Data - financials'!U51="","",'Raw Data - financials'!U51) -> 975.1 | W40: =IF('Raw Data - financials'!W51="","",'Raw Data - financials'!W51) -> 975 | AC40: =IF('Raw Data - financials'!AC51="","",'Raw Data - financials'!AC51) -> 1.43 | AD40: =IF('Raw Data - financials'!AD51="","",'Raw Data - financials'!AD51) -> 1.43 | AE40: =IF('Raw Data - financials'!AE51="","",'Raw Data - financials'!AE51) -> 5.43 | AF40: =IF('Raw Data - financials'!AF51="","",'Raw Data - financials'!AF51) -> 474.78 | AG40: =IF('Raw Data - financials'!AG51="","",'Raw Data - financials'!AG51) -> 610.65 | AH40: =IF('Raw Data - financials'!AH51="","",'Raw Data - financials'!AH51) -> 610.65 | AI40: =IF('Raw Data - financials'!AI51="","",'Raw Data - financials'!AI51) -> 975 | AJ40: =IF('Raw Data - financials'!AJ51="","",'Raw Data - financials'!AJ51) -> 975 | AK40: =IF(Projections!AK141="","",Projections!AK141) -> 975 | AL40: =IF(Projections!AL141="","",Projections!AL141) -> 975 | AM40: =IF(Projections!AM141="","",Projections!AM141) -> 975 | AN40: =IF(Projections!AN141="","",Projections!AN141) -> 975
A41: Other intangible assets | B41: Rs Mn | E41: =IF('Raw Data - financials'!E52="","",'Raw Data - financials'!E52) | G41: =IF('Raw Data - financials'!G52="","",'Raw Data - financials'!G52) -> 640.05 | I41: =IF('Raw Data - financials'!I52="","",'Raw Data - financials'!I52) -> 664.77 | K41: =IF('Raw Data - financials'!K52="","",'Raw Data - financials'!K52) -> 944.85 | M41: =IF('Raw Data - financials'!M52="","",'Raw Data - financials'!M52) -> 1009.09 | O41: =IF('Raw Data - financials'!O52="","",'Raw Data - financials'!O52) -> 1104.67 | Q41: =IF('Raw Data - financials'!Q52="","",'Raw Data - financials'!Q52) -> 1063.9 | S41: =IF('Raw Data - financials'!S52="","",'Raw Data - financials'!S52) -> 1357.4 | U41: =IF('Raw Data - financials'!U52="","",'Raw Data - financials'!U52) -> 1244.3 | W41: =IF('Raw Data - financials'!W52="","",'Raw Data - financials'!W52) -> 1490.1 | AC41: =IF('Raw Data - financials'!AC52="","",'Raw Data - financials'!AC52) -> 106.03 | AD41: =IF('Raw Data - financials'!AD52="","",'Raw Data - financials'!AD52) -> 127.45 | AE41: =IF('Raw Data - financials'!AE52="","",'Raw Data - financials'!AE52) -> 230.34 | AF41: =IF('Raw Data - financials'!AF52="","",'Raw Data - financials'!AF52) -> 640.05 | AG41: =IF('Raw Data - financials'!AG52="","",'Raw Data - financials'!AG52) -> 944.85 | AH41: =IF('Raw Data - financials'!AH52="","",'Raw Data - financials'!AH52) -> 1104.67 | AI41: =IF('Raw Data - financials'!AI52="","",'Raw Data - financials'!AI52) -> 1357.4 | AJ41: =IF('Raw Data - financials'!AJ52="","",'Raw Data - financials'!AJ52) -> 1490.1 | AK41: =IF(Projections!AK142="","",Projections!AK142) -> 1490.1 | AL41: =IF(Projections!AL142="","",Projections!AL142) -> 1490.1 | AM41: =IF(Projections!AM142="","",Projections!AM142) -> 1490.1 | AN41: =IF(Projections!AN142="","",Projections!AN142) -> 1490.1
A42: Right of use assets | B42: Rs Mn | E42: =IF('Raw Data - financials'!E53="","",'Raw Data - financials'!E53) | G42: =IF('Raw Data - financials'!G53="","",'Raw Data - financials'!G53) -> 2473.26 | I42: =IF('Raw Data - financials'!I53="","",'Raw Data - financials'!I53) -> 4069.36 | K42: =IF('Raw Data - financials'!K53="","",'Raw Data - financials'!K53) -> 3119.21 | M42: =IF('Raw Data - financials'!M53="","",'Raw Data - financials'!M53) -> 2768.35 | O42: =IF('Raw Data - financials'!O53="","",'Raw Data - financials'!O53) -> 2608.54 | Q42: =IF('Raw Data - financials'!Q53="","",'Raw Data - financials'!Q53) -> 2786.2 | S42: =IF('Raw Data - financials'!S53="","",'Raw Data - financials'!S53) -> 3298.6 | U42: =IF('Raw Data - financials'!U53="","",'Raw Data - financials'!U53) -> 3865.4 | W42: =IF('Raw Data - financials'!W53="","",'Raw Data - financials'!W53) -> 4614.7 | AC42: =IF('Raw Data - financials'!AC53="","",'Raw Data - financials'!AC53) -> 859.31 | AD42: =IF('Raw Data - financials'!AD53="","",'Raw Data - financials'!AD53) -> 1439.94 | AE42: =IF('Raw Data - financials'!AE53="","",'Raw Data - financials'!AE53) -> 1389.34 | AF42: =IF('Raw Data - financials'!AF53="","",'Raw Data - financials'!AF53) -> 2473.26 | AG42: =IF('Raw Data - financials'!AG53="","",'Raw Data - financials'!AG53) -> 3119.21 | AH42: =IF('Raw Data - financials'!AH53="","",'Raw Data - financials'!AH53) -> 2608.54 | AI42: =IF('Raw Data - financials'!AI53="","",'Raw Data - financials'!AI53) -> 3298.6 | AJ42: =IF('Raw Data - financials'!AJ53="","",'Raw Data - financials'!AJ53) -> 4614.7 | AK42: =IF(Projections!AK143="","",Projections!AK143) -> 4614.7 | AL42: =IF(Projections!AL143="","",Projections!AL143) -> 4614.7 | AM42: =IF(Projections!AM143="","",Projections!AM143) -> 4614.7 | AN42: =IF(Projections!AN143="","",Projections!AN143) -> 4614.7
A43: Intangible assets under development | B43: Rs Mn | E43: =IF('Raw Data - financials'!E54="","",'Raw Data - financials'!E54) | G43: =IF('Raw Data - financials'!G54="","",'Raw Data - financials'!G54) -> 147.31 | I43: =IF('Raw Data - financials'!I54="","",'Raw Data - financials'!I54) -> 246.38 | K43: =IF('Raw Data - financials'!K54="","",'Raw Data - financials'!K54) -> 288.56 | M43: =IF('Raw Data - financials'!M54="","",'Raw Data - financials'!M54) -> 254.59 | O43: =IF('Raw Data - financials'!O54="","",'Raw Data - financials'!O54) -> 236.99 | Q43: =IF('Raw Data - financials'!Q54="","",'Raw Data - financials'!Q54) -> 328.7 | S43: =IF('Raw Data - financials'!S54="","",'Raw Data - financials'!S54) -> 335.7 | U43: =IF('Raw Data - financials'!U54="","",'Raw Data - financials'!U54) -> 402.2 | W43: =IF('Raw Data - financials'!W54="","",'Raw Data - financials'!W54) -> 0 | AC43: =IF('Raw Data - financials'!AC54="","",'Raw Data - financials'!AC54) -> 0 | AD43: =IF('Raw Data - financials'!AD54="","",'Raw Data - financials'!AD54) -> 12.45 | AE43: =IF('Raw Data - financials'!AE54="","",'Raw Data - financials'!AE54) -> 3.88 | AF43: =IF('Raw Data - financials'!AF54="","",'Raw Data - financials'!AF54) -> 147.31 | AG43: =IF('Raw Data - financials'!AG54="","",'Raw Data - financials'!AG54) -> 288.56 | AH43: =IF('Raw Data - financials'!AH54="","",'Raw Data - financials'!AH54) -> 236.99 | AI43: =IF('Raw Data - financials'!AI54="","",'Raw Data - financials'!AI54) -> 335.7 | AJ43: =IF('Raw Data - financials'!AJ54="","",'Raw Data - financials'!AJ54) -> 0 | AK43: =IF(Projections!AK144="","",Projections!AK144) -> 0 | AL43: =IF(Projections!AL144="","",Projections!AL144) -> 0 | AM43: =IF(Projections!AM144="","",Projections!AM144) -> 0 | AN43: =IF(Projections!AN144="","",Projections!AN144) -> 0
A44: Investments accounted for using equity method | B44: Rs Mn | E44: =IF('Raw Data - financials'!E55="","",'Raw Data - financials'!E55) | G44: =IF('Raw Data - financials'!G55="","",'Raw Data - financials'!G55) -> 0 | I44: =IF('Raw Data - financials'!I55="","",'Raw Data - financials'!I55) -> 0 | K44: =IF('Raw Data - financials'!K55="","",'Raw Data - financials'!K55) -> 0 | M44: =IF('Raw Data - financials'!M55="","",'Raw Data - financials'!M55) -> 0 | O44: =IF('Raw Data - financials'!O55="","",'Raw Data - financials'!O55) -> 338.23 | Q44: =IF('Raw Data - financials'!Q55="","",'Raw Data - financials'!Q55) -> 327.6 | S44: =IF('Raw Data - financials'!S55="","",'Raw Data - financials'!S55) -> 0 | U44: =IF('Raw Data - financials'!U55="","",'Raw Data - financials'!U55) -> 0 | W44: =IF('Raw Data - financials'!W55="","",'Raw Data - financials'!W55) -> 0 | AC44: =IF('Raw Data - financials'!AC55="","",'Raw Data - financials'!AC55) -> 0 | AD44: =IF('Raw Data - financials'!AD55="","",'Raw Data - financials'!AD55) -> 0 | AE44: =IF('Raw Data - financials'!AE55="","",'Raw Data - financials'!AE55) -> 0 | AF44: =IF('Raw Data - financials'!AF55="","",'Raw Data - financials'!AF55) -> 0 | AG44: =IF('Raw Data - financials'!AG55="","",'Raw Data - financials'!AG55) -> 0 | AH44: =IF('Raw Data - financials'!AH55="","",'Raw Data - financials'!AH55) -> 338.23 | AI44: =IF('Raw Data - financials'!AI55="","",'Raw Data - financials'!AI55) -> 0 | AJ44: =IF('Raw Data - financials'!AJ55="","",'Raw Data - financials'!AJ55) -> 0 | AK44: =IF(Projections!AK145="","",Projections!AK145) -> 0 | AL44: =IF(Projections!AL145="","",Projections!AL145) -> 0 | AM44: =IF(Projections!AM145="","",Projections!AM145) -> 0 | AN44: =IF(Projections!AN145="","",Projections!AN145) -> 0
A45: Financial assets - Investments | B45: Rs Mn | E45: =IF('Raw Data - financials'!E56="","",'Raw Data - financials'!E56) | G45: =IF('Raw Data - financials'!G56="","",'Raw Data - financials'!G56) -> 0 | I45: =IF('Raw Data - financials'!I56="","",'Raw Data - financials'!I56) -> 405.08 | K45: =IF('Raw Data - financials'!K56="","",'Raw Data - financials'!K56) -> 381.2 | M45: =IF('Raw Data - financials'!M56="","",'Raw Data - financials'!M56) -> 356 | O45: =IF('Raw Data - financials'!O56="","",'Raw Data - financials'!O56) -> 4.88 | Q45: =IF('Raw Data - financials'!Q56="","",'Raw Data - financials'!Q56) -> 4.9 | S45: =IF('Raw Data - financials'!S56="","",'Raw Data - financials'!S56) -> 1.6 | U45: =IF('Raw Data - financials'!U56="","",'Raw Data - financials'!U56) -> 1.6 | W45: =IF('Raw Data - financials'!W56="","",'Raw Data - financials'!W56) -> 1.6 | AC45: =IF('Raw Data - financials'!AC56="","",'Raw Data - financials'!AC56) -> 32.3 | AD45: =IF('Raw Data - financials'!AD56="","",'Raw Data - financials'!AD56) -> 38.03 | AE45: =IF('Raw Data - financials'!AE56="","",'Raw Data - financials'!AE56) -> 13.19 | AF45: =IF('Raw Data - financials'!AF56="","",'Raw Data - financials'!AF56) -> 0 | AG45: =IF('Raw Data - financials'!AG56="","",'Raw Data - financials'!AG56) -> 381.2 | AH45: =IF('Raw Data - financials'!AH56="","",'Raw Data - financials'!AH56) -> 4.88 | AI45: =IF('Raw Data - financials'!AI56="","",'Raw Data - financials'!AI56) -> 1.6 | AJ45: =IF('Raw Data - financials'!AJ56="","",'Raw Data - financials'!AJ56) -> 1.6 | AK45: =IF(Projections!AK146="","",Projections!AK146) -> 1.6 | AL45: =IF(Projections!AL146="","",Projections!AL146) -> 1.6 | AM45: =IF(Projections!AM146="","",Projections!AM146) -> 1.6 | AN45: =IF(Projections!AN146="","",Projections!AN146) -> 1.6
A46: Financial assets - Loans | B46: Rs Mn | E46: =IF('Raw Data - financials'!E57="","",'Raw Data - financials'!E57) | G46: =IF('Raw Data - financials'!G57="","",'Raw Data - financials'!G57) -> 0 | I46: =IF('Raw Data - financials'!I57="","",'Raw Data - financials'!I57) -> 0 | K46: =IF('Raw Data - financials'!K57="","",'Raw Data - financials'!K57) -> 0 | M46: =IF('Raw Data - financials'!M57="","",'Raw Data - financials'!M57) -> 0 | O46: =IF('Raw Data - financials'!O57="","",'Raw Data - financials'!O57) -> 0 | Q46: =IF('Raw Data - financials'!Q57="","",'Raw Data - financials'!Q57) -> 0 | S46: =IF('Raw Data - financials'!S57="","",'Raw Data - financials'!S57) -> 0 | U46: =IF('Raw Data - financials'!U57="","",'Raw Data - financials'!U57) -> 0 | W46: =IF('Raw Data - financials'!W57="","",'Raw Data - financials'!W57) -> 0 | AC46: =IF('Raw Data - financials'!AC57="","",'Raw Data - financials'!AC57) -> 56.31 | AD46: =IF('Raw Data - financials'!AD57="","",'Raw Data - financials'!AD57) -> 105.84 | AE46: =IF('Raw Data - financials'!AE57="","",'Raw Data - financials'!AE57) -> 161.79 | AF46: =IF('Raw Data - financials'!AF57="","",'Raw Data - financials'!AF57) -> 0 | AG46: =IF('Raw Data - financials'!AG57="","",'Raw Data - financials'!AG57) -> 0 | AH46: =IF('Raw Data - financials'!AH57="","",'Raw Data - financials'!AH57) -> 0 | AI46: =IF('Raw Data - financials'!AI57="","",'Raw Data - financials'!AI57) -> 0 | AJ46: =IF('Raw Data - financials'!AJ57="","",'Raw Data - financials'!AJ57) -> 0 | AK46: =IF(Projections!AK147="","",Projections!AK147) -> 0 | AL46: =IF(Projections!AL147="","",Projections!AL147) -> 0 | AM46: =IF(Projections!AM147="","",Projections!AM147) -> 0 | AN46: =IF(Projections!AN147="","",Projections!AN147) -> 0
A47: Financial assets - Other financial assets | B47: Rs Mn | E47: =IF('Raw Data - financials'!E58="","",'Raw Data - financials'!E58) | G47: =IF('Raw Data - financials'!G58="","",'Raw Data - financials'!G58) -> 718.79 | I47: =IF('Raw Data - financials'!I58="","",'Raw Data - financials'!I58) -> 889.82 | K47: =IF('Raw Data - financials'!K58="","",'Raw Data - financials'!K58) -> 434.5 | M47: =IF('Raw Data - financials'!M58="","",'Raw Data - financials'!M58) -> 417.87 | O47: =IF('Raw Data - financials'!O58="","",'Raw Data - financials'!O58) -> 492.36 | Q47: =IF('Raw Data - financials'!Q58="","",'Raw Data - financials'!Q58) -> 1153.7 | S47: =IF('Raw Data - financials'!S58="","",'Raw Data - financials'!S58) -> 986.8 | U47: =IF('Raw Data - financials'!U58="","",'Raw Data - financials'!U58) -> 593.9 | W47: =IF('Raw Data - financials'!W58="","",'Raw Data - financials'!W58) -> 685.2 | AC47: =IF('Raw Data - financials'!AC58="","",'Raw Data - financials'!AC58) -> 0 | AD47: =IF('Raw Data - financials'!AD58="","",'Raw Data - financials'!AD58) -> 0 | AE47: =IF('Raw Data - financials'!AE58="","",'Raw Data - financials'!AE58) -> 0 | AF47: =IF('Raw Data - financials'!AF58="","",'Raw Data - financials'!AF58) -> 718.79 | AG47: =IF('Raw Data - financials'!AG58="","",'Raw Data - financials'!AG58) -> 434.5 | AH47: =IF('Raw Data - financials'!AH58="","",'Raw Data - financials'!AH58) -> 492.36 | AI47: =IF('Raw Data - financials'!AI58="","",'Raw Data - financials'!AI58) -> 986.8 | AJ47: =IF('Raw Data - financials'!AJ58="","",'Raw Data - financials'!AJ58) -> 685.2 | AK47: =IF(Projections!AK149="","",Projections!AK149) -> 922.25916 | AL47: =IF(Projections!AL149="","",Projections!AL149) -> 1211.5737 | AM47: =IF(Projections!AM149="","",Projections!AM149) -> 1591.6846 | AN47: =IF(Projections!AN149="","",Projections!AN149) -> 2091.0991
A48: Deferred tax assets (net) | B48: Rs Mn | E48: =IF('Raw Data - financials'!E59="","",'Raw Data - financials'!E59) | G48: =IF('Raw Data - financials'!G59="","",'Raw Data - financials'!G59) -> 1152.18 | I48: =IF('Raw Data - financials'!I59="","",'Raw Data - financials'!I59) -> 1424.09 | K48: =IF('Raw Data - financials'!K59="","",'Raw Data - financials'!K59) -> 1877.73 | M48: =IF('Raw Data - financials'!M59="","",'Raw Data - financials'!M59) -> 2258.39 | O48: =IF('Raw Data - financials'!O59="","",'Raw Data - financials'!O59) -> 2689.91 | Q48: =IF('Raw Data - financials'!Q59="","",'Raw Data - financials'!Q59) -> 3173.5 | S48: =IF('Raw Data - financials'!S59="","",'Raw Data - financials'!S59) -> 2579.5 | U48: =IF('Raw Data - financials'!U59="","",'Raw Data - financials'!U59) -> 2550.5 | W48: =IF('Raw Data - financials'!W59="","",'Raw Data - financials'!W59) -> 2687.8 | AC48: =IF('Raw Data - financials'!AC59="","",'Raw Data - financials'!AC59) -> 501.48 | AD48: =IF('Raw Data - financials'!AD59="","",'Raw Data - financials'!AD59) -> 506.11 | AE48: =IF('Raw Data - financials'!AE59="","",'Raw Data - financials'!AE59) -> 780.41 | AF48: =IF('Raw Data - financials'!AF59="","",'Raw Data - financials'!AF59) -> 1152.18 | AG48: =IF('Raw Data - financials'!AG59="","",'Raw Data - financials'!AG59) -> 1877.73 | AH48: =IF('Raw Data - financials'!AH59="","",'Raw Data - financials'!AH59) -> 2689.91 | AI48: =IF('Raw Data - financials'!AI59="","",'Raw Data - financials'!AI59) -> 2579.5 | AJ48: =IF('Raw Data - financials'!AJ59="","",'Raw Data - financials'!AJ59) -> 2687.8 | AK48: =IF(Projections!AK151="","",Projections!AK151) -> 2687.8 | AL48: =IF(Projections!AL151="","",Projections!AL151) -> 2687.8 | AM48: =IF(Projections!AM151="","",Projections!AM151) -> 2687.8 | AN48: =IF(Projections!AN151="","",Projections!AN151) -> 2687.8
A49: Non-current tax assets (net) | B49: Rs Mn | E49: =IF('Raw Data - financials'!E60="","",'Raw Data - financials'!E60) | G49: =IF('Raw Data - financials'!G60="","",'Raw Data - financials'!G60) -> 138.7 | I49: =IF('Raw Data - financials'!I60="","",'Raw Data - financials'!I60) -> 187.28 | K49: =IF('Raw Data - financials'!K60="","",'Raw Data - financials'!K60) -> 211.82 | M49: =IF('Raw Data - financials'!M60="","",'Raw Data - financials'!M60) -> 352.36 | O49: =IF('Raw Data - financials'!O60="","",'Raw Data - financials'!O60) -> 456.72 | Q49: =IF('Raw Data - financials'!Q60="","",'Raw Data - financials'!Q60) -> 22.8 | S49: =IF('Raw Data - financials'!S60="","",'Raw Data - financials'!S60) -> 639.5 | U49: =IF('Raw Data - financials'!U60="","",'Raw Data - financials'!U60) -> 844.4 | W49: =IF('Raw Data - financials'!W60="","",'Raw Data - financials'!W60) -> 622.6 | AC49: =IF('Raw Data - financials'!AC60="","",'Raw Data - financials'!AC60) -> 110.46 | AD49: =IF('Raw Data - financials'!AD60="","",'Raw Data - financials'!AD60) -> 110.45 | AE49: =IF('Raw Data - financials'!AE60="","",'Raw Data - financials'!AE60) -> 85.63 | AF49: =IF('Raw Data - financials'!AF60="","",'Raw Data - financials'!AF60) -> 138.7 | AG49: =IF('Raw Data - financials'!AG60="","",'Raw Data - financials'!AG60) -> 211.82 | AH49: =IF('Raw Data - financials'!AH60="","",'Raw Data - financials'!AH60) -> 456.72 | AI49: =IF('Raw Data - financials'!AI60="","",'Raw Data - financials'!AI60) -> 639.5 | AJ49: =IF('Raw Data - financials'!AJ60="","",'Raw Data - financials'!AJ60) -> 622.6 | AK49: =IF(Projections!AK152="","",Projections!AK152) -> 622.6 | AL49: =IF(Projections!AL152="","",Projections!AL152) -> 622.6 | AM49: =IF(Projections!AM152="","",Projections!AM152) -> 622.6 | AN49: =IF(Projections!AN152="","",Projections!AN152) -> 622.6
