Workbook

Sheet Projections
A1: INR Mn | B1: Unit | C1: Source / Driver | D1: 1Q22 | E1: 2Q22 | F1: 3Q22 | G1: 4Q22 | H1: 1Q23 | I1: 2Q23 | J1: 3Q23 | K1: 4Q23 | L1: 1Q24 | M1: 2Q24 | N1: 3Q24 | O1: 4Q24 | P1: 1Q25 | Q1: 2Q25 | R1: 3Q25 | S1: 4Q25 | T1: 1Q26 | U1: 2Q26 | V1: 3Q26 | W1: 4Q26 | X1: 1Q27 | Y1: 2Q27 | Z1: 3Q27 | AA1: 4Q27 | AC1: FY19 | AD1: FY20 | AE1: FY21 | AF1: FY22 | AG1: FY23 | AH1: FY24 | AI1: FY25 | AJ1: FY26 | AK1: FY27E | AL1: FY28E | AM1: FY29E | AN1: FY30E
A2: Fiscal Year End | D2: =DATE(2021,6,30) | E2: =EOMONTH(D2,-3) | F2: =EOMONTH(E2,-3) | G2: =EOMONTH(F2,-3) | H2: =EOMONTH(G2,-3) | I2: =EOMONTH(H2,-3) | J2: =EOMONTH(I2,-3) | K2: =EOMONTH(J2,-3) | L2: =EOMONTH(K2,-3) | ... AA2: =EOMONTH(Z2,-3) | AC2: =DATE(2019,3,31) | AD2: =DATE(2020,3,31) | AE2: =DATE(2021,3,31) | AF2: =DATE(2022,3,31) | AG2: =DATE(2023,3,31) | AH2: =DATE(2024,3,31) | AI2: =DATE(2025,3,31) | AJ2: =DATE(2026,3,31) | AK2: =DATE(2027,3,31) | AL2: =DATE(2028,3,31) | AM2: =DATE(2029,3,31) | AN2: =DATE(2030,3,31)
A3: All figures in INR Mn unless stated otherwise. Historical quarters (1Q22-4Q26) and historical annual columns (FY19-FY26) link to the Raw Data tabs. 1Q27-4Q27 are left blank for a later quarterly-projection pass. FY27E-FY30E are annual projections, each chained off the preceding column in this sheet: red (#A20000) cells are hardcoded assumptions -- edit these to change the forecast; black cells are formulas.
A4: SUMMARY
A5: Total GMV | B5: Rs Mn | C5: Formula | D5: =IFERROR(D32+D61+D84,"") | E5: =IFERROR(E32+E61+E84,"") | F5: =IFERROR(F32+F61+F84,"") | G5: =IFERROR(G32+G61+G84,"") | H5: =IFERROR(H32+H61+H84,"") | I5: =IFERROR(I32+I61+I84,"") | J5: =IFERROR(J32+J61+J84,"") | K5: =IFERROR(K32+K61+K84,"") | ... W5: =IFERROR(W32+W61+W84,"") | AC5: =IFERROR(AC32+AC61+AC84,"") | AD5: =IFERROR(AD32+AD61+AD84,"") | AE5: =IFERROR(AE32+AE61+AE84,"") | AF5: =IFERROR(AF32+AF61+AF84,"") | AG5: =IFERROR(AG32+AG61+AG84,"") | AH5: =IFERROR(AH32+AH61+AH84,"") | AI5: =IFERROR(AI32+AI61+AI84,"") | AJ5: =IFERROR(AJ32+AJ61+AJ84,"") | ... AN5: =IFERROR(AN32+AN61+AN84,"")
A6: YoY growth | B6: % | C6: Formula | H6: =IFERROR(H5/D5-1,"") | I6: =IFERROR(I5/E5-1,"") | J6: =IFERROR(J5/F5-1,"") | K6: =IFERROR(K5/G5-1,"") | L6: =IFERROR(L5/H5-1,"") | M6: =IFERROR(M5/I5-1,"") | N6: =IFERROR(N5/J5-1,"") | O6: =IFERROR(O5/K5-1,"") | ... W6: =IFERROR(W5/S5-1,"") | AD6: =IFERROR(AD5/AC5-1,"") | AE6: =IFERROR(AE5/AD5-1,"") | AF6: =IFERROR(AF5/AE5-1,"") | AG6: =IFERROR(AG5/AF5-1,"") | AH6: =IFERROR(AH5/AG5-1,"") | AI6: =IFERROR(AI5/AH5-1,"") | AJ6: =IFERROR(AJ5/AI5-1,"") | AK6: =IFERROR(AK5/AJ5-1,"") | ... AN6: =IFERROR(AN5/AM5-1,"")
A7: Total NSV | B7: Rs Mn | C7: Formula | D7: =IFERROR(D35+D64+D87,"") | E7: =IFERROR(E35+E64+E87,"") | F7: =IFERROR(F35+F64+F87,"") | G7: =IFERROR(G35+G64+G87,"") | H7: =IFERROR(H35+H64+H87,"") | I7: =IFERROR(I35+I64+I87,"") | J7: =IFERROR(J35+J64+J87,"") | K7: =IFERROR(K35+K64+K87,"") | ... W7: =IFERROR(W35+W64+W87,"") | AC7: =IFERROR(AC35+AC64+AC87,"") | AD7: =IFERROR(AD35+AD64+AD87,"") | AE7: =IFERROR(AE35+AE64+AE87,"") | AF7: =IFERROR(AF35+AF64+AF87,"") | AG7: =IFERROR(AG35+AG64+AG87,"") | AH7: =IFERROR(AH35+AH64+AH87,"") | AI7: =IFERROR(AI35+AI64+AI87,"") | AJ7: =IFERROR(AJ35+AJ64+AJ87,"") | ... AN7: =IFERROR(AN35+AN64+AN87,"")
A8: NSV / GMV | B8: % | C8: Formula | D8: =IFERROR(D7/D5,"") | E8: =IFERROR(E7/E5,"") | F8: =IFERROR(F7/F5,"") | G8: =IFERROR(G7/G5,"") | H8: =IFERROR(H7/H5,"") | I8: =IFERROR(I7/I5,"") | J8: =IFERROR(J7/J5,"") | K8: =IFERROR(K7/K5,"") | ... W8: =IFERROR(W7/W5,"") | AC8: =IFERROR(AC7/AC5,"") | AD8: =IFERROR(AD7/AD5,"") | AE8: =IFERROR(AE7/AE5,"") | AF8: =IFERROR(AF7/AF5,"") | AG8: =IFERROR(AG7/AG5,"") | AH8: =IFERROR(AH7/AH5,"") | AI8: =IFERROR(AI7/AI5,"") | AJ8: =IFERROR(AJ7/AJ5,"")
A9: Total Revenue | B9: Rs Mn | C9: Formula | D9: =IFERROR(D37+D66+D89,"") | E9: =IFERROR(E37+E66+E89,"") | F9: =IFERROR(F37+F66+F89,"") | G9: =IFERROR(G37+G66+G89,"") | H9: =IFERROR(H37+H66+H89,"") | I9: =IFERROR(I37+I66+I89,"") | J9: =IFERROR(J37+J66+J89,"") | K9: =IFERROR(K37+K66+K89,"") | ... W9: =IFERROR(W37+W66+W89,"") | AC9: =IFERROR(AC37+AC66+AC89,"") | AD9: =IFERROR(AD37+AD66+AD89,"") | AE9: =IFERROR(AE37+AE66+AE89,"") | AF9: =IFERROR(AF37+AF66+AF89,"") | AG9: =IFERROR(AG37+AG66+AG89,"") | AH9: =IFERROR(AH37+AH66+AH89,"") | AI9: =IFERROR(AI37+AI66+AI89,"") | AJ9: =IFERROR(AJ37+AJ66+AJ89,"") | ... AN9: =IFERROR(AN37+AN66+AN89,"")
A10: YoY growth | B10: % | C10: Formula | H10: =IFERROR(H9/D9-1,"") | I10: =IFERROR(I9/E9-1,"") | J10: =IFERROR(J9/F9-1,"") | K10: =IFERROR(K9/G9-1,"") | L10: =IFERROR(L9/H9-1,"") | M10: =IFERROR(M9/I9-1,"") | N10: =IFERROR(N9/J9-1,"") | O10: =IFERROR(O9/K9-1,"") | ... W10: =IFERROR(W9/S9-1,"") | AD10: =IFERROR(AD9/AC9-1,"") | AE10: =IFERROR(AE9/AD9-1,"") | AF10: =IFERROR(AF9/AE9-1,"") | AG10: =IFERROR(AG9/AF9-1,"") | AH10: =IFERROR(AH9/AG9-1,"") | AI10: =IFERROR(AI9/AH9-1,"") | AJ10: =IFERROR(AJ9/AI9-1,"") | AK10: =IFERROR(AK9/AJ9-1,"") | ... AN10: =IFERROR(AN9/AM9-1,"")
A11: Gross Profit | B11: Rs Mn | C11: Formula | D11: =IFERROR(D39+D68+D91,"") | E11: =IFERROR(E39+E68+E91,"") | F11: =IFERROR(F39+F68+F91,"") | G11: =IFERROR(G39+G68+G91,"") | H11: =IFERROR(H39+H68+H91,"") | I11: =IFERROR(I39+I68+I91,"") | J11: =IFERROR(J39+J68+J91,"") | K11: =IFERROR(K39+K68+K91,"") | ... W11: =IFERROR(W39+W68+W91,"") | AC11: =IFERROR(AC39+AC68+AC91,"") | AD11: =IFERROR(AD39+AD68+AD91,"") | AE11: =IFERROR(AE39+AE68+AE91,"") | AF11: =IFERROR(AF39+AF68+AF91,"") | AG11: =IFERROR(AG39+AG68+AG91,"") | AH11: =IFERROR(AH39+AH68+AH91,"") | AI11: =IFERROR(AI39+AI68+AI91,"") | AJ11: =IFERROR(AJ39+AJ68+AJ91,"") | ... AN11: =IFERROR(AN39+AN68+AN91,"")
A12: Gross margin (% of NSV) | B12: % | C12: Formula | D12: =IFERROR(D11/D7,"") | E12: =IFERROR(E11/E7,"") | F12: =IFERROR(F11/F7,"") | G12: =IFERROR(G11/G7,"") | H12: =IFERROR(H11/H7,"") | I12: =IFERROR(I11/I7,"") | J12: =IFERROR(J11/J7,"") | K12: =IFERROR(K11/K7,"") | ... W12: =IFERROR(W11/W7,"") | AC12: =IFERROR(AC11/AC7,"") | AD12: =IFERROR(AD11/AD7,"") | AE12: =IFERROR(AE11/AE7,"") | AF12: =IFERROR(AF11/AF7,"") | AG12: =IFERROR(AG11/AG7,"") | AH12: =IFERROR(AH11/AH7,"") | AI12: =IFERROR(AI11/AI7,"") | AJ12: =IFERROR(AJ11/AJ7,"")
A13: EBITDA | B13: Rs Mn | C13: Formula | D13: =D99 | E13: =E99 | F13: =F99 | G13: =G99 | H13: =H99 | I13: =I99 | J13: =J99 | K13: =K99 | ... W13: =W99 | AC13: =AC99 | AD13: =AD99 | AE13: =AE99 | AF13: =AF99 | AG13: =AG99 | AH13: =AH99 | AI13: =AI99 | AJ13: =AJ99 | ... AN13: =AN99
A14: EBITDA margin (% of NSV) | B14: % | C14: Formula | D14: =IFERROR(D13/D7,"") | E14: =IFERROR(E13/E7,"") | F14: =IFERROR(F13/F7,"") | G14: =IFERROR(G13/G7,"") | H14: =IFERROR(H13/H7,"") | I14: =IFERROR(I13/I7,"") | J14: =IFERROR(J13/J7,"") | K14: =IFERROR(K13/K7,"") | ... W14: =IFERROR(W13/W7,"") | AC14: =IFERROR(AC13/AC7,"") | AD14: =IFERROR(AD13/AD7,"") | AE14: =IFERROR(AE13/AE7,"") | AF14: =IFERROR(AF13/AF7,"") | AG14: =IFERROR(AG13/AG7,"") | AH14: =IFERROR(AH13/AH7,"") | AI14: =IFERROR(AI13/AI7,"") | AJ14: =IFERROR(AJ13/AJ7,"")
A15: PAT | B15: Rs Mn | C15: Formula | D15: =D111 | E15: =E111 | F15: =F111 | G15: =G111 | H15: =H111 | I15: =I111 | J15: =J111 | K15: =K111 | ... W15: =W111 | AC15: =AC111 | AD15: =AD111 | AE15: =AE111 | AF15: =AF111 | AG15: =AG111 | AH15: =AH111 | AI15: =AI111 | AJ15: =AJ111 | ... AN15: =AN111
A16: PAT margin (% of Revenue) | B16: % | C16: Formula | D16: =IFERROR(D15/D9,"") | E16: =IFERROR(E15/E9,"") | F16: =IFERROR(F15/F9,"") | G16: =IFERROR(G15/G9,"") | H16: =IFERROR(H15/H9,"") | I16: =IFERROR(I15/I9,"") | J16: =IFERROR(J15/J9,"") | K16: =IFERROR(K15/K9,"") | ... W16: =IFERROR(W15/W9,"") | AC16: =IFERROR(AC15/AC9,"") | AD16: =IFERROR(AD15/AD9,"") | AE16: =IFERROR(AE15/AE9,"") | AF16: =IFERROR(AF15/AF9,"") | AG16: =IFERROR(AG15/AG9,"") | AH16: =IFERROR(AH15/AH9,"") | AI16: =IFERROR(AI15/AI9,"") | AJ16: =IFERROR(AJ15/AJ9,"")
A17: EPS (diluted) | B17: Rs | C17: Formula | D17: =D114 | E17: =E114 | F17: =F114 | G17: =G114 | H17: =H114 | I17: =I114 | J17: =J114 | K17: =K114 | ... W17: =W114 | AC17: =AC114 | AD17: =AD114 | AE17: =AE114 | AF17: =AF114 | AG17: =AG114 | AH17: =AH114 | AI17: =AI114 | AJ17: =AJ114 | ... AN17: =AN114
A19: Segment mix (% of Total GMV)
A20: Beauty | B20: % | C20: Formula | D20: =IFERROR(D32/D5,"") | E20: =IFERROR(E32/E5,"") | F20: =IFERROR(F32/F5,"") | G20: =IFERROR(G32/G5,"") | H20: =IFERROR(H32/H5,"") | I20: =IFERROR(I32/I5,"") | J20: =IFERROR(J32/J5,"") | K20: =IFERROR(K32/K5,"") | ... W20: =IFERROR(W32/W5,"") | AC20: =IFERROR(AC32/AC5,"") | AD20: =IFERROR(AD32/AD5,"") | AE20: =IFERROR(AE32/AE5,"") | AF20: =IFERROR(AF32/AF5,"") | AG20: =IFERROR(AG32/AG5,"") | AH20: =IFERROR(AH32/AH5,"") | AI20: =IFERROR(AI32/AI5,"") | AJ20: =IFERROR(AJ32/AJ5,"") | ... AN20: =IFERROR(AN32/AN5,"")
A21: Fashion | B21: % | C21: Formula | D21: =IFERROR(D61/D5,"") | E21: =IFERROR(E61/E5,"") | F21: =IFERROR(F61/F5,"") | G21: =IFERROR(G61/G5,"") | H21: =IFERROR(H61/H5,"") | I21: =IFERROR(I61/I5,"") | J21: =IFERROR(J61/J5,"") | K21: =IFERROR(K61/K5,"") | ... W21: =IFERROR(W61/W5,"") | AC21: =IFERROR(AC61/AC5,"") | AD21: =IFERROR(AD61/AD5,"") | AE21: =IFERROR(AE61/AE5,"") | AF21: =IFERROR(AF61/AF5,"") | AG21: =IFERROR(AG61/AG5,"") | AH21: =IFERROR(AH61/AH5,"") | AI21: =IFERROR(AI61/AI5,"") | AJ21: =IFERROR(AJ61/AJ5,"") | ... AN21: =IFERROR(AN61/AN5,"")
A22: New Business | B22: % | C22: Formula | D22: =IFERROR(D84/D5,"") | E22: =IFERROR(E84/E5,"") | F22: =IFERROR(F84/F5,"") | G22: =IFERROR(G84/G5,"") | H22: =IFERROR(H84/H5,"") | I22: =IFERROR(I84/I5,"") | J22: =IFERROR(J84/J5,"") | K22: =IFERROR(K84/K5,"") | ... W22: =IFERROR(W84/W5,"") | AC22: =IFERROR(AC84/AC5,"") | AD22: =IFERROR(AD84/AD5,"") | AE22: =IFERROR(AE84/AE5,"") | AF22: =IFERROR(AF84/AF5,"") | AG22: =IFERROR(AG84/AG5,"") | AH22: =IFERROR(AH84/AH5,"") | AI22: =IFERROR(AI84/AI5,"") | AJ22: =IFERROR(AJ84/AJ5,"") | ... AN22: =IFERROR(AN84/AN5,"")
A24: BEAUTY (incl. SuperStore)
A25: Definition: BPC (online + offline) + Superstore by Nykaa + Nykaa Man Grooming + House of Nykaa owned brands. NOTE: AUTC/Orders/AOV here are sourced from the deck's 'BPC Vertical' KPI table, which is a narrower scope than the GMV/NSV/Revenue lines below (GMV includes SuperStore, BPC Vertical orders don't) -- see the equivalent caveat on the Raw Data - Ops KPIs tab. AOV = GMV/Orders here is therefore a blended incl-SuperStore figure, not Nykaa's own reported BPC AOV.
A26: Annual transacting customers (AUTC) | B26: mn | C26: Link: Raw Data - Ops KPIs | D26: ='Raw Data - Ops KPIs'!D35 | E26: ='Raw Data - Ops KPIs'!E35 | F26: ='Raw Data - Ops KPIs'!F35 | G26: ='Raw Data - Ops KPIs'!G35 | H26: ='Raw Data - Ops KPIs'!H35 | I26: ='Raw Data - Ops KPIs'!I35 | J26: ='Raw Data - Ops KPIs'!J35 | K26: ='Raw Data - Ops KPIs'!K35 | ... W26: ='Raw Data - Ops KPIs'!W35 | AF26: ='Raw Data - Ops KPIs'!AF35 | AG26: ='Raw Data - Ops KPIs'!AG35 | AH26: ='Raw Data - Ops KPIs'!AH35 | AI26: ='Raw Data - Ops KPIs'!AI35 | AJ26: ='Raw Data - Ops KPIs'!AJ35 | AK26: =AJ26*(1+AK27) | AL26: =AK26*(1+AL27) | AM26: =AL26*(1+AM27) | AN26: =AM26*(1+AN27)
A27: YoY growth | B27: % | C27: Assumption (edit me) | H27: =IFERROR(H26/D26-1,"") | I27: =IFERROR(I26/E26-1,"") | J27: =IFERROR(J26/F26-1,"") | K27: =IFERROR(K26/G26-1,"") | L27: =IFERROR(L26/H26-1,"") | M27: =IFERROR(M26/I26-1,"") | N27: =IFERROR(N26/J26-1,"") | O27: =IFERROR(O26/K26-1,"") | ... W27: =IFERROR(W26/S26-1,"") | AD27: =IFERROR(AD26/AC26-1,"") | AE27: =IFERROR(AE26/AD26-1,"") | AF27: =IFERROR(AF26/AE26-1,"") | AG27: =IFERROR(AG26/AF26-1,"") | AH27: =IFERROR(AH26/AG26-1,"") | AI27: =IFERROR(AI26/AH26-1,"") | AJ27: =IFERROR(AJ26/AI26-1,"") | AK27: 0.247 | AL27: 0.247 | AM27: 0.247 | AN27: 0.247
A28: Average order frequency | B28: x | C28: Assumption (edit me) | D28: =IFERROR(D29/D26,"") | E28: =IFERROR(E29/E26,"") | F28: =IFERROR(F29/F26,"") | G28: =IFERROR(G29/G26,"") | H28: =IFERROR(H29/H26,"") | I28: =IFERROR(I29/I26,"") | J28: =IFERROR(J29/J26,"") | K28: =IFERROR(K29/K26,"") | ... W28: =IFERROR(W29/W26,"") | AC28: =IFERROR(AC29/AC26,"") | AD28: =IFERROR(AD29/AD26,"") | AE28: =IFERROR(AE29/AE26,"") | AF28: =IFERROR(AF29/AF26,"") | AG28: =IFERROR(AG29/AG26,"") | AH28: =IFERROR(AH29/AH26,"") | AI28: =IFERROR(AI29/AI26,"") | AJ28: =IFERROR(AJ29/AJ26,"") | AK28: 3.34 | AL28: 3.34 | AM28: 3.34 | AN28: 3.34
A29: Number of orders | B29: mn | C29: Link: Raw Data - Ops KPIs | D29: ='Raw Data - Ops KPIs'!D37 | E29: ='Raw Data - Ops KPIs'!E37 | F29: ='Raw Data - Ops KPIs'!F37 | G29: ='Raw Data - Ops KPIs'!G37 | H29: ='Raw Data - Ops KPIs'!H37 | I29: ='Raw Data - Ops KPIs'!I37 | J29: ='Raw Data - Ops KPIs'!J37 | K29: ='Raw Data - Ops KPIs'!K37 | ... W29: ='Raw Data - Ops KPIs'!W37 | AF29: ='Raw Data - Ops KPIs'!AF37 | AG29: ='Raw Data - Ops KPIs'!AG37 | AH29: ='Raw Data - Ops KPIs'!AH37 | AI29: ='Raw Data - Ops KPIs'!AI37 | AJ29: ='Raw Data - Ops KPIs'!AJ37 | AK29: =AK26*AK28 | AL29: =AL26*AL28 | AM29: =AM26*AM28 | AN29: =AN26*AN28
A30: Average order value | B30: Rs | C30: Formula | D30: =IFERROR(D32/D29,"") | E30: =IFERROR(E32/E29,"") | F30: =IFERROR(F32/F29,"") | G30: =IFERROR(G32/G29,"") | H30: =IFERROR(H32/H29,"") | I30: =IFERROR(I32/I29,"") | J30: =IFERROR(J32/J29,"") | K30: =IFERROR(K32/K29,"") | ... W30: =IFERROR(W32/W29,"") | AC30: =IFERROR(AC32/AC29,"") | AD30: =IFERROR(AD32/AD29,"") | AE30: =IFERROR(AE32/AE29,"") | AF30: =IFERROR(AF32/AF29,"") | AG30: =IFERROR(AG32/AG29,"") | AH30: =IFERROR(AH32/AH29,"") | AI30: =IFERROR(AI32/AI29,"") | AJ30: =IFERROR(AJ32/AJ29,"") | AK30: =AJ30*(1+AK31) | AL30: =AK30*(1+AL31) | AM30: =AL30*(1+AM31) | AN30: =AM30*(1+AN31)
A31: YoY growth | B31: % | C31: Assumption (edit me) | AK31: 0.052 | AL31: 0.052 | AM31: 0.052 | AN31: 0.052
A32: GMV | B32: Rs Mn | C32: Link: Raw Data - Ops KPIs | D32: ='Raw Data - Ops KPIs'!D39 | E32: ='Raw Data - Ops KPIs'!E39 | F32: ='Raw Data - Ops KPIs'!F39 | G32: ='Raw Data - Ops KPIs'!G39 | H32: ='Raw Data - Ops KPIs'!H39 | I32: ='Raw Data - Ops KPIs'!I39 | J32: ='Raw Data - Ops KPIs'!J39 | K32: ='Raw Data - Ops KPIs'!K39 | ... W32: ='Raw Data - Ops KPIs'!W39 | AF32: ='Raw Data - Ops KPIs'!AF39 | AG32: ='Raw Data - Ops KPIs'!AG39 | AH32: ='Raw Data - Ops KPIs'!AH39 | AI32: ='Raw Data - Ops KPIs'!AI39 | AJ32: ='Raw Data - Ops KPIs'!AJ39 | AK32: =AK29*AK30 | AL32: =AL29*AL30 | AM32: =AM29*AM30 | AN32: =AN29*AN30
A33: YoY growth | B33: % | C33: Formula | H33: =IFERROR(H32/D32-1,"") | I33: =IFERROR(I32/E32-1,"") | J33: =IFERROR(J32/F32-1,"") | K33: =IFERROR(K32/G32-1,"") | L33: =IFERROR(L32/H32-1,"") | M33: =IFERROR(M32/I32-1,"") | N33: =IFERROR(N32/J32-1,"") | O33: =IFERROR(O32/K32-1,"") | ... W33: =IFERROR(W32/S32-1,"") | AD33: =IFERROR(AD32/AC32-1,"") | AE33: =IFERROR(AE32/AD32-1,"") | AF33: =IFERROR(AF32/AE32-1,"") | AG33: =IFERROR(AG32/AF32-1,"") | AH33: =IFERROR(AH32/AG32-1,"") | AI33: =IFERROR(AI32/AH32-1,"") | AJ33: =IFERROR(AJ32/AI32-1,"") | AK33: =IFERROR(AK32/AJ32-1,"") | ... AN33: =IFERROR(AN32/AM32-1,"")
A34: NSV / GMV | B34: % | C34: Assumption (edit me) | D34: =IFERROR(D35/D32,"") | E34: =IFERROR(E35/E32,"") | F34: =IFERROR(F35/F32,"") | G34: =IFERROR(G35/G32,"") | H34: =IFERROR(H35/H32,"") | I34: =IFERROR(I35/I32,"") | J34: =IFERROR(J35/J32,"") | K34: =IFERROR(K35/K32,"") | ... W34: =IFERROR(W35/W32,"") | AC34: =IFERROR(AC35/AC32,"") | AD34: =IFERROR(AD35/AD32,"") | AE34: =IFERROR(AE35/AE32,"") | AF34: =IFERROR(AF35/AF32,"") | AG34: =IFERROR(AG35/AG32,"") | AH34: =IFERROR(AH35/AH32,"") | AI34: =IFERROR(AI35/AI32,"") | AJ34: =IFERROR(AJ35/AJ32,"") | AK34: 0.569 | AL34: 0.569 | AM34: 0.569 | AN34: 0.569
A35: NSV | B35: Rs Mn | C35: Link: Raw Data - Ops KPIs | D35: ='Raw Data - Ops KPIs'!D42 | E35: ='Raw Data - Ops KPIs'!E42 | F35: ='Raw Data - Ops KPIs'!F42 | G35: ='Raw Data - Ops KPIs'!G42 | H35: ='Raw Data - Ops KPIs'!H42 | I35: ='Raw Data - Ops KPIs'!I42 | J35: ='Raw Data - Ops KPIs'!J42 | K35: ='Raw Data - Ops KPIs'!K42 | ... W35: ='Raw Data - Ops KPIs'!W42 | AF35: ='Raw Data - Ops KPIs'!AF42 | AG35: ='Raw Data - Ops KPIs'!AG42 | AH35: ='Raw Data - Ops KPIs'!AH42 | AI35: ='Raw Data - Ops KPIs'!AI42 | AJ35: ='Raw Data - Ops KPIs'!AJ42 | AK35: =AK32*AK34 | AL35: =AL32*AL34 | AM35: =AM32*AM34 | AN35: =AN32*AN34
A36: Revenue / NSV | B36: % | C36: Assumption (edit me) | D36: =IFERROR(D37/D35,"") | E36: =IFERROR(E37/E35,"") | F36: =IFERROR(F37/F35,"") | G36: =IFERROR(G37/G35,"") | H36: =IFERROR(H37/H35,"") | I36: =IFERROR(I37/I35,"") | J36: =IFERROR(J37/J35,"") | K36: =IFERROR(K37/K35,"") | ... W36: =IFERROR(W37/W35,"") | AC36: =IFERROR(AC37/AC35,"") | AD36: =IFERROR(AD37/AD35,"") | AE36: =IFERROR(AE37/AE35,"") | AF36: =IFERROR(AF37/AF35,"") | AG36: =IFERROR(AG37/AG35,"") | AH36: =IFERROR(AH37/AH35,"") | AI36: =IFERROR(AI37/AI35,"") | AJ36: =IFERROR(AJ37/AJ35,"") | AK36: 1.075 | AL36: 1.075 | AM36: 1.075 | AN36: 1.075
A37: Revenue | B37: Rs Mn | C37: Link: Raw Data - Ops KPIs | D37: ='Raw Data - Ops KPIs'!D44 | E37: ='Raw Data - Ops KPIs'!E44 | F37: ='Raw Data - Ops KPIs'!F44 | G37: ='Raw Data - Ops KPIs'!G44 | H37: ='Raw Data - Ops KPIs'!H44 | I37: ='Raw Data - Ops KPIs'!I44 | J37: ='Raw Data - Ops KPIs'!J44 | K37: ='Raw Data - Ops KPIs'!K44 | ... W37: ='Raw Data - Ops KPIs'!W44 | AF37: ='Raw Data - Ops KPIs'!AF44 | AG37: ='Raw Data - Ops KPIs'!AG44 | AH37: ='Raw Data - Ops KPIs'!AH44 | AI37: ='Raw Data - Ops KPIs'!AI44 | AJ37: ='Raw Data - Ops KPIs'!AJ44 | AK37: =AK35*AK36 | AL37: =AL35*AL36 | AM37: =AM35*AM36 | AN37: =AN35*AN36
A38: Gross margin (% of NSV) | B38: % | C38: Assumption (edit me) | D38: =IFERROR(D39/D35,"") | E38: =IFERROR(E39/E35,"") | F38: =IFERROR(F39/F35,"") | G38: =IFERROR(G39/G35,"") | H38: =IFERROR(H39/H35,"") | I38: =IFERROR(I39/I35,"") | J38: =IFERROR(J39/J35,"") | K38: =IFERROR(K39/K35,"") | ... W38: =IFERROR(W39/W35,"") | AC38: =IFERROR(AC39/AC35,"") | AD38: =IFERROR(AD39/AD35,"") | AE38: =IFERROR(AE39/AE35,"") | AF38: =IFERROR(AF39/AF35,"") | AG38: =IFERROR(AG39/AG35,"") | AH38: =IFERROR(AH39/AH35,"") | AI38: =IFERROR(AI39/AI35,"") | AJ38: =IFERROR(AJ39/AJ35,"") | AK38: 0.447 | AL38: 0.447 | AM38: 0.447 | AN38: 0.447
A39: Gross profit | B39: Rs Mn | C39: Link: Raw Data - Ops KPIs | D39: ='Raw Data - Ops KPIs'!D46 | E39: ='Raw Data - Ops KPIs'!E46 | F39: ='Raw Data - Ops KPIs'!F46 | G39: ='Raw Data - Ops KPIs'!G46 | H39: ='Raw Data - Ops KPIs'!H46 | I39: ='Raw Data - Ops KPIs'!I46 | J39: ='Raw Data - Ops KPIs'!J46 | K39: ='Raw Data - Ops KPIs'!K46 | ... W39: ='Raw Data - Ops KPIs'!W46 | AF39: ='Raw Data - Ops KPIs'!AF46 | AG39: ='Raw Data - Ops KPIs'!AG46 | AH39: ='Raw Data - Ops KPIs'!AH46 | AI39: ='Raw Data - Ops KPIs'!AI46 | AJ39: ='Raw Data - Ops KPIs'!AJ46 | AK39: =AK35*AK38 | AL39: =AL35*AL38 | AM39: =AM35*AM38 | AN39: =AN35*AN38
A40: Fulfilment (% of NSV) | B40: % | C40: Assumption (edit me) | D40: =IFERROR(D41/D35,"") | E40: =IFERROR(E41/E35,"") | F40: =IFERROR(F41/F35,"") | G40: =IFERROR(G41/G35,"") | H40: =IFERROR(H41/H35,"") | I40: =IFERROR(I41/I35,"") | J40: =IFERROR(J41/J35,"") | K40: =IFERROR(K41/K35,"") | ... W40: =IFERROR(W41/W35,"") | AC40: =IFERROR(AC41/AC35,"") | AD40: =IFERROR(AD41/AD35,"") | AE40: =IFERROR(AE41/AE35,"") | AF40: =IFERROR(AF41/AF35,"") | AG40: =IFERROR(AG41/AG35,"") | AH40: =IFERROR(AH41/AH35,"") | AI40: =IFERROR(AI41/AI35,"") | AJ40: =IFERROR(AJ41/AJ35,"") | AK40: 0.093 | AL40: 0.093 | AM40: 0.093 | AN40: 0.093
A41: Fulfilment cost | B41: Rs Mn | C41: Link: Raw Data - Ops KPIs | D41: ='Raw Data - Ops KPIs'!D48 | E41: ='Raw Data - Ops KPIs'!E48 | F41: ='Raw Data - Ops KPIs'!F48 | G41: ='Raw Data - Ops KPIs'!G48 | H41: ='Raw Data - Ops KPIs'!H48 | I41: ='Raw Data - Ops KPIs'!I48 | J41: ='Raw Data - Ops KPIs'!J48 | K41: ='Raw Data - Ops KPIs'!K48 | ... W41: ='Raw Data - Ops KPIs'!W48 | AF41: ='Raw Data - Ops KPIs'!AF48 | AG41: ='Raw Data - Ops KPIs'!AG48 | AH41: ='Raw Data - Ops KPIs'!AH48 | AI41: ='Raw Data - Ops KPIs'!AI48 | AJ41: ='Raw Data - Ops KPIs'!AJ48 | AK41: =AK35*AK40 | AL41: =AL35*AL40 | AM41: =AM35*AM40 | AN41: =AN35*AN40
A42: o/w Marketing (historical, linked) | B42: Rs Mn | C42: Link: Raw Data - Ops KPIs | D42: ='Raw Data - Ops KPIs'!D49 | E42: ='Raw Data - Ops KPIs'!E49 | F42: ='Raw Data - Ops KPIs'!F49 | G42: ='Raw Data - Ops KPIs'!G49 | H42: ='Raw Data - Ops KPIs'!H49 | I42: ='Raw Data - Ops KPIs'!I49 | J42: ='Raw Data - Ops KPIs'!J49 | K42: ='Raw Data - Ops KPIs'!K49 | ... W42: ='Raw Data - Ops KPIs'!W49 | AF42: ='Raw Data - Ops KPIs'!AF49 | AG42: ='Raw Data - Ops KPIs'!AG49 | AH42: ='Raw Data - Ops KPIs'!AH49 | AI42: ='Raw Data - Ops KPIs'!AI49 | AJ42: ='Raw Data - Ops KPIs'!AJ49
A43: o/w Selling & distribution (historical, linked) | B43: Rs Mn | C43: Link: Raw Data - Ops KPIs | D43: ='Raw Data - Ops KPIs'!D50 | E43: ='Raw Data - Ops KPIs'!E50 | F43: ='Raw Data - Ops KPIs'!F50 | G43: ='Raw Data - Ops KPIs'!G50 | H43: ='Raw Data - Ops KPIs'!H50 | I43: ='Raw Data - Ops KPIs'!I50 | J43: ='Raw Data - Ops KPIs'!J50 | K43: ='Raw Data - Ops KPIs'!K50 | ... W43: ='Raw Data - Ops KPIs'!W50 | AF43: ='Raw Data - Ops KPIs'!AF50 | AG43: ='Raw Data - Ops KPIs'!AG50 | AH43: ='Raw Data - Ops KPIs'!AH50 | AI43: ='Raw Data - Ops KPIs'!AI50 | AJ43: ='Raw Data - Ops KPIs'!AJ50
A44: Marketing & S&D (% of NSV, combined) | B44: % | C44: Assumption (edit me) | D44: =IFERROR(D45/D35,"") | E44: =IFERROR(E45/E35,"") | F44: =IFERROR(F45/F35,"") | G44: =IFERROR(G45/G35,"") | H44: =IFERROR(H45/H35,"") | I44: =IFERROR(I45/I35,"") | J44: =IFERROR(J45/J35,"") | K44: =IFERROR(K45/K35,"") | ... W44: =IFERROR(W45/W35,"") | AC44: =IFERROR(AC45/AC35,"") | AD44: =IFERROR(AD45/AD35,"") | AE44: =IFERROR(AE45/AE35,"") | AF44: =IFERROR(AF45/AF35,"") | AG44: =IFERROR(AG45/AG35,"") | AH44: =IFERROR(AH45/AH35,"") | AI44: =IFERROR(AI45/AI35,"") | AJ44: =IFERROR(AJ45/AJ35,"") | AK44: 0.128 | AL44: 0.128 | AM44: 0.128 | AN44: 0.128
A45: Marketing & S&D expense (combined) | B45: Rs Mn | C45: Formula | D45: =IF(AND(D42="",D43=""),"",IF(D42="",0,D42)+IF(D43="",0,D43)) | E45: =IF(AND(E42="",E43=""),"",IF(E42="",0,E42)+IF(E43="",0,E43)) | F45: =IF(AND(F42="",F43=""),"",IF(F42="",0,F42)+IF(F43="",0,F43)) | G45: =IF(AND(G42="",G43=""),"",IF(G42="",0,G42)+IF(G43="",0,G43)) | H45: =IF(AND(H42="",H43=""),"",IF(H42="",0,H42)+IF(H43="",0,H43)) | I45: =IF(AND(I42="",I43=""),"",IF(I42="",0,I42)+IF(I43="",0,I43)) | J45: =IF(AND(J42="",J43=""),"",IF(J42="",0,J42)+IF(J43="",0,J43)) | K45: =IF(AND(K42="",K43=""),"",IF(K42="",0,K42)+IF(K43="",0,K43)) | ... W45: =IF(AND(W42="",W43=""),"",IF(W42="",0,W42)+IF(W43="",0,W43)) | AC45: =IF(AND(AC42="",AC43=""),"",IF(AC42="",0,AC42)+IF(AC43="",0,AC43)) | AD45: =IF(AND(AD42="",AD43=""),"",IF(AD42="",0,AD42)+IF(AD43="",0,AD43)) | AE45: =IF(AND(AE42="",AE43=""),"",IF(AE42="",0,AE42)+IF(AE43="",0,AE43)) | AF45: =IF(AND(AF42="",AF43=""),"",IF(AF42="",0,AF42)+IF(AF43="",0,AF43)) | AG45: =IF(AND(AG42="",AG43=""),"",IF(AG42="",0,AG42)+IF(AG43="",0,AG43)) | AH45: =IF(AND(AH42="",AH43=""),"",IF(AH42="",0,AH42)+IF(AH43="",0,AH43)) | AI45: =IF(AND(AI42="",AI43=""),"",IF(AI42="",0,AI42)+IF(AI43="",0,AI43)) | AJ45: =IF(AND(AJ42="",AJ43=""),"",IF(AJ42="",0,AJ42)+IF(AJ43="",0,AJ43)) | AK45: =AK35*AK44 | AL45: =AL35*AL44 | AM45: =AM35*AM44 | AN45: =AN35*AN44
A46: Contribution profit | B46: Rs Mn | C46: Formula | D46: =IFERROR(D39-D41-D45,"") | E46: =IFERROR(E39-E41-E45,"") | F46: =IFERROR(F39-F41-F45,"") | G46: =IFERROR(G39-G41-G45,"") | H46: =IFERROR(H39-H41-H45,"") | I46: =IFERROR(I39-I41-I45,"") | J46: =IFERROR(J39-J41-J45,"") | K46: =IFERROR(K39-K41-K45,"") | ... W46: =IFERROR(W39-W41-W45,"") | AC46: =IFERROR(AC39-AC41-AC45,"") | AD46: =IFERROR(AD39-AD41-AD45,"") | AE46: =IFERROR(AE39-AE41-AE45,"") | AF46: =IFERROR(AF39-AF41-AF45,"") | AG46: =IFERROR(AG39-AG41-AG45,"") | AH46: =IFERROR(AH39-AH41-AH45,"") | AI46: =IFERROR(AI39-AI41-AI45,"") | AJ46: =IFERROR(AJ39-AJ41-AJ45,"") | ... AN46: =IFERROR(AN39-AN41-AN45,"")
A47: Contribution margin (% of NSV) | B47: % | C47: Formula | D47: =IFERROR(D46/D35,"") | E47: =IFERROR(E46/E35,"") | F47: =IFERROR(F46/F35,"") | G47: =IFERROR(G46/G35,"") | H47: =IFERROR(H46/H35,"") | I47: =IFERROR(I46/I35,"") | J47: =IFERROR(J46/J35,"") | K47: =IFERROR(K46/K35,"") | ... W47: =IFERROR(W46/W35,"") | AC47: =IFERROR(AC46/AC35,"") | AD47: =IFERROR(AD46/AD35,"") | AE47: =IFERROR(AE46/AE35,"") | AF47: =IFERROR(AF46/AF35,"") | AG47: =IFERROR(AG46/AG35,"") | AH47: =IFERROR(AH46/AH35,"") | AI47: =IFERROR(AI46/AI35,"") | AJ47: =IFERROR(AJ46/AJ35,"") | ... AN47: =IFERROR(AN46/AN35,"")
A48: Other expenses (% of NSV) | B48: % | C48: Assumption (edit me) | D48: =IFERROR(D49/D35,"") | E48: =IFERROR(E49/E35,"") | F48: =IFERROR(F49/F35,"") | G48: =IFERROR(G49/G35,"") | H48: =IFERROR(H49/H35,"") | I48: =IFERROR(I49/I35,"") | J48: =IFERROR(J49/J35,"") | K48: =IFERROR(K49/K35,"") | ... W48: =IFERROR(W49/W35,"") | AC48: =IFERROR(AC49/AC35,"") | AD48: =IFERROR(AD49/AD35,"") | AE48: =IFERROR(AE49/AE35,"") | AF48: =IFERROR(AF49/AF35,"") | AG48: =IFERROR(AG49/AG35,"") | AH48: =IFERROR(AH49/AH35,"") | AI48: =IFERROR(AI49/AI35,"") | AJ48: =IFERROR(AJ49/AJ35,"") | AK48: 0.129 | AL48: 0.129 | AM48: 0.129 | AN48: 0.129
A49: Other expenses (G&A + employee) | B49: Rs Mn | C49: Link: Raw Data - Ops KPIs | D49: ='Raw Data - Ops KPIs'!D53 | E49: ='Raw Data - Ops KPIs'!E53 | F49: ='Raw Data - Ops KPIs'!F53 | G49: ='Raw Data - Ops KPIs'!G53 | H49: ='Raw Data - Ops KPIs'!H53 | I49: ='Raw Data - Ops KPIs'!I53 | J49: ='Raw Data - Ops KPIs'!J53 | K49: ='Raw Data - Ops KPIs'!K53 | ... W49: ='Raw Data - Ops KPIs'!W53 | AF49: ='Raw Data - Ops KPIs'!AF53 | AG49: ='Raw Data - Ops KPIs'!AG53 | AH49: ='Raw Data - Ops KPIs'!AH53 | AI49: ='Raw Data - Ops KPIs'!AI53 | AJ49: ='Raw Data - Ops KPIs'!AJ53 | AK49: =AK35*AK48 | AL49: =AL35*AL48 | AM49: =AM35*AM48 | AN49: =AN35*AN48
A50: EBITDA | B50: Rs Mn | C50: Formula | D50: =IFERROR(D46-D49,"") | E50: =IFERROR(E46-E49,"") | F50: =IFERROR(F46-F49,"") | G50: =IFERROR(G46-G49,"") | H50: =IFERROR(H46-H49,"") | I50: =IFERROR(I46-I49,"") | J50: =IFERROR(J46-J49,"") | K50: =IFERROR(K46-K49,"") | ... W50: =IFERROR(W46-W49,"") | AC50: =IFERROR(AC46-AC49,"") | AD50: =IFERROR(AD46-AD49,"") | AE50: =IFERROR(AE46-AE49,"") | AF50: =IFERROR(AF46-AF49,"") | AG50: =IFERROR(AG46-AG49,"") | AH50: =IFERROR(AH46-AH49,"") | AI50: =IFERROR(AI46-AI49,"") | AJ50: =IFERROR(AJ46-AJ49,"") | ... AN50: =IFERROR(AN46-AN49,"")
A51: EBITDA margin (% of NSV) | B51: % | C51: Formula | D51: =IFERROR(D50/D35,"") | E51: =IFERROR(E50/E35,"") | F51: =IFERROR(F50/F35,"") | G51: =IFERROR(G50/G35,"") | H51: =IFERROR(H50/H35,"") | I51: =IFERROR(I50/I35,"") | J51: =IFERROR(J50/J35,"") | K51: =IFERROR(K50/K35,"") | ... W51: =IFERROR(W50/W35,"") | AC51: =IFERROR(AC50/AC35,"") | AD51: =IFERROR(AD50/AD35,"") | AE51: =IFERROR(AE50/AE35,"") | AF51: =IFERROR(AF50/AF35,"") | AG51: =IFERROR(AG50/AG35,"") | AH51: =IFERROR(AH50/AH35,"") | AI51: =IFERROR(AI50/AI35,"") | AJ51: =IFERROR(AJ50/AJ35,"") | ... AN51: =IFERROR(AN50/AN35,"")
A53: FASHION
A54: Definition: Nykaa Fashion + LBB + Nykaa Man Lifestyle.
A55: Annual transacting customers (AUTC) | B55: mn | C55: Link: Raw Data - Ops KPIs | D55: ='Raw Data - Ops KPIs'!D92 | E55: ='Raw Data - Ops KPIs'!E92 | F55: ='Raw Data - Ops KPIs'!F92 | G55: ='Raw Data - Ops KPIs'!G92 | H55: ='Raw Data - Ops KPIs'!H92 | I55: ='Raw Data - Ops KPIs'!I92 | J55: ='Raw Data - Ops KPIs'!J92 | K55: ='Raw Data - Ops KPIs'!K92 | ... W55: ='Raw Data - Ops KPIs'!W92 | AF55: ='Raw Data - Ops KPIs'!AF92 | AG55: ='Raw Data - Ops KPIs'!AG92 | AH55: ='Raw Data - Ops KPIs'!AH92 | AI55: ='Raw Data - Ops KPIs'!AI92 | AJ55: ='Raw Data - Ops KPIs'!AJ92 | AK55: =AJ55*(1+AK56) | AL55: =AK55*(1+AL56) | AM55: =AL55*(1+AM56) | AN55: =AM55*(1+AN56)
A56: YoY growth | B56: % | C56: Assumption (edit me) | H56: =IFERROR(H55/D55-1,"") | I56: =IFERROR(I55/E55-1,"") | J56: =IFERROR(J55/F55-1,"") | K56: =IFERROR(K55/G55-1,"") | L56: =IFERROR(L55/H55-1,"") | M56: =IFERROR(M55/I55-1,"") | N56: =IFERROR(N55/J55-1,"") | O56: =IFERROR(O55/K55-1,"") | ... W56: =IFERROR(W55/S55-1,"") | AD56: =IFERROR(AD55/AC55-1,"") | AE56: =IFERROR(AE55/AD55-1,"") | AF56: =IFERROR(AF55/AE55-1,"") | AG56: =IFERROR(AG55/AF55-1,"") | AH56: =IFERROR(AH55/AG55-1,"") | AI56: =IFERROR(AI55/AH55-1,"") | AJ56: =IFERROR(AJ55/AI55-1,"") | AK56: 0.344 | AL56: 0.344 | AM56: 0.344 | AN56: 0.344
A57: Average order frequency | B57: x | C57: Assumption (edit me) | D57: =IFERROR(D58/D55,"") | E57: =IFERROR(E58/E55,"") | F57: =IFERROR(F58/F55,"") | G57: =IFERROR(G58/G55,"") | H57: =IFERROR(H58/H55,"") | I57: =IFERROR(I58/I55,"") | J57: =IFERROR(J58/J55,"") | K57: =IFERROR(K58/K55,"") | ... W57: =IFERROR(W58/W55,"") | AC57: =IFERROR(AC58/AC55,"") | AD57: =IFERROR(AD58/AD55,"") | AE57: =IFERROR(AE58/AE55,"") | AF57: =IFERROR(AF58/AF55,"") | AG57: =IFERROR(AG58/AG55,"") | AH57: =IFERROR(AH58/AH55,"") | AI57: =IFERROR(AI58/AI55,"") | AJ57: =IFERROR(AJ58/AJ55,"") | AK57: 2.35 | AL57: 2.35 | AM57: 2.35 | AN57: 2.35
A58: Number of orders | B58: mn | C58: Link: Raw Data - Ops KPIs | D58: ='Raw Data - Ops KPIs'!D94 | E58: ='Raw Data - Ops KPIs'!E94 | F58: ='Raw Data - Ops KPIs'!F94 | G58: ='Raw Data - Ops KPIs'!G94 | H58: ='Raw Data - Ops KPIs'!H94 | I58: ='Raw Data - Ops KPIs'!I94 | J58: ='Raw Data - Ops KPIs'!J94 | K58: ='Raw Data - Ops KPIs'!K94 | ... W58: ='Raw Data - Ops KPIs'!W94 | AF58: ='Raw Data - Ops KPIs'!AF94 | AG58: ='Raw Data - Ops KPIs'!AG94 | AH58: ='Raw Data - Ops KPIs'!AH94 | AI58: ='Raw Data - Ops KPIs'!AI94 | AJ58: ='Raw Data - Ops KPIs'!AJ94 | AK58: =AK55*AK57 | AL58: =AL55*AL57 | AM58: =AM55*AM57 | AN58: =AN55*AN57
A59: Average order value | B59: Rs | C59: Formula | D59: =IFERROR(D61/D58,"") | E59: =IFERROR(E61/E58,"") | F59: =IFERROR(F61/F58,"") | G59: =IFERROR(G61/G58,"") | H59: =IFERROR(H61/H58,"") | I59: =IFERROR(I61/I58,"") | J59: =IFERROR(J61/J58,"") | K59: =IFERROR(K61/K58,"") | ... W59: =IFERROR(W61/W58,"") | AC59: =IFERROR(AC61/AC58,"") | AD59: =IFERROR(AD61/AD58,"") | AE59: =IFERROR(AE61/AE58,"") | AF59: =IFERROR(AF61/AF58,"") | AG59: =IFERROR(AG61/AG58,"") | AH59: =IFERROR(AH61/AH58,"") | AI59: =IFERROR(AI61/AI58,"") | AJ59: =IFERROR(AJ61/AJ58,"") | AK59: =AJ59*(1+AK60) | AL59: =AK59*(1+AL60) | AM59: =AL59*(1+AM60) | AN59: =AM59*(1+AN60)
A60: YoY growth | B60: % | C60: Assumption (edit me) | AK60: -0.007 | AL60: -0.007 | AM60: -0.007 | AN60: -0.007
A61: GMV | B61: Rs Mn | C61: Link: Raw Data - Ops KPIs | D61: ='Raw Data - Ops KPIs'!D96 | E61: ='Raw Data - Ops KPIs'!E96 | F61: ='Raw Data - Ops KPIs'!F96 | G61: ='Raw Data - Ops KPIs'!G96 | H61: ='Raw Data - Ops KPIs'!H96 | I61: ='Raw Data - Ops KPIs'!I96 | J61: ='Raw Data - Ops KPIs'!J96 | K61: ='Raw Data - Ops KPIs'!K96 | ... W61: ='Raw Data - Ops KPIs'!W96 | AF61: ='Raw Data - Ops KPIs'!AF96 | AG61: ='Raw Data - Ops KPIs'!AG96 | AH61: ='Raw Data - Ops KPIs'!AH96 | AI61: ='Raw Data - Ops KPIs'!AI96 | AJ61: ='Raw Data - Ops KPIs'!AJ96 | AK61: =AK58*AK59 | AL61: =AL58*AL59 | AM61: =AM58*AM59 | AN61: =AN58*AN59
A62: YoY growth | B62: % | C62: Formula | H62: =IFERROR(H61/D61-1,"") | I62: =IFERROR(I61/E61-1,"") | J62: =IFERROR(J61/F61-1,"") | K62: =IFERROR(K61/G61-1,"") | L62: =IFERROR(L61/H61-1,"") | M62: =IFERROR(M61/I61-1,"") | N62: =IFERROR(N61/J61-1,"") | O62: =IFERROR(O61/K61-1,"") | ... W62: =IFERROR(W61/S61-1,"") | AD62: =IFERROR(AD61/AC61-1,"") | AE62: =IFERROR(AE61/AD61-1,"") | AF62: =IFERROR(AF61/AE61-1,"") | AG62: =IFERROR(AG61/AF61-1,"") | AH62: =IFERROR(AH61/AG61-1,"") | AI62: =IFERROR(AI61/AH61-1,"") | AJ62: =IFERROR(AJ61/AI61-1,"") | AK62: =IFERROR(AK61/AJ61-1,"") | ... AN62: =IFERROR(AN61/AM61-1,"")
A63: NSV / GMV | B63: % | C63: Assumption (edit me) | D63: =IFERROR(D64/D61,"") | E63: =IFERROR(E64/E61,"") | F63: =IFERROR(F64/F61,"") | G63: =IFERROR(G64/G61,"") | H63: =IFERROR(H64/H61,"") | I63: =IFERROR(I64/I61,"") | J63: =IFERROR(J64/J61,"") | K63: =IFERROR(K64/K61,"") | ... W63: =IFERROR(W64/W61,"") | AC63: =IFERROR(AC64/AC61,"") | AD63: =IFERROR(AD64/AD61,"") | AE63: =IFERROR(AE64/AE61,"") | AF63: =IFERROR(AF64/AF61,"") | AG63: =IFERROR(AG64/AG61,"") | AH63: =IFERROR(AH64/AH61,"") | AI63: =IFERROR(AI64/AI61,"") | AJ63: =IFERROR(AJ64/AJ61,"") | AK63: 0.292 | AL63: 0.292 | AM63: 0.292 | AN63: 0.292
A64: NSV | B64: Rs Mn | C64: Link: Raw Data - Ops KPIs | D64: ='Raw Data - Ops KPIs'!D99 | E64: ='Raw Data - Ops KPIs'!E99 | F64: ='Raw Data - Ops KPIs'!F99 | G64: ='Raw Data - Ops KPIs'!G99 | H64: ='Raw Data - Ops KPIs'!H99 | I64: ='Raw Data - Ops KPIs'!I99 | J64: ='Raw Data - Ops KPIs'!J99 | K64: ='Raw Data - Ops KPIs'!K99 | ... W64: ='Raw Data - Ops KPIs'!W99 | AF64: ='Raw Data - Ops KPIs'!AF99 | AG64: ='Raw Data - Ops KPIs'!AG99 | AH64: ='Raw Data - Ops KPIs'!AH99 | AI64: ='Raw Data - Ops KPIs'!AI99 | AJ64: ='Raw Data - Ops KPIs'!AJ99 | AK64: =AK61*AK63 | AL64: =AL61*AL63 | AM64: =AM61*AM63 | AN64: =AN61*AN63
A65: Revenue / NSV | B65: % | C65: Assumption (edit me) | D65: =IFERROR(D66/D64,"") | E65: =IFERROR(E66/E64,"") | F65: =IFERROR(F66/F64,"") | G65: =IFERROR(G66/G64,"") | H65: =IFERROR(H66/H64,"") | I65: =IFERROR(I66/I64,"") | J65: =IFERROR(J66/J64,"") | K65: =IFERROR(K66/K64,"") | ... W65: =IFERROR(W66/W64,"") | AC65: =IFERROR(AC66/AC64,"") | AD65: =IFERROR(AD66/AD64,"") | AE65: =IFERROR(AE66/AE64,"") | AF65: =IFERROR(AF66/AF64,"") | AG65: =IFERROR(AG66/AG64,"") | AH65: =IFERROR(AH66/AH64,"") | AI65: =IFERROR(AI66/AI64,"") | AJ65: =IFERROR(AJ66/AJ64,"") | AK65: 0.575 | AL65: 0.575 | AM65: 0.575 | AN65: 0.575
A66: Revenue | B66: Rs Mn | C66: Link: Raw Data - Ops KPIs | D66: ='Raw Data - Ops KPIs'!D101 | E66: ='Raw Data - Ops KPIs'!E101 | F66: ='Raw Data - Ops KPIs'!F101 | G66: ='Raw Data - Ops KPIs'!G101 | H66: ='Raw Data - Ops KPIs'!H101 | I66: ='Raw Data - Ops KPIs'!I101 | J66: ='Raw Data - Ops KPIs'!J101 | K66: ='Raw Data - Ops KPIs'!K101 | ... W66: ='Raw Data - Ops KPIs'!W101 | AF66: ='Raw Data - Ops KPIs'!AF101 | AG66: ='Raw Data - Ops KPIs'!AG101 | AH66: ='Raw Data - Ops KPIs'!AH101 | AI66: ='Raw Data - Ops KPIs'!AI101 | AJ66: ='Raw Data - Ops KPIs'!AJ101 | AK66: =AK64*AK65 | AL66: =AL64*AL65 | AM66: =AM64*AM65 | AN66: =AN64*AN65
A67: Gross margin (% of NSV) | B67: % | C67: Assumption (edit me) | D67: =IFERROR(D68/D64,"") | E67: =IFERROR(E68/E64,"") | F67: =IFERROR(F68/F64,"") | G67: =IFERROR(G68/G64,"") | H67: =IFERROR(H68/H64,"") | I67: =IFERROR(I68/I64,"") | J67: =IFERROR(J68/J64,"") | K67: =IFERROR(K68/K64,"") | ... W67: =IFERROR(W68/W64,"") | AC67: =IFERROR(AC68/AC64,"") | AD67: =IFERROR(AD68/AD64,"") | AE67: =IFERROR(AE68/AE64,"") | AF67: =IFERROR(AF68/AF64,"") | AG67: =IFERROR(AG68/AG64,"") | AH67: =IFERROR(AH68/AH64,"") | AI67: =IFERROR(AI68/AI64,"") | AJ67: =IFERROR(AJ68/AJ64,"") | AK67: 0.478 | AL67: 0.478 | AM67: 0.478 | AN67: 0.478
A68: Gross profit | B68: Rs Mn | C68: Link: Raw Data - Ops KPIs | D68: ='Raw Data - Ops KPIs'!D103 | E68: ='Raw Data - Ops KPIs'!E103 | F68: ='Raw Data - Ops KPIs'!F103 | G68: ='Raw Data - Ops KPIs'!G103 | H68: ='Raw Data - Ops KPIs'!H103 | I68: ='Raw Data - Ops KPIs'!I103 | J68: ='Raw Data - Ops KPIs'!J103 | K68: ='Raw Data - Ops KPIs'!K103 | ... W68: ='Raw Data - Ops KPIs'!W103 | AF68: ='Raw Data - Ops KPIs'!AF103 | AG68: ='Raw Data - Ops KPIs'!AG103 | AH68: ='Raw Data - Ops KPIs'!AH103 | AI68: ='Raw Data - Ops KPIs'!AI103 | AJ68: ='Raw Data - Ops KPIs'!AJ103 | AK68: =AK64*AK67 | AL68: =AL64*AL67 | AM68: =AM64*AM67 | AN68: =AN64*AN67
A69: Fulfilment (% of NSV) | B69: % | C69: Assumption (edit me) | D69: =IFERROR(D70/D64,"") | E69: =IFERROR(E70/E64,"") | F69: =IFERROR(F70/F64,"") | G69: =IFERROR(G70/G64,"") | H69: =IFERROR(H70/H64,"") | I69: =IFERROR(I70/I64,"") | J69: =IFERROR(J70/J64,"") | K69: =IFERROR(K70/K64,"") | ... W69: =IFERROR(W70/W64,"") | AC69: =IFERROR(AC70/AC64,"") | AD69: =IFERROR(AD70/AD64,"") | AE69: =IFERROR(AE70/AE64,"") | AF69: =IFERROR(AF70/AF64,"") | AG69: =IFERROR(AG70/AG64,"") | AH69: =IFERROR(AH70/AH64,"") | AI69: =IFERROR(AI70/AI64,"") | AJ69: =IFERROR(AJ70/AJ64,"") | AK69: 0.113 | AL69: 0.113 | AM69: 0.113 | AN69: 0.113
A70: Fulfilment cost | B70: Rs Mn | C70: Link: Raw Data - Ops KPIs | D70: ='Raw Data - Ops KPIs'!D105 | E70: ='Raw Data - Ops KPIs'!E105 | F70: ='Raw Data - Ops KPIs'!F105 | G70: ='Raw Data - Ops KPIs'!G105 | H70: ='Raw Data - Ops KPIs'!H105 | I70: ='Raw Data - Ops KPIs'!I105 | J70: ='Raw Data - Ops KPIs'!J105 | K70: ='Raw Data - Ops KPIs'!K105 | ... W70: ='Raw Data - Ops KPIs'!W105 | AF70: ='Raw Data - Ops KPIs'!AF105 | AG70: ='Raw Data - Ops KPIs'!AG105 | AH70: ='Raw Data - Ops KPIs'!AH105 | AI70: ='Raw Data - Ops KPIs'!AI105 | AJ70: ='Raw Data - Ops KPIs'!AJ105 | AK70: =AK64*AK69 | AL70: =AL64*AL69 | AM70: =AM64*AM69 | AN70: =AN64*AN69
A71: o/w Marketing (historical, linked) | B71: Rs Mn | C71: Link: Raw Data - Ops KPIs | D71: ='Raw Data - Ops KPIs'!D106 | E71: ='Raw Data - Ops KPIs'!E106 | F71: ='Raw Data - Ops KPIs'!F106 | G71: ='Raw Data - Ops KPIs'!G106 | H71: ='Raw Data - Ops KPIs'!H106 | I71: ='Raw Data - Ops KPIs'!I106 | J71: ='Raw Data - Ops KPIs'!J106 | K71: ='Raw Data - Ops KPIs'!K106 | ... W71: ='Raw Data - Ops KPIs'!W106 | AF71: ='Raw Data - Ops KPIs'!AF106 | AG71: ='Raw Data - Ops KPIs'!AG106 | AH71: ='Raw Data - Ops KPIs'!AH106 | AI71: ='Raw Data - Ops KPIs'!AI106 | AJ71: ='Raw Data - Ops KPIs'!AJ106
A72: o/w Selling & distribution (historical, linked) | B72: Rs Mn | C72: Link: Raw Data - Ops KPIs | D72: ='Raw Data - Ops KPIs'!D107 | E72: ='Raw Data - Ops KPIs'!E107 | F72: ='Raw Data - Ops KPIs'!F107 | G72: ='Raw Data - Ops KPIs'!G107 | H72: ='Raw Data - Ops KPIs'!H107 | I72: ='Raw Data - Ops KPIs'!I107 | J72: ='Raw Data - Ops KPIs'!J107 | K72: ='Raw Data - Ops KPIs'!K107 | ... W72: ='Raw Data - Ops KPIs'!W107 | AF72: ='Raw Data - Ops KPIs'!AF107 | AG72: ='Raw Data - Ops KPIs'!AG107 | AH72: ='Raw Data - Ops KPIs'!AH107 | AI72: ='Raw Data - Ops KPIs'!AI107 | AJ72: ='Raw Data - Ops KPIs'!AJ107
A73: Marketing & S&D (% of NSV, combined) | B73: % | C73: Assumption (edit me) | D73: =IFERROR(D74/D64,"") | E73: =IFERROR(E74/E64,"") | F73: =IFERROR(F74/F64,"") | G73: =IFERROR(G74/G64,"") | H73: =IFERROR(H74/H64,"") | I73: =IFERROR(I74/I64,"") | J73: =IFERROR(J74/J64,"") | K73: =IFERROR(K74/K64,"") | ... W73: =IFERROR(W74/W64,"") | AC73: =IFERROR(AC74/AC64,"") | AD73: =IFERROR(AD74/AD64,"") | AE73: =IFERROR(AE74/AE64,"") | AF73: =IFERROR(AF74/AF64,"") | AG73: =IFERROR(AG74/AG64,"") | AH73: =IFERROR(AH74/AH64,"") | AI73: =IFERROR(AI74/AI64,"") | AJ73: =IFERROR(AJ74/AJ64,"") | AK73: 0.264 | AL73: 0.264 | AM73: 0.264 | AN73: 0.264
A74: Marketing & S&D expense (combined) | B74: Rs Mn | C74: Formula | D74: =IF(AND(D71="",D72=""),"",IF(D71="",0,D71)+IF(D72="",0,D72)) | E74: =IF(AND(E71="",E72=""),"",IF(E71="",0,E71)+IF(E72="",0,E72)) | F74: =IF(AND(F71="",F72=""),"",IF(F71="",0,F71)+IF(F72="",0,F72)) | G74: =IF(AND(G71="",G72=""),"",IF(G71="",0,G71)+IF(G72="",0,G72)) | H74: =IF(AND(H71="",H72=""),"",IF(H71="",0,H71)+IF(H72="",0,H72)) | I74: =IF(AND(I71="",I72=""),"",IF(I71="",0,I71)+IF(I72="",0,I72)) | J74: =IF(AND(J71="",J72=""),"",IF(J71="",0,J71)+IF(J72="",0,J72)) | K74: =IF(AND(K71="",K72=""),"",IF(K71="",0,K71)+IF(K72="",0,K72)) | ... W74: =IF(AND(W71="",W72=""),"",IF(W71="",0,W71)+IF(W72="",0,W72)) | AC74: =IF(AND(AC71="",AC72=""),"",IF(AC71="",0,AC71)+IF(AC72="",0,AC72)) | AD74: =IF(AND(AD71="",AD72=""),"",IF(AD71="",0,AD71)+IF(AD72="",0,AD72)) | AE74: =IF(AND(AE71="",AE72=""),"",IF(AE71="",0,AE71)+IF(AE72="",0,AE72)) | AF74: =IF(AND(AF71="",AF72=""),"",IF(AF71="",0,AF71)+IF(AF72="",0,AF72)) | AG74: =IF(AND(AG71="",AG72=""),"",IF(AG71="",0,AG71)+IF(AG72="",0,AG72)) | AH74: =IF(AND(AH71="",AH72=""),"",IF(AH71="",0,AH71)+IF(AH72="",0,AH72)) | AI74: =IF(AND(AI71="",AI72=""),"",IF(AI71="",0,AI71)+IF(AI72="",0,AI72)) | AJ74: =IF(AND(AJ71="",AJ72=""),"",IF(AJ71="",0,AJ71)+IF(AJ72="",0,AJ72)) | AK74: =AK64*AK73 | AL74: =AL64*AL73 | AM74: =AM64*AM73 | AN74: =AN64*AN73
A75: Contribution profit | B75: Rs Mn | C75: Formula | D75: =IFERROR(D68-D70-D74,"") | E75: =IFERROR(E68-E70-E74,"") | F75: =IFERROR(F68-F70-F74,"") | G75: =IFERROR(G68-G70-G74,"") | H75: =IFERROR(H68-H70-H74,"") | I75: =IFERROR(I68-I70-I74,"") | J75: =IFERROR(J68-J70-J74,"") | K75: =IFERROR(K68-K70-K74,"") | ... W75: =IFERROR(W68-W70-W74,"") | AC75: =IFERROR(AC68-AC70-AC74,"") | AD75: =IFERROR(AD68-AD70-AD74,"") | AE75: =IFERROR(AE68-AE70-AE74,"") | AF75: =IFERROR(AF68-AF70-AF74,"") | AG75: =IFERROR(AG68-AG70-AG74,"") | AH75: =IFERROR(AH68-AH70-AH74,"") | AI75: =IFERROR(AI68-AI70-AI74,"") | AJ75: =IFERROR(AJ68-AJ70-AJ74,"") | ... AN75: =IFERROR(AN68-AN70-AN74,"")
A76: Contribution margin (% of NSV) | B76: % | C76: Formula | D76: =IFERROR(D75/D64,"") | E76: =IFERROR(E75/E64,"") | F76: =IFERROR(F75/F64,"") | G76: =IFERROR(G75/G64,"") | H76: =IFERROR(H75/H64,"") | I76: =IFERROR(I75/I64,"") | J76: =IFERROR(J75/J64,"") | K76: =IFERROR(K75/K64,"") | ... W76: =IFERROR(W75/W64,"") | AC76: =IFERROR(AC75/AC64,"") | AD76: =IFERROR(AD75/AD64,"") | AE76: =IFERROR(AE75/AE64,"") | AF76: =IFERROR(AF75/AF64,"") | AG76: =IFERROR(AG75/AG64,"") | AH76: =IFERROR(AH75/AH64,"") | AI76: =IFERROR(AI75/AI64,"") | AJ76: =IFERROR(AJ75/AJ64,"") | ... AN76: =IFERROR(AN75/AN64,"")
A77: Other expenses (% of NSV) | B77: % | C77: Assumption (edit me) | D77: =IFERROR(D78/D64,"") | E77: =IFERROR(E78/E64,"") | F77: =IFERROR(F78/F64,"") | G77: =IFERROR(G78/G64,"") | H77: =IFERROR(H78/H64,"") | I77: =IFERROR(I78/I64,"") | J77: =IFERROR(J78/J64,"") | K77: =IFERROR(K78/K64,"") | ... W77: =IFERROR(W78/W64,"") | AC77: =IFERROR(AC78/AC64,"") | AD77: =IFERROR(AD78/AD64,"") | AE77: =IFERROR(AE78/AE64,"") | AF77: =IFERROR(AF78/AF64,"") | AG77: =IFERROR(AG78/AG64,"") | AH77: =IFERROR(AH78/AH64,"") | AI77: =IFERROR(AI78/AI64,"") | AJ77: =IFERROR(AJ78/AJ64,"") | AK77: 0.128 | AL77: 0.128 | AM77: 0.128 | AN77: 0.128
A78: Other expenses (G&A + employee) | B78: Rs Mn | C78: Link: Raw Data - Ops KPIs | D78: ='Raw Data - Ops KPIs'!D110 | E78: ='Raw Data - Ops KPIs'!E110 | F78: ='Raw Data - Ops KPIs'!F110 | G78: ='Raw Data - Ops KPIs'!G110 | H78: ='Raw Data - Ops KPIs'!H110 | I78: ='Raw Data - Ops KPIs'!I110 | J78: ='Raw Data - Ops KPIs'!J110 | K78: ='Raw Data - Ops KPIs'!K110 | ... W78: ='Raw Data - Ops KPIs'!W110 | AF78: ='Raw Data - Ops KPIs'!AF110 | AG78: ='Raw Data - Ops KPIs'!AG110 | AH78: ='Raw Data - Ops KPIs'!AH110 | AI78: ='Raw Data - Ops KPIs'!AI110 | AJ78: ='Raw Data - Ops KPIs'!AJ110 | AK78: =AK64*AK77 | AL78: =AL64*AL77 | AM78: =AM64*AM77 | AN78: =AN64*AN77
A79: EBITDA | B79: Rs Mn | C79: Formula | D79: =IFERROR(D75-D78,"") | E79: =IFERROR(E75-E78,"") | F79: =IFERROR(F75-F78,"") | G79: =IFERROR(G75-G78,"") | H79: =IFERROR(H75-H78,"") | I79: =IFERROR(I75-I78,"") | J79: =IFERROR(J75-J78,"") | K79: =IFERROR(K75-K78,"") | ... W79: =IFERROR(W75-W78,"") | AC79: =IFERROR(AC75-AC78,"") | AD79: =IFERROR(AD75-AD78,"") | AE79: =IFERROR(AE75-AE78,"") | AF79: =IFERROR(AF75-AF78,"") | AG79: =IFERROR(AG75-AG78,"") | AH79: =IFERROR(AH75-AH78,"") | AI79: =IFERROR(AI75-AI78,"") | AJ79: =IFERROR(AJ75-AJ78,"") | ... AN79: =IFERROR(AN75-AN78,"")
A80: EBITDA margin (% of NSV) | B80: % | C80: Formula | D80: =IFERROR(D79/D64,"") | E80: =IFERROR(E79/E64,"") | F80: =IFERROR(F79/F64,"") | G80: =IFERROR(G79/G64,"") | H80: =IFERROR(H79/H64,"") | I80: =IFERROR(I79/I64,"") | J80: =IFERROR(J79/J64,"") | K80: =IFERROR(K79/K64,"") | ... W80: =IFERROR(W79/W64,"") | AC80: =IFERROR(AC79/AC64,"") | AD80: =IFERROR(AD79/AD64,"") | AE80: =IFERROR(AE79/AE64,"") | AF80: =IFERROR(AF79/AF64,"") | AG80: =IFERROR(AG79/AG64,"") | AH80: =IFERROR(AH79/AH64,"") | AI80: =IFERROR(AI79/AI64,"") | AJ80: =IFERROR(AJ79/AJ64,"") | ... AN80: =IFERROR(AN79/AN64,"")
A82: NEW BUSINESS (GCC + International)
A83: Beauty retail in the Gulf Cooperation Council (via Apparel Group JV) and international markets. Small, volatile, residual segment (Total - Beauty - Fashion in the Raw Data tab) -- treat these projections as indicative only.
A84: GMV | B84: Rs Mn | C84: Link: Raw Data - Ops KPIs | D84: ='Raw Data - Ops KPIs'!D124 | E84: ='Raw Data - Ops KPIs'!E124 | F84: ='Raw Data - Ops KPIs'!F124 | G84: ='Raw Data - Ops KPIs'!G124 | H84: ='Raw Data - Ops KPIs'!H124 | I84: ='Raw Data - Ops KPIs'!I124 | J84: ='Raw Data - Ops KPIs'!J124 | K84: ='Raw Data - Ops KPIs'!K124 | ... W84: ='Raw Data - Ops KPIs'!W124 | AF84: ='Raw Data - Ops KPIs'!AF124 | AG84: ='Raw Data - Ops KPIs'!AG124 | AH84: ='Raw Data - Ops KPIs'!AH124 | AI84: ='Raw Data - Ops KPIs'!AI124 | AJ84: ='Raw Data - Ops KPIs'!AJ124 | AK84: =AJ84*(1+AK85) | AL84: =AK84*(1+AL85) | AM84: =AL84*(1+AM85) | AN84: =AM84*(1+AN85)
A85: YoY growth | B85: % | C85: Assumption (edit me) | H85: =IFERROR(H84/D84-1,"") | I85: =IFERROR(I84/E84-1,"") | J85: =IFERROR(J84/F84-1,"") | K85: =IFERROR(K84/G84-1,"") | L85: =IFERROR(L84/H84-1,"") | M85: =IFERROR(M84/I84-1,"") | N85: =IFERROR(N84/J84-1,"") | O85: =IFERROR(O84/K84-1,"") | ... W85: =IFERROR(W84/S84-1,"") | AD85: =IFERROR(AD84/AC84-1,"") | AE85: =IFERROR(AE84/AD84-1,"") | AF85: =IFERROR(AF84/AE84-1,"") | AG85: =IFERROR(AG84/AF84-1,"") | AH85: =IFERROR(AH84/AG84-1,"") | AI85: =IFERROR(AI84/AH84-1,"") | AJ85: =IFERROR(AJ84/AI84-1,"") | AK85: 0.3 | AL85: 0.3 | AM85: 0.3 | AN85: 0.3
A86: NSV / GMV | B86: % | C86: Assumption (edit me) | D86: =IFERROR(D87/D84,"") | E86: =IFERROR(E87/E84,"") | F86: =IFERROR(F87/F84,"") | G86: =IFERROR(G87/G84,"") | H86: =IFERROR(H87/H84,"") | I86: =IFERROR(I87/I84,"") | J86: =IFERROR(J87/J84,"") | K86: =IFERROR(K87/K84,"") | ... W86: =IFERROR(W87/W84,"") | AC86: =IFERROR(AC87/AC84,"") | AD86: =IFERROR(AD87/AD84,"") | AE86: =IFERROR(AE87/AE84,"") | AF86: =IFERROR(AF87/AF84,"") | AG86: =IFERROR(AG87/AG84,"") | AH86: =IFERROR(AH87/AH84,"") | AI86: =IFERROR(AI87/AI84,"") | AJ86: =IFERROR(AJ87/AJ84,"") | AK86: 0.85 | AL86: 0.85 | AM86: 0.85 | AN86: 0.85
A87: NSV | B87: Rs Mn | C87: Link: Raw Data - Ops KPIs | D87: ='Raw Data - Ops KPIs'!D126 | E87: ='Raw Data - Ops KPIs'!E126 | F87: ='Raw Data - Ops KPIs'!F126 | G87: ='Raw Data - Ops KPIs'!G126 | H87: ='Raw Data - Ops KPIs'!H126 | I87: ='Raw Data - Ops KPIs'!I126 | J87: ='Raw Data - Ops KPIs'!J126 | K87: ='Raw Data - Ops KPIs'!K126 | ... W87: ='Raw Data - Ops KPIs'!W126 | AF87: ='Raw Data - Ops KPIs'!AF126 | AG87: ='Raw Data - Ops KPIs'!AG126 | AH87: ='Raw Data - Ops KPIs'!AH126 | AI87: ='Raw Data - Ops KPIs'!AI126 | AJ87: ='Raw Data - Ops KPIs'!AJ126 | AK87: =AK84*AK86 | AL87: =AL84*AL86 | AM87: =AM84*AM86 | AN87: =AN84*AN86
A88: Revenue / NSV | B88: % | C88: Assumption (edit me) | D88: =IFERROR(D89/D87,"") | E88: =IFERROR(E89/E87,"") | F88: =IFERROR(F89/F87,"") | G88: =IFERROR(G89/G87,"") | H88: =IFERROR(H89/H87,"") | I88: =IFERROR(I89/I87,"") | J88: =IFERROR(J89/J87,"") | K88: =IFERROR(K89/K87,"") | ... W88: =IFERROR(W89/W87,"") | AC88: =IFERROR(AC89/AC87,"") | AD88: =IFERROR(AD89/AD87,"") | AE88: =IFERROR(AE89/AE87,"") | AF88: =IFERROR(AF89/AF87,"") | AG88: =IFERROR(AG89/AG87,"") | AH88: =IFERROR(AH89/AH87,"") | AI88: =IFERROR(AI89/AI87,"") | AJ88: =IFERROR(AJ89/AJ87,"") | AK88: 1.09 | AL88: 1.09 | AM88: 1.09 | AN88: 1.09
A89: Revenue | B89: Rs Mn | C89: Link: Raw Data - Ops KPIs | D89: ='Raw Data - Ops KPIs'!D127 | E89: ='Raw Data - Ops KPIs'!E127 | F89: ='Raw Data - Ops KPIs'!F127 | G89: ='Raw Data - Ops KPIs'!G127 | H89: ='Raw Data - Ops KPIs'!H127 | I89: ='Raw Data - Ops KPIs'!I127 | J89: ='Raw Data - Ops KPIs'!J127 | K89: ='Raw Data - Ops KPIs'!K127 | ... W89: ='Raw Data - Ops KPIs'!W127 | AF89: ='Raw Data - Ops KPIs'!AF127 | AG89: ='Raw Data - Ops KPIs'!AG127 | AH89: ='Raw Data - Ops KPIs'!AH127 | AI89: ='Raw Data - Ops KPIs'!AI127 | AJ89: ='Raw Data - Ops KPIs'!AJ127 | AK89: =AK87*AK88 | AL89: =AL87*AL88 | AM89: =AM87*AM88 | AN89: =AN87*AN88
A90: Contribution margin (% of NSV) | B90: % | C90: Assumption (edit me) | D90: =IFERROR(D91/D87,"") | E90: =IFERROR(E91/E87,"") | F90: =IFERROR(F91/F87,"") | G90: =IFERROR(G91/G87,"") | H90: =IFERROR(H91/H87,"") | I90: =IFERROR(I91/I87,"") | J90: =IFERROR(J91/J87,"") | K90: =IFERROR(K91/K87,"") | ... W90: =IFERROR(W91/W87,"") | AC90: =IFERROR(AC91/AC87,"") | AD90: =IFERROR(AD91/AD87,"") | AE90: =IFERROR(AE91/AE87,"") | AF90: =IFERROR(AF91/AF87,"") | AG90: =IFERROR(AG91/AG87,"") | AH90: =IFERROR(AH91/AH87,"") | AI90: =IFERROR(AI91/AI87,"") | AJ90: =IFERROR(AJ91/AJ87,"") | AK90: 0.16 | AL90: 0.16 | AM90: 0.16 | AN90: 0.16
A91: Contribution profit | B91: Rs Mn | C91: Link: Raw Data - Ops KPIs | D91: ='Raw Data - Ops KPIs'!D131 | E91: ='Raw Data - Ops KPIs'!E131 | F91: ='Raw Data - Ops KPIs'!F131 | G91: ='Raw Data - Ops KPIs'!G131 | H91: ='Raw Data - Ops KPIs'!H131 | I91: ='Raw Data - Ops KPIs'!I131 | J91: ='Raw Data - Ops KPIs'!J131 | K91: ='Raw Data - Ops KPIs'!K131 | ... W91: ='Raw Data - Ops KPIs'!W131 | AF91: ='Raw Data - Ops KPIs'!AF131 | AG91: ='Raw Data - Ops KPIs'!AG131 | AH91: ='Raw Data - Ops KPIs'!AH131 | AI91: ='Raw Data - Ops KPIs'!AI131 | AJ91: ='Raw Data - Ops KPIs'!AJ131 | AK91: =AK87*AK90 | AL91: =AL87*AL90 | AM91: =AM87*AM90 | AN91: =AN87*AN90
A92: Other expenses (% of NSV) | B92: % | C92: Assumption (edit me) | D92: =IFERROR(D93/D87,"") | E92: =IFERROR(E93/E87,"") | F92: =IFERROR(F93/F87,"") | G92: =IFERROR(G93/G87,"") | H92: =IFERROR(H93/H87,"") | I92: =IFERROR(I93/I87,"") | J92: =IFERROR(J93/J87,"") | K92: =IFERROR(K93/K87,"") | ... W92: =IFERROR(W93/W87,"") | AC92: =IFERROR(AC93/AC87,"") | AD92: =IFERROR(AD93/AD87,"") | AE92: =IFERROR(AE93/AE87,"") | AF92: =IFERROR(AF93/AF87,"") | AG92: =IFERROR(AG93/AG87,"") | AH92: =IFERROR(AH93/AH87,"") | AI92: =IFERROR(AI93/AI87,"") | AJ92: =IFERROR(AJ93/AJ87,"") | AK92: -0.1 | AL92: -0.1 | AM92: -0.1 | AN92: -0.1
A93: Other expenses (G&A + employee) | B93: Rs Mn | C93: Link: Raw Data - Ops KPIs | D93: ='Raw Data - Ops KPIs'!D132 | E93: ='Raw Data - Ops KPIs'!E132 | F93: ='Raw Data - Ops KPIs'!F132 | G93: ='Raw Data - Ops KPIs'!G132 | H93: ='Raw Data - Ops KPIs'!H132 | I93: ='Raw Data - Ops KPIs'!I132 | J93: ='Raw Data - Ops KPIs'!J132 | K93: ='Raw Data - Ops KPIs'!K132 | ... W93: ='Raw Data - Ops KPIs'!W132 | AF93: ='Raw Data - Ops KPIs'!AF132 | AG93: ='Raw Data - Ops KPIs'!AG132 | AH93: ='Raw Data - Ops KPIs'!AH132 | AI93: ='Raw Data - Ops KPIs'!AI132 | AJ93: ='Raw Data - Ops KPIs'!AJ132 | AK93: =AK87*AK92 | AL93: =AL87*AL92 | AM93: =AM87*AM92 | AN93: =AN87*AN92
A94: EBITDA | B94: Rs Mn | C94: Formula | D94: =IFERROR(D91-D93,"") | E94: =IFERROR(E91-E93,"") | F94: =IFERROR(F91-F93,"") | G94: =IFERROR(G91-G93,"") | H94: =IFERROR(H91-H93,"") | I94: =IFERROR(I91-I93,"") | J94: =IFERROR(J91-J93,"") | K94: =IFERROR(K91-K93,"") | ... W94: =IFERROR(W91-W93,"") | AC94: =IFERROR(AC91-AC93,"") | AD94: =IFERROR(AD91-AD93,"") | AE94: =IFERROR(AE91-AE93,"") | AF94: =IFERROR(AF91-AF93,"") | AG94: =IFERROR(AG91-AG93,"") | AH94: =IFERROR(AH91-AH93,"") | AI94: =IFERROR(AI91-AI93,"") | AJ94: =IFERROR(AJ91-AJ93,"") | ... AN94: =IFERROR(AN91-AN93,"")
A95: EBITDA margin (% of NSV) | B95: % | C95: Formula | D95: =IFERROR(D94/D87,"") | E95: =IFERROR(E94/E87,"") | F95: =IFERROR(F94/F87,"") | G95: =IFERROR(G94/G87,"") | H95: =IFERROR(H94/H87,"") | I95: =IFERROR(I94/I87,"") | J95: =IFERROR(J94/J87,"") | K95: =IFERROR(K94/K87,"") | ... W95: =IFERROR(W94/W87,"") | AC95: =IFERROR(AC94/AC87,"") | AD95: =IFERROR(AD94/AD87,"") | AE95: =IFERROR(AE94/AE87,"") | AF95: =IFERROR(AF94/AF87,"") | AG95: =IFERROR(AG94/AG87,"") | AH95: =IFERROR(AH94/AH87,"") | AI95: =IFERROR(AI94/AI87,"") | AJ95: =IFERROR(AJ94/AJ87,"") | ... AN95: =IFERROR(AN94/AN87,"")
A97: CONSOLIDATED BRIDGE (EBITDA TO EPS)
A98: Segment EBITDAs (Beauty + Fashion + New Business) roll up here, then D&A / finance costs / other income / tax bring it down to PAT and EPS -- these lines aren't split by segment in Nykaa's disclosure, so they only exist at the consolidated level.
A99: Total EBITDA (Beauty + Fashion + New Business) | B99: Rs Mn | C99: Formula | D99: =IFERROR(D50+D79+D94,"") | E99: =IFERROR(E50+E79+E94,"") | F99: =IFERROR(F50+F79+F94,"") | G99: =IFERROR(G50+G79+G94,"") | H99: =IFERROR(H50+H79+H94,"") | I99: =IFERROR(I50+I79+I94,"") | J99: =IFERROR(J50+J79+J94,"") | K99: =IFERROR(K50+K79+K94,"") | ... W99: =IFERROR(W50+W79+W94,"") | AC99: =IFERROR(AC50+AC79+AC94,"") | AD99: =IFERROR(AD50+AD79+AD94,"") | AE99: =IFERROR(AE50+AE79+AE94,"") | AF99: =IFERROR(AF50+AF79+AF94,"") | AG99: =IFERROR(AG50+AG79+AG94,"") | AH99: =IFERROR(AH50+AH79+AH94,"") | AI99: =IFERROR(AI50+AI79+AI94,"") | AJ99: =IFERROR(AJ50+AJ79+AJ94,"") | ... AN99: =IFERROR(AN50+AN79+AN94,"")
A100: EBITDA margin (% of Revenue) | B100: % | C100: Formula | D100: =IFERROR(D99/D9,"") | E100: =IFERROR(E99/E9,"") | F100: =IFERROR(F99/F9,"") | G100: =IFERROR(G99/G9,"") | H100: =IFERROR(H99/H9,"") | I100: =IFERROR(I99/I9,"") | J100: =IFERROR(J99/J9,"") | K100: =IFERROR(K99/K9,"") | ... W100: =IFERROR(W99/W9,"") | AC100: =IFERROR(AC99/AC9,"") | AD100: =IFERROR(AD99/AD9,"") | AE100: =IFERROR(AE99/AE9,"") | AF100: =IFERROR(AF99/AF9,"") | AG100: =IFERROR(AG99/AG9,"") | AH100: =IFERROR(AH99/AH9,"") | AI100: =IFERROR(AI99/AI9,"") | AJ100: =IFERROR(AJ99/AJ9,"") | ... AN100: =IFERROR(AN99/AN9,"")
A101: D&A (% of Revenue) | B101: % | C101: Assumption (edit me) | D101: =IFERROR(D102/D9,"") | E101: =IFERROR(E102/E9,"") | F101: =IFERROR(F102/F9,"") | G101: =IFERROR(G102/G9,"") | H101: =IFERROR(H102/H9,"") | I101: =IFERROR(I102/I9,"") | J101: =IFERROR(J102/J9,"") | K101: =IFERROR(K102/K9,"") | ... W101: =IFERROR(W102/W9,"") | AC101: =IFERROR(AC102/AC9,"") | AD101: =IFERROR(AD102/AD9,"") | AE101: =IFERROR(AE102/AE9,"") | AF101: =IFERROR(AF102/AF9,"") | AG101: =IFERROR(AG102/AG9,"") | AH101: =IFERROR(AH102/AH9,"") | AI101: =IFERROR(AI102/AI9,"") | AJ101: =IFERROR(AJ102/AJ9,"") | AK101: 0.032 | AL101: 0.032 | AM101: 0.032 | AN101: 0.032
A102: Depreciation & amortisation | B102: Rs Mn | C102: Link: Raw Data - financials | D102: ='Raw Data - financials'!D15 | E102: ='Raw Data - financials'!E15 | F102: ='Raw Data - financials'!F15 | G102: ='Raw Data - financials'!G15 | H102: ='Raw Data - financials'!H15 | I102: ='Raw Data - financials'!I15 | J102: ='Raw Data - financials'!J15 | K102: ='Raw Data - financials'!K15 | ... W102: ='Raw Data - financials'!W15 | AC102: ='Raw Data - financials'!AC15 | AD102: ='Raw Data - financials'!AD15 | AE102: ='Raw Data - financials'!AE15 | AF102: ='Raw Data - financials'!AF15 | AG102: ='Raw Data - financials'!AG15 | AH102: ='Raw Data - financials'!AH15 | AI102: ='Raw Data - financials'!AI15 | AJ102: ='Raw Data - financials'!AJ15 | AK102: =AK9*AK101 | AL102: =AL9*AL101 | AM102: =AM9*AM101 | AN102: =AN9*AN101
A103: EBIT | B103: Rs Mn | C103: Formula | D103: =IFERROR(D99-D102,"") | E103: =IFERROR(E99-E102,"") | F103: =IFERROR(F99-F102,"") | G103: =IFERROR(G99-G102,"") | H103: =IFERROR(H99-H102,"") | I103: =IFERROR(I99-I102,"") | J103: =IFERROR(J99-J102,"") | K103: =IFERROR(K99-K102,"") | ... W103: =IFERROR(W99-W102,"") | AC103: =IFERROR(AC99-AC102,"") | AD103: =IFERROR(AD99-AD102,"") | AE103: =IFERROR(AE99-AE102,"") | AF103: =IFERROR(AF99-AF102,"") | AG103: =IFERROR(AG99-AG102,"") | AH103: =IFERROR(AH99-AH102,"") | AI103: =IFERROR(AI99-AI102,"") | AJ103: =IFERROR(AJ99-AJ102,"") | ... AN103: =IFERROR(AN99-AN102,"")
A104: Finance costs (% of Revenue) | B104: % | C104: Assumption (edit me) | D104: =IFERROR(D105/D9,"") | E104: =IFERROR(E105/E9,"") | F104: =IFERROR(F105/F9,"") | G104: =IFERROR(G105/G9,"") | H104: =IFERROR(H105/H9,"") | I104: =IFERROR(I105/I9,"") | J104: =IFERROR(J105/J9,"") | K104: =IFERROR(K105/K9,"") | ... W104: =IFERROR(W105/W9,"") | AC104: =IFERROR(AC105/AC9,"") | AD104: =IFERROR(AD105/AD9,"") | AE104: =IFERROR(AE105/AE9,"") | AF104: =IFERROR(AF105/AF9,"") | AG104: =IFERROR(AG105/AG9,"") | AH104: =IFERROR(AH105/AH9,"") | AI104: =IFERROR(AI105/AI9,"") | AJ104: =IFERROR(AJ105/AJ9,"") | AK104: 0.0117 | AL104: 0.0117 | AM104: 0.0117 | AN104: 0.0117
A105: Finance costs | B105: Rs Mn | C105: Link: Raw Data - financials | D105: ='Raw Data - financials'!D14 | E105: ='Raw Data - financials'!E14 | F105: ='Raw Data - financials'!F14 | G105: ='Raw Data - financials'!G14 | H105: ='Raw Data - financials'!H14 | I105: ='Raw Data - financials'!I14 | J105: ='Raw Data - financials'!J14 | K105: ='Raw Data - financials'!K14 | ... W105: ='Raw Data - financials'!W14 | AC105: ='Raw Data - financials'!AC14 | AD105: ='Raw Data - financials'!AD14 | AE105: ='Raw Data - financials'!AE14 | AF105: ='Raw Data - financials'!AF14 | AG105: ='Raw Data - financials'!AG14 | AH105: ='Raw Data - financials'!AH14 | AI105: ='Raw Data - financials'!AI14 | AJ105: ='Raw Data - financials'!AJ14 | AK105: =AK9*AK104 | AL105: =AL9*AL104 | AM105: =AM9*AM104 | AN105: =AN9*AN104
...

Sheet Raw Data - financials
A1: INR Mn | B1: Unit | C1: Source | D1: 1Q22 | E1: 2Q22 | F1: 3Q22 | G1: 4Q22 | H1: 1Q23 | I1: 2Q23 | J1: 3Q23 | K1: 4Q23 | L1: 1Q24 | M1: 2Q24 | N1: 3Q24 | O1: 4Q24 | P1: 1Q25 | Q1: 2Q25 | R1: 3Q25 | S1: 4Q25 | T1: 1Q26 | U1: 2Q26 | V1: 3Q26 | W1: 4Q26 | X1: 1Q27 | Y1: 2Q27 | Z1: 3Q27 | AA1: 4Q27 | AC1: FY19 | AD1: FY20 | AE1: FY21 | AF1: FY22 | AG1: FY23 | AH1: FY24 | AI1: FY25 | AJ1: FY26
A2: Fiscal Year End | D2: =EOMONTH(E2,-3) | E2: =EOMONTH(F2,-3) | F2: =EOMONTH(G2,-3) | G2: =EOMONTH(H2,-3) | H2: =EOMONTH(I2,-3) | I2: =EOMONTH(J2,-3) | J2: =EOMONTH(K2,-3) | K2: =EOMONTH(L2,-3) | ... V2: =EOMONTH(W2,-3) | W2: 46112 | X2: =EOMONTH(W2,3) | Y2: =EOMONTH(X2,3) | Z2: =EOMONTH(Y2,3) | AA2: =EOMONTH(Z2,3) | AC2: 43555 | AD2: 43921 | AE2: 44286 | AF2: 44651 | AG2: 45016 | AH2: 45382 | AI2: 45747 | AJ2: 46112
A3: All figures in INR Mn unless stated otherwise.
A4: PROFIT & LOSS (CONSOLIDATED)
A5: Revenue from operations | B5: INR Mn | C5: Company filings | D5: 8169.91 | E5: 8852.64 | F5: 10983.6 | G5: 9733.2 | H5: 11484.21 | I5: 12308.29 | J5: 14628.26 | K5: 13017.24 | L5: 14218.24 | M5: 15070.24 | N5: 17887.98 | O5: 16679.8 | P5: 17461.1 | Q5: 18747.4 | R5: 22672.1 | S5: 20617.6 | T5: 21549.4 | U5: 23459.8 | V5: 28732.6 | W5: 26481.7 | AC5: 11113.94 | AD5: 17675.33 | AE5: 24408.96 | AF5: 37739.35 | AG5: 51438 | AH5: 63856.26 | AI5: 79498.2 | AJ5: 100223.5
A6: Other income | B6: INR Mn | C6: Company filings | D6: 47.22 | E6: 51.98 | F6: 59.13 | G6: 111.39 | H6: 83.63 | I6: 64.76 | J6: 56.36 | K6: 97.38 | L6: 67.21 | M6: 85.73 | N6: 75.84 | O6: 70.63 | P6: 73.3 | Q6: 54.5 | R6: 55.3 | S6: 89.5 | T6: 93.3 | U6: 80.3 | V6: 62.6 | W6: 91.5 | AC6: 49.88 | AD6: 103.17 | AE6: 117.41 | AF6: 269.72 | AG6: 302.13 | AH6: 299.42 | AI6: 272.6 | AJ6: 327.7
A7: Total Income | B7: INR Mn | D7: =SUM(D5:D6) | E7: =SUM(E5:E6) | F7: =SUM(F5:F6) | G7: =SUM(G5:G6) | H7: =SUM(H5:H6) | I7: =SUM(I5:I6) | J7: =SUM(J5:J6) | K7: =SUM(K5:K6) | ... W7: =SUM(W5:W6) | AC7: =SUM(AC5:AC6) | AD7: =SUM(AD5:AD6) | AE7: =SUM(AE5:AE6) | AF7: =SUM(AF5:AF6) | AG7: =SUM(AG5:AG6) | AH7: =SUM(AH5:AH6) | AI7: =SUM(AI5:AI6) | AJ7: =SUM(AJ5:AJ6)
A9: Expenses
A10: Cost of material consumed | B10: INR Mn | C10: Company filings | D10: 229.37 | E10: 179.32 | F10: 176.56 | G10: 257.87 | H10: 232.97 | I10: 222.51 | J10: 166.08 | K10: 972.77 | L10: 186 | M10: 155.06 | N10: 235.19 | O10: 74.87 | P10: 25.9 | Q10: 14.5 | R10: 27.8 | S10: 12.8 | T10: 33.3 | U10: 3.4 | V10: 22.1 | W10: 87.3 | AC10: 2.41 | AD10: 173.43 | AE10: 382.41 | AF10: 843.12 | AG10: 1594.33 | AH10: 651.13 | AI10: 81 | AJ10: 146.1
A11: Purchase of traded goods | B11: INR Mn | C11: Company filings | D11: 5509.42 | E11: 4848.33 | F11: 6902.15 | G11: 6643.6 | H11: 7415.45 | I11: 5858.02 | J11: 9188.98 | K11: 6017.46 | L11: 9781.98 | M11: 5530.25 | N11: 12322.52 | O11: 10182.01 | P11: 11718 | Q11: 10860.8 | R11: 12849.6 | S11: 11402.3 | T11: 14444.5 | U11: 11965.3 | V11: 15047.7 | W11: 15728.3 | AC11: 7852.43 | AD11: 11787.46 | AE11: 14956.06 | AF11: 24078.31 | AG11: 28479.91 | AH11: 37816.75 | AI11: 46830.8 | AJ11: 57185.8
A12: Changes in inventories of finished goods and stock-in-trade | B12: INR Mn | C12: Company filings | D12: -885.47 | E12: 42.57 | F12: -1182.69 | G12: -1420.88 | H12: -1263 | I12: 650.38 | J12: -1073.5 | K12: 268.69 | L12: -1935.99 | M12: 2888.69 | N12: -2277.21 | O12: -679.51 | P12: -1842.6 | Q12: -338.1 | R12: -116.7 | S12: 112.3 | T12: -2543.5 | U12: 955.7 | V12: 688 | W12: -1366.8 | AC12: -1252.07 | AD12: -1818.84 | AE12: -460.22 | AF12: -3621.28 | AG12: -1417.43 | AH12: -2004.02 | AI12: -2185.2 | AJ12: -2266.6
A13: Employee benefits expense | B13: INR Mn | C13: Company filings | D13: 726.05 | E13: 694.01 | F13: 933.21 | G13: 908 | H13: 1147.09 | I13: 1217.61 | J13: 1279.16 | K13: 1273.31 | L13: 1385.76 | M13: 1363.2 | N13: 1479.3 | O13: 1420.75 | P13: 1558.6 | Q13: 1614.9 | R13: 1746 | S13: 1741.2 | T13: 1820.2 | U13: 1827.7 | V13: 2029 | W13: 2038.4 | AC13: 1172.96 | AD13: 1956.13 | AE13: 2836.47 | AF13: 3259.39 | AG13: 4917.17 | AH13: 5649.01 | AI13: 6660.7 | AJ13: 7715.3
A14: Finance costs | B14: INR Mn | C14: Company filings | D14: 90.14 | E14: 113.49 | F14: 127.9 | G14: 133.58 | H14: 150.63 | I14: 203.56 | J14: 204.25 | K14: 187.61 | L14: 185.48 | M14: 213.09 | N14: 218.41 | O14: 211.34 | P14: 213.1 | Q14: 242.3 | R14: 319.3 | S14: 298.5 | T14: 301.6 | U14: 314.7 | V14: 291.6 | W14: 263.3 | AC14: 263.42 | AD14: 442.93 | AE14: 307.01 | AF14: 465.11 | AG14: 746.05 | AH14: 828.32 | AI14: 1073.2 | AJ14: 1171.2
A15: Depreciation and amortisation expense | B15: INR Mn | C15: Company filings | D15: 194.97 | E15: 213.08 | F15: 251.24 | G15: 304.84 | H15: 310.12 | I15: 385.02 | J15: 507 | K15: 530.42 | L15: 519.2 | M15: 546.36 | N15: 580.28 | O15: 596.49 | P15: 600.6 | Q15: 636.2 | R15: 698.2 | S15: 729 | T15: 761.4 | U15: 790.9 | V15: 808.8 | W15: 842.2 | AC15: 308.76 | AD15: 595.09 | AE15: 671.28 | AF15: 964.13 | AG15: 1732.56 | AH15: 2242.33 | AI15: 2664 | AJ15: 3203.3
A16: Other expenses | B16: INR Mn | C16: Company filings | D16: 2321.16 | E16: 2800.17 | F16: 3464.6 | G16: 2959.42 | H16: 3491.18 | I16: 3748.4 | J16: 4285.94 | K16: 3778.07 | L16: 4065.83 | M16: 4326.75 | N16: 5140.44 | O16: 4748.86 | P16: 5040 | Q16: 5558.7 | R16: 6757.6 | S16: 6015.5 | T16: 6388.1 | U16: 7118.2 | V16: 8648.2 | W16: 7765.3 | AC16: 3133.11 | AD16: 4766.6 | AE16: 5079.98 | AF16: 11547.23 | AG16: 15303.59 | AH16: 18281.89 | AI16: 23371.8 | AJ16: 29919.8
A17: Total Expenses | B17: INR Mn | D17: =SUM(D10:D16) | E17: =SUM(E10:E16) | F17: =SUM(F10:F16) | G17: =SUM(G10:G16) | H17: =SUM(H10:H16) | I17: =SUM(I10:I16) | J17: =SUM(J10:J16) | K17: =SUM(K10:K16) | ... W17: =SUM(W10:W16) | AC17: =SUM(AC10:AC16) | AD17: =SUM(AD10:AD16) | AE17: =SUM(AE10:AE16) | AF17: =SUM(AF10:AF16) | AG17: =SUM(AG10:AG16) | AH17: =SUM(AH10:AH16) | AI17: =SUM(AI10:AI16) | AJ17: =SUM(AJ10:AJ16)
A19: Profit Before Exceptional Items and Tax | B19: INR Mn | D19: =D7-D17 | E19: =E7-E17 | F19: =F7-F17 | G19: =G7-G17 | H19: =H7-H17 | I19: =I7-I17 | J19: =J7-J17 | K19: =K7-K17 | ... W19: =W7-W17 | AC19: =AC7-AC17 | AD19: =AD7-AD17 | AE19: =AE7-AE17 | AF19: =AF7-AF17 | AG19: =AG7-AG17 | AH19: =AH7-AH17 | AI19: =AI7-AI17 | AJ19: =AJ7-AJ17
A20: Exceptional items, net | B20: INR Mn | C20: Company filings | D20: 0 | E20: 0 | F20: 0 | G20: 0 | H20: 0 | I20: 0 | J20: 0 | K20: 0 | L20: 0 | M20: 0 | N20: 0 | O20: 0 | P20: 0 | Q20: 0 | R20: 0 | S20: 0 | T20: 0 | U20: 10.4 | V20: 163.6 | W20: 0 | AC20: 0 | AD20: 0 | AE20: 0 | AF20: 0 | AG20: 0 | AH20: 0 | AI20: 0 | AJ20: 174
A21: Profit Before Tax | B21: INR Mn | D21: =D19-D20 | E21: =E19-E20 | F21: =F19-F20 | G21: =G19-G20 | H21: =H19-H20 | I21: =I19-I20 | J21: =J19-J20 | K21: =K19-K20 | ... W21: =W19-W20 | AC21: =AC19-AC20 | AD21: =AD19-AD20 | AE21: =AE19-AE20 | AF21: =AF19-AF20 | AG21: =AG19-AG20 | AH21: =AH19-AH20 | AI21: =AI19-AI20 | AJ21: =AJ19-AJ20
A23: Tax expense
A24: Current tax | B24: INR Mn | C24: Company filings | D24: 133.64 | E24: 3.66 | F24: 144.35 | G24: 141.28 | H24: 113.25 | I24: 215.91 | J24: 270.99 | K24: 260.96 | L24: 236.23 | M24: 215.86 | N24: 308.98 | O24: 306.28 | P24: 420.3 | Q24: 211.2 | R24: 319.9 | S24: -536.4 | T24: 177.3 | U24: 209.2 | V24: 279.2 | W24: 709.2 | AC24: 0 | AD24: 45.37 | AE24: 400.78 | AF24: 422.93 | AG24: 861.11 | AH24: 1067.35 | AI24: 415 | AJ24: 1374.9
A25: Current tax pertaining to earlier years | B25: INR Mn | C25: Company filings | D25: 0 | E25: 0 | F25: 0 | G25: 23.46 | H25: 0 | I25: 0 | J25: 0 | K25: 0 | L25: 0 | M25: 0 | N25: 0 | O25: 0 | P25: 0 | Q25: 0 | R25: 0 | S25: 0 | T25: 0 | U25: 0 | V25: 0 | W25: 0 | AC25: 0 | AD25: 0 | AE25: 0 | AF25: 23.46 | AG25: 0 | AH25: 0 | AI25: 0 | AJ25: 0
A26: Deferred tax expense/(credit) | B26: INR Mn | C26: Company filings | D26: -137.37 | E26: -1.73 | F26: -64.74 | G26: -124.27 | H26: -86.72 | I26: -184.91 | J26: -236.32 | K26: -217.42 | L26: -203.6 | M26: -176.18 | N26: -226.43 | O26: -208.03 | P26: -341.9 | Q26: -133 | R26: -144 | S26: 741.4 | T26: 15.1 | U26: 14.8 | V26: 139.6 | W26: -281.5 | AC26: -71.81 | AD26: -6.27 | AE26: -266.85 | AF26: -328.11 | AG26: -725.37 | AH26: -814.24 | AI26: 122.5 | AJ26: -112
A27: Deferred tax credit for unrecognised business loss (earlier years) | B27: INR Mn | C27: Company filings | D27: 0 | E27: 0 | F27: 0 | G27: -58.1 | H27: 0 | I27: 0 | J27: 0 | K27: 0 | L27: 0 | M27: 0 | N27: 0 | O27: 0 | P27: 0 | Q27: 0 | R27: 0 | S27: 0 | T27: 0 | U27: 0 | V27: 0 | W27: 0 | AC27: 0 | AD27: 0 | AE27: 0 | AF27: -58.1 | AG27: 0 | AH27: 0 | AI27: 0 | AJ27: 0
A28: Total Tax Expense/(Income) | B28: INR Mn | D28: =SUM(D24:D27) | E28: =SUM(E24:E27) | F28: =SUM(F24:F27) | G28: =SUM(G24:G27) | H28: =SUM(H24:H27) | I28: =SUM(I24:I27) | J28: =SUM(J24:J27) | K28: =SUM(K24:K27) | ... W28: =SUM(W24:W27) | AC28: =SUM(AC24:AC27) | AD28: =SUM(AD24:AD27) | AE28: =SUM(AE24:AE27) | AF28: =SUM(AF24:AF27) | AG28: =SUM(AG24:AG27) | AH28: =SUM(AH24:AH27) | AI28: =SUM(AI24:AI27) | AJ28: =SUM(AJ24:AJ27)
A30: Net Profit After Tax | B30: INR Mn | D30: =D21-D28 | E30: =E21-E28 | F30: =F21-F28 | G30: =G21-G28 | H30: =H21-H28 | I30: =I21-I28 | J30: =J21-J28 | K30: =K21-K28 | ... W30: =W21-W28 | AC30: =AC21-AC28 | AD30: =AD21-AD28 | AE30: =AE21-AE28 | AF30: =AF21-AF28 | AG30: =AG21-AG28 | AH30: =AH21-AH28 | AI30: =AI21-AI28 | AJ30: =AJ21-AJ28
A31: Share in profit/(loss) of associate | B31: INR Mn | C31: Company filings | D31: 0 | E31: 0 | F31: 0 | G31: 0 | H31: -6.77 | I31: -4.64 | J31: -7.19 | K31: -20 | L31: -10.31 | M31: -14.89 | N31: -7.8 | O31: -6.66 | P31: -6 | Q31: -4.7 | R31: -5.6 | S31: 0 | T31: 0 | U31: 0 | V31: 0 | W31: 0 | AC31: 0 | AD31: 0 | AE31: 0 | AF31: 0 | AG31: -38.6 | AH31: -39.67 | AI31: -16.3 | AJ31: 0
A32: Net Profit/(Loss) for the Period | B32: INR Mn | D32: =D30+D31 | E32: =E30+E31 | F32: =F30+F31 | G32: =G30+G31 | H32: =H30+H31 | I32: =I30+I31 | J32: =J30+J31 | K32: =K30+K31 | ... W32: =W30+W31 | AC32: =AC30+AC31 | AD32: =AD30+AD31 | AE32: =AE30+AE31 | AF32: =AF30+AF31 | AG32: =AG30+AG31 | AH32: =AH30+AH31 | AI32: =AI30+AI31 | AJ32: =AJ30+AJ31
A34: Attributable to:
A35: Equity shareholders of parent | B35: INR Mn | C35: Company filings | D35: 34.15 | E35: 11.7 | F35: 279.3 | G35: 85.6 | H35: 45.5 | I35: 41.08 | J35: 81.93 | K35: 24.11 | L35: 33.03 | M35: 58.46 | N35: 161.86 | O35: 69.31 | P35: 96.4 | Q35: 100.4 | R35: 261.2 | S35: 202.8 | T35: 233.2 | U35: 344.3 | V35: 633.1 | W35: 783.8 | AC35: -245.18 | AD35: -166.09 | AE35: 618.48 | AF35: 410.75 | AG35: 192.62 | AH35: 322.65 | AI35: 660.8 | AJ35: 1994.4
A36: Non-controlling interests | B36: INR Mn | C36: Company filings | D36: 1.07 | E36: 0.02 | F36: 10.85 | G36: -9.81 | H36: 4.6 | I36: 10.83 | J36: 2.92 | K36: -1.36 | L36: 21.22 | M36: 19.54 | N36: 12.68 | O36: 21.4 | P36: 40 | Q36: 29.3 | R36: 2.9 | S36: -12.3 | T36: 11.5 | U36: -14.5 | V36: 44.3 | W36: 3.7 | AC36: -0.21 | AD36: 2.69 | AE36: 0.97 | AF36: 2.13 | AG36: 16.99 | AH36: 74.84 | AI36: 59.9 | AJ36: 45
A38: Total Other Comprehensive Income/(Loss), net of tax | B38: INR Mn | C38: Company filings | P38: 0 | Q38: -20.2 | R38: -1.3 | S38: -21.6 | T38: 1.2 | U38: 22.5 | V38: 4.8 | W38: 23.5 | AC38: 2.51 | AD38: 1.09 | AE38: -21.8 | AF38: 5.56 | AG38: 1.57 | AH38: 4.43 | AI38: -43.1 | AJ38: 52 | AL38: =SUM(D38:G38)-AF38 | AM38: =SUM(H38:K38)-AG38 | AN38: =SUM(L38:O38)-AH38
A39: Total Comprehensive Income/(Loss) | B39: INR Mn | D39: =D32+D38 | E39: =E32+E38 | F39: =F32+F38 | G39: =G32+G38 | H39: =H32+H38 | I39: =I32+I38 | J39: =J32+J38 | K39: =K32+K38 | ... W39: =W32+W38 | AC39: =AC32+AC38 | AD39: =AD32+AD38 | AE39: =AE32+AE38 | AF39: =AF32+AF38 | AG39: =AG32+AG38 | AH39: =AH32+AH38 | AI39: =AI32+AI38 | AJ39: =AJ32+AJ38 | AL39: =SUM(D39:G39)-AF39 | AM39: =SUM(H39:K39)-AG39 | AN39: =SUM(L39:O39)-AH39
A41: Basic EPS | B41: INR | C41: Company filings | D41: 0.08 | E41: 0.03 | F41: 0.6 | G41: 0.18 | H41: 0 | I41: 0.01 | J41: 0.03 | K41: 0.01 | L41: 0.02 | M41: 0.02 | N41: 0.06 | O41: 0.02 | P41: 0.03 | Q41: 0.04 | R41: 0.09 | S41: 0.07 | T41: 0.08 | U41: 0.12 | V41: 0.22 | W41: 0.27 | AC41: -17.7 | AD41: -11.63 | AE41: 41.66 | AF41: 0.88 | AG41: 0.07 | AH41: 0.11 | AI41: 0.23 | AJ41: 0.7
A42: Diluted EPS | B42: INR | C42: Company filings | D42: 0.07 | E42: 0.03 | F42: 0.6 | G42: 0.18 | H42: 0 | I42: 0.01 | J42: 0.03 | K42: 0.01 | L42: 0.02 | M42: 0.02 | N42: 0.06 | O42: 0.02 | P42: 0.03 | Q42: 0.04 | R42: 0.09 | S42: 0.07 | T42: 0.08 | U42: 0.12 | V42: 0.22 | W42: 0.27 | AC42: -17.7 | AD42: -11.63 | AE42: 40.07 | AF42: 0.87 | AG42: 0.07 | AH42: 0.11 | AI42: 0.23 | AJ42: 0.7
A43: Note: FY19-FY21 EPS computed on face value of Rs 10/share (Restated Ind AS statements, RHP); face value changed to Re 1/share from FY22 following share sub-division. Not directly comparable across the break.
A46: BALANCE SHEET (CONSOLIDATED)
A47: ASSETS
A48: Non-current assets
A49: Property, plant and equipment | B49: INR Mn | C49: Company filings | G49: 1244.42 | I49: 1713.47 | K49: 2313.46 | M49: 2315.23 | O49: 2357.72 | Q49: 2351.5 | S49: 2717.2 | U49: 2712.6 | W49: 2999.7 | AC49: 429.05 | AD49: 701.49 | AE49: 686.52 | AF49: 1244.42 | AG49: 2313.46 | AH49: 2357.72 | AI49: 2717.2 | AJ49: 2999.7
A50: Capital work-in-progress | B50: INR Mn | C50: Company filings | G50: 97.64 | I50: 108.64 | K50: 20.22 | M50: 8.52 | O50: 60.77 | Q50: 20.6 | S50: 31.7 | U50: 46.9 | W50: 92.5 | AC50: 3.2 | AD50: 7.78 | AE50: 19.69 | AF50: 97.64 | AG50: 20.22 | AH50: 60.77 | AI50: 31.7 | AJ50: 92.5
A51: Goodwill | B51: INR Mn | C51: Company filings | G51: 474.78 | I51: 789.04 | K51: 610.65 | M51: 610.65 | O51: 610.65 | Q51: 610.7 | S51: 975 | U51: 975.1 | W51: 975 | AC51: 1.43 | AD51: 1.43 | AE51: 5.43 | AF51: 474.78 | AG51: 610.65 | AH51: 610.65 | AI51: 975 | AJ51: 975
A52: Other intangible assets | B52: INR Mn | C52: Company filings | G52: 640.05 | I52: 664.77 | K52: 944.85 | M52: 1009.09 | O52: 1104.67 | Q52: 1063.9 | S52: 1357.4 | U52: 1244.3 | W52: 1490.1 | AC52: 106.03 | AD52: 127.45 | AE52: 230.34 | AF52: 640.05 | AG52: 944.85 | AH52: 1104.67 | AI52: 1357.4 | AJ52: 1490.1
A53: Right of use assets | B53: INR Mn | C53: Company filings | G53: 2473.26 | I53: 4069.36 | K53: 3119.21 | M53: 2768.35 | O53: 2608.54 | Q53: 2786.2 | S53: 3298.6 | U53: 3865.4 | W53: 4614.7 | AC53: 859.31 | AD53: 1439.94 | AE53: 1389.34 | AF53: 2473.26 | AG53: 3119.21 | AH53: 2608.54 | AI53: 3298.6 | AJ53: 4614.7
A54: Intangible assets under development | B54: INR Mn | C54: Company filings | G54: 147.31 | I54: 246.38 | K54: 288.56 | M54: 254.59 | O54: 236.99 | Q54: 328.7 | S54: 335.7 | U54: 402.2 | W54: 0 | AC54: 0 | AD54: 12.45 | AE54: 3.88 | AF54: 147.31 | AG54: 288.56 | AH54: 236.99 | AI54: 335.7 | AJ54: 0
A55: Investments accounted for using equity method | B55: INR Mn | C55: Company filings | G55: 0 | I55: 0 | K55: 0 | M55: 0 | O55: 338.23 | Q55: 327.6 | S55: 0 | U55: 0 | W55: 0 | AC55: 0 | AD55: 0 | AE55: 0 | AF55: 0 | AG55: 0 | AH55: 338.23 | AI55: 0 | AJ55: 0
A56: Financial assets - Investments | B56: INR Mn | C56: Company filings | G56: 0 | I56: 405.08 | K56: 381.2 | M56: 356 | O56: 4.88 | Q56: 4.9 | S56: 1.6 | U56: 1.6 | W56: 1.6 | AC56: 32.3 | AD56: 38.03 | AE56: 13.19 | AF56: 0 | AG56: 381.2 | AH56: 4.88 | AI56: 1.6 | AJ56: 1.6
A57: Financial assets - Loans | B57: INR Mn | C57: Company filings | G57: 0 | I57: 0 | K57: 0 | M57: 0 | O57: 0 | Q57: 0 | S57: 0 | U57: 0 | W57: 0 | AC57: 56.31 | AD57: 105.84 | AE57: 161.79 | AF57: 0 | AG57: 0 | AH57: 0 | AI57: 0 | AJ57: 0
A58: Financial assets - Other financial assets | B58: INR Mn | C58: Company filings | G58: 718.79 | I58: 889.82 | K58: 434.5 | M58: 417.87 | O58: 492.36 | Q58: 1153.7 | S58: 986.8 | U58: 593.9 | W58: 685.2 | AC58: 0 | AD58: 0 | AE58: 0 | AF58: 718.79 | AG58: 434.5 | AH58: 492.36 | AI58: 986.8 | AJ58: 685.2
A59: Deferred tax assets (net) | B59: INR Mn | C59: Company filings | G59: 1152.18 | I59: 1424.09 | K59: 1877.73 | M59: 2258.39 | O59: 2689.91 | Q59: 3173.5 | S59: 2579.5 | U59: 2550.5 | W59: 2687.8 | AC59: 501.48 | AD59: 506.11 | AE59: 780.41 | AF59: 1152.18 | AG59: 1877.73 | AH59: 2689.91 | AI59: 2579.5 | AJ59: 2687.8
A60: Non-current tax assets (net) | B60: INR Mn | C60: Company filings | G60: 138.7 | I60: 187.28 | K60: 211.82 | M60: 352.36 | O60: 456.72 | Q60: 22.8 | S60: 639.5 | U60: 844.4 | W60: 622.6 | AC60: 110.46 | AD60: 110.45 | AE60: 85.63 | AF60: 138.7 | AG60: 211.82 | AH60: 456.72 | AI60: 639.5 | AJ60: 622.6
A61: Other non-current assets | B61: INR Mn | C61: Company filings | G61: 102.69 | I61: 235.41 | K61: 241.6 | M61: 191.36 | O61: 115.36 | Q61: 82.9 | S61: 101.5 | U61: 51.8 | W61: 55.2 | AC61: 16.73 | AD61: 38.91 | AE61: 13.53 | AF61: 102.69 | AG61: 241.6 | AH61: 115.36 | AI61: 101.5 | AJ61: 55.2
A62: Total Non-Current Assets | B62: INR Mn | G62: =SUM(G49:G61) | I62: =SUM(I49:I61) | K62: =SUM(K49:K61) | M62: =SUM(M49:M61) | O62: =SUM(O49:O61) | Q62: =SUM(Q49:Q61) | S62: =SUM(S49:S61) | U62: =SUM(U49:U61) | W62: =SUM(W49:W61) | AC62: =SUM(AC49:AC61) | AD62: =SUM(AD49:AD61) | AE62: =SUM(AE49:AE61) | AF62: =SUM(AF49:AF61) | AG62: =SUM(AG49:AG61) | AH62: =SUM(AH49:AH61) | AI62: =SUM(AI49:AI61) | AJ62: =SUM(AJ49:AJ61)
A64: Current assets
A65: Inventories | B65: INR Mn | C65: Company filings | G65: 8756.21 | I65: 9332.37 | K65: 10051.4 | M65: 10937.07 | O65: 11920.46 | Q65: 14111 | S65: 14175.4 | U65: 15729.2 | W65: 16421.6 | AC65: 2445.96 | AD65: 4453.36 | AE65: 4980.92 | AF65: 8756.21 | AG65: 10051.4 | AH65: 11920.46 | AI65: 14175.4 | AJ65: 16421.6
A66: Financial assets - Investments | B66: INR Mn | C66: Company filings | G66: 0 | I66: 0 | K66: 0 | M66: 0 | O66: 0 | Q66: 0 | S66: 0 | U66: 0 | W66: 0 | AC66: 1350.4 | AD66: 0 | AE66: 0 | AF66: 0 | AG66: 0 | AH66: 0 | AI66: 0 | AJ66: 0
A67: Trade receivables | B67: INR Mn | C67: Company filings | G67: 945.33 | I67: 1263.57 | K67: 1635.31 | M67: 1764.15 | O67: 2416 | Q67: 2547 | S67: 2466.1 | U67: 2588 | W67: 2893.8 | AC67: 579.24 | AD67: 984.32 | AE67: 766.35 | AF67: 945.33 | AG67: 1635.31 | AH67: 2416 | AI67: 2466.1 | AJ67: 2893.8
A68: Cash and cash equivalents | B68: INR Mn | C68: Company filings | G68: 658.9 | I68: 259.14 | K68: 413.76 | M68: 259.63 | O68: 757.77 | Q68: 836.7 | S68: 1249.4 | U68: 1125.7 | W68: 1772 | AC68: 114.1 | AD68: 1011.91 | AE68: 835.82 | AF68: 658.9 | AG68: 413.76 | AH68: 757.77 | AI68: 1249.4 | AJ68: 1772
A69: Bank balance other than cash and cash equivalents | B69: INR Mn | C69: Company filings | G69: 2011.53 | I69: 1353.82 | K69: 1073.64 | M69: 1193.95 | O69: 1640.81 | Q69: 1110.9 | S69: 922.1 | U69: 1011 | W69: 1428.3 | AC69: 5.34 | AD69: 744.28 | AE69: 1640.88 | AF69: 2011.53 | AG69: 1073.64 | AH69: 1640.81 | AI69: 922.1 | AJ69: 1428.3
A70: Financial assets - Loans | B70: INR Mn | C70: Company filings | G70: 0 | I70: 0 | K70: 0 | M70: 0 | O70: 0 | Q70: 0 | S70: 0 | U70: 0 | W70: 0 | AC70: 48.19 | AD70: 74.11 | AE70: 54.26 | AF70: 0 | AG70: 0 | AH70: 0 | AI70: 0 | AJ70: 0
A71: Other financial assets (current) | B71: INR Mn | C71: Company filings | G71: 4878.78 | I71: 2552.45 | K71: 2644.86 | M71: 2723.34 | O71: 1833.22 | Q71: 1729.5 | S71: 2693 | U71: 3192.8 | W71: 3122.5 | AC71: 466.83 | AD71: 258.99 | AE71: 520.12 | AF71: 4878.78 | AG71: 2644.86 | AH71: 1833.22 | AI71: 2693 | AJ71: 3122.5
A72: Other current assets | B72: INR Mn | C72: Company filings | G72: 2019.78 | I72: 3369.24 | K72: 3237.01 | M72: 3938.04 | O72: 4361.2 | Q72: 4972.1 | S72: 5264.8 | U72: 6388.6 | W72: 6251.2 | AC72: 630.21 | AD72: 627.97 | AE72: 831.8 | AF72: 2019.78 | AG72: 3237.01 | AH72: 4361.2 | AI72: 5264.8 | AJ72: 6251.2
A73: Total Current Assets | B73: INR Mn | G73: =SUM(G65:G72) | I73: =SUM(I65:I72) | K73: =SUM(K65:K72) | M73: =SUM(M65:M72) | O73: =SUM(O65:O72) | Q73: =SUM(Q65:Q72) | S73: =SUM(S65:S72) | U73: =SUM(U65:U72) | W73: =SUM(W65:W72) | AC73: =SUM(AC65:AC72) | AD73: =SUM(AD65:AD72) | AE73: =SUM(AE65:AE72) | AF73: =SUM(AF65:AF72) | AG73: =SUM(AG65:AG72) | AH73: =SUM(AH65:AH72) | AI73: =SUM(AI65:AI72) | AJ73: =SUM(AJ65:AJ72)
A75: TOTAL ASSETS | B75: INR Mn | G75: =G62+G73 | I75: =I62+I73 | K75: =K62+K73 | M75: =M62+M73 | O75: =O62+O73 | Q75: =Q62+Q73 | S75: =S62+S73 | U75: =U62+U73 | W75: =W62+W73 | AC75: =AC62+AC73 | AD75: =AD62+AD73 | AE75: =AE62+AE73 | AF75: =AF62+AF73 | AG75: =AG62+AG73 | AH75: =AH62+AH73 | AI75: =AI62+AI73 | AJ75: =AJ62+AJ73
A77: EQUITY AND LIABILITIES
A78: Equity
A79: Equity share capital | B79: INR Mn | C79: Company filings | G79: 474.11 | I79: 474.55 | K79: 2852.45 | M79: 2853.73 | O79: 2855.99 | Q79: 2857.9 | S79: 2859.3 | U79: 2861.3 | W79: 2863.3 | AC79: 142.43 | AD79: 145.5 | AE79: 150.58 | AF79: 474.11 | AG79: 2852.45 | AH79: 2855.99 | AI79: 2859.3 | AJ79: 2863.3
A80: Other equity | B80: INR Mn | C80: Company filings | G80: 12924.89 | I80: 13138.2 | K80: 10927.65 | M80: 11059.05 | O80: 9766.34 | Q80: 10190 | S80: 10153.5 | U80: 11017.2 | W80: 11516.5 | AC80: 2163.15 | AD80: 3075.99 | AE80: 4748.81 | AF80: 12924.89 | AG80: 10927.65 | AH80: 9766.34 | AI80: 10153.5 | AJ80: 11516.5
A81: Equity attributable to equity holders of the parent | B81: INR Mn | G81: =SUM(G79:G80) | I81: =SUM(I79:I80) | K81: =SUM(K79:K80) | M81: =SUM(M79:M80) | O81: =SUM(O79:O80) | Q81: =SUM(Q79:Q80) | S81: =SUM(S79:S80) | U81: =SUM(U79:U80) | W81: =SUM(W79:W80) | AC81: =SUM(AC79:AC80) | AD81: =SUM(AD79:AD80) | AE81: =SUM(AE79:AE80) | AF81: =SUM(AF79:AF80) | AG81: =SUM(AG79:AG80) | AH81: =SUM(AH79:AH80) | AI81: =SUM(AI79:AI80) | AJ81: =SUM(AJ79:AJ80)
A82: Non-controlling interest | B82: INR Mn | C82: Company filings | G82: 56.15 | I82: 95.09 | K82: 141.45 | M82: 182.6 | O82: 188.11 | Q82: 287.8 | S82: 413.8 | U82: 515.8 | W82: 641.2 | AC82: 4.69 | AD82: 7.38 | AE82: 8.36 | AF82: 56.15 | AG82: 141.45 | AH82: 188.11 | AI82: 413.8 | AJ82: 641.2
A83: Total Equity | B83: INR Mn | G83: =G81+G82 | I83: =I81+I82 | K83: =K81+K82 | M83: =M81+M82 | O83: =O81+O82 | Q83: =Q81+Q82 | S83: =S81+S82 | U83: =U81+U82 | W83: =W81+W82 | AC83: =AC81+AC82 | AD83: =AD81+AD82 | AE83: =AE81+AE82 | AF83: =AF81+AF82 | AG83: =AG81+AG82 | AH83: =AH81+AH82 | AI83: =AI81+AI82 | AJ83: =AJ81+AJ82
A85: Non-current liabilities
A86: Borrowings | B86: INR Mn | C86: Company filings | G86: 9.22 | I86: 6.53 | K86: 3.61 | M86: 0.47 | O86: 0 | Q86: 625 | S86: 1102.1 | U86: 327.4 | W86: 183.3 | AC86: 1.28 | AD86: 1.5 | AE86: 16.6 | AF86: 9.22 | AG86: 3.61 | AH86: 0 | AI86: 1102.1 | AJ86: 183.3
A87: Lease liabilities | B87: INR Mn | C87: Company filings | G87: 2043.19 | I87: 3354.12 | K87: 2133.68 | M87: 1766.89 | O87: 1593.03 | Q87: 1665.8 | S87: 2115.5 | U87: 2562 | W87: 2968.5 | AC87: 763.61 | AD87: 1302.58 | AE87: 1073.9 | AF87: 2043.19 | AG87: 2133.68 | AH87: 1593.03 | AI87: 2115.5 | AJ87: 2968.5
A88: Other financial liabilities | B88: INR Mn | C88: Company filings | G88: 1222.26 | I88: 1280.33 | K88: 1373.2 | M88: 0 | O88: 711.85 | Q88: 0 | S88: 1358.8 | U88: 0 | W88: 16.6 | AC88: 0 | AD88: 0 | AE88: 0 | AF88: 1222.26 | AG88: 1373.2 | AH88: 711.85 | AI88: 1358.8 | AJ88: 16.6
A89: Provisions | B89: INR Mn | C89: Company filings | G89: 77.96 | I89: 89.21 | K89: 92.65 | M89: 108.65 | O89: 102.21 | Q89: 145.5 | S89: 186.4 | U89: 187 | W89: 341.9 | AC89: 24.46 | AD89: 52.61 | AE89: 73.45 | AF89: 77.96 | AG89: 92.65 | AH89: 102.21 | AI89: 186.4 | AJ89: 341.9
A90: Total Non-Current Liabilities | B90: INR Mn | G90: =SUM(G86:G89) | I90: =SUM(I86:I89) | K90: =SUM(K86:K89) | M90: =SUM(M86:M89) | O90: =SUM(O86:O89) | Q90: =SUM(Q86:Q89) | S90: =SUM(S86:S89) | U90: =SUM(U86:U89) | W90: =SUM(W86:W89) | AC90: =SUM(AC86:AC89) | AD90: =SUM(AD86:AD89) | AE90: =SUM(AE86:AE89) | AF90: =SUM(AF86:AF89) | AG90: =SUM(AG86:AG89) | AH90: =SUM(AH86:AH89) | AI90: =SUM(AI86:AI89) | AJ90: =SUM(AJ86:AJ89)
A92: Current liabilities
A93: Borrowings | B93: INR Mn | C93: Company filings | G93: 3321.12 | I93: 4862.24 | K93: 4600.01 | M93: 6596.02 | O93: 6803.95 | Q93: 9388.7 | S93: 8511.5 | U93: 9571.1 | W93: 7288.8 | AC93: 2254.48 | AD93: 2673.26 | AE93: 1858.05 | AF93: 3321.12 | AG93: 4600.01 | AH93: 6803.95 | AI93: 8511.5 | AJ93: 7288.8
A94: Lease liabilities | B94: INR Mn | C94: Company filings | G94: 552.7 | I94: 844.52 | K94: 1247.63 | M94: 1293.16 | O94: 1297.89 | Q94: 1383.4 | S94: 1476.8 | U94: 1609.7 | W94: 1937.5 | AC94: 84.63 | AD94: 147.44 | AE94: 378.16 | AF94: 552.7 | AG94: 1247.63 | AH94: 1297.89 | AI94: 1476.8 | AJ94: 1937.5
A95: Trade payables - micro & small enterprises | B95: INR Mn | C95: Company filings | G95: 560.7 | I95: 228.37 | K95: 418.93 | M95: 510.01 | O95: 370.16 | Q95: 423.4 | S95: 452.6 | U95: 762.4 | W95: 1163.4 | AC95: 12.77 | AD95: 104.6 | AE95: 90.75 | AF95: 560.7 | AG95: 418.93 | AH95: 370.16 | AI95: 452.6 | AJ95: 1163.4
A96: Trade payables - other creditors | B96: INR Mn | C96: Company filings | G96: 3059.84 | I96: 1559.62 | K96: 2234.96 | M96: 2367.64 | O96: 3496.76 | Q96: 5040.7 | S96: 5895.7 | U96: 6144.8 | W96: 6161.6 | AC96: 1804.89 | AD96: 3028.05 | AE96: 3071.37 | AF96: 3059.84 | AG96: 2234.96 | AH96: 3496.76 | AI96: 5895.7 | AJ96: 6161.6
A97: Other financial liabilities | B97: INR Mn | C97: Company filings | G97: 1666.92 | I97: 2319.95 | K97: 2703.61 | M97: 3962.46 | O97: 6084.58 | Q97: 4540.9 | S97: 4386.1 | U97: 6755.2 | W97: 9473 | AC97: 275.44 | AD97: 470.53 | AE97: 850.14 | AF97: 1666.92 | AG97: 2703.61 | AH97: 6084.58 | AI97: 4386.1 | AJ97: 9473
A98: Provisions | B98: INR Mn | C98: Company filings | G98: 88.66 | I98: 97.1 | K98: 113.86 | M98: 87.54 | O98: 86.9 | Q98: 113.6 | S98: 101.9 | U98: 123.8 | W98: 268.1 | AC98: 0.37 | AD98: 0.67 | AE98: 108.47 | AF98: 88.66 | AG98: 113.86 | AH98: 86.9 | AI98: 101.9 | AJ98: 268.1
A99: Contract liabilities | B99: INR Mn | C99: Company filings | G99: 160.41 | I99: 258.81 | K99: 234.78 | M99: 249.52 | O99: 273.42 | Q99: 271.7 | S99: 376.1 | U99: 561.8 | W99: 600.7 | AC99: 101.91 | AD99: 148.7 | AE99: 169.15 | AF99: 160.41 | AG99: 234.78 | AH99: 273.42 | AI99: 376.1 | AJ99: 600.7
A100: Current tax liabilities (net) | B100: INR Mn | C100: Company filings | G100: 21.73 | I100: 80.4 | K100: 0 | M100: 0 | O100: 0 | Q100: 299.8 | S100: 0 | U100: 0 | W100: 0 | AC100: 0 | AD100: 2.69 | AE100: 246.94 | AF100: 21.73 | AG100: 0 | AH100: 0 | AI100: 0 | AJ100: 0
A101: Other current liabilities | B101: INR Mn | C101: Company filings | G101: 220.49 | I101: 174.89 | K101: 421.31 | M101: 320.85 | O101: 375.07 | S101: 405.2 | U101: 324.5 | W101: 689.4 | AC101: 122.46 | AD101: 83.32 | AE101: 175.17 | AF101: 220.49 | AG101: 421.31 | AH101: 375.07 | AI101: 405.2 | AJ101: 689.4
A102: Total Current Liabilities | B102: INR Mn | G102: =SUM(G93:G101) | I102: =SUM(I93:I101) | K102: =SUM(K93:K101) | M102: =SUM(M93:M101) | O102: =SUM(O93:O101) | Q102: =SUM(Q93:Q101) | S102: =SUM(S93:S101) | U102: =SUM(U93:U101) | W102: =SUM(W93:W101) | AC102: =SUM(AC93:AC101) | AD102: =SUM(AD93:AD101) | AE102: =SUM(AE93:AE101) | AF102: =SUM(AF93:AF101) | AG102: =SUM(AG93:AG101) | AH102: =SUM(AH93:AH101) | AI102: =SUM(AI93:AI101) | AJ102: =SUM(AJ93:AJ101)
A104: Total Liabilities | B104: INR Mn | G104: =G90+G102 | I104: =I90+I102 | K104: =K90+K102 | M104: =M90+M102 | O104: =O90+O102 | Q104: =Q90+Q102 | S104: =S90+S102 | U104: =U90+U102 | W104: =W90+W102 | AC104: =AC90+AC102 | AD104: =AD90+AD102 | AE104: =AE90+AE102 | AF104: =AF90+AF102 | AG104: =AG90+AG102 | AH104: =AH90+AH102 | AI104: =AI90+AI102 | AJ104: =AJ90+AJ102
A105: TOTAL EQUITY AND LIABILITIES | B105: INR Mn | G105: =G83+G104 | I105: =I83+I104 | K105: =K83+K104 | M105: =M83+M104 | O105: =O83+O104 | Q105: =Q83+Q104 | S105: =S83+S104 | U105: =U83+U104 | W105: =W83+W104 | AC105: =AC83+AC104 | AD105: =AD83+AD104 | AE105: =AE83+AE104 | AF105: =AF83+AF104 | AG105: =AG83+AG104 | AH105: =AH83+AH104 | AI105: =AI83+AI104 | AJ105: =AJ83+AJ104
A106: Check (Total Assets - Total Equity and Liabilities) | B106: INR Mn | G106: =G75-G105 | I106: =I75-I105 | K106: =K75-K105 | M106: =M75-M105 | O106: =O75-O105 | Q106: =Q75-Q105 | S106: =S75-S105 | U106: =U75-U105 | W106: =W75-W105 | AC106: =AC75-AC105 | AD106: =AD75-AD105 | AE106: =AE75-AE105 | AF106: =AF75-AF105 | AG106: =AG75-AG105 | AH106: =AH75-AH105 | AI106: =AI75-AI105 | AJ106: =AJ75-AJ105
A109: CASH FLOW STATEMENT (CONSOLIDATED)
A110: Profit/(loss) before tax (per Statement of Profit and Loss) | B110: INR Mn | C110: Company filings | AC110: -317.2 | AD110: -124.3 | AE110: 753.38 | AF110: 473.06 | AG110: 383.95 | AH110: 690.27 | AI110: 1274.5 | AJ110: 3302.3
A111: Adjustments to reconcile profit before tax to net cash flows
A112: Depreciation of PP&E and right-of-use assets | B112: INR Mn | C112: Company filings | AC112: 308.76 | AD112: 595.09 | AE112: 671.28 | AF112: 835 | AG112: 1559.73 | AH112: 1998.62 | AI112: 2321.2 | AJ112: 2766.1
A113: Amortisation of intangible assets | B113: INR Mn | C113: Company filings | AC113: 0 | AD113: 0 | AE113: 0 | AF113: 129.12 | AG113: 172.81 | AH113: 243.71 | AI113: 342.8 | AJ113: 437.2
A114: Interest expense and other finance costs | B114: INR Mn | C114: Company filings | AC114: 263.42 | AD114: 442.93 | AE114: 307.01 | AF114: 465.11 | AG114: 746.05 | AH114: 828.32 | AI114: 1073.2 | AJ114: 1171.2
A115: Foreign exchange (gain)/loss | B115: INR Mn | C115: Company filings | AC115: 0 | AD115: 0 | AE115: 0 | AF115: 0.65 | AG115: -3.11 | AH115: 6.41 | AI115: 0 | AJ115: -31.9
A116: Realised gain from sale of investments | B116: INR Mn | C116: Company filings | AC116: 0 | AD116: -74.41 | AE116: 0 | AF116: 0 | AG116: 0 | AH116: 0 | AI116: 0 | AJ116: 0
A117: Unrealised gain on fair valuation of investments | B117: INR Mn | C117: Company filings | AC117: -15.28 | AD117: 0 | AE117: 0 | AF117: 0 | AG117: 0 | AH117: 0 | AI117: 0 | AJ117: 0
...

Sheet Raw Data - Ops KPIs
A3: All figures in INR Mn unless stated otherwise.
A5: Metric | B5: Unit | C5: Source - Deck section | D5: Q1FY22 | E5: Q2FY22 | F5: Q3FY22 | G5: Q4FY22 | H5: Q1FY23 | I5: Q2FY23 | J5: Q3FY23 | K5: Q4FY23 | L5: Q1FY24 | M5: Q2FY24 | N5: Q3FY24 | O5: Q4FY24 | P5: Q1FY25 | Q5: Q2FY25 | R5: Q3FY25 | S5: Q4FY25 | T5: Q1FY26 | U5: Q2FY26 | V5: Q3FY26 | W5: Q4FY26 | X5: Q1FY27 | Y5: Q2FY27 | Z5: Q3FY27 | AA5: Q4FY27 | AF5: FY22 | AG5: FY23 | AH5: FY24 | AI5: FY25 | AJ5: FY26
A6: Consolidated Operating KPIs
A7: Number of visits | B7: mn | C7: One Nykaa Highlights | D7: 312.4 | E7: 335 | F7: 347 | G7: 328 | H7: 354 | I7: 372 | J7: 403 | K7: 369 | L7: 395 | M7: 430 | N7: 468 | O7: 447 | AF7: =IF(COUNT(D7:G7)=0,"",SUM(D7:G7)) | AG7: =IF(COUNT(H7:K7)=0,"",SUM(H7:K7)) | AH7: =IF(COUNT(L7:O7)=0,"",SUM(L7:O7)) | AI7: =IF(COUNT(P7:S7)=0,"",SUM(P7:S7)) | AJ7: =IF(COUNT(T7:W7)=0,"",SUM(T7:W7))
A8: Annual transacting customers | B8: mn | C8: One Nykaa Highlights | D8: 7.7 | E8: 8.6 | F8: 9.4 | G8: 10.2 | H8: 11 | I8: 11.7 | J8: 12.5 | K8: 13 | L8: 13.5 | M8: 14 | N8: 14.6 | O8: 15.4 | AF8: =IF(G8="","",G8) | AG8: =IF(K8="","",K8) | AH8: =IF(O8="","",O8) | AI8: =IF(S8="","",S8) | AJ8: =IF(W8="","",W8)
A9: YoY growth | B9: % | H9: =IFERROR(H8/D8-1,"") | I9: =IFERROR(I8/E8-1,"") | J9: =IFERROR(J8/F8-1,"") | K9: =IFERROR(K8/G8-1,"") | L9: =IFERROR(L8/H8-1,"") | M9: =IFERROR(M8/I8-1,"") | N9: =IFERROR(N8/J8-1,"") | O9: =IFERROR(O8/K8-1,"") | ... AA9: =IFERROR(AA8/W8-1,"") | AF9: =IFERROR(AF8/AE8-1,"") | AG9: =IFERROR(AG8/AF8-1,"") | AH9: =IFERROR(AH8/AG8-1,"") | AI9: =IFERROR(AI8/AH8-1,"") | AJ9: =IFERROR(AJ8/AI8-1,"")
A10: Number of orders | B10: mn | C10: One Nykaa Highlights | D10: 7 | E10: 7.4 | F10: 9 | G10: 8.7 | H10: 9.9 | I10: 10.1 | J10: 11.6 | K10: 10.6 | L10: 11.4 | M10: 12.2 | N10: 13.7 | O10: 13.4 | AF10: =IF(COUNT(D10:G10)=0,"",SUM(D10:G10)) | AG10: =IF(COUNT(H10:K10)=0,"",SUM(H10:K10)) | AH10: =IF(COUNT(L10:O10)=0,"",SUM(L10:O10)) | AI10: =IF(COUNT(P10:S10)=0,"",SUM(P10:S10)) | AJ10: =IF(COUNT(T10:W10)=0,"",SUM(T10:W10))
A11: Total GMV | B11: Rs Mn | C11: One Nykaa Highlights | D11: 14696 | E11: 16229 | F11: 20428 | G11: 17979 | H11: 21588 | I11: 23457 | J11: 27965 | K11: 24454 | L11: 26678 | M11: 29435 | N11: 36195 | O11: 32163 | P11: 33209 | Q11: 36525 | R11: 45279 | S11: 41020 | T11: 41820 | U11: 47440 | V11: 57950 | W11: 52410 | AF11: =IF(COUNT(D11:G11)=0,"",SUM(D11:G11)) | AG11: =IF(COUNT(H11:K11)=0,"",SUM(H11:K11)) | AH11: =IF(COUNT(L11:O11)=0,"",SUM(L11:O11)) | AI11: =IF(COUNT(P11:S11)=0,"",SUM(P11:S11)) | AJ11: =IF(COUNT(T11:W11)=0,"",SUM(T11:W11))
A12: YoY growth | B12: % | H12: =IFERROR(H11/D11-1,"") | I12: =IFERROR(I11/E11-1,"") | J12: =IFERROR(J11/F11-1,"") | K12: =IFERROR(K11/G11-1,"") | L12: =IFERROR(L11/H11-1,"") | M12: =IFERROR(M11/I11-1,"") | N12: =IFERROR(N11/J11-1,"") | O12: =IFERROR(O11/K11-1,"") | ... AA12: =IFERROR(AA11/W11-1,"") | AF12: =IFERROR(AF11/AE11-1,"") | AG12: =IFERROR(AG11/AF11-1,"") | AH12: =IFERROR(AH11/AG11-1,"") | AI12: =IFERROR(AI11/AH11-1,"") | AJ12: =IFERROR(AJ11/AI11-1,"")
A13: QoQ growth | B13: % | E13: =IFERROR(E11/D11-1,"") | F13: =IFERROR(F11/E11-1,"") | G13: =IFERROR(G11/F11-1,"") | H13: =IFERROR(H11/G11-1,"") | I13: =IFERROR(I11/H11-1,"") | J13: =IFERROR(J11/I11-1,"") | K13: =IFERROR(K11/J11-1,"") | L13: =IFERROR(L11/K11-1,"") | ... AA13: =IFERROR(AA11/Z11-1,"")
A14: Total NSV | B14: Rs Mn | C14: One Nykaa Highlights | D14: 8050 | E14: 8688 | F14: 10729 | G14: 9650 | H14: 11272 | I14: 12049 | J14: 14401 | K14: 12904 | L14: 14205 | M14: 14982 | N14: 17866 | O14: 16489 | P14: 17183 | Q14: 18432 | R14: 22190 | S14: 20430 | T14: 21370 | U14: 23400 | V14: 28440 | W14: 26780 | AF14: =IF(COUNT(D14:G14)=0,"",SUM(D14:G14)) | AG14: =IF(COUNT(H14:K14)=0,"",SUM(H14:K14)) | AH14: =IF(COUNT(L14:O14)=0,"",SUM(L14:O14)) | AI14: =IF(COUNT(P14:S14)=0,"",SUM(P14:S14)) | AJ14: =IF(COUNT(T14:W14)=0,"",SUM(T14:W14))
A15: NSV / GMV | B15: % | D15: =IFERROR(D14/D11,"") | E15: =IFERROR(E14/E11,"") | F15: =IFERROR(F14/F11,"") | G15: =IFERROR(G14/G11,"") | H15: =IFERROR(H14/H11,"") | I15: =IFERROR(I14/I11,"") | J15: =IFERROR(J14/J11,"") | K15: =IFERROR(K14/K11,"") | ... AA15: =IFERROR(AA14/AA11,"") | AF15: =IFERROR(AF14/AF11,"") | AG15: =IFERROR(AG14/AG11,"") | AH15: =IFERROR(AH14/AH11,"") | AI15: =IFERROR(AI14/AI11,"") | AJ15: =IFERROR(AJ14/AJ11,"")
A16: Total Revenue | B16: Rs Mn | C16: One Nykaa Highlights / Financial Performance | D16: 8169.91 | E16: 8852.64 | F16: 10983.6 | G16: 9733.2 | H16: 11484.21 | I16: 12308.29 | J16: 14628.26 | K16: 13017.24 | L16: 14218.24 | M16: 15070.24 | N16: 17887.98 | O16: 16679.8 | P16: 17461.1 | Q16: 18747.4 | R16: 22672.1 | S16: 20617.6 | T16: 21549.4 | U16: 23459.8 | V16: 28732.6 | W16: 26480 | AF16: =IF(COUNT(D16:G16)=0,"",SUM(D16:G16)) | AG16: =IF(COUNT(H16:K16)=0,"",SUM(H16:K16)) | AH16: =IF(COUNT(L16:O16)=0,"",SUM(L16:O16)) | AI16: =IF(COUNT(P16:S16)=0,"",SUM(P16:S16)) | AJ16: =IF(COUNT(T16:W16)=0,"",SUM(T16:W16))
A17: YoY growth | B17: % | H17: =IFERROR(H16/D16-1,"") | I17: =IFERROR(I16/E16-1,"") | J17: =IFERROR(J16/F16-1,"") | K17: =IFERROR(K16/G16-1,"") | L17: =IFERROR(L16/H16-1,"") | M17: =IFERROR(M16/I16-1,"") | N17: =IFERROR(N16/J16-1,"") | O17: =IFERROR(O16/K16-1,"") | ... AA17: =IFERROR(AA16/W16-1,"") | AF17: =IFERROR(AF16/AE16-1,"") | AG17: =IFERROR(AG16/AF16-1,"") | AH17: =IFERROR(AH16/AG16-1,"") | AI17: =IFERROR(AI16/AH16-1,"") | AJ17: =IFERROR(AJ16/AI16-1,"")
A18: Revenue / NSV | B18: % | D18: =IFERROR(D16/D14,"") | E18: =IFERROR(E16/E14,"") | F18: =IFERROR(F16/F14,"") | G18: =IFERROR(G16/G14,"") | H18: =IFERROR(H16/H14,"") | I18: =IFERROR(I16/I14,"") | J18: =IFERROR(J16/J14,"") | K18: =IFERROR(K16/K14,"") | ... AA18: =IFERROR(AA16/AA14,"") | AF18: =IFERROR(AF16/AF14,"") | AG18: =IFERROR(AG16/AG14,"") | AH18: =IFERROR(AH16/AH14,"") | AI18: =IFERROR(AI16/AI14,"") | AJ18: =IFERROR(AJ16/AJ14,"")
A19: Gross profit | B19: Rs Mn | C19: Financial Performance (Total column) | D19: 3316.59 | E19: 3782.42 | F19: 5087.58 | G19: 4252.61 | H19: 5098.79 | I19: 5577.38 | J19: 6346.7 | K19: 5758.32 | L19: 6186.25 | M19: 6496.24 | N19: 7607.48 | O19: 7102.43 | P19: 7559.8 | Q19: 8210.2 | R19: 9911.4 | S19: 9090.2 | T19: 9615.1 | U19: 10535.4 | V19: 12974.8 | W19: 12030 | AF19: =IF(COUNT(D19:G19)=0,"",SUM(D19:G19)) | AG19: =IF(COUNT(H19:K19)=0,"",SUM(H19:K19)) | AH19: =IF(COUNT(L19:O19)=0,"",SUM(L19:O19)) | AI19: =IF(COUNT(P19:S19)=0,"",SUM(P19:S19)) | AJ19: =IF(COUNT(T19:W19)=0,"",SUM(T19:W19))
A20: Gross margin (% of NSV) | B20: % | D20: =IFERROR(D19/D14,"") | E20: =IFERROR(E19/E14,"") | F20: =IFERROR(F19/F14,"") | G20: =IFERROR(G19/G14,"") | H20: =IFERROR(H19/H14,"") | I20: =IFERROR(I19/I14,"") | J20: =IFERROR(J19/J14,"") | K20: =IFERROR(K19/K14,"") | ... AA20: =IFERROR(AA19/AA14,"") | AF20: =IFERROR(AF19/AF14,"") | AG20: =IFERROR(AG19/AG14,"") | AH20: =IFERROR(AH19/AH14,"") | AI20: =IFERROR(AI19/AI14,"") | AJ20: =IFERROR(AJ19/AJ14,"")
A21: Fulfilment cost | B21: Rs Mn | C21: Financial Performance (Total column) | D21: 934 | E21: 910 | F21: 1162 | G21: 949 | H21: 1294 | I21: 1454 | J21: 1288 | K21: 1286 | L21: 1357 | M21: 1459 | N21: 1718 | O21: 1550 | P21: 1667 | Q21: 1748 | R21: 2090 | S21: 1920 | T21: 2030 | U21: 2270 | V21: 2690 | W21: 2600 | AF21: =IF(COUNT(D21:G21)=0,"",SUM(D21:G21)) | AG21: =IF(COUNT(H21:K21)=0,"",SUM(H21:K21)) | AH21: =IF(COUNT(L21:O21)=0,"",SUM(L21:O21)) | AI21: =IF(COUNT(P21:S21)=0,"",SUM(P21:S21)) | AJ21: =IF(COUNT(T21:W21)=0,"",SUM(T21:W21))
A22: Marketing & S&D expense (combined) | B22: Rs Mn | C22: Financial Performance (Total column) | D22: 1099 | E22: 1521 | F22: 1846 | G22: 1561 | H22: 1524 | I22: 1635 | J22: 1982 | K22: 1670 | L22: 1919 | M22: 2036 | N22: 2558 | O22: 2361 | P22: 2483 | Q22: 2767 | R22: 3620 | S22: 3160 | T22: 3180 | U22: 3560 | V22: 4380 | W22: 3740 | AF22: =IF(COUNT(D22:G22)=0,"",SUM(D22:G22)) | AG22: =IF(COUNT(H22:K22)=0,"",SUM(H22:K22)) | AH22: =IF(COUNT(L22:O22)=0,"",SUM(L22:O22)) | AI22: =IF(COUNT(P22:S22)=0,"",SUM(P22:S22)) | AJ22: =IF(COUNT(T22:W22)=0,"",SUM(T22:W22))
A23: Contribution profit | B23: Rs Mn | D23: =IF(OR(ISBLANK(D19),ISBLANK(D21),ISBLANK(D22)),"",IFERROR(D19-D21-D22,"")) | E23: =IF(OR(ISBLANK(E19),ISBLANK(E21),ISBLANK(E22)),"",IFERROR(E19-E21-E22,"")) | F23: =IF(OR(ISBLANK(F19),ISBLANK(F21),ISBLANK(F22)),"",IFERROR(F19-F21-F22,"")) | G23: =IF(OR(ISBLANK(G19),ISBLANK(G21),ISBLANK(G22)),"",IFERROR(G19-G21-G22,"")) | H23: =IF(OR(ISBLANK(H19),ISBLANK(H21),ISBLANK(H22)),"",IFERROR(H19-H21-H22,"")) | I23: =IF(OR(ISBLANK(I19),ISBLANK(I21),ISBLANK(I22)),"",IFERROR(I19-I21-I22,"")) | J23: =IF(OR(ISBLANK(J19),ISBLANK(J21),ISBLANK(J22)),"",IFERROR(J19-J21-J22,"")) | K23: =IF(OR(ISBLANK(K19),ISBLANK(K21),ISBLANK(K22)),"",IFERROR(K19-K21-K22,"")) | ... AA23: =IF(OR(ISBLANK(AA19),ISBLANK(AA21),ISBLANK(AA22)),"",IFERROR(AA19-AA21-AA22,"")) | AF23: =IF(OR(ISBLANK(AF19),ISBLANK(AF21),ISBLANK(AF22)),"",IFERROR(AF19-AF21-AF22,"")) | AG23: =IF(OR(ISBLANK(AG19),ISBLANK(AG21),ISBLANK(AG22)),"",IFERROR(AG19-AG21-AG22,"")) | AH23: =IF(OR(ISBLANK(AH19),ISBLANK(AH21),ISBLANK(AH22)),"",IFERROR(AH19-AH21-AH22,"")) | AI23: =IF(OR(ISBLANK(AI19),ISBLANK(AI21),ISBLANK(AI22)),"",IFERROR(AI19-AI21-AI22,"")) | AJ23: =IF(OR(ISBLANK(AJ19),ISBLANK(AJ21),ISBLANK(AJ22)),"",IFERROR(AJ19-AJ21-AJ22,""))
A24: Contribution margin (% of NSV) | B24: % | D24: =IFERROR(D23/D14,"") | E24: =IFERROR(E23/E14,"") | F24: =IFERROR(F23/F14,"") | G24: =IFERROR(G23/G14,"") | H24: =IFERROR(H23/H14,"") | I24: =IFERROR(I23/I14,"") | J24: =IFERROR(J23/J14,"") | K24: =IFERROR(K23/K14,"") | ... AA24: =IFERROR(AA23/AA14,"") | AF24: =IFERROR(AF23/AF14,"") | AG24: =IFERROR(AG23/AG14,"") | AH24: =IFERROR(AH23/AH14,"") | AI24: =IFERROR(AI23/AI14,"") | AJ24: =IFERROR(AJ23/AJ14,"")
A25: Other expenses (G&A + employee) | B25: Rs Mn | C25: Financial Performance (Total column) | D25: 1014.15 | E25: 1063.18 | F25: 1735.81 | G25: 1357 | H25: 1820.27 | I25: 1877.01 | J25: 2295.1 | K25: 2095.38 | L25: 2175.59 | M25: 2194.95 | N25: 2343.74 | O25: 2258.61 | P25: 2448.6 | Q25: 2658.6 | R25: 2793.6 | S25: 2676.7 | T25: 2898.3 | U25: 2995.9 | V25: 3387.2 | W25: 3470 | AF25: =IF(COUNT(D25:G25)=0,"",SUM(D25:G25)) | AG25: =IF(COUNT(H25:K25)=0,"",SUM(H25:K25)) | AH25: =IF(COUNT(L25:O25)=0,"",SUM(L25:O25)) | AI25: =IF(COUNT(P25:S25)=0,"",SUM(P25:S25)) | AJ25: =IF(COUNT(T25:W25)=0,"",SUM(T25:W25))
A26: EBITDA | B26: Rs Mn | D26: =IF(OR(ISBLANK(D23),ISBLANK(D25)),"",IFERROR(D23-D25,"")) | E26: =IF(OR(ISBLANK(E23),ISBLANK(E25)),"",IFERROR(E23-E25,"")) | F26: =IF(OR(ISBLANK(F23),ISBLANK(F25)),"",IFERROR(F23-F25,"")) | G26: =IF(OR(ISBLANK(G23),ISBLANK(G25)),"",IFERROR(G23-G25,"")) | H26: =IF(OR(ISBLANK(H23),ISBLANK(H25)),"",IFERROR(H23-H25,"")) | I26: =IF(OR(ISBLANK(I23),ISBLANK(I25)),"",IFERROR(I23-I25,"")) | J26: =IF(OR(ISBLANK(J23),ISBLANK(J25)),"",IFERROR(J23-J25,"")) | K26: =IF(OR(ISBLANK(K23),ISBLANK(K25)),"",IFERROR(K23-K25,"")) | ... AA26: =IF(OR(ISBLANK(AA23),ISBLANK(AA25)),"",IFERROR(AA23-AA25,"")) | AF26: =IF(OR(ISBLANK(AF23),ISBLANK(AF25)),"",IFERROR(AF23-AF25,"")) | AG26: =IF(OR(ISBLANK(AG23),ISBLANK(AG25)),"",IFERROR(AG23-AG25,"")) | AH26: =IF(OR(ISBLANK(AH23),ISBLANK(AH25)),"",IFERROR(AH23-AH25,"")) | AI26: =IF(OR(ISBLANK(AI23),ISBLANK(AI25)),"",IFERROR(AI23-AI25,"")) | AJ26: =IF(OR(ISBLANK(AJ23),ISBLANK(AJ25)),"",IFERROR(AJ23-AJ25,""))
A27: EBITDA margin (% of NSV) | B27: % | D27: =IFERROR(D26/D14,"") | E27: =IFERROR(E26/E14,"") | F27: =IFERROR(F26/F14,"") | G27: =IFERROR(G26/G14,"") | H27: =IFERROR(H26/H14,"") | I27: =IFERROR(I26/I14,"") | J27: =IFERROR(J26/J14,"") | K27: =IFERROR(K26/K14,"") | ... AA27: =IFERROR(AA26/AA14,"") | AF27: =IFERROR(AF26/AF14,"") | AG27: =IFERROR(AG26/AG14,"") | AH27: =IFERROR(AH26/AH14,"") | AI27: =IFERROR(AI26/AI14,"") | AJ27: =IFERROR(AJ26/AJ14,"")
A29: Beauty (incl. SuperStore) - Omnichannel Retail
A30: Definition: BPC (online + offline) + Superstore by Nykaa + Nykaa Man Grooming + House of Nykaa owned brands
A31: Number of visits | B31: mn | C31: Beauty Omnichannel Retail | D31: 205 | E31: 211 | F31: 221 | G31: 204 | H31: 222 | I31: 234 | J31: 250 | K31: 231 | L31: 269 | M31: 287 | N31: 311 | O31: 303 | P31: 330 | Q31: 357 | R31: 401 | S31: 393 | T31: 411 | U31: 450 | V31: 538 | W31: =AJ31-SUM(T31:V31) | AF31: =IF(COUNT(D31:G31)=0,"",SUM(D31:G31)) | AG31: =IF(COUNT(H31:K31)=0,"",SUM(H31:K31)) | AH31: =IF(COUNT(L31:O31)=0,"",SUM(L31:O31)) | AI31: =IF(COUNT(P31:S31)=0,"",SUM(P31:S31)) | AJ31: 1894
A32: Monthly average unique visitors | B32: mn | C32: Beauty Omnichannel Retail | D32: 17.3 | E32: 19.4 | F32: 19.8 | G32: 18.5 | H32: 21.8 | I32: 22.1 | J32: 24.2 | K32: 22.5 | L32: 27.3 | M32: 26.8 | N32: 29.6 | O32: 31.9 | P32: 32.6 | Q32: 34.2 | R32: 38.1 | S32: 38 | T32: 38.8 | U32: 41.6 | V32: 50.7 | AF32: =IFERROR(AVERAGE(D32:G32),"") | AG32: =IFERROR(AVERAGE(H32:K32),"") | AH32: 30.2 | AI32: =IFERROR(AVERAGE(P32:S32),"") | AJ32: 44.7
A33: Conversion - orders/visits | B33: % | D33: =IFERROR(D37/D31,"") | E33: =IFERROR(E37/E31,"") | F33: =IFERROR(F37/F31,"") | G33: =IFERROR(G37/G31,"") | H33: =IFERROR(H37/H31,"") | I33: =IFERROR(I37/I31,"") | J33: =IFERROR(J37/J31,"") | K33: =IFERROR(K37/K31,"") | ... AA33: =IFERROR(AA37/AA31,"") | AF33: =IFERROR(AF37/AF31,"") | AG33: =IFERROR(AG37/AG31,"") | AH33: =IFERROR(AH37/AH31,"") | AI33: =IFERROR(AI37/AI31,"") | AJ33: =IFERROR(AJ37/AJ31,"")
A34: Conversion - transacting customers/visits | B34: % | D34: =IFERROR(D35/D31,"") | E34: =IFERROR(E35/E31,"") | F34: =IFERROR(F35/F31,"") | G34: =IFERROR(G35/G31,"") | H34: =IFERROR(H35/H31,"") | I34: =IFERROR(I35/I31,"") | J34: =IFERROR(J35/J31,"") | K34: =IFERROR(K35/K31,"") | ... AA34: =IFERROR(AA35/AA31,"") | AF34: =IFERROR(AF35/AF31,"") | AG34: =IFERROR(AG35/AG31,"") | AH34: =IFERROR(AH35/AH31,"") | AI34: =IFERROR(AI35/AI31,"") | AJ34: =IFERROR(AJ35/AJ31,"")
A35: Annual transacting customers | B35: mn | C35: Beauty Omnichannel Retail | D35: 6.5 | E35: 7 | F35: 7.5 | G35: 8 | H35: 8.6 | I35: 9.1 | J35: 9.6 | K35: 10 | L35: 10.9 | M35: 10.7 | N35: 11.7 | O35: 12.4 | P35: 13.1 | Q35: 13.7 | R35: 14.8 | S35: 15.8 | T35: 16.5 | U35: 17.5 | V35: 18.7 | W35: 19.7 | AF35: =IF(G35="","",G35) | AG35: =IF(K35="","",K35) | AH35: =IF(O35="","",O35) | AI35: =IF(S35="","",S35) | AJ35: =IF(W35="","",W35)
A36: Average order frequency | B36: x | D36: =IFERROR(D37*4/D35,"") | E36: =IFERROR(E37*4/E35,"") | F36: =IFERROR(F37*4/F35,"") | G36: =IFERROR(G37*4/G35,"") | H36: =IFERROR(H37*4/H35,"") | I36: =IFERROR(I37*4/I35,"") | J36: =IFERROR(J37*4/J35,"") | K36: =IFERROR(K37*4/K35,"") | ... AA36: =IFERROR(AA37*4/AA35,"") | AF36: =IFERROR(AF37*4/AF35,"") | AG36: =IFERROR(AG37*4/AG35,"") | AH36: =IFERROR(AH37*4/AH35,"") | AI36: =IFERROR(AI37*4/AI35,"") | AJ36: =IFERROR(AJ37*4/AJ35,"")
A37: Number of orders | B37: mn | C37: Beauty Omnichannel Retail | D37: 5.8 | E37: 6 | F37: 7.5 | G37: 7.2 | H37: 8.1 | I37: 8.4 | J37: 9.5 | K37: 8.8 | L37: 9.9 | M37: 10.5 | N37: 11.6 | O37: 11.7 | P37: 12.4 | Q37: 12.9 | R37: 15 | S37: 14.2 | T37: 14.5 | U37: 15.7 | V37: 18.1 | W37: =AJ37-SUM(T37:V37) | AF37: =IF(COUNT(D37:G37)=0,"",SUM(D37:G37)) | AG37: =IF(COUNT(H37:K37)=0,"",SUM(H37:K37)) | AH37: =IF(COUNT(L37:O37)=0,"",SUM(L37:O37)) | AI37: =IF(COUNT(P37:S37)=0,"",SUM(P37:S37)) | AJ37: 65.8
A38: Average order value | B38: Rs | D38: =IFERROR(D39/D37,"") | E38: =IFERROR(E39/E37,"") | F38: =IFERROR(F39/F37,"") | G38: =IFERROR(G39/G37,"") | H38: =IFERROR(H39/H37,"") | I38: =IFERROR(I39/I37,"") | J38: =IFERROR(J39/J37,"") | K38: =IFERROR(K39/K37,"") | ... AA38: =IFERROR(AA39/AA37,"") | AF38: =IFERROR(AF39/AF37,"") | AG38: =IFERROR(AG39/AG37,"") | AH38: =IFERROR(AH39/AH37,"") | AI38: =IFERROR(AI39/AI37,"") | AJ38: =IFERROR(AJ39/AJ37,"")
A39: GMV | B39: Rs Mn | C39: Beauty Omnichannel Retail | L39: 19908 | M39: 21559 | N39: 25696 | O39: 23390 | P39: 25429 | Q39: 27833 | R39: 33899 | S39: 30580 | T39: 32080 | U39: 35510 | V39: 43020 | W39: 38920 | AF39: =IF(COUNT(D39:G39)=0,"",SUM(D39:G39)) | AG39: =IF(COUNT(H39:K39)=0,"",SUM(H39:K39)) | AH39: =IF(COUNT(L39:O39)=0,"",SUM(L39:O39)) | AI39: =IF(COUNT(P39:S39)=0,"",SUM(P39:S39)) | AJ39: =IF(COUNT(T39:W39)=0,"",SUM(T39:W39))
A40: YoY growth | B40: % | H40: =IFERROR(H39/D39-1,"") | I40: =IFERROR(I39/E39-1,"") | J40: =IFERROR(J39/F39-1,"") | K40: =IFERROR(K39/G39-1,"") | L40: =IFERROR(L39/H39-1,"") | M40: =IFERROR(M39/I39-1,"") | N40: =IFERROR(N39/J39-1,"") | O40: =IFERROR(O39/K39-1,"") | ... AA40: =IFERROR(AA39/W39-1,"") | AF40: =IFERROR(AF39/AE39-1,"") | AG40: =IFERROR(AG39/AF39-1,"") | AH40: =IFERROR(AH39/AG39-1,"") | AI40: =IFERROR(AI39/AH39-1,"") | AJ40: =IFERROR(AJ39/AI39-1,"")
A41: QoQ growth | B41: % | E41: =IFERROR(E39/D39-1,"") | F41: =IFERROR(F39/E39-1,"") | G41: =IFERROR(G39/F39-1,"") | H41: =IFERROR(H39/G39-1,"") | I41: =IFERROR(I39/H39-1,"") | J41: =IFERROR(J39/I39-1,"") | K41: =IFERROR(K39/J39-1,"") | L41: =IFERROR(L39/K39-1,"") | ... AA41: =IFERROR(AA39/Z39-1,"")
A42: NSV | B42: Rs Mn | C42: Beauty Omnichannel Retail | L42: 12121 | M42: 12566 | N42: 14954 | O42: 13979 | P42: 14695 | Q42: 15661 | R42: 18817 | S42: 17570 | T42: 18340 | U42: 19810 | V42: 24210 | W42: 22690 | AF42: =IF(COUNT(D42:G42)=0,"",SUM(D42:G42)) | AG42: =IF(COUNT(H42:K42)=0,"",SUM(H42:K42)) | AH42: =IF(COUNT(L42:O42)=0,"",SUM(L42:O42)) | AI42: =IF(COUNT(P42:S42)=0,"",SUM(P42:S42)) | AJ42: =IF(COUNT(T42:W42)=0,"",SUM(T42:W42))
A43: NSV / GMV | B43: % | D43: =IFERROR(D42/D39,"") | E43: =IFERROR(E42/E39,"") | F43: =IFERROR(F42/F39,"") | G43: =IFERROR(G42/G39,"") | H43: =IFERROR(H42/H39,"") | I43: =IFERROR(I42/I39,"") | J43: =IFERROR(J42/J39,"") | K43: =IFERROR(K42/K39,"") | ... AA43: =IFERROR(AA42/AA39,"") | AF43: =IFERROR(AF42/AF39,"") | AG43: =IFERROR(AG42/AG39,"") | AH43: =IFERROR(AH42/AH39,"") | AI43: =IFERROR(AI42/AI39,"") | AJ43: =IFERROR(AJ42/AJ39,"")
A44: Revenue | B44: Rs Mn | C44: Beauty Omnichannel Retail / Financial Performance | L44: 12984 | N44: 16227 | O44: 15190 | P44: 15935 | Q44: 17029 | R44: 20601 | S44: 18950 | T44: 19750 | U44: 21320 | V44: 26220 | W44: 24100 | AF44: =IF(COUNT(D44:G44)=0,"",SUM(D44:G44)) | AG44: =IF(COUNT(H44:K44)=0,"",SUM(H44:K44)) | AH44: =IF(COUNT(L44:O44)=0,"",SUM(L44:O44)) | AI44: =IF(COUNT(P44:S44)=0,"",SUM(P44:S44)) | AJ44: =IF(COUNT(T44:W44)=0,"",SUM(T44:W44))
A45: Revenue / NSV | B45: % | D45: =IFERROR(D44/D42,"") | E45: =IFERROR(E44/E42,"") | F45: =IFERROR(F44/F42,"") | G45: =IFERROR(G44/G42,"") | H45: =IFERROR(H44/H42,"") | I45: =IFERROR(I44/I42,"") | J45: =IFERROR(J44/J42,"") | K45: =IFERROR(K44/K42,"") | ... AA45: =IFERROR(AA44/AA42,"") | AF45: =IFERROR(AF44/AF42,"") | AG45: =IFERROR(AG44/AG42,"") | AH45: =IFERROR(AH44/AH42,"") | AI45: =IFERROR(AI44/AI42,"") | AJ45: =IFERROR(AJ44/AJ42,"")
A46: Gross profit | B46: Rs Mn | C46: Financial Performance | L46: 5223 | N46: 6317 | O46: 5950 | P46: 6328 | Q46: 6828 | R46: 8175 | S46: 7790 | T46: 8190 | U46: 8840 | V46: 10850 | W46: 10130 | AF46: =IF(COUNT(D46:G46)=0,"",SUM(D46:G46)) | AG46: =IF(COUNT(H46:K46)=0,"",SUM(H46:K46)) | AH46: =IF(COUNT(L46:O46)=0,"",SUM(L46:O46)) | AI46: =IF(COUNT(P46:S46)=0,"",SUM(P46:S46)) | AJ46: =IF(COUNT(T46:W46)=0,"",SUM(T46:W46))
A47: Gross margin (% of NSV) | B47: % | D47: =IFERROR(D46/D42,"") | E47: =IFERROR(E46/E42,"") | F47: =IFERROR(F46/F42,"") | G47: =IFERROR(G46/G42,"") | H47: =IFERROR(H46/H42,"") | I47: =IFERROR(I46/I42,"") | J47: =IFERROR(J46/J42,"") | K47: =IFERROR(K46/K42,"") | ... AA47: =IFERROR(AA46/AA42,"") | AF47: =IFERROR(AF46/AF42,"") | AG47: =IFERROR(AG46/AG42,"") | AH47: =IFERROR(AH46/AH42,"") | AI47: =IFERROR(AI46/AI42,"") | AJ47: =IFERROR(AJ46/AJ42,"")
A48: Fulfilment cost | B48: Rs Mn | C48: Financial Performance | L48: 1114 | N48: 1396 | O48: 1280 | P48: 1417 | Q48: 1488 | R48: 1749 | S48: 1630 | T48: 1700 | U48: 1870 | V48: 2220 | W48: 2150 | AF48: =IF(COUNT(D48:G48)=0,"",SUM(D48:G48)) | AG48: =IF(COUNT(H48:K48)=0,"",SUM(H48:K48)) | AH48: =IF(COUNT(L48:O48)=0,"",SUM(L48:O48)) | AI48: =IF(COUNT(P48:S48)=0,"",SUM(P48:S48)) | AJ48: =IF(COUNT(T48:W48)=0,"",SUM(T48:W48))
A49: Marketing expenses | B49: Rs Mn | C49: Financial Performance | L49: 971 | N49: 1414 | O49: 1210 | P49: 1268 | Q49: 1462 | R49: 1897 | S49: 1570 | T49: 2340 | U49: 2600 | V49: 3190 | W49: 2780 | AF49: =IF(COUNT(D49:G49)=0,"",SUM(D49:G49)) | AG49: =IF(COUNT(H49:K49)=0,"",SUM(H49:K49)) | AH49: =IF(COUNT(L49:O49)=0,"",SUM(L49:O49)) | AI49: =IF(COUNT(P49:S49)=0,"",SUM(P49:S49)) | AJ49: =IF(COUNT(T49:W49)=0,"",SUM(T49:W49))
A50: Selling & distribution expense | B50: Rs Mn | C50: Financial Performance | L50: 285 | N50: 385 | O50: 400 | P50: 413 | Q50: 439 | R50: 532 | S50: 550 | T50: 0 | U50: 0 | V50: 0 | W50: 0 | AF50: =IF(COUNT(D50:G50)=0,"",SUM(D50:G50)) | AG50: =IF(COUNT(H50:K50)=0,"",SUM(H50:K50)) | AH50: =IF(COUNT(L50:O50)=0,"",SUM(L50:O50)) | AI50: =IF(COUNT(P50:S50)=0,"",SUM(P50:S50)) | AJ50: =IF(COUNT(T50:W50)=0,"",SUM(T50:W50))
A51: Contribution profit | B51: Rs Mn | D51: =IF(OR(ISBLANK(D46),ISBLANK(D48),ISBLANK(D49),ISBLANK(D50)),"",IFERROR(D46-D48-D49-D50,"")) | E51: =IF(OR(ISBLANK(E46),ISBLANK(E48),ISBLANK(E49),ISBLANK(E50)),"",IFERROR(E46-E48-E49-E50,"")) | F51: =IF(OR(ISBLANK(F46),ISBLANK(F48),ISBLANK(F49),ISBLANK(F50)),"",IFERROR(F46-F48-F49-F50,"")) | G51: =IF(OR(ISBLANK(G46),ISBLANK(G48),ISBLANK(G49),ISBLANK(G50)),"",IFERROR(G46-G48-G49-G50,"")) | H51: =IF(OR(ISBLANK(H46),ISBLANK(H48),ISBLANK(H49),ISBLANK(H50)),"",IFERROR(H46-H48-H49-H50,"")) | I51: =IF(OR(ISBLANK(I46),ISBLANK(I48),ISBLANK(I49),ISBLANK(I50)),"",IFERROR(I46-I48-I49-I50,"")) | J51: =IF(OR(ISBLANK(J46),ISBLANK(J48),ISBLANK(J49),ISBLANK(J50)),"",IFERROR(J46-J48-J49-J50,"")) | K51: =IF(OR(ISBLANK(K46),ISBLANK(K48),ISBLANK(K49),ISBLANK(K50)),"",IFERROR(K46-K48-K49-K50,"")) | ... AA51: =IF(OR(ISBLANK(AA46),ISBLANK(AA48),ISBLANK(AA49),ISBLANK(AA50)),"",IFERROR(AA46-AA48-AA49-AA50,"")) | AF51: =IF(OR(ISBLANK(AF46),ISBLANK(AF48),ISBLANK(AF49),ISBLANK(AF50)),"",IFERROR(AF46-AF48-AF49-AF50,"")) | AG51: =IF(OR(ISBLANK(AG46),ISBLANK(AG48),ISBLANK(AG49),ISBLANK(AG50)),"",IFERROR(AG46-AG48-AG49-AG50,"")) | AH51: =IF(OR(ISBLANK(AH46),ISBLANK(AH48),ISBLANK(AH49),ISBLANK(AH50)),"",IFERROR(AH46-AH48-AH49-AH50,"")) | AI51: =IF(OR(ISBLANK(AI46),ISBLANK(AI48),ISBLANK(AI49),ISBLANK(AI50)),"",IFERROR(AI46-AI48-AI49-AI50,"")) | AJ51: =IF(OR(ISBLANK(AJ46),ISBLANK(AJ48),ISBLANK(AJ49),ISBLANK(AJ50)),"",IFERROR(AJ46-AJ48-AJ49-AJ50,""))
A52: Contribution margin (% of NSV) | B52: % | D52: =IFERROR(D51/D42,"") | E52: =IFERROR(E51/E42,"") | F52: =IFERROR(F51/F42,"") | G52: =IFERROR(G51/G42,"") | H52: =IFERROR(H51/H42,"") | I52: =IFERROR(I51/I42,"") | J52: =IFERROR(J51/J42,"") | K52: =IFERROR(K51/K42,"") | ... AA52: =IFERROR(AA51/AA42,"") | AF52: =IFERROR(AF51/AF42,"") | AG52: =IFERROR(AG51/AG42,"") | AH52: =IFERROR(AH51/AH42,"") | AI52: =IFERROR(AI51/AI42,"") | AJ52: =IFERROR(AJ51/AJ42,"")
A53: Other expenses (G&A + employee) | B53: Rs Mn | C53: Financial Performance | L53: 1800 | N53: 1890 | O53: 1790 | P53: 1975 | Q53: 2095 | R53: 2345 | S53: 2360 | T53: 2500 | U53: 2590 | V53: 2990 | W53: 2870 | AF53: =IF(COUNT(D53:G53)=0,"",SUM(D53:G53)) | AG53: =IF(COUNT(H53:K53)=0,"",SUM(H53:K53)) | AH53: =IF(COUNT(L53:O53)=0,"",SUM(L53:O53)) | AI53: =IF(COUNT(P53:S53)=0,"",SUM(P53:S53)) | AJ53: =IF(COUNT(T53:W53)=0,"",SUM(T53:W53))
A54: EBITDA | B54: Rs Mn | D54: =IF(OR(ISBLANK(D51),ISBLANK(D53)),"",IFERROR(D51-D53,"")) | E54: =IF(OR(ISBLANK(E51),ISBLANK(E53)),"",IFERROR(E51-E53,"")) | F54: =IF(OR(ISBLANK(F51),ISBLANK(F53)),"",IFERROR(F51-F53,"")) | G54: =IF(OR(ISBLANK(G51),ISBLANK(G53)),"",IFERROR(G51-G53,"")) | H54: =IF(OR(ISBLANK(H51),ISBLANK(H53)),"",IFERROR(H51-H53,"")) | I54: =IF(OR(ISBLANK(I51),ISBLANK(I53)),"",IFERROR(I51-I53,"")) | J54: =IF(OR(ISBLANK(J51),ISBLANK(J53)),"",IFERROR(J51-J53,"")) | K54: =IF(OR(ISBLANK(K51),ISBLANK(K53)),"",IFERROR(K51-K53,"")) | ... AA54: =IF(OR(ISBLANK(AA51),ISBLANK(AA53)),"",IFERROR(AA51-AA53,"")) | AF54: =IF(OR(ISBLANK(AF51),ISBLANK(AF53)),"",IFERROR(AF51-AF53,"")) | AG54: =IF(OR(ISBLANK(AG51),ISBLANK(AG53)),"",IFERROR(AG51-AG53,"")) | AH54: =IF(OR(ISBLANK(AH51),ISBLANK(AH53)),"",IFERROR(AH51-AH53,"")) | AI54: =IF(OR(ISBLANK(AI51),ISBLANK(AI53)),"",IFERROR(AI51-AI53,"")) | AJ54: =IF(OR(ISBLANK(AJ51),ISBLANK(AJ53)),"",IFERROR(AJ51-AJ53,""))
A55: EBITDA margin (% of NSV) | B55: % | D55: =IFERROR(D54/D42,"") | E55: =IFERROR(E54/E42,"") | F55: =IFERROR(F54/F42,"") | G55: =IFERROR(G54/G42,"") | H55: =IFERROR(H54/H42,"") | I55: =IFERROR(I54/I42,"") | J55: =IFERROR(J54/J42,"") | K55: =IFERROR(K54/K42,"") | ... AA55: =IFERROR(AA54/AA42,"") | AF55: =IFERROR(AF54/AF42,"") | AG55: =IFERROR(AG54/AG42,"") | AH55: =IFERROR(AH54/AH42,"") | AI55: =IFERROR(AI54/AI42,"") | AJ55: =IFERROR(AJ54/AJ42,"")
A57: BPC / Luxe store count | B57: # | C57: Beauty Omnichannel Retail | E57: 84 | G57: 104 | I57: 124 | J57: 141 | K57: 145 | O57: 187 | R57: 221 | AF57: =IF(G57="","",G57) | AG57: =IF(K57="","",K57) | AH57: =IF(O57="","",O57) | AI57: =IF(S57="","",S57) | AJ57: =IF(W57="","",W57)
A58: Number of cities (retail) | B58: # | C58: Beauty Omnichannel Retail | D58: 39 | E58: 41 | F58: 45 | G58: 49 | H58: 52 | I58: 53 | J58: 56 | K58: 60 | M58: 61 | Q58: 72 | R58: 73 | S58: 79 | U58: 90 | AF58: =IF(G58="","",G58) | AG58: =IF(K58="","",K58) | AH58: =IF(O58="","",O58) | AI58: =IF(S58="","",S58) | AJ58: =IF(W58="","",W58)
A59: Total retail space | B59: sq ft | C59: Beauty Omnichannel Retail | E59: 0.07 | G59: 0.1 | I59: 0.12 | J59: 0.14 | O59: 0.17 | R59: 0.21 | AF59: =IF(G59="","",G59) | AG59: =IF(K59="","",K59) | AH59: =IF(O59="","",O59) | AI59: =IF(S59="","",S59) | AJ59: =IF(W59="","",W59)
A60: BPC app downloads (cumulative) | B60: mn | C60: Beauty Omnichannel Retail | AF60: =IF(G60="","",G60) | AG60: =IF(K60="","",K60) | AH60: =IF(O60="","",O60) | AI60: =IF(S60="","",S60) | AJ60: =IF(W60="","",W60)
A62: House of Nykaa (owned brands portfolio)
A63: House of Nykaa - Beauty brands GMV | B63: Rs Mn | C63: House of Nykaa | D63: 851 | E63: 1202 | F63: 1746 | G63: 1779 | H63: 1663 | I63: 1966 | J63: 2247 | K63: 2013 | L63: 2310 | M63: 2438 | N63: 3152 | O63: 3054 | P63: 3406 | Q63: 3602 | R63: 4686 | S63: 5260 | T63: 5780 | U63: 6270 | V63: 7750 | AF63: =IF(COUNT(D63:G63)=0,"",SUM(D63:G63)) | AG63: =IF(COUNT(H63:K63)=0,"",SUM(H63:K63)) | AH63: =IF(COUNT(L63:O63)=0,"",SUM(L63:O63)) | AI63: =IF(COUNT(P63:S63)=0,"",SUM(P63:S63)) | AJ63: =IF(COUNT(T63:W63)=0,"",SUM(T63:W63))
A64: of which: Dot & Key GMV | B64: Rs Mn | C64: House of Nykaa | AF64: =IF(COUNT(D64:G64)=0,"",SUM(D64:G64)) | AG64: =IF(COUNT(H64:K64)=0,"",SUM(H64:K64)) | AH64: =IF(COUNT(L64:O64)=0,"",SUM(L64:O64)) | AI64: =IF(COUNT(P64:S64)=0,"",SUM(P64:S64)) | AJ64: =IF(COUNT(T64:W64)=0,"",SUM(T64:W64))
A65: of which: Kay Beauty GMV | B65: Rs Mn | C65: House of Nykaa | AF65: =IF(COUNT(D65:G65)=0,"",SUM(D65:G65)) | AG65: =IF(COUNT(H65:K65)=0,"",SUM(H65:K65)) | AH65: =IF(COUNT(L65:O65)=0,"",SUM(L65:O65)) | AI65: =IF(COUNT(P65:S65)=0,"",SUM(P65:S65)) | AJ65: =IF(COUNT(T65:W65)=0,"",SUM(T65:W65))
A66: House of Nykaa - Fashion brands GMV | B66: Rs Mn | C66: House of Nykaa | D66: 210 | E66: 290 | F66: 406 | H66: 706 | I66: 780 | J66: 902 | L66: 916 | M66: 989 | N66: 1174 | P66: 903 | Q66: 1090 | R66: 1200 | S66: 1120 | T66: 970 | U66: 950 | AF66: =IF(COUNT(D66:G66)=0,"",SUM(D66:G66)) | AG66: =IF(COUNT(H66:K66)=0,"",SUM(H66:K66)) | AH66: =IF(COUNT(L66:O66)=0,"",SUM(L66:O66)) | AI66: =IF(COUNT(P66:S66)=0,"",SUM(P66:S66)) | AJ66: =IF(COUNT(T66:W66)=0,"",SUM(T66:W66))
A67: House of Nykaa - Total owned-brand GMV | B67: Rs Mn | D67: =IFERROR(D63+D66,"") | E67: =IFERROR(E63+E66,"") | F67: =IFERROR(F63+F66,"") | G67: =IFERROR(G63+G66,"") | H67: =IFERROR(H63+H66,"") | I67: =IFERROR(I63+I66,"") | J67: =IFERROR(J63+J66,"") | K67: =IFERROR(K63+K66,"") | ... AA67: =IFERROR(AA63+AA66,"") | AF67: =IFERROR(AF63+AF66,"") | AG67: =IFERROR(AG63+AG66,"") | AH67: =IFERROR(AH63+AH66,"") | AI67: =IFERROR(AI63+AI66,"") | AJ67: =IFERROR(AJ63+AJ66,"")
A68: Share of total company GMV | B68: % | D68: =IFERROR(D67/D11,"") | E68: =IFERROR(E67/E11,"") | F68: =IFERROR(F67/F11,"") | G68: =IFERROR(G67/G11,"") | H68: =IFERROR(H67/H11,"") | I68: =IFERROR(I67/I11,"") | J68: =IFERROR(J67/J11,"") | K68: =IFERROR(K67/K11,"") | ... AA68: =IFERROR(AA67/AA11,"") | AF68: =IFERROR(AF67/AF11,"") | AG68: =IFERROR(AG67/AG11,"") | AH68: =IFERROR(AH67/AH11,"") | AI68: =IFERROR(AI67/AI11,"") | AJ68: =IFERROR(AJ67/AJ11,"")
A69: Number of owned brands (House of Nykaa) | B69: # | C69: House of Nykaa | D69: 7 | E69: 8 | F69: 9 | G69: 10 | H69: 10 | I69: 10 | J69: 10 | K69: 12 | L69: 13 | AF69: =IF(G69="","",G69) | AG69: =IF(K69="","",K69) | AH69: =IF(O69="","",O69) | AI69: =IF(S69="","",S69) | AJ69: =IF(W69="","",W69)
A71: eB2B: Superstore by Nykaa
A72: B2B distribution platform selling to offline beauty retailers. Cost breakdown not separately disclosed as of this build -- Nykaa has so far only given qualitative bps commentary; revisit once/if a full P&L split is disclosed.
A73: GMV | B73: Rs Mn | C73: eB2B: Superstore by Nykaa | G73: 214 | J73: 1012 | N73: 1700 | R73: 2597 | AF73: =IF(COUNT(D73:G73)=0,"",SUM(D73:G73)) | AG73: =IF(COUNT(H73:K73)=0,"",SUM(H73:K73)) | AH73: =IF(COUNT(L73:O73)=0,"",SUM(L73:O73)) | AI73: =IF(COUNT(P73:S73)=0,"",SUM(P73:S73)) | AJ73: =IF(COUNT(T73:W73)=0,"",SUM(T73:W73))
A74: YoY growth | B74: % | H74: =IFERROR(H73/D73-1,"") | I74: =IFERROR(I73/E73-1,"") | J74: =IFERROR(J73/F73-1,"") | K74: =IFERROR(K73/G73-1,"") | L74: =IFERROR(L73/H73-1,"") | M74: =IFERROR(M73/I73-1,"") | N74: =IFERROR(N73/J73-1,"") | O74: =IFERROR(O73/K73-1,"") | ... AA74: =IFERROR(AA73/W73-1,"") | AF74: =IFERROR(AF73/AE73-1,"") | AG74: =IFERROR(AG73/AF73-1,"") | AH74: =IFERROR(AH73/AG73-1,"") | AI74: =IFERROR(AI73/AH73-1,"") | AJ74: =IFERROR(AJ73/AI73-1,"")
A75: NSV | B75: Rs Mn | C75: eB2B: Superstore by Nykaa | AF75: =IF(COUNT(D75:G75)=0,"",SUM(D75:G75)) | AG75: =IF(COUNT(H75:K75)=0,"",SUM(H75:K75)) | AH75: =IF(COUNT(L75:O75)=0,"",SUM(L75:O75)) | AI75: =IF(COUNT(P75:S75)=0,"",SUM(P75:S75)) | AJ75: =IF(COUNT(T75:W75)=0,"",SUM(T75:W75))
A76: Contribution to Beauty GMV | B76: % | D76: =IFERROR(D73/D39,"") | E76: =IFERROR(E73/E39,"") | F76: =IFERROR(F73/F39,"") | G76: =IFERROR(G73/G39,"") | H76: =IFERROR(H73/H39,"") | I76: =IFERROR(I73/I39,"") | J76: =IFERROR(J73/J39,"") | K76: =IFERROR(K73/K39,"") | ... AA76: =IFERROR(AA73/AA39,"") | AF76: =IFERROR(AF73/AF39,"") | AG76: =IFERROR(AG73/AG39,"") | AH76: =IFERROR(AH73/AH39,"") | AI76: =IFERROR(AI73/AI39,"") | AJ76: =IFERROR(AJ73/AJ39,"")
A77: Beauty (ex-SuperStore) -- derived, not directly disclosed since 4Q24
A78: Beauty (ex-SuperStore) GMV | B78: Rs Mn | D78: =IF(OR(ISBLANK(D39),ISBLANK(D73)),"",IFERROR(D39-D73,"")) | E78: =IF(OR(ISBLANK(E39),ISBLANK(E73)),"",IFERROR(E39-E73,"")) | F78: =IF(OR(ISBLANK(F39),ISBLANK(F73)),"",IFERROR(F39-F73,"")) | G78: =IF(OR(ISBLANK(G39),ISBLANK(G73)),"",IFERROR(G39-G73,"")) | H78: =IF(OR(ISBLANK(H39),ISBLANK(H73)),"",IFERROR(H39-H73,"")) | I78: =IF(OR(ISBLANK(I39),ISBLANK(I73)),"",IFERROR(I39-I73,"")) | J78: =IF(OR(ISBLANK(J39),ISBLANK(J73)),"",IFERROR(J39-J73,"")) | K78: =IF(OR(ISBLANK(K39),ISBLANK(K73)),"",IFERROR(K39-K73,"")) | ... AA78: =IF(OR(ISBLANK(AA39),ISBLANK(AA73)),"",IFERROR(AA39-AA73,"")) | AF78: =IF(OR(ISBLANK(AF39),ISBLANK(AF73)),"",IFERROR(AF39-AF73,"")) | AG78: =IF(OR(ISBLANK(AG39),ISBLANK(AG73)),"",IFERROR(AG39-AG73,"")) | AH78: =IF(OR(ISBLANK(AH39),ISBLANK(AH73)),"",IFERROR(AH39-AH73,"")) | AI78: =IF(OR(ISBLANK(AI39),ISBLANK(AI73)),"",IFERROR(AI39-AI73,"")) | AJ78: =IF(OR(ISBLANK(AJ39),ISBLANK(AJ73)),"",IFERROR(AJ39-AJ73,""))
A79: Beauty (ex-SuperStore) NSV | B79: Rs Mn | D79: =IF(OR(ISBLANK(D42),ISBLANK(D75)),"",IFERROR(D42-D75,"")) | E79: =IF(OR(ISBLANK(E42),ISBLANK(E75)),"",IFERROR(E42-E75,"")) | F79: =IF(OR(ISBLANK(F42),ISBLANK(F75)),"",IFERROR(F42-F75,"")) | G79: =IF(OR(ISBLANK(G42),ISBLANK(G75)),"",IFERROR(G42-G75,"")) | H79: =IF(OR(ISBLANK(H42),ISBLANK(H75)),"",IFERROR(H42-H75,"")) | I79: =IF(OR(ISBLANK(I42),ISBLANK(I75)),"",IFERROR(I42-I75,"")) | J79: =IF(OR(ISBLANK(J42),ISBLANK(J75)),"",IFERROR(J42-J75,"")) | K79: =IF(OR(ISBLANK(K42),ISBLANK(K75)),"",IFERROR(K42-K75,"")) | ... AA79: =IF(OR(ISBLANK(AA42),ISBLANK(AA75)),"",IFERROR(AA42-AA75,"")) | AF79: =IF(OR(ISBLANK(AF42),ISBLANK(AF75)),"",IFERROR(AF42-AF75,"")) | AG79: =IF(OR(ISBLANK(AG42),ISBLANK(AG75)),"",IFERROR(AG42-AG75,"")) | AH79: =IF(OR(ISBLANK(AH42),ISBLANK(AH75)),"",IFERROR(AH42-AH75,"")) | AI79: =IF(OR(ISBLANK(AI42),ISBLANK(AI75)),"",IFERROR(AI42-AI75,"")) | AJ79: =IF(OR(ISBLANK(AJ42),ISBLANK(AJ75)),"",IFERROR(AJ42-AJ75,""))
A80: Transacting retailers | B80: # | C80: eB2B: Superstore by Nykaa | F80: 4153 | G80: 18806 | H80: 45030 | I80: 73412 | J80: 92415 | L80: 119564 | M80: 129431 | N80: 146000 | P80: 210000 | Q80: 235000 | R80: 256000 | S80: 276000 | T80: 305000 | U80: 332000 | V80: 359000 | AF80: =IF(G80="","",G80) | AG80: =IF(K80="","",K80) | AH80: =IF(O80="","",O80) | AI80: =IF(S80="","",S80) | AJ80: =IF(W80="","",W80)
A81: Activation rate (% of registered retailers) | B81: % | C81: eB2B: Superstore by Nykaa | F81: 0.36 | G81: 0.46 | J81: 0.69 | K81: 0.71 | AF81: =IF(G81="","",G81) | AG81: =IF(K81="","",K81) | AH81: =IF(O81="","",O81) | AI81: =IF(S81="","",S81) | AJ81: =IF(W81="","",W81)
A82: Cities | B82: # | C82: eB2B: Superstore by Nykaa | F82: 88 | G82: 302 | H82: 516 | I82: 659 | J82: 652 | K82: 700 | L82: 699 | M82: 770 | R82: 1100 | S82: 1100 | AF82: =IF(G82="","",G82) | AG82: =IF(K82="","",K82) | AH82: =IF(O82="","",O82) | AI82: =IF(S82="","",S82) | AJ82: =IF(W82="","",W82)
A83: Brands listed | B83: # | C83: eB2B: Superstore by Nykaa | F83: 31 | G83: 134 | H83: 165 | I83: 182 | J83: 185 | K83: 190 | L83: 188 | AF83: =IF(G83="","",G83) | AG83: =IF(K83="","",K83) | AH83: =IF(O83="","",O83) | AI83: =IF(S83="","",S83) | AJ83: =IF(W83="","",W83)
A84: Orders | B84: '000 | C84: eB2B: Superstore by Nykaa | F84: 8.8 | G84: 48.6 | H84: 103.7 | I84: 172.7 | J84: 216 | K84: 728.9 | L84: 263.9 | M84: 280 | N84: 337 | Q84: 406 | AF84: =IF(COUNT(D84:G84)=0,"",SUM(D84:G84)) | AG84: =IF(COUNT(H84:K84)=0,"",SUM(H84:K84)) | AH84: =IF(COUNT(L84:O84)=0,"",SUM(L84:O84)) | AI84: =IF(COUNT(P84:S84)=0,"",SUM(P84:S84)) | AJ84: =IF(COUNT(T84:W84)=0,"",SUM(T84:W84))
A86: Fashion
A87: Definition: Nykaa Fashion + LBB + Nykaa Man Lifestyle
A88: Number of visits | B88: mn | C88: Fashion | D88: 98 | E88: 115 | F88: 115 | G88: 113 | H88: 118 | I88: 122 | J88: 137 | K88: 127 | L88: 126 | M88: 145 | N88: 157 | O88: 144 | P88: 127 | Q88: 147 | R88: 169 | S88: 174 | T88: 165 | U88: 191 | V88: 221 | W88: =AJ88-SUM(T88:V88) | AF88: =IF(COUNT(D88:G88)=0,"",SUM(D88:G88)) | AG88: =IF(COUNT(H88:K88)=0,"",SUM(H88:K88)) | AH88: =IF(COUNT(L88:O88)=0,"",SUM(L88:O88)) | AI88: =IF(COUNT(P88:S88)=0,"",SUM(P88:S88)) | AJ88: 787
A89: Monthly average unique visitors | B89: mn | C89: Fashion | D89: 13.4 | E89: 16.2 | F89: 16.4 | G89: 16 | H89: 16.2 | I89: 16.4 | J89: 19.4 | K89: 17.3 | L89: 16.6 | M89: 17.6 | N89: 18.8 | O89: 17.4 | P89: 15.8 | Q89: 18.1 | R89: 20.5 | S89: 22.2 | T89: 20.4 | U89: 23.5 | V89: 27.7 | AF89: =IFERROR(AVERAGE(D89:G89),"") | AG89: =IFERROR(AVERAGE(H89:K89),"") | AH89: 17.6 | AI89: =IFERROR(AVERAGE(P89:S89),"") | AJ89: 24.2
A90: Conversion - orders/visits | B90: % | D90: =IFERROR(D94/D88,"") | E90: =IFERROR(E94/E88,"") | F90: =IFERROR(F94/F88,"") | G90: =IFERROR(G94/G88,"") | H90: =IFERROR(H94/H88,"") | I90: =IFERROR(I94/I88,"") | J90: =IFERROR(J94/J88,"") | K90: =IFERROR(K94/K88,"") | ... AA90: =IFERROR(AA94/AA88,"") | AF90: =IFERROR(AF94/AF88,"") | AG90: =IFERROR(AG94/AG88,"") | AH90: =IFERROR(AH94/AH88,"") | AI90: =IFERROR(AI94/AI88,"") | AJ90: =IFERROR(AJ94/AJ88,"")
A91: Conversion - transacting customers/visits | B91: % | D91: =IFERROR(D92/D88,"") | E91: =IFERROR(E92/E88,"") | F91: =IFERROR(F92/F88,"") | G91: =IFERROR(G92/G88,"") | H91: =IFERROR(H92/H88,"") | I91: =IFERROR(I92/I88,"") | J91: =IFERROR(J92/J88,"") | K91: =IFERROR(K92/K88,"") | ... AA91: =IFERROR(AA92/AA88,"") | AF91: =IFERROR(AF92/AF88,"") | AG91: =IFERROR(AG92/AG88,"") | AH91: =IFERROR(AH92/AH88,"") | AI91: =IFERROR(AI92/AI88,"") | AJ91: =IFERROR(AJ92/AJ88,"")
A92: Annual transacting customers | B92: mn | C92: Fashion | D92: 1 | E92: 1.3 | F92: 1.6 | G92: 1.8 | H92: 2 | I92: 2.1 | J92: 2.4 | K92: 2.5 | L92: 2.6 | M92: 2.8 | N92: 2.9 | O92: 3 | P92: 3.1 | Q92: 3 | R92: 3.1 | S92: 3.2 | T92: 3.4 | U92: 3.7 | V92: 4.1 | W92: 4.3 | AF92: =IF(G92="","",G92) | AG92: =IF(K92="","",K92) | AH92: =IF(O92="","",O92) | AI92: =IF(S92="","",S92) | AJ92: =IF(W92="","",W92)
A93: Average order frequency | B93: x | D93: =IFERROR(D94*4/D92,"") | E93: =IFERROR(E94*4/E92,"") | F93: =IFERROR(F94*4/F92,"") | G93: =IFERROR(G94*4/G92,"") | H93: =IFERROR(H94*4/H92,"") | I93: =IFERROR(I94*4/I92,"") | J93: =IFERROR(J94*4/J92,"") | K93: =IFERROR(K94*4/K92,"") | ... AA93: =IFERROR(AA94*4/AA92,"") | AF93: =IFERROR(AF94*4/AF92,"") | AG93: =IFERROR(AG94*4/AG92,"") | AH93: =IFERROR(AH94*4/AH92,"") | AI93: =IFERROR(AI94*4/AI92,"") | AJ93: =IFERROR(AJ94*4/AJ92,"")
A94: Number of orders | B94: mn | C94: Fashion | D94: 1.1 | E94: 1.3 | F94: 1.3 | G94: 1.3 | H94: 1.5 | I94: 1.4 | J94: 1.7 | K94: 1.4 | L94: 1.5 | M94: 1.6 | N94: 2.1 | O94: 1.8 | P94: 1.7 | Q94: 1.8 | R94: 2.1 | S94: 2.1 | T94: 2 | U94: 2.4 | V94: 3 | W94: =AJ94-SUM(T94:V94) | AF94: =IF(COUNT(D94:G94)=0,"",SUM(D94:G94)) | AG94: =IF(COUNT(H94:K94)=0,"",SUM(H94:K94)) | AH94: =IF(COUNT(L94:O94)=0,"",SUM(L94:O94)) | AI94: =IF(COUNT(P94:S94)=0,"",SUM(P94:S94)) | AJ94: 10.1
A95: Average order value | B95: Rs | D95: =IFERROR(D96/D94,"") | E95: =IFERROR(E96/E94,"") | F95: =IFERROR(F96/F94,"") | G95: =IFERROR(G96/G94,"") | H95: =IFERROR(H96/H94,"") | I95: =IFERROR(I96/I94,"") | J95: =IFERROR(J96/J94,"") | K95: =IFERROR(K96/K94,"") | ... AA95: =IFERROR(AA96/AA94,"") | AF95: =IFERROR(AF96/AF94,"") | AG95: =IFERROR(AG96/AG94,"") | AH95: =IFERROR(AH96/AH94,"") | AI95: =IFERROR(AI96/AI94,"") | AJ95: =IFERROR(AJ96/AJ94,"")
A96: GMV | B96: Rs Mn | C96: Fashion | L96: 6758 | M96: 7872 | N96: 10465 | O96: 8760 | P96: 7741 | Q96: 8633 | R96: 11299 | S96: 10370 | T96: 9640 | U96: 11800 | V96: 14760 | W96: 13340 | AF96: =IF(COUNT(D96:G96)=0,"",SUM(D96:G96)) | AG96: =IF(COUNT(H96:K96)=0,"",SUM(H96:K96)) | AH96: =IF(COUNT(L96:O96)=0,"",SUM(L96:O96)) | AI96: =IF(COUNT(P96:S96)=0,"",SUM(P96:S96)) | AJ96: =IF(COUNT(T96:W96)=0,"",SUM(T96:W96))
A97: YoY growth | B97: % | H97: =IFERROR(H96/D96-1,"") | I97: =IFERROR(I96/E96-1,"") | J97: =IFERROR(J96/F96-1,"") | K97: =IFERROR(K96/G96-1,"") | L97: =IFERROR(L96/H96-1,"") | M97: =IFERROR(M96/I96-1,"") | N97: =IFERROR(N96/J96-1,"") | O97: =IFERROR(O96/K96-1,"") | ... AA97: =IFERROR(AA96/W96-1,"") | AF97: =IFERROR(AF96/AE96-1,"") | AG97: =IFERROR(AG96/AF96-1,"") | AH97: =IFERROR(AH96/AG96-1,"") | AI97: =IFERROR(AI96/AH96-1,"") | AJ97: =IFERROR(AJ96/AI96-1,"")
A98: QoQ growth | B98: % | E98: =IFERROR(E96/D96-1,"") | F98: =IFERROR(F96/E96-1,"") | G98: =IFERROR(G96/F96-1,"") | H98: =IFERROR(H96/G96-1,"") | I98: =IFERROR(I96/H96-1,"") | J98: =IFERROR(J96/I96-1,"") | K98: =IFERROR(K96/J96-1,"") | L98: =IFERROR(L96/K96-1,"") | ... AA98: =IFERROR(AA96/Z96-1,"")
A99: NSV | B99: Rs Mn | C99: Fashion | L99: 2089 | M99: 2411 | N99: 2899 | O99: 2479 | P99: 2449 | Q99: 2713 | R99: 3295 | S99: 2800 | T99: 2940 | U99: 3460 | V99: 4100 | W99: 3970 | AF99: =IF(COUNT(D99:G99)=0,"",SUM(D99:G99)) | AG99: =IF(COUNT(H99:K99)=0,"",SUM(H99:K99)) | AH99: =IF(COUNT(L99:O99)=0,"",SUM(L99:O99)) | AI99: =IF(COUNT(P99:S99)=0,"",SUM(P99:S99)) | AJ99: =IF(COUNT(T99:W99)=0,"",SUM(T99:W99))
A100: NSV / GMV | B100: % | D100: =IFERROR(D99/D96,"") | E100: =IFERROR(E99/E96,"") | F100: =IFERROR(F99/F96,"") | G100: =IFERROR(G99/G96,"") | H100: =IFERROR(H99/H96,"") | I100: =IFERROR(I99/I96,"") | J100: =IFERROR(J99/J96,"") | K100: =IFERROR(K99/K96,"") | ... AA100: =IFERROR(AA99/AA96,"") | AF100: =IFERROR(AF99/AF96,"") | AG100: =IFERROR(AG99/AG96,"") | AH100: =IFERROR(AH99/AH96,"") | AI100: =IFERROR(AI99/AI96,"") | AJ100: =IFERROR(AJ99/AJ96,"")
A101: Revenue | B101: Rs Mn | C101: Fashion / Financial Performance | F101: 900 | J101: 1339 | L101: 1225 | M101: 1365 | N101: 1640 | O101: 1454 | P101: 1486 | Q101: 1661 | R101: 1990 | S101: 1610 | T101: 1710 | U101: 2010 | V101: 2350 | W101: 2250 | AF101: =IF(COUNT(D101:G101)=0,"",SUM(D101:G101)) | AG101: =IF(COUNT(H101:K101)=0,"",SUM(H101:K101)) | AH101: =IF(COUNT(L101:O101)=0,"",SUM(L101:O101)) | AI101: =IF(COUNT(P101:S101)=0,"",SUM(P101:S101)) | AJ101: =IF(COUNT(T101:W101)=0,"",SUM(T101:W101))
A102: Revenue / NSV | B102: % | D102: =IFERROR(D101/D99,"") | E102: =IFERROR(E101/E99,"") | F102: =IFERROR(F101/F99,"") | G102: =IFERROR(G101/G99,"") | H102: =IFERROR(H101/H99,"") | I102: =IFERROR(I101/I99,"") | J102: =IFERROR(J101/J99,"") | K102: =IFERROR(K101/K99,"") | ... AA102: =IFERROR(AA101/AA99,"") | AF102: =IFERROR(AF101/AF99,"") | AG102: =IFERROR(AG101/AG99,"") | AH102: =IFERROR(AH101/AH99,"") | AI102: =IFERROR(AI101/AI99,"") | AJ102: =IFERROR(AJ101/AJ99,"")
A103: Gross profit | B103: Rs Mn | C103: Financial Performance | L103: 957 | M103: 1061 | N103: 1274 | O103: 1137 | P103: 1210 | Q103: 1348 | R103: 1691 | S103: 1270 | T103: 1390 | U103: 1650 | V103: 2040 | W103: 1840 | AF103: =IF(COUNT(D103:G103)=0,"",SUM(D103:G103)) | AG103: =IF(COUNT(H103:K103)=0,"",SUM(H103:K103)) | AH103: =IF(COUNT(L103:O103)=0,"",SUM(L103:O103)) | AI103: =IF(COUNT(P103:S103)=0,"",SUM(P103:S103)) | AJ103: =IF(COUNT(T103:W103)=0,"",SUM(T103:W103))
A104: Gross margin (% of NSV) | B104: % | D104: =IFERROR(D103/D99,"") | E104: =IFERROR(E103/E99,"") | F104: =IFERROR(F103/F99,"") | G104: =IFERROR(G103/G99,"") | H104: =IFERROR(H103/H99,"") | I104: =IFERROR(I103/I99,"") | J104: =IFERROR(J103/J99,"") | K104: =IFERROR(K103/K99,"") | ... AA104: =IFERROR(AA103/AA99,"") | AF104: =IFERROR(AF103/AF99,"") | AG104: =IFERROR(AG103/AG99,"") | AH104: =IFERROR(AH103/AH99,"") | AI104: =IFERROR(AI103/AI99,"") | AJ104: =IFERROR(AJ103/AJ99,"")
A105: Fulfilment cost | B105: Rs Mn | C105: Financial Performance | L105: 237 | M105: 283 | N105: 318 | O105: 259 | P105: 237 | Q105: 248 | R105: 330 | S105: 280 | T105: 330 | U105: 390 | V105: 460 | W105: 450 | AF105: =IF(COUNT(D105:G105)=0,"",SUM(D105:G105)) | AG105: =IF(COUNT(H105:K105)=0,"",SUM(H105:K105)) | AH105: =IF(COUNT(L105:O105)=0,"",SUM(L105:O105)) | AI105: =IF(COUNT(P105:S105)=0,"",SUM(P105:S105)) | AJ105: =IF(COUNT(T105:W105)=0,"",SUM(T105:W105))
A106: Marketing expenses | B106: Rs Mn | C106: Financial Performance | L106: 594 | N106: 714 | O106: 620 | P106: 672 | Q106: 790 | R106: 1007 | S106: 840 | T106: 830 | U106: 930 | V106: 1150 | W106: 910 | AF106: =IF(COUNT(D106:G106)=0,"",SUM(D106:G106)) | AG106: =IF(COUNT(H106:K106)=0,"",SUM(H106:K106)) | AH106: =IF(COUNT(L106:O106)=0,"",SUM(L106:O106)) | AI106: =IF(COUNT(P106:S106)=0,"",SUM(P106:S106)) | AJ106: =IF(COUNT(T106:W106)=0,"",SUM(T106:W106))
A107: Selling & distribution expense | B107: Rs Mn | C107: Financial Performance | L107: 37 | N107: 42 | O107: 40 | P107: 52 | Q107: 54 | R107: 65 | S107: 60 | T107: 0 | U107: 0 | V107: 0 | W107: 0 | AF107: =IF(COUNT(D107:G107)=0,"",SUM(D107:G107)) | AG107: =IF(COUNT(H107:K107)=0,"",SUM(H107:K107)) | AH107: =IF(COUNT(L107:O107)=0,"",SUM(L107:O107)) | AI107: =IF(COUNT(P107:S107)=0,"",SUM(P107:S107)) | AJ107: =IF(COUNT(T107:W107)=0,"",SUM(T107:W107))
A108: Contribution profit | B108: Rs Mn | D108: =IF(OR(ISBLANK(D103),ISBLANK(D105),ISBLANK(D106),ISBLANK(D107)),"",IFERROR(D103-D105-D106-D107,"")) | E108: =IF(OR(ISBLANK(E103),ISBLANK(E105),ISBLANK(E106),ISBLANK(E107)),"",IFERROR(E103-E105-E106-E107,"")) | F108: =IF(OR(ISBLANK(F103),ISBLANK(F105),ISBLANK(F106),ISBLANK(F107)),"",IFERROR(F103-F105-F106-F107,"")) | G108: =IF(OR(ISBLANK(G103),ISBLANK(G105),ISBLANK(G106),ISBLANK(G107)),"",IFERROR(G103-G105-G106-G107,"")) | H108: =IF(OR(ISBLANK(H103),ISBLANK(H105),ISBLANK(H106),ISBLANK(H107)),"",IFERROR(H103-H105-H106-H107,"")) | I108: =IF(OR(ISBLANK(I103),ISBLANK(I105),ISBLANK(I106),ISBLANK(I107)),"",IFERROR(I103-I105-I106-I107,"")) | J108: =IF(OR(ISBLANK(J103),ISBLANK(J105),ISBLANK(J106),ISBLANK(J107)),"",IFERROR(J103-J105-J106-J107,"")) | K108: =IF(OR(ISBLANK(K103),ISBLANK(K105),ISBLANK(K106),ISBLANK(K107)),"",IFERROR(K103-K105-K106-K107,"")) | ... AA108: =IF(OR(ISBLANK(AA103),ISBLANK(AA105),ISBLANK(AA106),ISBLANK(AA107)),"",IFERROR(AA103-AA105-AA106-AA107,"")) | AF108: =IF(OR(ISBLANK(AF103),ISBLANK(AF105),ISBLANK(AF106),ISBLANK(AF107)),"",IFERROR(AF103-AF105-AF106-AF107,"")) | AG108: =IF(OR(ISBLANK(AG103),ISBLANK(AG105),ISBLANK(AG106),ISBLANK(AG107)),"",IFERROR(AG103-AG105-AG106-AG107,"")) | AH108: =IF(OR(ISBLANK(AH103),ISBLANK(AH105),ISBLANK(AH106),ISBLANK(AH107)),"",IFERROR(AH103-AH105-AH106-AH107,"")) | AI108: =IF(OR(ISBLANK(AI103),ISBLANK(AI105),ISBLANK(AI106),ISBLANK(AI107)),"",IFERROR(AI103-AI105-AI106-AI107,"")) | AJ108: =IF(OR(ISBLANK(AJ103),ISBLANK(AJ105),ISBLANK(AJ106),ISBLANK(AJ107)),"",IFERROR(AJ103-AJ105-AJ106-AJ107,""))
...

Sheet Financial Statements
A1: INR Mn | B1: Unit | C1: Source | D1: 1Q22 | E1: 2Q22 | F1: 3Q22 | G1: 4Q22 | H1: 1Q23 | I1: 2Q23 | J1: 3Q23 | K1: 4Q23 | L1: 1Q24 | M1: 2Q24 | N1: 3Q24 | O1: 4Q24 | P1: 1Q25 | Q1: 2Q25 | R1: 3Q25 | S1: 4Q25 | T1: 1Q26 | U1: 2Q26 | V1: 3Q26 | W1: 4Q26 | X1: 1Q27 | Y1: 2Q27 | Z1: 3Q27 | AA1: 4Q27 | AC1: FY19 | AD1: FY20 | AE1: FY21 | AF1: FY22 | AG1: FY23 | AH1: FY24 | AI1: FY25 | AJ1: FY26 | AK1: FY27E | AL1: FY28E | AM1: FY29E | AN1: FY30E
A2: Fiscal Year End | D2: =DATE(2021,6,30) | E2: =EOMONTH(D2,-3) | F2: =EOMONTH(E2,-3) | G2: =EOMONTH(F2,-3) | H2: =EOMONTH(G2,-3) | I2: =EOMONTH(H2,-3) | J2: =EOMONTH(I2,-3) | K2: =EOMONTH(J2,-3) | L2: =EOMONTH(K2,-3) | ... AA2: =EOMONTH(Z2,-3) | AC2: =DATE(2019,3,31) | AD2: =DATE(2020,3,31) | AE2: =DATE(2021,3,31) | AF2: =DATE(2022,3,31) | AG2: =DATE(2023,3,31) | AH2: =DATE(2024,3,31) | AI2: =DATE(2025,3,31) | AJ2: =DATE(2026,3,31) | AK2: =DATE(2027,3,31) | AL2: =DATE(2028,3,31) | AM2: =DATE(2029,3,31) | AN2: =DATE(2030,3,31)
A3: All figures in INR Mn unless stated otherwise. This sheet is a reported-format presentation, linked to the Projections sheet (KPI/PnL/BS builds) and to Raw Data - financials (for historical line-item granularity Projections doesn't carry). Where the Projections sheet only models a combined or summarized figure, the projected columns (FY27E-30E) show that combined value on ONE representative line within the group and leave the other reported sub-lines blank -- add your own split assumptions there if/when you want more granularity. Historical quarters/years are actuals, linked either from Projections (for figures already tied there) or directly from Raw Data - financials. Balance Sheet follows Nykaa's own disclosure cadence (Q2/Q4 only); Cash Flow is disclosed annually only, so both sections are annual-only in the projected columns and Q2/Q4-only historically.
A4: PROFIT & LOSS (CONSOLIDATED, REPORTED FORMAT)
A5: Revenue, Other income, COGS (combined), Employee benefits, Finance costs, D&A, Other expenses (plug), Tax (combined) and PAT/EPS are the SAME figures as the Projections sheet's Consolidated P&L block -- linked, not re-derived. The individual reported sub-lines below each combined line (e.g. 'Purchase of traded goods', 'Current tax pertaining to earlier years') are actuals for historical periods but are not separately modeled for FY27E-30E, so they show 0 there -- the full projected value sits on the first sub-line of each group (Cost of material consumed; Current tax).
A6: Revenue from operations | B6: Rs Mn | D6: =IF('Raw Data - financials'!D5="","",'Raw Data - financials'!D5) | E6: =IF('Raw Data - financials'!E5="","",'Raw Data - financials'!E5) | F6: =IF('Raw Data - financials'!F5="","",'Raw Data - financials'!F5) | G6: =IF('Raw Data - financials'!G5="","",'Raw Data - financials'!G5) | H6: =IF('Raw Data - financials'!H5="","",'Raw Data - financials'!H5) | I6: =IF('Raw Data - financials'!I5="","",'Raw Data - financials'!I5) | J6: =IF('Raw Data - financials'!J5="","",'Raw Data - financials'!J5) | K6: =IF('Raw Data - financials'!K5="","",'Raw Data - financials'!K5) | ... W6: =IF('Raw Data - financials'!W5="","",'Raw Data - financials'!W5) | AC6: =IF('Raw Data - financials'!AC5="","",'Raw Data - financials'!AC5) | AD6: =IF('Raw Data - financials'!AD5="","",'Raw Data - financials'!AD5) | AE6: =IF('Raw Data - financials'!AE5="","",'Raw Data - financials'!AE5) | AF6: =IF('Raw Data - financials'!AF5="","",'Raw Data - financials'!AF5) | AG6: =IF('Raw Data - financials'!AG5="","",'Raw Data - financials'!AG5) | AH6: =IF('Raw Data - financials'!AH5="","",'Raw Data - financials'!AH5) | AI6: =IF('Raw Data - financials'!AI5="","",'Raw Data - financials'!AI5) | AJ6: =IF('Raw Data - financials'!AJ5="","",'Raw Data - financials'!AJ5) | AK6: =IF('Projections'!AK118="","",'Projections'!AK118) | AL6: =IF('Projections'!AL118="","",'Projections'!AL118) | AM6: =IF('Projections'!AM118="","",'Projections'!AM118) | AN6: =IF('Projections'!AN118="","",'Projections'!AN118)
A7: Other income | B7: Rs Mn | D7: =IF('Projections'!D119="","",'Projections'!D119) | E7: =IF('Projections'!E119="","",'Projections'!E119) | F7: =IF('Projections'!F119="","",'Projections'!F119) | G7: =IF('Projections'!G119="","",'Projections'!G119) | H7: =IF('Projections'!H119="","",'Projections'!H119) | I7: =IF('Projections'!I119="","",'Projections'!I119) | J7: =IF('Projections'!J119="","",'Projections'!J119) | K7: =IF('Projections'!K119="","",'Projections'!K119) | ... W7: =IF('Projections'!W119="","",'Projections'!W119) | AC7: =IF('Projections'!AC119="","",'Projections'!AC119) | AD7: =IF('Projections'!AD119="","",'Projections'!AD119) | AE7: =IF('Projections'!AE119="","",'Projections'!AE119) | AF7: =IF('Projections'!AF119="","",'Projections'!AF119) | AG7: =IF('Projections'!AG119="","",'Projections'!AG119) | AH7: =IF('Projections'!AH119="","",'Projections'!AH119) | AI7: =IF('Projections'!AI119="","",'Projections'!AI119) | AJ7: =IF('Projections'!AJ119="","",'Projections'!AJ119) | ... AN7: =IF('Projections'!AN119="","",'Projections'!AN119)
A8: Total Income | B8: Rs Mn | D8: =IFERROR(D6+D7,"") | E8: =IFERROR(E6+E7,"") | F8: =IFERROR(F6+F7,"") | G8: =IFERROR(G6+G7,"") | H8: =IFERROR(H6+H7,"") | I8: =IFERROR(I6+I7,"") | J8: =IFERROR(J6+J7,"") | K8: =IFERROR(K6+K7,"") | ... W8: =IFERROR(W6+W7,"") | AC8: =IFERROR(AC6+AC7,"") | AD8: =IFERROR(AD6+AD7,"") | AE8: =IFERROR(AE6+AE7,"") | AF8: =IFERROR(AF6+AF7,"") | AG8: =IFERROR(AG6+AG7,"") | AH8: =IFERROR(AH6+AH7,"") | AI8: =IFERROR(AI6+AI7,"") | AJ8: =IFERROR(AJ6+AJ7,"") | ... AN8: =IFERROR(AN6+AN7,"")
A10: Expenses
A11: Cost of material consumed | B11: Rs Mn | D11: =IF('Raw Data - financials'!D10="","",'Raw Data - financials'!D10) | E11: =IF('Raw Data - financials'!E10="","",'Raw Data - financials'!E10) | F11: =IF('Raw Data - financials'!F10="","",'Raw Data - financials'!F10) | G11: =IF('Raw Data - financials'!G10="","",'Raw Data - financials'!G10) | H11: =IF('Raw Data - financials'!H10="","",'Raw Data - financials'!H10) | I11: =IF('Raw Data - financials'!I10="","",'Raw Data - financials'!I10) | J11: =IF('Raw Data - financials'!J10="","",'Raw Data - financials'!J10) | K11: =IF('Raw Data - financials'!K10="","",'Raw Data - financials'!K10) | ... W11: =IF('Raw Data - financials'!W10="","",'Raw Data - financials'!W10) | AC11: =IF('Raw Data - financials'!AC10="","",'Raw Data - financials'!AC10) | AD11: =IF('Raw Data - financials'!AD10="","",'Raw Data - financials'!AD10) | AE11: =IF('Raw Data - financials'!AE10="","",'Raw Data - financials'!AE10) | AF11: =IF('Raw Data - financials'!AF10="","",'Raw Data - financials'!AF10) | AG11: =IF('Raw Data - financials'!AG10="","",'Raw Data - financials'!AG10) | AH11: =IF('Raw Data - financials'!AH10="","",'Raw Data - financials'!AH10) | AI11: =IF('Raw Data - financials'!AI10="","",'Raw Data - financials'!AI10) | AJ11: =IF('Raw Data - financials'!AJ10="","",'Raw Data - financials'!AJ10) | AK11: =IF('Projections'!AK123="","",'Projections'!AK123) | AL11: =IF('Projections'!AL123="","",'Projections'!AL123) | AM11: =IF('Projections'!AM123="","",'Projections'!AM123) | AN11: =IF('Projections'!AN123="","",'Projections'!AN123)
A12: Purchase of traded goods | B12: Rs Mn | D12: =IF('Raw Data - financials'!D11="","",'Raw Data - financials'!D11) | E12: =IF('Raw Data - financials'!E11="","",'Raw Data - financials'!E11) | F12: =IF('Raw Data - financials'!F11="","",'Raw Data - financials'!F11) | G12: =IF('Raw Data - financials'!G11="","",'Raw Data - financials'!G11) | H12: =IF('Raw Data - financials'!H11="","",'Raw Data - financials'!H11) | I12: =IF('Raw Data - financials'!I11="","",'Raw Data - financials'!I11) | J12: =IF('Raw Data - financials'!J11="","",'Raw Data - financials'!J11) | K12: =IF('Raw Data - financials'!K11="","",'Raw Data - financials'!K11) | ... W12: =IF('Raw Data - financials'!W11="","",'Raw Data - financials'!W11) | AC12: =IF('Raw Data - financials'!AC11="","",'Raw Data - financials'!AC11) | AD12: =IF('Raw Data - financials'!AD11="","",'Raw Data - financials'!AD11) | AE12: =IF('Raw Data - financials'!AE11="","",'Raw Data - financials'!AE11) | AF12: =IF('Raw Data - financials'!AF11="","",'Raw Data - financials'!AF11) | AG12: =IF('Raw Data - financials'!AG11="","",'Raw Data - financials'!AG11) | AH12: =IF('Raw Data - financials'!AH11="","",'Raw Data - financials'!AH11) | AI12: =IF('Raw Data - financials'!AI11="","",'Raw Data - financials'!AI11) | AJ12: =IF('Raw Data - financials'!AJ11="","",'Raw Data - financials'!AJ11) | AK12: 0 | AL12: 0 | AM12: 0 | AN12: 0
A13: Changes in inventories of finished goods and stock-in-trade | B13: Rs Mn | D13: =IF('Raw Data - financials'!D12="","",'Raw Data - financials'!D12) | E13: =IF('Raw Data - financials'!E12="","",'Raw Data - financials'!E12) | F13: =IF('Raw Data - financials'!F12="","",'Raw Data - financials'!F12) | G13: =IF('Raw Data - financials'!G12="","",'Raw Data - financials'!G12) | H13: =IF('Raw Data - financials'!H12="","",'Raw Data - financials'!H12) | I13: =IF('Raw Data - financials'!I12="","",'Raw Data - financials'!I12) | J13: =IF('Raw Data - financials'!J12="","",'Raw Data - financials'!J12) | K13: =IF('Raw Data - financials'!K12="","",'Raw Data - financials'!K12) | ... W13: =IF('Raw Data - financials'!W12="","",'Raw Data - financials'!W12) | AC13: =IF('Raw Data - financials'!AC12="","",'Raw Data - financials'!AC12) | AD13: =IF('Raw Data - financials'!AD12="","",'Raw Data - financials'!AD12) | AE13: =IF('Raw Data - financials'!AE12="","",'Raw Data - financials'!AE12) | AF13: =IF('Raw Data - financials'!AF12="","",'Raw Data - financials'!AF12) | AG13: =IF('Raw Data - financials'!AG12="","",'Raw Data - financials'!AG12) | AH13: =IF('Raw Data - financials'!AH12="","",'Raw Data - financials'!AH12) | AI13: =IF('Raw Data - financials'!AI12="","",'Raw Data - financials'!AI12) | AJ13: =IF('Raw Data - financials'!AJ12="","",'Raw Data - financials'!AJ12) | AK13: 0 | AL13: 0 | AM13: 0 | AN13: 0
A14: Employee benefits expense | B14: Rs Mn | D14: =IF('Projections'!D125="","",'Projections'!D125) | E14: =IF('Projections'!E125="","",'Projections'!E125) | F14: =IF('Projections'!F125="","",'Projections'!F125) | G14: =IF('Projections'!G125="","",'Projections'!G125) | H14: =IF('Projections'!H125="","",'Projections'!H125) | I14: =IF('Projections'!I125="","",'Projections'!I125) | J14: =IF('Projections'!J125="","",'Projections'!J125) | K14: =IF('Projections'!K125="","",'Projections'!K125) | ... W14: =IF('Projections'!W125="","",'Projections'!W125) | AC14: =IF('Projections'!AC125="","",'Projections'!AC125) | AD14: =IF('Projections'!AD125="","",'Projections'!AD125) | AE14: =IF('Projections'!AE125="","",'Projections'!AE125) | AF14: =IF('Projections'!AF125="","",'Projections'!AF125) | AG14: =IF('Projections'!AG125="","",'Projections'!AG125) | AH14: =IF('Projections'!AH125="","",'Projections'!AH125) | AI14: =IF('Projections'!AI125="","",'Projections'!AI125) | AJ14: =IF('Projections'!AJ125="","",'Projections'!AJ125) | ... AN14: =IF('Projections'!AN125="","",'Projections'!AN125)
A15: Finance costs | B15: Rs Mn | D15: =IF('Projections'!D126="","",'Projections'!D126) | E15: =IF('Projections'!E126="","",'Projections'!E126) | F15: =IF('Projections'!F126="","",'Projections'!F126) | G15: =IF('Projections'!G126="","",'Projections'!G126) | H15: =IF('Projections'!H126="","",'Projections'!H126) | I15: =IF('Projections'!I126="","",'Projections'!I126) | J15: =IF('Projections'!J126="","",'Projections'!J126) | K15: =IF('Projections'!K126="","",'Projections'!K126) | ... W15: =IF('Projections'!W126="","",'Projections'!W126) | AC15: =IF('Projections'!AC126="","",'Projections'!AC126) | AD15: =IF('Projections'!AD126="","",'Projections'!AD126) | AE15: =IF('Projections'!AE126="","",'Projections'!AE126) | AF15: =IF('Projections'!AF126="","",'Projections'!AF126) | AG15: =IF('Projections'!AG126="","",'Projections'!AG126) | AH15: =IF('Projections'!AH126="","",'Projections'!AH126) | AI15: =IF('Projections'!AI126="","",'Projections'!AI126) | AJ15: =IF('Projections'!AJ126="","",'Projections'!AJ126) | ... AN15: =IF('Projections'!AN126="","",'Projections'!AN126)
A16: Depreciation and amortisation expense | B16: Rs Mn | D16: =IF('Projections'!D127="","",'Projections'!D127) | E16: =IF('Projections'!E127="","",'Projections'!E127) | F16: =IF('Projections'!F127="","",'Projections'!F127) | G16: =IF('Projections'!G127="","",'Projections'!G127) | H16: =IF('Projections'!H127="","",'Projections'!H127) | I16: =IF('Projections'!I127="","",'Projections'!I127) | J16: =IF('Projections'!J127="","",'Projections'!J127) | K16: =IF('Projections'!K127="","",'Projections'!K127) | ... W16: =IF('Projections'!W127="","",'Projections'!W127) | AC16: =IF('Projections'!AC127="","",'Projections'!AC127) | AD16: =IF('Projections'!AD127="","",'Projections'!AD127) | AE16: =IF('Projections'!AE127="","",'Projections'!AE127) | AF16: =IF('Projections'!AF127="","",'Projections'!AF127) | AG16: =IF('Projections'!AG127="","",'Projections'!AG127) | AH16: =IF('Projections'!AH127="","",'Projections'!AH127) | AI16: =IF('Projections'!AI127="","",'Projections'!AI127) | AJ16: =IF('Projections'!AJ127="","",'Projections'!AJ127) | ... AN16: =IF('Projections'!AN127="","",'Projections'!AN127)
A17: Other expenses | B17: Rs Mn | D17: =IF('Projections'!D128="","",'Projections'!D128) | E17: =IF('Projections'!E128="","",'Projections'!E128) | F17: =IF('Projections'!F128="","",'Projections'!F128) | G17: =IF('Projections'!G128="","",'Projections'!G128) | H17: =IF('Projections'!H128="","",'Projections'!H128) | I17: =IF('Projections'!I128="","",'Projections'!I128) | J17: =IF('Projections'!J128="","",'Projections'!J128) | K17: =IF('Projections'!K128="","",'Projections'!K128) | ... W17: =IF('Projections'!W128="","",'Projections'!W128) | AC17: =IF('Projections'!AC128="","",'Projections'!AC128) | AD17: =IF('Projections'!AD128="","",'Projections'!AD128) | AE17: =IF('Projections'!AE128="","",'Projections'!AE128) | AF17: =IF('Projections'!AF128="","",'Projections'!AF128) | AG17: =IF('Projections'!AG128="","",'Projections'!AG128) | AH17: =IF('Projections'!AH128="","",'Projections'!AH128) | AI17: =IF('Projections'!AI128="","",'Projections'!AI128) | AJ17: =IF('Projections'!AJ128="","",'Projections'!AJ128) | ... AN17: =IF('Projections'!AN128="","",'Projections'!AN128)
A18: Total Expenses | B18: Rs Mn | D18: =IFERROR(D11+D12+D13+D14+D15+D16+D17,"") | E18: =IFERROR(E11+E12+E13+E14+E15+E16+E17,"") | F18: =IFERROR(F11+F12+F13+F14+F15+F16+F17,"") | G18: =IFERROR(G11+G12+G13+G14+G15+G16+G17,"") | H18: =IFERROR(H11+H12+H13+H14+H15+H16+H17,"") | I18: =IFERROR(I11+I12+I13+I14+I15+I16+I17,"") | J18: =IFERROR(J11+J12+J13+J14+J15+J16+J17,"") | K18: =IFERROR(K11+K12+K13+K14+K15+K16+K17,"") | ... W18: =IFERROR(W11+W12+W13+W14+W15+W16+W17,"") | AC18: =IFERROR(AC11+AC12+AC13+AC14+AC15+AC16+AC17,"") | AD18: =IFERROR(AD11+AD12+AD13+AD14+AD15+AD16+AD17,"") | AE18: =IFERROR(AE11+AE12+AE13+AE14+AE15+AE16+AE17,"") | AF18: =IFERROR(AF11+AF12+AF13+AF14+AF15+AF16+AF17,"") | AG18: =IFERROR(AG11+AG12+AG13+AG14+AG15+AG16+AG17,"") | AH18: =IFERROR(AH11+AH12+AH13+AH14+AH15+AH16+AH17,"") | AI18: =IFERROR(AI11+AI12+AI13+AI14+AI15+AI16+AI17,"") | AJ18: =IFERROR(AJ11+AJ12+AJ13+AJ14+AJ15+AJ16+AJ17,"") | ... AN18: =IFERROR(AN11+AN12+AN13+AN14+AN15+AN16+AN17,"")
A20: Profit Before Exceptional Items and Tax | B20: Rs Mn | D20: =IFERROR(D8-D18,"") | E20: =IFERROR(E8-E18,"") | F20: =IFERROR(F8-F18,"") | G20: =IFERROR(G8-G18,"") | H20: =IFERROR(H8-H18,"") | I20: =IFERROR(I8-I18,"") | J20: =IFERROR(J8-J18,"") | K20: =IFERROR(K8-K18,"") | ... W20: =IFERROR(W8-W18,"") | AC20: =IFERROR(AC8-AC18,"") | AD20: =IFERROR(AD8-AD18,"") | AE20: =IFERROR(AE8-AE18,"") | AF20: =IFERROR(AF8-AF18,"") | AG20: =IFERROR(AG8-AG18,"") | AH20: =IFERROR(AH8-AH18,"") | AI20: =IFERROR(AI8-AI18,"") | AJ20: =IFERROR(AJ8-AJ18,"") | ... AN20: =IFERROR(AN8-AN18,"")
A21: Exceptional items, net | B21: Rs Mn | D21: =IF('Raw Data - financials'!D20="","",'Raw Data - financials'!D20) | E21: =IF('Raw Data - financials'!E20="","",'Raw Data - financials'!E20) | F21: =IF('Raw Data - financials'!F20="","",'Raw Data - financials'!F20) | G21: =IF('Raw Data - financials'!G20="","",'Raw Data - financials'!G20) | H21: =IF('Raw Data - financials'!H20="","",'Raw Data - financials'!H20) | I21: =IF('Raw Data - financials'!I20="","",'Raw Data - financials'!I20) | J21: =IF('Raw Data - financials'!J20="","",'Raw Data - financials'!J20) | K21: =IF('Raw Data - financials'!K20="","",'Raw Data - financials'!K20) | ... W21: =IF('Raw Data - financials'!W20="","",'Raw Data - financials'!W20) | AC21: =IF('Raw Data - financials'!AC20="","",'Raw Data - financials'!AC20) | AD21: =IF('Raw Data - financials'!AD20="","",'Raw Data - financials'!AD20) | AE21: =IF('Raw Data - financials'!AE20="","",'Raw Data - financials'!AE20) | AF21: =IF('Raw Data - financials'!AF20="","",'Raw Data - financials'!AF20) | AG21: =IF('Raw Data - financials'!AG20="","",'Raw Data - financials'!AG20) | AH21: =IF('Raw Data - financials'!AH20="","",'Raw Data - financials'!AH20) | AI21: =IF('Raw Data - financials'!AI20="","",'Raw Data - financials'!AI20) | AJ21: =IF('Raw Data - financials'!AJ20="","",'Raw Data - financials'!AJ20) | AK21: 0 | AL21: 0 | AM21: 0 | AN21: 0
A22: Profit Before Tax | B22: Rs Mn | D22: =IFERROR(D20-D21,"") | E22: =IFERROR(E20-E21,"") | F22: =IFERROR(F20-F21,"") | G22: =IFERROR(G20-G21,"") | H22: =IFERROR(H20-H21,"") | I22: =IFERROR(I20-I21,"") | J22: =IFERROR(J20-J21,"") | K22: =IFERROR(K20-K21,"") | ... W22: =IFERROR(W20-W21,"") | AC22: =IFERROR(AC20-AC21,"") | AD22: =IFERROR(AD20-AD21,"") | AE22: =IFERROR(AE20-AE21,"") | AF22: =IFERROR(AF20-AF21,"") | AG22: =IFERROR(AG20-AG21,"") | AH22: =IFERROR(AH20-AH21,"") | AI22: =IFERROR(AI20-AI21,"") | AJ22: =IFERROR(AJ20-AJ21,"") | ... AN22: =IFERROR(AN20-AN21,"")
A24: Tax expense
A25: Current tax | B25: Rs Mn | D25: =IF('Raw Data - financials'!D24="","",'Raw Data - financials'!D24) | E25: =IF('Raw Data - financials'!E24="","",'Raw Data - financials'!E24) | F25: =IF('Raw Data - financials'!F24="","",'Raw Data - financials'!F24) | G25: =IF('Raw Data - financials'!G24="","",'Raw Data - financials'!G24) | H25: =IF('Raw Data - financials'!H24="","",'Raw Data - financials'!H24) | I25: =IF('Raw Data - financials'!I24="","",'Raw Data - financials'!I24) | J25: =IF('Raw Data - financials'!J24="","",'Raw Data - financials'!J24) | K25: =IF('Raw Data - financials'!K24="","",'Raw Data - financials'!K24) | ... W25: =IF('Raw Data - financials'!W24="","",'Raw Data - financials'!W24) | AC25: =IF('Raw Data - financials'!AC24="","",'Raw Data - financials'!AC24) | AD25: =IF('Raw Data - financials'!AD24="","",'Raw Data - financials'!AD24) | AE25: =IF('Raw Data - financials'!AE24="","",'Raw Data - financials'!AE24) | AF25: =IF('Raw Data - financials'!AF24="","",'Raw Data - financials'!AF24) | AG25: =IF('Raw Data - financials'!AG24="","",'Raw Data - financials'!AG24) | AH25: =IF('Raw Data - financials'!AH24="","",'Raw Data - financials'!AH24) | AI25: =IF('Raw Data - financials'!AI24="","",'Raw Data - financials'!AI24) | AJ25: =IF('Raw Data - financials'!AJ24="","",'Raw Data - financials'!AJ24) | AK25: =IF('Projections'!AK131="","",'Projections'!AK131) | AL25: =IF('Projections'!AL131="","",'Projections'!AL131) | AM25: =IF('Projections'!AM131="","",'Projections'!AM131) | AN25: =IF('Projections'!AN131="","",'Projections'!AN131)
A26: Current tax pertaining to earlier years | B26: Rs Mn | D26: =IF('Raw Data - financials'!D25="","",'Raw Data - financials'!D25) | E26: =IF('Raw Data - financials'!E25="","",'Raw Data - financials'!E25) | F26: =IF('Raw Data - financials'!F25="","",'Raw Data - financials'!F25) | G26: =IF('Raw Data - financials'!G25="","",'Raw Data - financials'!G25) | H26: =IF('Raw Data - financials'!H25="","",'Raw Data - financials'!H25) | I26: =IF('Raw Data - financials'!I25="","",'Raw Data - financials'!I25) | J26: =IF('Raw Data - financials'!J25="","",'Raw Data - financials'!J25) | K26: =IF('Raw Data - financials'!K25="","",'Raw Data - financials'!K25) | ... W26: =IF('Raw Data - financials'!W25="","",'Raw Data - financials'!W25) | AC26: =IF('Raw Data - financials'!AC25="","",'Raw Data - financials'!AC25) | AD26: =IF('Raw Data - financials'!AD25="","",'Raw Data - financials'!AD25) | AE26: =IF('Raw Data - financials'!AE25="","",'Raw Data - financials'!AE25) | AF26: =IF('Raw Data - financials'!AF25="","",'Raw Data - financials'!AF25) | AG26: =IF('Raw Data - financials'!AG25="","",'Raw Data - financials'!AG25) | AH26: =IF('Raw Data - financials'!AH25="","",'Raw Data - financials'!AH25) | AI26: =IF('Raw Data - financials'!AI25="","",'Raw Data - financials'!AI25) | AJ26: =IF('Raw Data - financials'!AJ25="","",'Raw Data - financials'!AJ25) | AK26: 0 | AL26: 0 | AM26: 0 | AN26: 0
A27: Deferred tax expense/(credit) | B27: Rs Mn | D27: =IF('Raw Data - financials'!D26="","",'Raw Data - financials'!D26) | E27: =IF('Raw Data - financials'!E26="","",'Raw Data - financials'!E26) | F27: =IF('Raw Data - financials'!F26="","",'Raw Data - financials'!F26) | G27: =IF('Raw Data - financials'!G26="","",'Raw Data - financials'!G26) | H27: =IF('Raw Data - financials'!H26="","",'Raw Data - financials'!H26) | I27: =IF('Raw Data - financials'!I26="","",'Raw Data - financials'!I26) | J27: =IF('Raw Data - financials'!J26="","",'Raw Data - financials'!J26) | K27: =IF('Raw Data - financials'!K26="","",'Raw Data - financials'!K26) | ... W27: =IF('Raw Data - financials'!W26="","",'Raw Data - financials'!W26) | AC27: =IF('Raw Data - financials'!AC26="","",'Raw Data - financials'!AC26) | AD27: =IF('Raw Data - financials'!AD26="","",'Raw Data - financials'!AD26) | AE27: =IF('Raw Data - financials'!AE26="","",'Raw Data - financials'!AE26) | AF27: =IF('Raw Data - financials'!AF26="","",'Raw Data - financials'!AF26) | AG27: =IF('Raw Data - financials'!AG26="","",'Raw Data - financials'!AG26) | AH27: =IF('Raw Data - financials'!AH26="","",'Raw Data - financials'!AH26) | AI27: =IF('Raw Data - financials'!AI26="","",'Raw Data - financials'!AI26) | AJ27: =IF('Raw Data - financials'!AJ26="","",'Raw Data - financials'!AJ26) | AK27: 0 | AL27: 0 | AM27: 0 | AN27: 0
A28: Deferred tax credit for unrecognised business loss (earlier years) | B28: Rs Mn | D28: =IF('Raw Data - financials'!D27="","",'Raw Data - financials'!D27) | E28: =IF('Raw Data - financials'!E27="","",'Raw Data - financials'!E27) | F28: =IF('Raw Data - financials'!F27="","",'Raw Data - financials'!F27) | G28: =IF('Raw Data - financials'!G27="","",'Raw Data - financials'!G27) | H28: =IF('Raw Data - financials'!H27="","",'Raw Data - financials'!H27) | I28: =IF('Raw Data - financials'!I27="","",'Raw Data - financials'!I27) | J28: =IF('Raw Data - financials'!J27="","",'Raw Data - financials'!J27) | K28: =IF('Raw Data - financials'!K27="","",'Raw Data - financials'!K27) | ... W28: =IF('Raw Data - financials'!W27="","",'Raw Data - financials'!W27) | AC28: =IF('Raw Data - financials'!AC27="","",'Raw Data - financials'!AC27) | AD28: =IF('Raw Data - financials'!AD27="","",'Raw Data - financials'!AD27) | AE28: =IF('Raw Data - financials'!AE27="","",'Raw Data - financials'!AE27) | AF28: =IF('Raw Data - financials'!AF27="","",'Raw Data - financials'!AF27) | AG28: =IF('Raw Data - financials'!AG27="","",'Raw Data - financials'!AG27) | AH28: =IF('Raw Data - financials'!AH27="","",'Raw Data - financials'!AH27) | AI28: =IF('Raw Data - financials'!AI27="","",'Raw Data - financials'!AI27) | AJ28: =IF('Raw Data - financials'!AJ27="","",'Raw Data - financials'!AJ27) | AK28: 0 | AL28: 0 | AM28: 0 | AN28: 0
A29: Total Tax Expense/(Income) | B29: Rs Mn | D29: =IFERROR(D25+D26+D27+D28,"") | E29: =IFERROR(E25+E26+E27+E28,"") | F29: =IFERROR(F25+F26+F27+F28,"") | G29: =IFERROR(G25+G26+G27+G28,"") | H29: =IFERROR(H25+H26+H27+H28,"") | I29: =IFERROR(I25+I26+I27+I28,"") | J29: =IFERROR(J25+J26+J27+J28,"") | K29: =IFERROR(K25+K26+K27+K28,"") | ... W29: =IFERROR(W25+W26+W27+W28,"") | AC29: =IFERROR(AC25+AC26+AC27+AC28,"") | AD29: =IFERROR(AD25+AD26+AD27+AD28,"") | AE29: =IFERROR(AE25+AE26+AE27+AE28,"") | AF29: =IFERROR(AF25+AF26+AF27+AF28,"") | AG29: =IFERROR(AG25+AG26+AG27+AG28,"") | AH29: =IFERROR(AH25+AH26+AH27+AH28,"") | AI29: =IFERROR(AI25+AI26+AI27+AI28,"") | AJ29: =IFERROR(AJ25+AJ26+AJ27+AJ28,"") | ... AN29: =IFERROR(AN25+AN26+AN27+AN28,"")
A31: Profit After Tax (PAT) | B31: Rs Mn | D31: =IFERROR(D22-D29,"") | E31: =IFERROR(E22-E29,"") | F31: =IFERROR(F22-F29,"") | G31: =IFERROR(G22-G29,"") | H31: =IFERROR(H22-H29,"") | I31: =IFERROR(I22-I29,"") | J31: =IFERROR(J22-J29,"") | K31: =IFERROR(K22-K29,"") | ... W31: =IFERROR(W22-W29,"") | AC31: =IFERROR(AC22-AC29,"") | AD31: =IFERROR(AD22-AD29,"") | AE31: =IFERROR(AE22-AE29,"") | AF31: =IFERROR(AF22-AF29,"") | AG31: =IFERROR(AG22-AG29,"") | AH31: =IFERROR(AH22-AH29,"") | AI31: =IFERROR(AI22-AI29,"") | AJ31: =IFERROR(AJ22-AJ29,"") | ... AN31: =IFERROR(AN22-AN29,"")
A32: EPS (diluted) | B32: Rs | D32: =IF('Projections'!D133="","",'Projections'!D133) | E32: =IF('Projections'!E133="","",'Projections'!E133) | F32: =IF('Projections'!F133="","",'Projections'!F133) | G32: =IF('Projections'!G133="","",'Projections'!G133) | H32: =IF('Projections'!H133="","",'Projections'!H133) | I32: =IF('Projections'!I133="","",'Projections'!I133) | J32: =IF('Projections'!J133="","",'Projections'!J133) | K32: =IF('Projections'!K133="","",'Projections'!K133) | ... W32: =IF('Projections'!W133="","",'Projections'!W133) | AC32: =IF('Projections'!AC133="","",'Projections'!AC133) | AD32: =IF('Projections'!AD133="","",'Projections'!AD133) | AE32: =IF('Projections'!AE133="","",'Projections'!AE133) | AF32: =IF('Projections'!AF133="","",'Projections'!AF133) | AG32: =IF('Projections'!AG133="","",'Projections'!AG133) | AH32: =IF('Projections'!AH133="","",'Projections'!AH133) | AI32: =IF('Projections'!AI133="","",'Projections'!AI133) | AJ32: =IF('Projections'!AJ133="","",'Projections'!AJ133) | ... AN32: =IF('Projections'!AN133="","",'Projections'!AN133)
A34: BALANCE SHEET (CONSOLIDATED, REPORTED FORMAT)
A35: Historical quarters/years link straight to Raw Data - financials actuals (full granularity). For FY27E-30E, only the lines that map to the Projections sheet's summarized Balance Sheet are populated (Property, plant and equipment carries the full 'Fixed assets & intangibles, net' figure; Financial assets - Investments carries the combined Investments figure; Other non-current assets carries the combined Other assets figure; Borrowings [non-current] carries total Borrowings; Trade payables - other creditors carries total Trade payables; Other current liabilities carries combined Other liabilities) -- the remaining reported sub-lines in each group are left blank/0 for projected years. Subtotals (Total Non-Current/Current Assets etc.) are formulas here, not links, so they work for both historical and projected columns; they tie to the Raw Data actuals historically and to the Projections summarized Balance Sheet for FY27E-30E.
A36: ASSETS
A37: Non-current assets
A38: Property, plant and equipment | B38: Rs Mn | E38: =IF('Raw Data - financials'!E49="","",'Raw Data - financials'!E49) | G38: =IF('Raw Data - financials'!G49="","",'Raw Data - financials'!G49) | I38: =IF('Raw Data - financials'!I49="","",'Raw Data - financials'!I49) | K38: =IF('Raw Data - financials'!K49="","",'Raw Data - financials'!K49) | M38: =IF('Raw Data - financials'!M49="","",'Raw Data - financials'!M49) | O38: =IF('Raw Data - financials'!O49="","",'Raw Data - financials'!O49) | Q38: =IF('Raw Data - financials'!Q49="","",'Raw Data - financials'!Q49) | S38: =IF('Raw Data - financials'!S49="","",'Raw Data - financials'!S49) | U38: =IF('Raw Data - financials'!U49="","",'Raw Data - financials'!U49) | W38: =IF('Raw Data - financials'!W49="","",'Raw Data - financials'!W49) | AC38: =IF('Raw Data - financials'!AC49="","",'Raw Data - financials'!AC49) | AD38: =IF('Raw Data - financials'!AD49="","",'Raw Data - financials'!AD49) | AE38: =IF('Raw Data - financials'!AE49="","",'Raw Data - financials'!AE49) | AF38: =IF('Raw Data - financials'!AF49="","",'Raw Data - financials'!AF49) | AG38: =IF('Raw Data - financials'!AG49="","",'Raw Data - financials'!AG49) | AH38: =IF('Raw Data - financials'!AH49="","",'Raw Data - financials'!AH49) | AI38: =IF('Raw Data - financials'!AI49="","",'Raw Data - financials'!AI49) | AJ38: =IF('Raw Data - financials'!AJ49="","",'Raw Data - financials'!AJ49) | AK38: =IF('Projections'!AK139="","",'Projections'!AK139) | AL38: =IF('Projections'!AL139="","",'Projections'!AL139) | AM38: =IF('Projections'!AM139="","",'Projections'!AM139) | AN38: =IF('Projections'!AN139="","",'Projections'!AN139)
A39: Capital work-in-progress | B39: Rs Mn | E39: =IF('Raw Data - financials'!E50="","",'Raw Data - financials'!E50) | G39: =IF('Raw Data - financials'!G50="","",'Raw Data - financials'!G50) | I39: =IF('Raw Data - financials'!I50="","",'Raw Data - financials'!I50) | K39: =IF('Raw Data - financials'!K50="","",'Raw Data - financials'!K50) | M39: =IF('Raw Data - financials'!M50="","",'Raw Data - financials'!M50) | O39: =IF('Raw Data - financials'!O50="","",'Raw Data - financials'!O50) | Q39: =IF('Raw Data - financials'!Q50="","",'Raw Data - financials'!Q50) | S39: =IF('Raw Data - financials'!S50="","",'Raw Data - financials'!S50) | U39: =IF('Raw Data - financials'!U50="","",'Raw Data - financials'!U50) | W39: =IF('Raw Data - financials'!W50="","",'Raw Data - financials'!W50) | AC39: =IF('Raw Data - financials'!AC50="","",'Raw Data - financials'!AC50) | AD39: =IF('Raw Data - financials'!AD50="","",'Raw Data - financials'!AD50) | AE39: =IF('Raw Data - financials'!AE50="","",'Raw Data - financials'!AE50) | AF39: =IF('Raw Data - financials'!AF50="","",'Raw Data - financials'!AF50) | AG39: =IF('Raw Data - financials'!AG50="","",'Raw Data - financials'!AG50) | AH39: =IF('Raw Data - financials'!AH50="","",'Raw Data - financials'!AH50) | AI39: =IF('Raw Data - financials'!AI50="","",'Raw Data - financials'!AI50) | AJ39: =IF('Raw Data - financials'!AJ50="","",'Raw Data - financials'!AJ50) | AK39: 0 | AL39: 0 | AM39: 0 | AN39: 0
A40: Goodwill | B40: Rs Mn | E40: =IF('Raw Data - financials'!E51="","",'Raw Data - financials'!E51) | G40: =IF('Raw Data - financials'!G51="","",'Raw Data - financials'!G51) | I40: =IF('Raw Data - financials'!I51="","",'Raw Data - financials'!I51) | K40: =IF('Raw Data - financials'!K51="","",'Raw Data - financials'!K51) | M40: =IF('Raw Data - financials'!M51="","",'Raw Data - financials'!M51) | O40: =IF('Raw Data - financials'!O51="","",'Raw Data - financials'!O51) | Q40: =IF('Raw Data - financials'!Q51="","",'Raw Data - financials'!Q51) | S40: =IF('Raw Data - financials'!S51="","",'Raw Data - financials'!S51) | U40: =IF('Raw Data - financials'!U51="","",'Raw Data - financials'!U51) | W40: =IF('Raw Data - financials'!W51="","",'Raw Data - financials'!W51) | AC40: =IF('Raw Data - financials'!AC51="","",'Raw Data - financials'!AC51) | AD40: =IF('Raw Data - financials'!AD51="","",'Raw Data - financials'!AD51) | AE40: =IF('Raw Data - financials'!AE51="","",'Raw Data - financials'!AE51) | AF40: =IF('Raw Data - financials'!AF51="","",'Raw Data - financials'!AF51) | AG40: =IF('Raw Data - financials'!AG51="","",'Raw Data - financials'!AG51) | AH40: =IF('Raw Data - financials'!AH51="","",'Raw Data - financials'!AH51) | AI40: =IF('Raw Data - financials'!AI51="","",'Raw Data - financials'!AI51) | AJ40: =IF('Raw Data - financials'!AJ51="","",'Raw Data - financials'!AJ51) | AK40: 0 | AL40: 0 | AM40: 0 | AN40: 0
A41: Other intangible assets | B41: Rs Mn | E41: =IF('Raw Data - financials'!E52="","",'Raw Data - financials'!E52) | G41: =IF('Raw Data - financials'!G52="","",'Raw Data - financials'!G52) | I41: =IF('Raw Data - financials'!I52="","",'Raw Data - financials'!I52) | K41: =IF('Raw Data - financials'!K52="","",'Raw Data - financials'!K52) | M41: =IF('Raw Data - financials'!M52="","",'Raw Data - financials'!M52) | O41: =IF('Raw Data - financials'!O52="","",'Raw Data - financials'!O52) | Q41: =IF('Raw Data - financials'!Q52="","",'Raw Data - financials'!Q52) | S41: =IF('Raw Data - financials'!S52="","",'Raw Data - financials'!S52) | U41: =IF('Raw Data - financials'!U52="","",'Raw Data - financials'!U52) | W41: =IF('Raw Data - financials'!W52="","",'Raw Data - financials'!W52) | AC41: =IF('Raw Data - financials'!AC52="","",'Raw Data - financials'!AC52) | AD41: =IF('Raw Data - financials'!AD52="","",'Raw Data - financials'!AD52) | AE41: =IF('Raw Data - financials'!AE52="","",'Raw Data - financials'!AE52) | AF41: =IF('Raw Data - financials'!AF52="","",'Raw Data - financials'!AF52) | AG41: =IF('Raw Data - financials'!AG52="","",'Raw Data - financials'!AG52) | AH41: =IF('Raw Data - financials'!AH52="","",'Raw Data - financials'!AH52) | AI41: =IF('Raw Data - financials'!AI52="","",'Raw Data - financials'!AI52) | AJ41: =IF('Raw Data - financials'!AJ52="","",'Raw Data - financials'!AJ52) | AK41: 0 | AL41: 0 | AM41: 0 | AN41: 0
A42: Right of use assets | B42: Rs Mn | E42: =IF('Raw Data - financials'!E53="","",'Raw Data - financials'!E53) | G42: =IF('Raw Data - financials'!G53="","",'Raw Data - financials'!G53) | I42: =IF('Raw Data - financials'!I53="","",'Raw Data - financials'!I53) | K42: =IF('Raw Data - financials'!K53="","",'Raw Data - financials'!K53) | M42: =IF('Raw Data - financials'!M53="","",'Raw Data - financials'!M53) | O42: =IF('Raw Data - financials'!O53="","",'Raw Data - financials'!O53) | Q42: =IF('Raw Data - financials'!Q53="","",'Raw Data - financials'!Q53) | S42: =IF('Raw Data - financials'!S53="","",'Raw Data - financials'!S53) | U42: =IF('Raw Data - financials'!U53="","",'Raw Data - financials'!U53) | W42: =IF('Raw Data - financials'!W53="","",'Raw Data - financials'!W53) | AC42: =IF('Raw Data - financials'!AC53="","",'Raw Data - financials'!AC53) | AD42: =IF('Raw Data - financials'!AD53="","",'Raw Data - financials'!AD53) | AE42: =IF('Raw Data - financials'!AE53="","",'Raw Data - financials'!AE53) | AF42: =IF('Raw Data - financials'!AF53="","",'Raw Data - financials'!AF53) | AG42: =IF('Raw Data - financials'!AG53="","",'Raw Data - financials'!AG53) | AH42: =IF('Raw Data - financials'!AH53="","",'Raw Data - financials'!AH53) | AI42: =IF('Raw Data - financials'!AI53="","",'Raw Data - financials'!AI53) | AJ42: =IF('Raw Data - financials'!AJ53="","",'Raw Data - financials'!AJ53) | AK42: 0 | AL42: 0 | AM42: 0 | AN42: 0
A43: Intangible assets under development | B43: Rs Mn | E43: =IF('Raw Data - financials'!E54="","",'Raw Data - financials'!E54) | G43: =IF('Raw Data - financials'!G54="","",'Raw Data - financials'!G54) | I43: =IF('Raw Data - financials'!I54="","",'Raw Data - financials'!I54) | K43: =IF('Raw Data - financials'!K54="","",'Raw Data - financials'!K54) | M43: =IF('Raw Data - financials'!M54="","",'Raw Data - financials'!M54) | O43: =IF('Raw Data - financials'!O54="","",'Raw Data - financials'!O54) | Q43: =IF('Raw Data - financials'!Q54="","",'Raw Data - financials'!Q54) | S43: =IF('Raw Data - financials'!S54="","",'Raw Data - financials'!S54) | U43: =IF('Raw Data - financials'!U54="","",'Raw Data - financials'!U54) | W43: =IF('Raw Data - financials'!W54="","",'Raw Data - financials'!W54) | AC43: =IF('Raw Data - financials'!AC54="","",'Raw Data - financials'!AC54) | AD43: =IF('Raw Data - financials'!AD54="","",'Raw Data - financials'!AD54) | AE43: =IF('Raw Data - financials'!AE54="","",'Raw Data - financials'!AE54) | AF43: =IF('Raw Data - financials'!AF54="","",'Raw Data - financials'!AF54) | AG43: =IF('Raw Data - financials'!AG54="","",'Raw Data - financials'!AG54) | AH43: =IF('Raw Data - financials'!AH54="","",'Raw Data - financials'!AH54) | AI43: =IF('Raw Data - financials'!AI54="","",'Raw Data - financials'!AI54) | AJ43: =IF('Raw Data - financials'!AJ54="","",'Raw Data - financials'!AJ54) | AK43: 0 | AL43: 0 | AM43: 0 | AN43: 0
A44: Investments accounted for using equity method | B44: Rs Mn | E44: =IF('Raw Data - financials'!E55="","",'Raw Data - financials'!E55) | G44: =IF('Raw Data - financials'!G55="","",'Raw Data - financials'!G55) | I44: =IF('Raw Data - financials'!I55="","",'Raw Data - financials'!I55) | K44: =IF('Raw Data - financials'!K55="","",'Raw Data - financials'!K55) | M44: =IF('Raw Data - financials'!M55="","",'Raw Data - financials'!M55) | O44: =IF('Raw Data - financials'!O55="","",'Raw Data - financials'!O55) | Q44: =IF('Raw Data - financials'!Q55="","",'Raw Data - financials'!Q55) | S44: =IF('Raw Data - financials'!S55="","",'Raw Data - financials'!S55) | U44: =IF('Raw Data - financials'!U55="","",'Raw Data - financials'!U55) | W44: =IF('Raw Data - financials'!W55="","",'Raw Data - financials'!W55) | AC44: =IF('Raw Data - financials'!AC55="","",'Raw Data - financials'!AC55) | AD44: =IF('Raw Data - financials'!AD55="","",'Raw Data - financials'!AD55) | AE44: =IF('Raw Data - financials'!AE55="","",'Raw Data - financials'!AE55) | AF44: =IF('Raw Data - financials'!AF55="","",'Raw Data - financials'!AF55) | AG44: =IF('Raw Data - financials'!AG55="","",'Raw Data - financials'!AG55) | AH44: =IF('Raw Data - financials'!AH55="","",'Raw Data - financials'!AH55) | AI44: =IF('Raw Data - financials'!AI55="","",'Raw Data - financials'!AI55) | AJ44: =IF('Raw Data - financials'!AJ55="","",'Raw Data - financials'!AJ55) | AK44: 0 | AL44: 0 | AM44: 0 | AN44: 0
A45: Financial assets - Investments | B45: Rs Mn | E45: =IF('Raw Data - financials'!E56="","",'Raw Data - financials'!E56) | G45: =IF('Raw Data - financials'!G56="","",'Raw Data - financials'!G56) | I45: =IF('Raw Data - financials'!I56="","",'Raw Data - financials'!I56) | K45: =IF('Raw Data - financials'!K56="","",'Raw Data - financials'!K56) | M45: =IF('Raw Data - financials'!M56="","",'Raw Data - financials'!M56) | O45: =IF('Raw Data - financials'!O56="","",'Raw Data - financials'!O56) | Q45: =IF('Raw Data - financials'!Q56="","",'Raw Data - financials'!Q56) | S45: =IF('Raw Data - financials'!S56="","",'Raw Data - financials'!S56) | U45: =IF('Raw Data - financials'!U56="","",'Raw Data - financials'!U56) | W45: =IF('Raw Data - financials'!W56="","",'Raw Data - financials'!W56) | AC45: =IF('Raw Data - financials'!AC56="","",'Raw Data - financials'!AC56) | AD45: =IF('Raw Data - financials'!AD56="","",'Raw Data - financials'!AD56) | AE45: =IF('Raw Data - financials'!AE56="","",'Raw Data - financials'!AE56) | AF45: =IF('Raw Data - financials'!AF56="","",'Raw Data - financials'!AF56) | AG45: =IF('Raw Data - financials'!AG56="","",'Raw Data - financials'!AG56) | AH45: =IF('Raw Data - financials'!AH56="","",'Raw Data - financials'!AH56) | AI45: =IF('Raw Data - financials'!AI56="","",'Raw Data - financials'!AI56) | AJ45: =IF('Raw Data - financials'!AJ56="","",'Raw Data - financials'!AJ56) | AK45: =IF('Projections'!AK140="","",'Projections'!AK140) | AL45: =IF('Projections'!AL140="","",'Projections'!AL140) | AM45: =IF('Projections'!AM140="","",'Projections'!AM140) | AN45: =IF('Projections'!AN140="","",'Projections'!AN140)
A46: Financial assets - Loans | B46: Rs Mn | E46: =IF('Raw Data - financials'!E57="","",'Raw Data - financials'!E57) | G46: =IF('Raw Data - financials'!G57="","",'Raw Data - financials'!G57) | I46: =IF('Raw Data - financials'!I57="","",'Raw Data - financials'!I57) | K46: =IF('Raw Data - financials'!K57="","",'Raw Data - financials'!K57) | M46: =IF('Raw Data - financials'!M57="","",'Raw Data - financials'!M57) | O46: =IF('Raw Data - financials'!O57="","",'Raw Data - financials'!O57) | Q46: =IF('Raw Data - financials'!Q57="","",'Raw Data - financials'!Q57) | S46: =IF('Raw Data - financials'!S57="","",'Raw Data - financials'!S57) | U46: =IF('Raw Data - financials'!U57="","",'Raw Data - financials'!U57) | W46: =IF('Raw Data - financials'!W57="","",'Raw Data - financials'!W57) | AC46: =IF('Raw Data - financials'!AC57="","",'Raw Data - financials'!AC57) | AD46: =IF('Raw Data - financials'!AD57="","",'Raw Data - financials'!AD57) | AE46: =IF('Raw Data - financials'!AE57="","",'Raw Data - financials'!AE57) | AF46: =IF('Raw Data - financials'!AF57="","",'Raw Data - financials'!AF57) | AG46: =IF('Raw Data - financials'!AG57="","",'Raw Data - financials'!AG57) | AH46: =IF('Raw Data - financials'!AH57="","",'Raw Data - financials'!AH57) | AI46: =IF('Raw Data - financials'!AI57="","",'Raw Data - financials'!AI57) | AJ46: =IF('Raw Data - financials'!AJ57="","",'Raw Data - financials'!AJ57) | AK46: 0 | AL46: 0 | AM46: 0 | AN46: 0
A47: Financial assets - Other financial assets | B47: Rs Mn | E47: =IF('Raw Data - financials'!E58="","",'Raw Data - financials'!E58) | G47: =IF('Raw Data - financials'!G58="","",'Raw Data - financials'!G58) | I47: =IF('Raw Data - financials'!I58="","",'Raw Data - financials'!I58) | K47: =IF('Raw Data - financials'!K58="","",'Raw Data - financials'!K58) | M47: =IF('Raw Data - financials'!M58="","",'Raw Data - financials'!M58) | O47: =IF('Raw Data - financials'!O58="","",'Raw Data - financials'!O58) | Q47: =IF('Raw Data - financials'!Q58="","",'Raw Data - financials'!Q58) | S47: =IF('Raw Data - financials'!S58="","",'Raw Data - financials'!S58) | U47: =IF('Raw Data - financials'!U58="","",'Raw Data - financials'!U58) | W47: =IF('Raw Data - financials'!W58="","",'Raw Data - financials'!W58) | AC47: =IF('Raw Data - financials'!AC58="","",'Raw Data - financials'!AC58) | AD47: =IF('Raw Data - financials'!AD58="","",'Raw Data - financials'!AD58) | AE47: =IF('Raw Data - financials'!AE58="","",'Raw Data - financials'!AE58) | AF47: =IF('Raw Data - financials'!AF58="","",'Raw Data - financials'!AF58) | AG47: =IF('Raw Data - financials'!AG58="","",'Raw Data - financials'!AG58) | AH47: =IF('Raw Data - financials'!AH58="","",'Raw Data - financials'!AH58) | AI47: =IF('Raw Data - financials'!AI58="","",'Raw Data - financials'!AI58) | AJ47: =IF('Raw Data - financials'!AJ58="","",'Raw Data - financials'!AJ58) | AK47: 0 | AL47: 0 | AM47: 0 | AN47: 0
A48: Deferred tax assets (net) | B48: Rs Mn | E48: =IF('Raw Data - financials'!E59="","",'Raw Data - financials'!E59) | G48: =IF('Raw Data - financials'!G59="","",'Raw Data - financials'!G59) | I48: =IF('Raw Data - financials'!I59="","",'Raw Data - financials'!I59) | K48: =IF('Raw Data - financials'!K59="","",'Raw Data - financials'!K59) | M48: =IF('Raw Data - financials'!M59="","",'Raw Data - financials'!M59) | O48: =IF('Raw Data - financials'!O59="","",'Raw Data - financials'!O59) | Q48: =IF('Raw Data - financials'!Q59="","",'Raw Data - financials'!Q59) | S48: =IF('Raw Data - financials'!S59="","",'Raw Data - financials'!S59) | U48: =IF('Raw Data - financials'!U59="","",'Raw Data - financials'!U59) | W48: =IF('Raw Data - financials'!W59="","",'Raw Data - financials'!W59) | AC48: =IF('Raw Data - financials'!AC59="","",'Raw Data - financials'!AC59) | AD48: =IF('Raw Data - financials'!AD59="","",'Raw Data - financials'!AD59) | AE48: =IF('Raw Data - financials'!AE59="","",'Raw Data - financials'!AE59) | AF48: =IF('Raw Data - financials'!AF59="","",'Raw Data - financials'!AF59) | AG48: =IF('Raw Data - financials'!AG59="","",'Raw Data - financials'!AG59) | AH48: =IF('Raw Data - financials'!AH59="","",'Raw Data - financials'!AH59) | AI48: =IF('Raw Data - financials'!AI59="","",'Raw Data - financials'!AI59) | AJ48: =IF('Raw Data - financials'!AJ59="","",'Raw Data - financials'!AJ59) | AK48: 0 | AL48: 0 | AM48: 0 | AN48: 0
A49: Non-current tax assets (net) | B49: Rs Mn | E49: =IF('Raw Data - financials'!E60="","",'Raw Data - financials'!E60) | G49: =IF('Raw Data - financials'!G60="","",'Raw Data - financials'!G60) | I49: =IF('Raw Data - financials'!I60="","",'Raw Data - financials'!I60) | K49: =IF('Raw Data - financials'!K60="","",'Raw Data - financials'!K60) | M49: =IF('Raw Data - financials'!M60="","",'Raw Data - financials'!M60) | O49: =IF('Raw Data - financials'!O60="","",'Raw Data - financials'!O60) | Q49: =IF('Raw Data - financials'!Q60="","",'Raw Data - financials'!Q60) | S49: =IF('Raw Data - financials'!S60="","",'Raw Data - financials'!S60) | U49: =IF('Raw Data - financials'!U60="","",'Raw Data - financials'!U60) | W49: =IF('Raw Data - financials'!W60="","",'Raw Data - financials'!W60) | AC49: =IF('Raw Data - financials'!AC60="","",'Raw Data - financials'!AC60) | AD49: =IF('Raw Data - financials'!AD60="","",'Raw Data - financials'!AD60) | AE49: =IF('Raw Data - financials'!AE60="","",'Raw Data - financials'!AE60) | AF49: =IF('Raw Data - financials'!AF60="","",'Raw Data - financials'!AF60) | AG49: =IF('Raw Data - financials'!AG60="","",'Raw Data - financials'!AG60) | AH49: =IF('Raw Data - financials'!AH60="","",'Raw Data - financials'!AH60) | AI49: =IF('Raw Data - financials'!AI60="","",'Raw Data - financials'!AI60) | AJ49: =IF('Raw Data - financials'!AJ60="","",'Raw Data - financials'!AJ60) | AK49: 0 | AL49: 0 | AM49: 0 | AN49: 0
A50: Other non-current assets | B50: Rs Mn | E50: =IF('Raw Data - financials'!E61="","",'Raw Data - financials'!E61) | G50: =IF('Raw Data - financials'!G61="","",'Raw Data - financials'!G61) | I50: =IF('Raw Data - financials'!I61="","",'Raw Data - financials'!I61) | K50: =IF('Raw Data - financials'!K61="","",'Raw Data - financials'!K61) | M50: =IF('Raw Data - financials'!M61="","",'Raw Data - financials'!M61) | O50: =IF('Raw Data - financials'!O61="","",'Raw Data - financials'!O61) | Q50: =IF('Raw Data - financials'!Q61="","",'Raw Data - financials'!Q61) | S50: =IF('Raw Data - financials'!S61="","",'Raw Data - financials'!S61) | U50: =IF('Raw Data - financials'!U61="","",'Raw Data - financials'!U61) | W50: =IF('Raw Data - financials'!W61="","",'Raw Data - financials'!W61) | AC50: =IF('Raw Data - financials'!AC61="","",'Raw Data - financials'!AC61) | AD50: =IF('Raw Data - financials'!AD61="","",'Raw Data - financials'!AD61) | AE50: =IF('Raw Data - financials'!AE61="","",'Raw Data - financials'!AE61) | AF50: =IF('Raw Data - financials'!AF61="","",'Raw Data - financials'!AF61) | AG50: =IF('Raw Data - financials'!AG61="","",'Raw Data - financials'!AG61) | AH50: =IF('Raw Data - financials'!AH61="","",'Raw Data - financials'!AH61) | AI50: =IF('Raw Data - financials'!AI61="","",'Raw Data - financials'!AI61) | AJ50: =IF('Raw Data - financials'!AJ61="","",'Raw Data - financials'!AJ61) | AK50: =IF('Projections'!AK146="","",'Projections'!AK146) | AL50: =IF('Projections'!AL146="","",'Projections'!AL146) | AM50: =IF('Projections'!AM146="","",'Projections'!AM146) | AN50: =IF('Projections'!AN146="","",'Projections'!AN146)
A51: Total Non-Current Assets | B51: Rs Mn | E51: =IFERROR(E38+E39+E40+E41+E42+E43+E44+E45+E46+E47+E48+E49+E50,"") | G51: =IFERROR(G38+G39+G40+G41+G42+G43+G44+G45+G46+G47+G48+G49+G50,"") | I51: =IFERROR(I38+I39+I40+I41+I42+I43+I44+I45+I46+I47+I48+I49+I50,"") | K51: =IFERROR(K38+K39+K40+K41+K42+K43+K44+K45+K46+K47+K48+K49+K50,"") | M51: =IFERROR(M38+M39+M40+M41+M42+M43+M44+M45+M46+M47+M48+M49+M50,"") | O51: =IFERROR(O38+O39+O40+O41+O42+O43+O44+O45+O46+O47+O48+O49+O50,"") | Q51: =IFERROR(Q38+Q39+Q40+Q41+Q42+Q43+Q44+Q45+Q46+Q47+Q48+Q49+Q50,"") | S51: =IFERROR(S38+S39+S40+S41+S42+S43+S44+S45+S46+S47+S48+S49+S50,"") | U51: =IFERROR(U38+U39+U40+U41+U42+U43+U44+U45+U46+U47+U48+U49+U50,"") | W51: =IFERROR(W38+W39+W40+W41+W42+W43+W44+W45+W46+W47+W48+W49+W50,"") | AC51: =IFERROR(AC38+AC39+AC40+AC41+AC42+AC43+AC44+AC45+AC46+AC47+AC48+AC49+AC50,"") | AD51: =IFERROR(AD38+AD39+AD40+AD41+AD42+AD43+AD44+AD45+AD46+AD47+AD48+AD49+AD50,"") | AE51: =IFERROR(AE38+AE39+AE40+AE41+AE42+AE43+AE44+AE45+AE46+AE47+AE48+AE49+AE50,"") | AF51: =IFERROR(AF38+AF39+AF40+AF41+AF42+AF43+AF44+AF45+AF46+AF47+AF48+AF49+AF50,"") | AG51: =IFERROR(AG38+AG39+AG40+AG41+AG42+AG43+AG44+AG45+AG46+AG47+AG48+AG49+AG50,"") | AH51: =IFERROR(AH38+AH39+AH40+AH41+AH42+AH43+AH44+AH45+AH46+AH47+AH48+AH49+AH50,"") | AI51: =IFERROR(AI38+AI39+AI40+AI41+AI42+AI43+AI44+AI45+AI46+AI47+AI48+AI49+AI50,"") | AJ51: =IFERROR(AJ38+AJ39+AJ40+AJ41+AJ42+AJ43+AJ44+AJ45+AJ46+AJ47+AJ48+AJ49+AJ50,"") | ... AN51: =IFERROR(AN38+AN39+AN40+AN41+AN42+AN43+AN44+AN45+AN46+AN47+AN48+AN49+AN50,"")
A53: Current assets
A54: Inventories | B54: Rs Mn | E54: =IF('Raw Data - financials'!E65="","",'Raw Data - financials'!E65) | G54: =IF('Raw Data - financials'!G65="","",'Raw Data - financials'!G65) | I54: =IF('Raw Data - financials'!I65="","",'Raw Data - financials'!I65) | K54: =IF('Raw Data - financials'!K65="","",'Raw Data - financials'!K65) | M54: =IF('Raw Data - financials'!M65="","",'Raw Data - financials'!M65) | O54: =IF('Raw Data - financials'!O65="","",'Raw Data - financials'!O65) | Q54: =IF('Raw Data - financials'!Q65="","",'Raw Data - financials'!Q65) | S54: =IF('Raw Data - financials'!S65="","",'Raw Data - financials'!S65) | U54: =IF('Raw Data - financials'!U65="","",'Raw Data - financials'!U65) | W54: =IF('Raw Data - financials'!W65="","",'Raw Data - financials'!W65) | AC54: =IF('Raw Data - financials'!AC65="","",'Raw Data - financials'!AC65) | AD54: =IF('Raw Data - financials'!AD65="","",'Raw Data - financials'!AD65) | AE54: =IF('Raw Data - financials'!AE65="","",'Raw Data - financials'!AE65) | AF54: =IF('Raw Data - financials'!AF65="","",'Raw Data - financials'!AF65) | AG54: =IF('Raw Data - financials'!AG65="","",'Raw Data - financials'!AG65) | AH54: =IF('Raw Data - financials'!AH65="","",'Raw Data - financials'!AH65) | AI54: =IF('Raw Data - financials'!AI65="","",'Raw Data - financials'!AI65) | AJ54: =IF('Raw Data - financials'!AJ65="","",'Raw Data - financials'!AJ65) | AK54: =IF('Projections'!AK142="","",'Projections'!AK142) | AL54: =IF('Projections'!AL142="","",'Projections'!AL142) | AM54: =IF('Projections'!AM142="","",'Projections'!AM142) | AN54: =IF('Projections'!AN142="","",'Projections'!AN142)
A55: Financial assets - Investments (current) | B55: Rs Mn | E55: =IF('Raw Data - financials'!E66="","",'Raw Data - financials'!E66) | G55: =IF('Raw Data - financials'!G66="","",'Raw Data - financials'!G66) | I55: =IF('Raw Data - financials'!I66="","",'Raw Data - financials'!I66) | K55: =IF('Raw Data - financials'!K66="","",'Raw Data - financials'!K66) | M55: =IF('Raw Data - financials'!M66="","",'Raw Data - financials'!M66) | O55: =IF('Raw Data - financials'!O66="","",'Raw Data - financials'!O66) | Q55: =IF('Raw Data - financials'!Q66="","",'Raw Data - financials'!Q66) | S55: =IF('Raw Data - financials'!S66="","",'Raw Data - financials'!S66) | U55: =IF('Raw Data - financials'!U66="","",'Raw Data - financials'!U66) | W55: =IF('Raw Data - financials'!W66="","",'Raw Data - financials'!W66) | AC55: =IF('Raw Data - financials'!AC66="","",'Raw Data - financials'!AC66) | AD55: =IF('Raw Data - financials'!AD66="","",'Raw Data - financials'!AD66) | AE55: =IF('Raw Data - financials'!AE66="","",'Raw Data - financials'!AE66) | AF55: =IF('Raw Data - financials'!AF66="","",'Raw Data - financials'!AF66) | AG55: =IF('Raw Data - financials'!AG66="","",'Raw Data - financials'!AG66) | AH55: =IF('Raw Data - financials'!AH66="","",'Raw Data - financials'!AH66) | AI55: =IF('Raw Data - financials'!AI66="","",'Raw Data - financials'!AI66) | AJ55: =IF('Raw Data - financials'!AJ66="","",'Raw Data - financials'!AJ66) | AK55: 0 | AL55: 0 | AM55: 0 | AN55: 0
A56: Trade receivables | B56: Rs Mn | E56: =IF('Raw Data - financials'!E67="","",'Raw Data - financials'!E67) | G56: =IF('Raw Data - financials'!G67="","",'Raw Data - financials'!G67) | I56: =IF('Raw Data - financials'!I67="","",'Raw Data - financials'!I67) | K56: =IF('Raw Data - financials'!K67="","",'Raw Data - financials'!K67) | M56: =IF('Raw Data - financials'!M67="","",'Raw Data - financials'!M67) | O56: =IF('Raw Data - financials'!O67="","",'Raw Data - financials'!O67) | Q56: =IF('Raw Data - financials'!Q67="","",'Raw Data - financials'!Q67) | S56: =IF('Raw Data - financials'!S67="","",'Raw Data - financials'!S67) | U56: =IF('Raw Data - financials'!U67="","",'Raw Data - financials'!U67) | W56: =IF('Raw Data - financials'!W67="","",'Raw Data - financials'!W67) | AC56: =IF('Raw Data - financials'!AC67="","",'Raw Data - financials'!AC67) | AD56: =IF('Raw Data - financials'!AD67="","",'Raw Data - financials'!AD67) | AE56: =IF('Raw Data - financials'!AE67="","",'Raw Data - financials'!AE67) | AF56: =IF('Raw Data - financials'!AF67="","",'Raw Data - financials'!AF67) | AG56: =IF('Raw Data - financials'!AG67="","",'Raw Data - financials'!AG67) | AH56: =IF('Raw Data - financials'!AH67="","",'Raw Data - financials'!AH67) | AI56: =IF('Raw Data - financials'!AI67="","",'Raw Data - financials'!AI67) | AJ56: =IF('Raw Data - financials'!AJ67="","",'Raw Data - financials'!AJ67) | AK56: =IF('Projections'!AK144="","",'Projections'!AK144) | AL56: =IF('Projections'!AL144="","",'Projections'!AL144) | AM56: =IF('Projections'!AM144="","",'Projections'!AM144) | AN56: =IF('Projections'!AN144="","",'Projections'!AN144)
A57: Cash and cash equivalents | B57: Rs Mn | E57: =IF('Raw Data - financials'!E68="","",'Raw Data - financials'!E68) | G57: =IF('Raw Data - financials'!G68="","",'Raw Data - financials'!G68) | I57: =IF('Raw Data - financials'!I68="","",'Raw Data - financials'!I68) | K57: =IF('Raw Data - financials'!K68="","",'Raw Data - financials'!K68) | M57: =IF('Raw Data - financials'!M68="","",'Raw Data - financials'!M68) | O57: =IF('Raw Data - financials'!O68="","",'Raw Data - financials'!O68) | Q57: =IF('Raw Data - financials'!Q68="","",'Raw Data - financials'!Q68) | S57: =IF('Raw Data - financials'!S68="","",'Raw Data - financials'!S68) | U57: =IF('Raw Data - financials'!U68="","",'Raw Data - financials'!U68) | W57: =IF('Raw Data - financials'!W68="","",'Raw Data - financials'!W68) | AC57: =IF('Raw Data - financials'!AC68="","",'Raw Data - financials'!AC68) | AD57: =IF('Raw Data - financials'!AD68="","",'Raw Data - financials'!AD68) | AE57: =IF('Raw Data - financials'!AE68="","",'Raw Data - financials'!AE68) | AF57: =IF('Raw Data - financials'!AF68="","",'Raw Data - financials'!AF68) | AG57: =IF('Raw Data - financials'!AG68="","",'Raw Data - financials'!AG68) | AH57: =IF('Raw Data - financials'!AH68="","",'Raw Data - financials'!AH68) | AI57: =IF('Raw Data - financials'!AI68="","",'Raw Data - financials'!AI68) | AJ57: =IF('Raw Data - financials'!AJ68="","",'Raw Data - financials'!AJ68) | AK57: =IFERROR('Projections'!AK147-AK58,"") | AL57: =IFERROR('Projections'!AL147-AL58,"") | AM57: =IFERROR('Projections'!AM147-AM58,"") | AN57: =IFERROR('Projections'!AN147-AN58,"")
A58: Bank balance other than cash and cash equivalents | B58: Rs Mn | C58: Held flat at FY26 actual | E58: =IF('Raw Data - financials'!E69="","",'Raw Data - financials'!E69) | G58: =IF('Raw Data - financials'!G69="","",'Raw Data - financials'!G69) | I58: =IF('Raw Data - financials'!I69="","",'Raw Data - financials'!I69) | K58: =IF('Raw Data - financials'!K69="","",'Raw Data - financials'!K69) | M58: =IF('Raw Data - financials'!M69="","",'Raw Data - financials'!M69) | O58: =IF('Raw Data - financials'!O69="","",'Raw Data - financials'!O69) | Q58: =IF('Raw Data - financials'!Q69="","",'Raw Data - financials'!Q69) | S58: =IF('Raw Data - financials'!S69="","",'Raw Data - financials'!S69) | U58: =IF('Raw Data - financials'!U69="","",'Raw Data - financials'!U69) | W58: =IF('Raw Data - financials'!W69="","",'Raw Data - financials'!W69) | AC58: =IF('Raw Data - financials'!AC69="","",'Raw Data - financials'!AC69) | AD58: =IF('Raw Data - financials'!AD69="","",'Raw Data - financials'!AD69) | AE58: =IF('Raw Data - financials'!AE69="","",'Raw Data - financials'!AE69) | AF58: =IF('Raw Data - financials'!AF69="","",'Raw Data - financials'!AF69) | AG58: =IF('Raw Data - financials'!AG69="","",'Raw Data - financials'!AG69) | AH58: =IF('Raw Data - financials'!AH69="","",'Raw Data - financials'!AH69) | AI58: =IF('Raw Data - financials'!AI69="","",'Raw Data - financials'!AI69) | AJ58: =IF('Raw Data - financials'!AJ69="","",'Raw Data - financials'!AJ69) | AK58: =IFERROR(AJ58,"") | AL58: =IFERROR(AJ58,"") | AM58: =IFERROR(AJ58,"") | AN58: =IFERROR(AJ58,"")
A59: Financial assets - Loans (current) | B59: Rs Mn | E59: =IF('Raw Data - financials'!E70="","",'Raw Data - financials'!E70) | G59: =IF('Raw Data - financials'!G70="","",'Raw Data - financials'!G70) | I59: =IF('Raw Data - financials'!I70="","",'Raw Data - financials'!I70) | K59: =IF('Raw Data - financials'!K70="","",'Raw Data - financials'!K70) | M59: =IF('Raw Data - financials'!M70="","",'Raw Data - financials'!M70) | O59: =IF('Raw Data - financials'!O70="","",'Raw Data - financials'!O70) | Q59: =IF('Raw Data - financials'!Q70="","",'Raw Data - financials'!Q70) | S59: =IF('Raw Data - financials'!S70="","",'Raw Data - financials'!S70) | U59: =IF('Raw Data - financials'!U70="","",'Raw Data - financials'!U70) | W59: =IF('Raw Data - financials'!W70="","",'Raw Data - financials'!W70) | AC59: =IF('Raw Data - financials'!AC70="","",'Raw Data - financials'!AC70) | AD59: =IF('Raw Data - financials'!AD70="","",'Raw Data - financials'!AD70) | AE59: =IF('Raw Data - financials'!AE70="","",'Raw Data - financials'!AE70) | AF59: =IF('Raw Data - financials'!AF70="","",'Raw Data - financials'!AF70) | AG59: =IF('Raw Data - financials'!AG70="","",'Raw Data - financials'!AG70) | AH59: =IF('Raw Data - financials'!AH70="","",'Raw Data - financials'!AH70) | AI59: =IF('Raw Data - financials'!AI70="","",'Raw Data - financials'!AI70) | AJ59: =IF('Raw Data - financials'!AJ70="","",'Raw Data - financials'!AJ70) | AK59: 0 | AL59: 0 | AM59: 0 | AN59: 0
A60: Other financial assets (current) | B60: Rs Mn | E60: =IF('Raw Data - financials'!E71="","",'Raw Data - financials'!E71) | G60: =IF('Raw Data - financials'!G71="","",'Raw Data - financials'!G71) | I60: =IF('Raw Data - financials'!I71="","",'Raw Data - financials'!I71) | K60: =IF('Raw Data - financials'!K71="","",'Raw Data - financials'!K71) | M60: =IF('Raw Data - financials'!M71="","",'Raw Data - financials'!M71) | O60: =IF('Raw Data - financials'!O71="","",'Raw Data - financials'!O71) | Q60: =IF('Raw Data - financials'!Q71="","",'Raw Data - financials'!Q71) | S60: =IF('Raw Data - financials'!S71="","",'Raw Data - financials'!S71) | U60: =IF('Raw Data - financials'!U71="","",'Raw Data - financials'!U71) | W60: =IF('Raw Data - financials'!W71="","",'Raw Data - financials'!W71) | AC60: =IF('Raw Data - financials'!AC71="","",'Raw Data - financials'!AC71) | AD60: =IF('Raw Data - financials'!AD71="","",'Raw Data - financials'!AD71) | AE60: =IF('Raw Data - financials'!AE71="","",'Raw Data - financials'!AE71) | AF60: =IF('Raw Data - financials'!AF71="","",'Raw Data - financials'!AF71) | AG60: =IF('Raw Data - financials'!AG71="","",'Raw Data - financials'!AG71) | AH60: =IF('Raw Data - financials'!AH71="","",'Raw Data - financials'!AH71) | AI60: =IF('Raw Data - financials'!AI71="","",'Raw Data - financials'!AI71) | AJ60: =IF('Raw Data - financials'!AJ71="","",'Raw Data - financials'!AJ71) | AK60: 0 | AL60: 0 | AM60: 0 | AN60: 0
A61: Other current assets | B61: Rs Mn | E61: =IF('Raw Data - financials'!E72="","",'Raw Data - financials'!E72) | G61: =IF('Raw Data - financials'!G72="","",'Raw Data - financials'!G72) | I61: =IF('Raw Data - financials'!I72="","",'Raw Data - financials'!I72) | K61: =IF('Raw Data - financials'!K72="","",'Raw Data - financials'!K72) | M61: =IF('Raw Data - financials'!M72="","",'Raw Data - financials'!M72) | O61: =IF('Raw Data - financials'!O72="","",'Raw Data - financials'!O72) | Q61: =IF('Raw Data - financials'!Q72="","",'Raw Data - financials'!Q72) | S61: =IF('Raw Data - financials'!S72="","",'Raw Data - financials'!S72) | U61: =IF('Raw Data - financials'!U72="","",'Raw Data - financials'!U72) | W61: =IF('Raw Data - financials'!W72="","",'Raw Data - financials'!W72) | AC61: =IF('Raw Data - financials'!AC72="","",'Raw Data - financials'!AC72) | AD61: =IF('Raw Data - financials'!AD72="","",'Raw Data - financials'!AD72) | AE61: =IF('Raw Data - financials'!AE72="","",'Raw Data - financials'!AE72) | AF61: =IF('Raw Data - financials'!AF72="","",'Raw Data - financials'!AF72) | AG61: =IF('Raw Data - financials'!AG72="","",'Raw Data - financials'!AG72) | AH61: =IF('Raw Data - financials'!AH72="","",'Raw Data - financials'!AH72) | AI61: =IF('Raw Data - financials'!AI72="","",'Raw Data - financials'!AI72) | AJ61: =IF('Raw Data - financials'!AJ72="","",'Raw Data - financials'!AJ72) | AK61: 0 | AL61: 0 | AM61: 0 | AN61: 0
A62: Total Current Assets | B62: Rs Mn | E62: =IFERROR(E54+E55+E56+E57+E58+E59+E60+E61,"") | G62: =IFERROR(G54+G55+G56+G57+G58+G59+G60+G61,"") | I62: =IFERROR(I54+I55+I56+I57+I58+I59+I60+I61,"") | K62: =IFERROR(K54+K55+K56+K57+K58+K59+K60+K61,"") | M62: =IFERROR(M54+M55+M56+M57+M58+M59+M60+M61,"") | O62: =IFERROR(O54+O55+O56+O57+O58+O59+O60+O61,"") | Q62: =IFERROR(Q54+Q55+Q56+Q57+Q58+Q59+Q60+Q61,"") | S62: =IFERROR(S54+S55+S56+S57+S58+S59+S60+S61,"") | U62: =IFERROR(U54+U55+U56+U57+U58+U59+U60+U61,"") | W62: =IFERROR(W54+W55+W56+W57+W58+W59+W60+W61,"") | AC62: =IFERROR(AC54+AC55+AC56+AC57+AC58+AC59+AC60+AC61,"") | AD62: =IFERROR(AD54+AD55+AD56+AD57+AD58+AD59+AD60+AD61,"") | AE62: =IFERROR(AE54+AE55+AE56+AE57+AE58+AE59+AE60+AE61,"") | AF62: =IFERROR(AF54+AF55+AF56+AF57+AF58+AF59+AF60+AF61,"") | AG62: =IFERROR(AG54+AG55+AG56+AG57+AG58+AG59+AG60+AG61,"") | AH62: =IFERROR(AH54+AH55+AH56+AH57+AH58+AH59+AH60+AH61,"") | AI62: =IFERROR(AI54+AI55+AI56+AI57+AI58+AI59+AI60+AI61,"") | AJ62: =IFERROR(AJ54+AJ55+AJ56+AJ57+AJ58+AJ59+AJ60+AJ61,"") | ... AN62: =IFERROR(AN54+AN55+AN56+AN57+AN58+AN59+AN60+AN61,"")
A64: TOTAL ASSETS | B64: Rs Mn | E64: =IFERROR(E51+E62,"") | G64: =IFERROR(G51+G62,"") | I64: =IFERROR(I51+I62,"") | K64: =IFERROR(K51+K62,"") | M64: =IFERROR(M51+M62,"") | O64: =IFERROR(O51+O62,"") | Q64: =IFERROR(Q51+Q62,"") | S64: =IFERROR(S51+S62,"") | U64: =IFERROR(U51+U62,"") | W64: =IFERROR(W51+W62,"") | AC64: =IFERROR(AC51+AC62,"") | AD64: =IFERROR(AD51+AD62,"") | AE64: =IFERROR(AE51+AE62,"") | AF64: =IFERROR(AF51+AF62,"") | AG64: =IFERROR(AG51+AG62,"") | AH64: =IFERROR(AH51+AH62,"") | AI64: =IFERROR(AI51+AI62,"") | AJ64: =IFERROR(AJ51+AJ62,"") | ... AN64: =IFERROR(AN51+AN62,"")
A66: EQUITY AND LIABILITIES
A67: Equity
A68: Equity share capital | B68: Rs Mn | E68: =IF('Raw Data - financials'!E79="","",'Raw Data - financials'!E79) | G68: =IF('Raw Data - financials'!G79="","",'Raw Data - financials'!G79) | I68: =IF('Raw Data - financials'!I79="","",'Raw Data - financials'!I79) | K68: =IF('Raw Data - financials'!K79="","",'Raw Data - financials'!K79) | M68: =IF('Raw Data - financials'!M79="","",'Raw Data - financials'!M79) | O68: =IF('Raw Data - financials'!O79="","",'Raw Data - financials'!O79) | Q68: =IF('Raw Data - financials'!Q79="","",'Raw Data - financials'!Q79) | S68: =IF('Raw Data - financials'!S79="","",'Raw Data - financials'!S79) | U68: =IF('Raw Data - financials'!U79="","",'Raw Data - financials'!U79) | W68: =IF('Raw Data - financials'!W79="","",'Raw Data - financials'!W79) | AC68: =IF('Raw Data - financials'!AC79="","",'Raw Data - financials'!AC79) | AD68: =IF('Raw Data - financials'!AD79="","",'Raw Data - financials'!AD79) | AE68: =IF('Raw Data - financials'!AE79="","",'Raw Data - financials'!AE79) | AF68: =IF('Raw Data - financials'!AF79="","",'Raw Data - financials'!AF79) | AG68: =IF('Raw Data - financials'!AG79="","",'Raw Data - financials'!AG79) | AH68: =IF('Raw Data - financials'!AH79="","",'Raw Data - financials'!AH79) | AI68: =IF('Raw Data - financials'!AI79="","",'Raw Data - financials'!AI79) | AJ68: =IF('Raw Data - financials'!AJ79="","",'Raw Data - financials'!AJ79) | AK68: =IF('Projections'!AK151="","",'Projections'!AK151) | AL68: =IF('Projections'!AL151="","",'Projections'!AL151) | AM68: =IF('Projections'!AM151="","",'Projections'!AM151) | AN68: =IF('Projections'!AN151="","",'Projections'!AN151)
A69: Other equity | B69: Rs Mn | E69: =IF('Raw Data - financials'!E80="","",'Raw Data - financials'!E80) | G69: =IF('Raw Data - financials'!G80="","",'Raw Data - financials'!G80) | I69: =IF('Raw Data - financials'!I80="","",'Raw Data - financials'!I80) | K69: =IF('Raw Data - financials'!K80="","",'Raw Data - financials'!K80) | M69: =IF('Raw Data - financials'!M80="","",'Raw Data - financials'!M80) | O69: =IF('Raw Data - financials'!O80="","",'Raw Data - financials'!O80) | Q69: =IF('Raw Data - financials'!Q80="","",'Raw Data - financials'!Q80) | S69: =IF('Raw Data - financials'!S80="","",'Raw Data - financials'!S80) | U69: =IF('Raw Data - financials'!U80="","",'Raw Data - financials'!U80) | W69: =IF('Raw Data - financials'!W80="","",'Raw Data - financials'!W80) | AC69: =IF('Raw Data - financials'!AC80="","",'Raw Data - financials'!AC80) | AD69: =IF('Raw Data - financials'!AD80="","",'Raw Data - financials'!AD80) | AE69: =IF('Raw Data - financials'!AE80="","",'Raw Data - financials'!AE80) | AF69: =IF('Raw Data - financials'!AF80="","",'Raw Data - financials'!AF80) | AG69: =IF('Raw Data - financials'!AG80="","",'Raw Data - financials'!AG80) | AH69: =IF('Raw Data - financials'!AH80="","",'Raw Data - financials'!AH80) | AI69: =IF('Raw Data - financials'!AI80="","",'Raw Data - financials'!AI80) | AJ69: =IF('Raw Data - financials'!AJ80="","",'Raw Data - financials'!AJ80) | AK69: =IF('Projections'!AK153="","",'Projections'!AK153) | AL69: =IF('Projections'!AL153="","",'Projections'!AL153) | AM69: =IF('Projections'!AM153="","",'Projections'!AM153) | AN69: =IF('Projections'!AN153="","",'Projections'!AN153)
A70: Equity attributable to equity holders of the parent | B70: Rs Mn | E70: =IFERROR(E68+E69,"") | G70: =IFERROR(G68+G69,"") | I70: =IFERROR(I68+I69,"") | K70: =IFERROR(K68+K69,"") | M70: =IFERROR(M68+M69,"") | O70: =IFERROR(O68+O69,"") | Q70: =IFERROR(Q68+Q69,"") | S70: =IFERROR(S68+S69,"") | U70: =IFERROR(U68+U69,"") | W70: =IFERROR(W68+W69,"") | AC70: =IFERROR(AC68+AC69,"") | AD70: =IFERROR(AD68+AD69,"") | AE70: =IFERROR(AE68+AE69,"") | AF70: =IFERROR(AF68+AF69,"") | AG70: =IFERROR(AG68+AG69,"") | AH70: =IFERROR(AH68+AH69,"") | AI70: =IFERROR(AI68+AI69,"") | AJ70: =IFERROR(AJ68+AJ69,"") | ... AN70: =IFERROR(AN68+AN69,"")
A71: Non-controlling interest | B71: Rs Mn | E71: =IF('Raw Data - financials'!E82="","",'Raw Data - financials'!E82) | G71: =IF('Raw Data - financials'!G82="","",'Raw Data - financials'!G82) | I71: =IF('Raw Data - financials'!I82="","",'Raw Data - financials'!I82) | K71: =IF('Raw Data - financials'!K82="","",'Raw Data - financials'!K82) | M71: =IF('Raw Data - financials'!M82="","",'Raw Data - financials'!M82) | O71: =IF('Raw Data - financials'!O82="","",'Raw Data - financials'!O82) | Q71: =IF('Raw Data - financials'!Q82="","",'Raw Data - financials'!Q82) | S71: =IF('Raw Data - financials'!S82="","",'Raw Data - financials'!S82) | U71: =IF('Raw Data - financials'!U82="","",'Raw Data - financials'!U82) | W71: =IF('Raw Data - financials'!W82="","",'Raw Data - financials'!W82) | AC71: =IF('Raw Data - financials'!AC82="","",'Raw Data - financials'!AC82) | AD71: =IF('Raw Data - financials'!AD82="","",'Raw Data - financials'!AD82) | AE71: =IF('Raw Data - financials'!AE82="","",'Raw Data - financials'!AE82) | AF71: =IF('Raw Data - financials'!AF82="","",'Raw Data - financials'!AF82) | AG71: =IF('Raw Data - financials'!AG82="","",'Raw Data - financials'!AG82) | AH71: =IF('Raw Data - financials'!AH82="","",'Raw Data - financials'!AH82) | AI71: =IF('Raw Data - financials'!AI82="","",'Raw Data - financials'!AI82) | AJ71: =IF('Raw Data - financials'!AJ82="","",'Raw Data - financials'!AJ82) | AK71: 0 | AL71: 0 | AM71: 0 | AN71: 0
A72: Total Equity | B72: Rs Mn | E72: =IFERROR(E70+E71,"") | G72: =IFERROR(G70+G71,"") | I72: =IFERROR(I70+I71,"") | K72: =IFERROR(K70+K71,"") | M72: =IFERROR(M70+M71,"") | O72: =IFERROR(O70+O71,"") | Q72: =IFERROR(Q70+Q71,"") | S72: =IFERROR(S70+S71,"") | U72: =IFERROR(U70+U71,"") | W72: =IFERROR(W70+W71,"") | AC72: =IFERROR(AC70+AC71,"") | AD72: =IFERROR(AD70+AD71,"") | AE72: =IFERROR(AE70+AE71,"") | AF72: =IFERROR(AF70+AF71,"") | AG72: =IFERROR(AG70+AG71,"") | AH72: =IFERROR(AH70+AH71,"") | AI72: =IFERROR(AI70+AI71,"") | AJ72: =IFERROR(AJ70+AJ71,"") | ... AN72: =IFERROR(AN70+AN71,"")
A74: Non-current liabilities
A75: Borrowings | B75: Rs Mn | E75: =IF('Raw Data - financials'!E86="","",'Raw Data - financials'!E86) | G75: =IF('Raw Data - financials'!G86="","",'Raw Data - financials'!G86) | I75: =IF('Raw Data - financials'!I86="","",'Raw Data - financials'!I86) | K75: =IF('Raw Data - financials'!K86="","",'Raw Data - financials'!K86) | M75: =IF('Raw Data - financials'!M86="","",'Raw Data - financials'!M86) | O75: =IF('Raw Data - financials'!O86="","",'Raw Data - financials'!O86) | Q75: =IF('Raw Data - financials'!Q86="","",'Raw Data - financials'!Q86) | S75: =IF('Raw Data - financials'!S86="","",'Raw Data - financials'!S86) | U75: =IF('Raw Data - financials'!U86="","",'Raw Data - financials'!U86) | W75: =IF('Raw Data - financials'!W86="","",'Raw Data - financials'!W86) | AC75: =IF('Raw Data - financials'!AC86="","",'Raw Data - financials'!AC86) | AD75: =IF('Raw Data - financials'!AD86="","",'Raw Data - financials'!AD86) | AE75: =IF('Raw Data - financials'!AE86="","",'Raw Data - financials'!AE86) | AF75: =IF('Raw Data - financials'!AF86="","",'Raw Data - financials'!AF86) | AG75: =IF('Raw Data - financials'!AG86="","",'Raw Data - financials'!AG86) | AH75: =IF('Raw Data - financials'!AH86="","",'Raw Data - financials'!AH86) | AI75: =IF('Raw Data - financials'!AI86="","",'Raw Data - financials'!AI86) | AJ75: =IF('Raw Data - financials'!AJ86="","",'Raw Data - financials'!AJ86) | AK75: =IF('Projections'!AK154="","",'Projections'!AK154) | AL75: =IF('Projections'!AL154="","",'Projections'!AL154) | AM75: =IF('Projections'!AM154="","",'Projections'!AM154) | AN75: =IF('Projections'!AN154="","",'Projections'!AN154)
